Workbook

Sheet 00_README
A1: MODELO DE DECISIONES - PRODUCTION MANAGER (EXSIM / MEZQUITE)
A3: INSTRUCCIONES DE USO:
A5: PASO 1: Actualizar inventarios iniciales
A6: - Ve a 01_INPUTS_MASTER y pega los inventarios de FG, materiales y assemblies del reporte del simulador
A8: PASO 2: Ingresar demanda forecast
A9: - Ve a 02_DEMAND y captura la demanda esperada por región y subperiodo (pares: 2,4,6,8)
A11: PASO 3: Definir MPS (Master Production Schedule)
A12: - Ve a 03_MPS_S5 y ajusta el target de FG final si deseas colchón de inventario
A14: PASO 4: Verificar flujo de producción
A15: - Ve a 04_FLOW_S1_S5 para ver el plan por sección considerando lead times
A17: PASO 5: Verificar capacidad
A18: - Ve a 05_CAPACITY para identificar cuellos de botella (máquinas/labor/materiales)
... A45: TODO: Campos marcados con 'TODO' deben actualizarse del reporte del simulador

Sheet 01_INPUTS_MASTER
A1: PARÁMETROS MAESTROS DEL MODELO
A3: SUBPERIODOS
A4: Subperiodo | B4: 1 | C4: 2 | D4: 3 | E4: 4 | F4: 5 | G4: 6 | H4: 7 | I4: 8
A5: Es subperiodo de venta? | B5: 0 | C5: 1 | D5: 0 | E5: 1 | F5: 0 | G5: 1 | H5: 0 | I5: 1
A7: PLANTAS / REGIONES
A8: Región | B8: Tiene Planta? | C8: Módulos Planta | D8: Módulos Almacén | E8: Salario Quincena
A9: Center | B9: 1 | C9: 4 | D9: 48 | E9: 27.3
A10: West | B10: 1 | C10: 2 | D10: 25 | E10: 27.3
A11: North | B11: 0 | C11: 0 | D11: 20 | E11: 0
A12: East | B12: 0 | C12: 0 | D12: 0 | E12: 0
A13: South | B13: 0 | C13: 0 | D13: 0 | E13: 0
A15: MÁQUINAS
A16: Tipo | B16: Capacidad/Quinc | C16: Espacios | D16: kW | E16: Costo | F16: Vida Útil | G16: Workers/Máq | H16: Center Qty | I16: West Qty | J16: Sección
A17: M1 | B17: 200 | C17: 1 | D17: 10 | E17: 10600 | F17: 10 | G17: 1 | H17: 7 | I17: 3 | J17: S1
A18: M2 | B18: 70 | C18: 1 | D18: 9 | E18: 7000 | F18: 10 | G18: 1 | H18: 22 | I18: 9 | J18: S2
A19: M3-alpha | B19: 450 | C19: 5 | D19: 15 | E19: 88500 | F19: 20 | G19: 30 | H19: 3 | I19: 1 | J19: S3
A20: M3-beta | B20: 600 | C20: 6 | D20: 16 | E20: 155400 | F20: 20 | G20: 6 | H20: 0 | I20: 0 | J20: S3
A21: M4-S3 | B21: 400 | C21: 1 | D21: 6 | E21: 2500 | F21: 8 | G21: 1 | H21: 4 | I21: 2 | J21: S3
A22: M4-S4 | B22: 150 | C22: 1 | D22: 6 | E22: 2500 | F22: 8 | G22: 1 | H22: 10 | I22: 3 | J22: S4
A23: M4-S5 | B23: 130 | C23: 1 | D23: 6 | E23: 2500 | F23: 8 | G23: 1 | H23: 11 | I23: 3 | J23: S5
A24: Crews-S5 | B24: 50 | C24: 0 | D24: 0 | E24: 0 | F24: 0 | G24: 3 | H24: 25 | I24: 7 | J24: S5
A26: LABOR
A27: Salario mínimo/quincena | B27: 26
A28: Overtime cost/worker/quinc | B28: 12
A29: Hiring cost/worker | B29: 240
A30: Layoff cost/worker | B30: 220
A31: Indirect labor % | B31: 0.5
A33: ENERGÍA
A34: Costo fijo $/kW instalado/periodo | B34: 10
A35: Costo variable $/kWh | B35: 0.06
A36: Horas/subperiodo | B36: 80
A38: MATERIALES - PIECES (Batch, inicio periodo)
A39: Piece | B39: Batch Size | C39: Costo/Batch | D39: Consumo/Electroclean | E39: Inv Inicial Center | F39: Inv Inicial West
A40: Piece 1 | B40: 1 | C40: 60 | D40: 0.01 | E40: 94 | F40: 36
A41: Piece 2 | B41: 100 | C41: 7 | D41: 8 | E41: 3844 | F41: 1424
A42: Piece 3 | B42: 30 | C42: 36 | D42: 0.3 | E42: 3125 | F42: 1208
A43: Piece 4 | B43: 60 | C43: 24 | D43: 0.6 | E43: 6131 | F43: 2356
A44: Piece 5 | B44: 100 | C44: 30 | D44: 2 | E44: 16736 | F44: 6456
A45: Piece 6 | B45: 150 | C45: 28 | D45: 0.75 | E45: 4439 | F45: 1596
A47: MATERIALES - PARTS A/B (Batch, cualquier subperiodo) | L47: PARTS INV INITIAL
A48: Part | B48: Batch Size | C48: Precio Supp A | D48: Precio Supp B | E48: Precio Supp C | F48: Ordering Cost | G48: Holding Cost/unit | H48: Consumo/EC | L48: Part | M48: Center | N48: West
A49: Part A | B49: 30 | C49: 125 | D49: 100 | E49: 140 | F49: 2300 | G49: 0.3 | H49: 1 | L49: Part A | M49: 0 | N49: 0
A50: Part B | B50: 12 | C50: 330 | D50: 264 | E50: 370 | F50: 6000 | G50: 4.5 | H50: 0.2 | L50: Part B | M50: 0 | N50: 0
A52: ASSEMBLIES - Holding Costs | L52: SUPPLIER SETUP
A53: Assembly | B53: Holding Cost/unit/quinc | C53: Inv Inicial Center | D53: Inv Inicial West | L53: Plant | M53: Supp Part A | N53: Supp Part B | O53: Discount % | P53: Pay Terms | Q53: Risk B
A54: Assembly A | B54: 0.2 | C54: 7432 | D54: 3622 | L54: Center | M54: A | N54: A | O54: 0 | P54: 1 | Q54: 0.2
A55: Assembly B | B55: 0.4 | C55: 6528 | D55: 0 | L55: West | M55: A | N55: A | O55: 0 | P55: 1 | Q55: 0.2
A56: Assembly C | B56: 0.6 | C56: 6682 | D56: 0
A57: Assembly D | B57: 0.2 | C57: 0 | D57: 0
A59: ESPACIOS
A60: Espacios por módulo | B60: 18
A61: Costo módulo planta | B61: 50000
A62: Costo leasing emergencia/módulo | B62: 75000
A63: Costo admin/módulo/periodo | B63: 10000
A65: FINISHED GOODS - INVENTARIOS INICIALES
A66: Región | B66: FG Inicial | C66: Capacidad Almacén
A67: Center | B67: 1737 | C67: 4800
A68: West | B68: 1299 | C68: 2500
A69: North | B69: 0 | C69: 2000
A70: East | B70: 0 | C70: 0
A71: South | B71: 0 | C71: 0

Sheet 02_DEMAND
A1: DEMANDA Y VENTAS POR REGIÓN Y SUBPERIODO
A3: Región | B3: Concepto | C3: S1 | D3: S2 | E3: S3 | F3: S4 | G3: S5 | H3: S6 | I3: S7 | J3: S8 | K3: TOTAL
A4: Center
B5: Demanda Forecast | C5: 0 | D5: 1000 | E5: 0 | F5: 1000 | G5: 0 | H5: 1000 | I5: 0 | J5: 1000 | K5: =SUM(C5:J5) -> 4000
B6: Es Subperiodo Venta? | C6: ='01_INPUTS_MASTER'!B5 -> 0 | D6: ='01_INPUTS_MASTER'!C5 -> 1 | E6: ='01_INPUTS_MASTER'!D5 -> 0 | F6: ='01_INPUTS_MASTER'!E5 -> 1 | G6: ='01_INPUTS_MASTER'!F5 -> 0 | H6: ='01_INPUTS_MASTER'!G5 -> 1 | I6: ='01_INPUTS_MASTER'!H5 -> 0 | J6: ='01_INPUTS_MASTER'!I5 -> 1
B7: Demanda Real | C7: =IF(C6=1,C5,0) -> 0 | D7: =IF(D6=1,D5,0) -> 1000 | E7: =IF(E6=1,E5,0) -> 0 | F7: =IF(F6=1,F5,0) -> 1000 | G7: =IF(G6=1,G5,0) -> 0 | H7: =IF(H6=1,H5,0) -> 1000 | I7: =IF(I6=1,I5,0) -> 0 | J7: =IF(J6=1,J5,0) -> 1000 | K7: =SUM(C7:J7) -> 4000
B8: FG Inicial | C8: ='01_INPUTS_MASTER'!B67 -> 1737 | D8: =C13 -> 1737 | E8: =D13 -> 1737 | F8: =E13 -> 1737 | G8: =F13 -> 1737 | H8: =G13 -> 1737 | I8: =H13 -> 1737 | J8: =I13 -> 1737
B9: Recepciones (prod+envíos) | C9: ='04_FLOW_S1_S5'!D9 -> 0 | D9: ='04_FLOW_S1_S5'!E9 -> 1000 | E9: ='04_FLOW_S1_S5'!F9 -> 0 | F9: ='04_FLOW_S1_S5'!G9 -> 1000 | G9: ='04_FLOW_S1_S5'!H9 -> 0 | H9: ='04_FLOW_S1_S5'!I9 -> 1000 | I9: ='04_FLOW_S1_S5'!J9 -> 0 | J9: ='04_FLOW_S1_S5'!K9 -> 1000 | K9: =SUM(C9:J9) -> 4000
B10: FG Disponible | C10: =C8+C9 -> 1737 | D10: =D8+D9 -> 2737 | E10: =E8+E9 -> 1737 | F10: =F8+F9 -> 2737 | G10: =G8+G9 -> 1737 | H10: =H8+H9 -> 2737 | I10: =I8+I9 -> 1737 | J10: =J8+J9 -> 2737
B11: Ventas Posibles | C11: =MIN(C7,C10) -> 0 | D11: =MIN(D7,D10) -> 1000 | E11: =MIN(E7,E10) -> 0 | F11: =MIN(F7,F10) -> 1000 | G11: =MIN(G7,G10) -> 0 | H11: =MIN(H7,H10) -> 1000 | I11: =MIN(I7,I10) -> 0 | J11: =MIN(J7,J10) -> 1000 | K11: =SUM(C11:J11) -> 4000
B12: Ventas Perdidas | C12: =MAX(0,C7-C11) -> 0 | D12: =MAX(0,D7-D11) -> 0 | E12: =MAX(0,E7-E11) -> 0 | F12: =MAX(0,F7-F11) -> 0 | G12: =MAX(0,G7-G11) -> 0 | H12: =MAX(0,H7-H11) -> 0 | I12: =MAX(0,I7-I11) -> 0 | J12: =MAX(0,J7-J11) -> 0 | K12: =SUM(C12:J12) -> 0
B13: FG Final | C13: =C10-C11 -> 1737 | D13: =D10-D11 -> 1737 | E13: =E10-E11 -> 1737 | F13: =F10-F11 -> 1737 | G13: =G10-G11 -> 1737 | H13: =H10-H11 -> 1737 | I13: =I10-I11 -> 1737 | J13: =J10-J11 -> 1737
A15: West
B16: Demanda Forecast | C16: 0 | D16: 1000 | E16: 0 | F16: 1000 | G16: 0 | H16: 1000 | I16: 0 | J16: 1000 | K16: =SUM(C16:J16) -> 4000
B17: Es Subperiodo Venta? | C17: ='01_INPUTS_MASTER'!B5 -> 0 | D17: ='01_INPUTS_MASTER'!C5 -> 1 | E17: ='01_INPUTS_MASTER'!D5 -> 0 | F17: ='01_INPUTS_MASTER'!E5 -> 1 | G17: ='01_INPUTS_MASTER'!F5 -> 0 | H17: ='01_INPUTS_MASTER'!G5 -> 1 | I17: ='01_INPUTS_MASTER'!H5 -> 0 | J17: ='01_INPUTS_MASTER'!I5 -> 1
B18: Demanda Real | C18: =IF(C17=1,C16,0) -> 0 | D18: =IF(D17=1,D16,0) -> 1000 | E18: =IF(E17=1,E16,0) -> 0 | F18: =IF(F17=1,F16,0) -> 1000 | G18: =IF(G17=1,G16,0) -> 0 | H18: =IF(H17=1,H16,0) -> 1000 | I18: =IF(I17=1,I16,0) -> 0 | J18: =IF(J17=1,J16,0) -> 1000 | K18: =SUM(C18:J18) -> 4000
B19: FG Inicial | C19: ='01_INPUTS_MASTER'!B68 -> 1299 | D19: =C24 -> 1299 | E19: =D24 -> 1299 | F19: =E24 -> 1299 | G19: =F24 -> 1299 | H19: =G24 -> 1299 | I19: =H24 -> 1299 | J19: =I24 -> 1299
B20: Recepciones (prod+envíos) | C20: ='04_FLOW_S1_S5'!D40 -> 0 | D20: ='04_FLOW_S1_S5'!E40 -> 1000 | E20: ='04_FLOW_S1_S5'!F40 -> 0 | F20: ='04_FLOW_S1_S5'!G40 -> 1000 | G20: ='04_FLOW_S1_S5'!H40 -> 0 | H20: ='04_FLOW_S1_S5'!I40 -> 1000 | I20: ='04_FLOW_S1_S5'!J40 -> 0 | J20: ='04_FLOW_S1_S5'!K40 -> 1000 | K20: =SUM(C20:J20) -> 4000
B21: FG Disponible | C21: =C19+C20 -> 1299 | D21: =D19+D20 -> 2299 | E21: =E19+E20 -> 1299 | F21: =F19+F20 -> 2299 | G21: =G19+G20 -> 1299 | H21: =H19+H20 -> 2299 | I21: =I19+I20 -> 1299 | J21: =J19+J20 -> 2299
B22: Ventas Posibles | C22: =MIN(C18,C21) -> 0 | D22: =MIN(D18,D21) -> 1000 | E22: =MIN(E18,E21) -> 0 | F22: =MIN(F18,F21) -> 1000 | G22: =MIN(G18,G21) -> 0 | H22: =MIN(H18,H21) -> 1000 | I22: =MIN(I18,I21) -> 0 | J22: =MIN(J18,J21) -> 1000 | K22: =SUM(C22:J22) -> 4000
B23: Ventas Perdidas | C23: =MAX(0,C18-C22) -> 0 | D23: =MAX(0,D18-D22) -> 0 | E23: =MAX(0,E18-E22) -> 0 | F23: =MAX(0,F18-F22) -> 0 | G23: =MAX(0,G18-G22) -> 0 | H23: =MAX(0,H18-H22) -> 0 | I23: =MAX(0,I18-I22) -> 0 | J23: =MAX(0,J18-J22) -> 0 | K23: =SUM(C23:J23) -> 0
B24: FG Final | C24: =C21-C22 -> 1299 | D24: =D21-D22 -> 1299 | E24: =E21-E22 -> 1299 | F24: =F21-F22 -> 1299 | G24: =G21-G22 -> 1299 | H24: =H21-H22 -> 1299 | I24: =I21-I22 -> 1299 | J24: =J21-J22 -> 1299
A26: North
B27: Demanda Forecast | C27: 0 | D27: 1000 | E27: 0 | F27: 1000 | G27: 0 | H27: 1000 | I27: 0 | J27: 1000 | K27: =SUM(C27:J27) -> 4000
B28: Es Subperiodo Venta? | C28: ='01_INPUTS_MASTER'!B5 -> 0 | D28: ='01_INPUTS_MASTER'!C5 -> 1 | E28: ='01_INPUTS_MASTER'!D5 -> 0 | F28: ='01_INPUTS_MASTER'!E5 -> 1 | G28: ='01_INPUTS_MASTER'!F5 -> 0 | H28: ='01_INPUTS_MASTER'!G5 -> 1 | I28: ='01_INPUTS_MASTER'!H5 -> 0 | J28: ='01_INPUTS_MASTER'!I5 -> 1
B29: Demanda Real | C29: =IF(C28=1,C27,0) -> 0 | D29: =IF(D28=1,D27,0) -> 1000 | E29: =IF(E28=1,E27,0) -> 0 | F29: =IF(F28=1,F27,0) -> 1000 | G29: =IF(G28=1,G27,0) -> 0 | H29: =IF(H28=1,H27,0) -> 1000 | I29: =IF(I28=1,I27,0) -> 0 | J29: =IF(J28=1,J27,0) -> 1000 | K29: =SUM(C29:J29) -> 4000
B30: FG Inicial | C30: ='01_INPUTS_MASTER'!B69 -> 0 | D30: =C35 -> 0 | E30: =D35 -> 0 | F30: =E35 -> 0 | G30: =F35 -> 0 | H30: =G35 -> 0 | I30: =H35 -> 0 | J30: =I35 -> 0
B31: Recepciones (prod+envíos) | C31: 0 | D31: 0 | E31: 0 | F31: 0 | G31: 0 | H31: 0 | I31: 0 | J31: 0 | K31: =SUM(C31:J31) -> 0
B32: FG Disponible | C32: =C30+C31 -> 0 | D32: =D30+D31 -> 0 | E32: =E30+E31 -> 0 | F32: =F30+F31 -> 0 | G32: =G30+G31 -> 0 | H32: =H30+H31 -> 0 | I32: =I30+I31 -> 0 | J32: =J30+J31 -> 0
B33: Ventas Posibles | C33: =MIN(C29,C32) -> 0 | D33: =MIN(D29,D32) -> 0 | E33: =MIN(E29,E32) -> 0 | F33: =MIN(F29,F32) -> 0 | G33: =MIN(G29,G32) -> 0 | H33: =MIN(H29,H32) -> 0 | I33: =MIN(I29,I32) -> 0 | J33: =MIN(J29,J32) -> 0 | K33: =SUM(C33:J33) -> 0
B34: Ventas Perdidas | C34: =MAX(0,C29-C33) -> 0 | D34: =MAX(0,D29-D33) -> 1000 | E34: =MAX(0,E29-E33) -> 0 | F34: =MAX(0,F29-F33) -> 1000 | G34: =MAX(0,G29-G33) -> 0 | H34: =MAX(0,H29-H33) -> 1000 | I34: =MAX(0,I29-I33) -> 0 | J34: =MAX(0,J29-J33) -> 1000 | K34: =SUM(C34:J34) -> 4000
B35: FG Final | C35: =C32-C33 -> 0 | D35: =D32-D33 -> 0 | E35: =E32-E33 -> 0 | F35: =F32-F33 -> 0 | G35: =G32-G33 -> 0 | H35: =H32-H33 -> 0 | I35: =I32-I33 -> 0 | J35: =J32-J33 -> 0
A37: East
B38: Demanda Forecast | C38: 0 | D38: 1000 | E38: 0 | F38: 1000 | G38: 0 | H38: 1000 | I38: 0 | J38: 1000 | K38: =SUM(C38:J38) -> 4000
B39: Es Subperiodo Venta? | C39: ='01_INPUTS_MASTER'!B5 -> 0 | D39: ='01_INPUTS_MASTER'!C5 -> 1 | E39: ='01_INPUTS_MASTER'!D5 -> 0 | F39: ='01_INPUTS_MASTER'!E5 -> 1 | G39: ='01_INPUTS_MASTER'!F5 -> 0 | H39: ='01_INPUTS_MASTER'!G5 -> 1 | I39: ='01_INPUTS_MASTER'!H5 -> 0 | J39: ='01_INPUTS_MASTER'!I5 -> 1
B40: Demanda Real | C40: =IF(C39=1,C38,0) -> 0 | D40: =IF(D39=1,D38,0) -> 1000 | E40: =IF(E39=1,E38,0) -> 0 | F40: =IF(F39=1,F38,0) -> 1000 | G40: =IF(G39=1,G38,0) -> 0 | H40: =IF(H39=1,H38,0) -> 1000 | I40: =IF(I39=1,I38,0) -> 0 | J40: =IF(J39=1,J38,0) -> 1000 | K40: =SUM(C40:J40) -> 4000
B41: FG Inicial | C41: ='01_INPUTS_MASTER'!B70 -> 0 | D41: =C46 -> 0 | E41: =D46 -> 0 | F41: =E46 -> 0 | G41: =F46 -> 0 | H41: =G46 -> 0 | I41: =H46 -> 0 | J41: =I46 -> 0
B42: Recepciones (prod+envíos) | C42: 0 | D42: 0 | E42: 0 | F42: 0 | G42: 0 | H42: 0 | I42: 0 | J42: 0 | K42: =SUM(C42:J42) -> 0
B43: FG Disponible | C43: =C41+C42 -> 0 | D43: =D41+D42 -> 0 | E43: =E41+E42 -> 0 | F43: =F41+F42 -> 0 | G43: =G41+G42 -> 0 | H43: =H41+H42 -> 0 | I43: =I41+I42 -> 0 | J43: =J41+J42 -> 0
B44: Ventas Posibles | C44: =MIN(C40,C43) -> 0 | D44: =MIN(D40,D43) -> 0 | E44: =MIN(E40,E43) -> 0 | F44: =MIN(F40,F43) -> 0 | G44: =MIN(G40,G43) -> 0 | H44: =MIN(H40,H43) -> 0 | I44: =MIN(I40,I43) -> 0 | J44: =MIN(J40,J43) -> 0 | K44: =SUM(C44:J44) -> 0
B45: Ventas Perdidas | C45: =MAX(0,C40-C44) -> 0 | D45: =MAX(0,D40-D44) -> 1000 | E45: =MAX(0,E40-E44) -> 0 | F45: =MAX(0,F40-F44) -> 1000 | G45: =MAX(0,G40-G44) -> 0 | H45: =MAX(0,H40-H44) -> 1000 | I45: =MAX(0,I40-I44) -> 0 | J45: =MAX(0,J40-J44) -> 1000 | K45: =SUM(C45:J45) -> 4000
B46: FG Final | C46: =C43-C44 -> 0 | D46: =D43-D44 -> 0 | E46: =E43-E44 -> 0 | F46: =F43-F44 -> 0 | G46: =G43-G44 -> 0 | H46: =H43-H44 -> 0 | I46: =I43-I44 -> 0 | J46: =J43-J44 -> 0
A48: South
B49: Demanda Forecast | C49: 0 | D49: 1000 | E49: 0 | F49: 1000 | G49: 0 | H49: 1000 | I49: 0 | J49: 1000 | K49: =SUM(C49:J49) -> 4000
B50: Es Subperiodo Venta? | C50: ='01_INPUTS_MASTER'!B5 -> 0 | D50: ='01_INPUTS_MASTER'!C5 -> 1 | E50: ='01_INPUTS_MASTER'!D5 -> 0 | F50: ='01_INPUTS_MASTER'!E5 -> 1 | G50: ='01_INPUTS_MASTER'!F5 -> 0 | H50: ='01_INPUTS_MASTER'!G5 -> 1 | I50: ='01_INPUTS_MASTER'!H5 -> 0 | J50: ='01_INPUTS_MASTER'!I5 -> 1
B51: Demanda Real | C51: =IF(C50=1,C49,0) -> 0 | D51: =IF(D50=1,D49,0) -> 1000 | E51: =IF(E50=1,E49,0) -> 0 | F51: =IF(F50=1,F49,0) -> 1000 | G51: =IF(G50=1,G49,0) -> 0 | H51: =IF(H50=1,H49,0) -> 1000 | I51: =IF(I50=1,I49,0) -> 0 | J51: =IF(J50=1,J49,0) -> 1000 | K51: =SUM(C51:J51) -> 4000
B52: FG Inicial | C52: ='01_INPUTS_MASTER'!B71 -> 0 | D52: =C57 -> 0 | E52: =D57 -> 0 | F52: =E57 -> 0 | G52: =F57 -> 0 | H52: =G57 -> 0 | I52: =H57 -> 0 | J52: =I57 -> 0
B53: Recepciones (prod+envíos) | C53: 0 | D53: 0 | E53: 0 | F53: 0 | G53: 0 | H53: 0 | I53: 0 | J53: 0 | K53: =SUM(C53:J53) -> 0
B54: FG Disponible | C54: =C52+C53 -> 0 | D54: =D52+D53 -> 0 | E54: =E52+E53 -> 0 | F54: =F52+F53 -> 0 | G54: =G52+G53 -> 0 | H54: =H52+H53 -> 0 | I54: =I52+I53 -> 0 | J54: =J52+J53 -> 0
B55: Ventas Posibles | C55: =MIN(C51,C54) -> 0 | D55: =MIN(D51,D54) -> 0 | E55: =MIN(E51,E54) -> 0 | F55: =MIN(F51,F54) -> 0 | G55: =MIN(G51,G54) -> 0 | H55: =MIN(H51,H54) -> 0 | I55: =MIN(I51,I54) -> 0 | J55: =MIN(J51,J54) -> 0 | K55: =SUM(C55:J55) -> 0
B56: Ventas Perdidas | C56: =MAX(0,C51-C55) -> 0 | D56: =MAX(0,D51-D55) -> 1000 | E56: =MAX(0,E51-E55) -> 0 | F56: =MAX(0,F51-F55) -> 1000 | G56: =MAX(0,G51-G55) -> 0 | H56: =MAX(0,H51-H55) -> 1000 | I56: =MAX(0,I51-I55) -> 0 | J56: =MAX(0,J51-J55) -> 1000 | K56: =SUM(C56:J56) -> 4000
B57: FG Final | C57: =C54-C55 -> 0 | D57: =D54-D55 -> 0 | E57: =E54-E55 -> 0 | F57: =F54-F55 -> 0 | G57: =G54-G55 -> 0 | H57: =H54-H55 -> 0 | I57: =I54-I55 -> 0 | J57: =J54-J55 -> 0

Sheet 03_MPS_S5
A1: MASTER PRODUCTION SCHEDULE - SECCIÓN 5 (Electroclean)
A3: Target FG Final (colchón) | B3: 0
A5: Región | B5: Concepto | C5: S1 | D5: S2 | E5: S3 | F5: S4 | G5: S5 | H5: S6 | I5: S7 | J5: S8 | K5: TOTAL
A6: Center
B7: Demanda (de 02_DEMAND) | C7: ='02_DEMAND'!C7 -> 0 | D7: ='02_DEMAND'!D7 -> 1000 | E7: ='02_DEMAND'!E7 -> 0 | F7: ='02_DEMAND'!F7 -> 1000 | G7: ='02_DEMAND'!G7 -> 0 | H7: ='02_DEMAND'!H7 -> 1000 | I7: ='02_DEMAND'!I7 -> 0 | J7: ='02_DEMAND'!J7 -> 1000 | K7: =SUM(C7:J7) -> 4000
B8: Target FG Final | C8: =$B$3 -> 0 | D8: =$B$3 -> 0 | E8: =$B$3 -> 0 | F8: =$B$3 -> 0 | G8: =$B$3 -> 0 | H8: =$B$3 -> 0 | I8: =$B$3 -> 0 | J8: =$B$3 -> 0 | K8: =SUM(C8:J8) -> 0
B9: FG Inicial | C9: ='01_INPUTS_MASTER'!B67 -> 1737 | D9: =C8 -> 0 | E9: =D8 -> 0 | F9: =E8 -> 0 | G9: =F8 -> 0 | H9: =G8 -> 0 | I9: =H8 -> 0 | J9: =I8 -> 0 | K9: =SUM(C9:J9) -> 1737
B10: Req_S5 = Demanda + Target - FG Inicial | C10: =MAX(0,C7+C8-C9) -> 0 | D10: =MAX(0,D7+D8-D9) -> 1000 | E10: =MAX(0,E7+E8-E9) -> 0 | F10: =MAX(0,F7+F8-F9) -> 1000 | G10: =MAX(0,G7+G8-G9) -> 0 | H10: =MAX(0,H7+H8-H9) -> 1000 | I10: =MAX(0,I7+I8-I9) -> 0 | J10: =MAX(0,J7+J8-J9) -> 1000 | K10: =SUM(C10:J10) -> 4000
B11: Plan Producción S5 | C11: =C10 -> 0 | D11: =D10 -> 1000 | E11: =E10 -> 0 | F11: =F10 -> 1000 | G11: =G10 -> 0 | H11: =H10 -> 1000 | I11: =I10 -> 0 | J11: =J10 -> 1000 | K11: =SUM(C11:J11) -> 4000
A13: West
B14: Demanda (de 02_DEMAND) | C14: ='02_DEMAND'!C18 -> 0 | D14: ='02_DEMAND'!D18 -> 1000 | E14: ='02_DEMAND'!E18 -> 0 | F14: ='02_DEMAND'!F18 -> 1000 | G14: ='02_DEMAND'!G18 -> 0 | H14: ='02_DEMAND'!H18 -> 1000 | I14: ='02_DEMAND'!I18 -> 0 | J14: ='02_DEMAND'!J18 -> 1000 | K14: =SUM(C14:J14) -> 4000
B15: Target FG Final | C15: =$B$3 -> 0 | D15: =$B$3 -> 0 | E15: =$B$3 -> 0 | F15: =$B$3 -> 0 | G15: =$B$3 -> 0 | H15: =$B$3 -> 0 | I15: =$B$3 -> 0 | J15: =$B$3 -> 0 | K15: =SUM(C15:J15) -> 0
B16: FG Inicial | C16: ='01_INPUTS_MASTER'!B68 -> 1299 | D16: =C15 -> 0 | E16: =D15 -> 0 | F16: =E15 -> 0 | G16: =F15 -> 0 | H16: =G15 -> 0 | I16: =H15 -> 0 | J16: =I15 -> 0 | K16: =SUM(C16:J16) -> 1299
B17: Req_S5 = Demanda + Target - FG Inicial | C17: =MAX(0,C14+C15-C16) -> 0 | D17: =MAX(0,D14+D15-D16) -> 1000 | E17: =MAX(0,E14+E15-E16) -> 0 | F17: =MAX(0,F14+F15-F16) -> 1000 | G17: =MAX(0,G14+G15-G16) -> 0 | H17: =MAX(0,H14+H15-H16) -> 1000 | I17: =MAX(0,I14+I15-I16) -> 0 | J17: =MAX(0,J14+J15-J16) -> 1000 | K17: =SUM(C17:J17) -> 4000
B18: Plan Producción S5 | C18: =C17 -> 0 | D18: =D17 -> 1000 | E18: =E17 -> 0 | F18: =F17 -> 1000 | G18: =G17 -> 0 | H18: =H17 -> 1000 | I18: =I17 -> 0 | J18: =J17 -> 1000 | K18: =SUM(C18:J18) -> 4000
A20: North
B21: Demanda (de 02_DEMAND) | C21: ='02_DEMAND'!C29 -> 0 | D21: ='02_DEMAND'!D29 -> 1000 | E21: ='02_DEMAND'!E29 -> 0 | F21: ='02_DEMAND'!F29 -> 1000 | G21: ='02_DEMAND'!G29 -> 0 | H21: ='02_DEMAND'!H29 -> 1000 | I21: ='02_DEMAND'!I29 -> 0 | J21: ='02_DEMAND'!J29 -> 1000 | K21: =SUM(C21:J21) -> 4000
B22: Target FG Final | C22: =$B$3 -> 0 | D22: =$B$3 -> 0 | E22: =$B$3 -> 0 | F22: =$B$3 -> 0 | G22: =$B$3 -> 0 | H22: =$B$3 -> 0 | I22: =$B$3 -> 0 | J22: =$B$3 -> 0 | K22: =SUM(C22:J22) -> 0
B23: FG Inicial | C23: ='01_INPUTS_MASTER'!B69 -> 0 | D23: =C22 -> 0 | E23: =D22 -> 0 | F23: =E22 -> 0 | G23: =F22 -> 0 | H23: =G22 -> 0 | I23: =H22 -> 0 | J23: =I22 -> 0 | K23: =SUM(C23:J23) -> 0
B24: Req_S5 = Demanda + Target - FG Inicial | C24: =MAX(0,C21+C22-C23) -> 0 | D24: =MAX(0,D21+D22-D23) -> 1000 | E24: =MAX(0,E21+E22-E23) -> 0 | F24: =MAX(0,F21+F22-F23) -> 1000 | G24: =MAX(0,G21+G22-G23) -> 0 | H24: =MAX(0,H21+H22-H23) -> 1000 | I24: =MAX(0,I21+I22-I23) -> 0 | J24: =MAX(0,J21+J22-J23) -> 1000 | K24: =SUM(C24:J24) -> 4000
B25: Plan Producción S5 | C25: =C24 -> 0 | D25: =D24 -> 1000 | E25: =E24 -> 0 | F25: =F24 -> 1000 | G25: =G24 -> 0 | H25: =H24 -> 1000 | I25: =I24 -> 0 | J25: =J24 -> 1000 | K25: =SUM(C25:J25) -> 4000
A27: East
B28: Demanda (de 02_DEMAND) | C28: ='02_DEMAND'!C40 -> 0 | D28: ='02_DEMAND'!D40 -> 1000 | E28: ='02_DEMAND'!E40 -> 0 | F28: ='02_DEMAND'!F40 -> 1000 | G28: ='02_DEMAND'!G40 -> 0 | H28: ='02_DEMAND'!H40 -> 1000 | I28: ='02_DEMAND'!I40 -> 0 | J28: ='02_DEMAND'!J40 -> 1000 | K28: =SUM(C28:J28) -> 4000
B29: Target FG Final | C29: =$B$3 -> 0 | D29: =$B$3 -> 0 | E29: =$B$3 -> 0 | F29: =$B$3 -> 0 | G29: =$B$3 -> 0 | H29: =$B$3 -> 0 | I29: =$B$3 -> 0 | J29: =$B$3 -> 0 | K29: =SUM(C29:J29) -> 0
B30: FG Inicial | C30: ='01_INPUTS_MASTER'!B70 -> 0 | D30: =C29 -> 0 | E30: =D29 -> 0 | F30: =E29 -> 0 | G30: =F29 -> 0 | H30: =G29 -> 0 | I30: =H29 -> 0 | J30: =I29 -> 0 | K30: =SUM(C30:J30) -> 0
B31: Req_S5 = Demanda + Target - FG Inicial | C31: =MAX(0,C28+C29-C30) -> 0 | D31: =MAX(0,D28+D29-D30) -> 1000 | E31: =MAX(0,E28+E29-E30) -> 0 | F31: =MAX(0,F28+F29-F30) -> 1000 | G31: =MAX(0,G28+G29-G30) -> 0 | H31: =MAX(0,H28+H29-H30) -> 1000 | I31: =MAX(0,I28+I29-I30) -> 0 | J31: =MAX(0,J28+J29-J30) -> 1000 | K31: =SUM(C31:J31) -> 4000
B32: Plan Producción S5 | C32: =C31 -> 0 | D32: =D31 -> 1000 | E32: =E31 -> 0 | F32: =F31 -> 1000 | G32: =G31 -> 0 | H32: =H31 -> 1000 | I32: =I31 -> 0 | J32: =J31 -> 1000 | K32: =SUM(C32:J32) -> 4000
A34: South
B35: Demanda (de 02_DEMAND) | C35: ='02_DEMAND'!C51 -> 0 | D35: ='02_DEMAND'!D51 -> 1000 | E35: ='02_DEMAND'!E51 -> 0 | F35: ='02_DEMAND'!F51 -> 1000 | G35: ='02_DEMAND'!G51 -> 0 | H35: ='02_DEMAND'!H51 -> 1000 | I35: ='02_DEMAND'!I51 -> 0 | J35: ='02_DEMAND'!J51 -> 1000 | K35: =SUM(C35:J35) -> 4000
B36: Target FG Final | C36: =$B$3 -> 0 | D36: =$B$3 -> 0 | E36: =$B$3 -> 0 | F36: =$B$3 -> 0 | G36: =$B$3 -> 0 | H36: =$B$3 -> 0 | I36: =$B$3 -> 0 | J36: =$B$3 -> 0 | K36: =SUM(C36:J36) -> 0
B37: FG Inicial | C37: ='01_INPUTS_MASTER'!B71 -> 0 | D37: =C36 -> 0 | E37: =D36 -> 0 | F37: =E36 -> 0 | G37: =F36 -> 0 | H37: =G36 -> 0 | I37: =H36 -> 0 | J37: =I36 -> 0 | K37: =SUM(C37:J37) -> 0
B38: Req_S5 = Demanda + Target - FG Inicial | C38: =MAX(0,C35+C36-C37) -> 0 | D38: =MAX(0,D35+D36-D37) -> 1000 | E38: =MAX(0,E35+E36-E37) -> 0 | F38: =MAX(0,F35+F36-F37) -> 1000 | G38: =MAX(0,G35+G36-G37) -> 0 | H38: =MAX(0,H35+H36-H37) -> 1000 | I38: =MAX(0,I35+I36-I37) -> 0 | J38: =MAX(0,J35+J36-J37) -> 1000 | K38: =SUM(C38:J38) -> 4000
B39: Plan Producción S5 | C39: =C38 -> 0 | D39: =D38 -> 1000 | E39: =E38 -> 0 | F39: =F38 -> 1000 | G39: =G38 -> 0 | H39: =H38 -> 1000 | I39: =I38 -> 0 | J39: =J38 -> 1000 | K39: =SUM(C39:J39) -> 4000

Sheet 04_FLOW_S1_S5
A1: FLUJO DE PRODUCCIÓN POR SECCIÓN (WIP) - BACK-SCHEDULING
A3: Lead time = 1 subperiodo por sección. Plan_S4 alimenta S5, Plan_S3 alimenta S4, etc.
A5: Planta | B5: Sección | C5: Concepto | D5: S1 | E5: S2 | F5: S3 | G5: S4 | H5: S5 | I5: S6 | J5: S7 | K5: S8
A6: Center
B7: S5 | C7: Plan Producción | D7: ='03_MPS_S5'!C11 -> 0 | E7: ='03_MPS_S5'!D11 -> 1000 | F7: ='03_MPS_S5'!E11 -> 0 | G7: ='03_MPS_S5'!F11 -> 1000 | H7: ='03_MPS_S5'!G11 -> 0 | I7: ='03_MPS_S5'!H11 -> 1000 | J7: ='03_MPS_S5'!I11 -> 0 | K7: ='03_MPS_S5'!J11 -> 1000
B8: S5 | C8: Inv Inicial | D8: ='01_INPUTS_MASTER'!B67 -> 1737 | E8: =D11 -> 1737 | F8: =E11 -> 1737 | G8: =F11 -> 1737 | H8: =G11 -> 1737 | I8: =H11 -> 1737 | J8: =I11 -> 1737 | K8: =J11 -> 1737
B9: S5 | C9: Producido | D9: =D7 -> 0 | E9: =E7 -> 1000 | F9: =F7 -> 0 | G9: =G7 -> 1000 | H9: =H7 -> 0 | I9: =I7 -> 1000 | J9: =J7 -> 0 | K9: =K7 -> 1000
B10: S5 | C10: Consumido | D10: ='02_DEMAND'!C11 -> 0 | E10: ='02_DEMAND'!D11 -> 1000 | F10: ='02_DEMAND'!E11 -> 0 | G10: ='02_DEMAND'!F11 -> 1000 | H10: ='02_DEMAND'!G11 -> 0 | I10: ='02_DEMAND'!H11 -> 1000 | J10: ='02_DEMAND'!I11 -> 0 | K10: ='02_DEMAND'!J11 -> 1000
B11: S5 | C11: Inv Final | D11: =D8+D9-D10 -> 1737 | E11: =E8+E9-E10 -> 1737 | F11: =F8+F9-F10 -> 1737 | G11: =G8+G9-G10 -> 1737 | H11: =H8+H9-H10 -> 1737 | I11: =I8+I9-I10 -> 1737 | J11: =J8+J9-J10 -> 1737 | K11: =K8+K9-K10 -> 1737
B13: S4 | C13: Plan Producción | D13: =E7 -> 1000 | E13: =F7 -> 0 | F13: =G7 -> 1000 | G13: =H7 -> 0 | H13: =I7 -> 1000 | I13: =J7 -> 0 | J13: =K7 -> 1000 | K13: =0 -> 0
B14: S4 | C14: Inv Inicial | D14: ='01_INPUTS_MASTER'!C57 -> 0 | E14: =D17 -> 0 | F14: =E17 -> 0 | G14: =F17 -> 0 | H14: =G17 -> 0 | I14: =H17 -> 0 | J14: =I17 -> 0 | K14: =J17 -> 0
B15: S4 | C15: Producido | D15: =D13 -> 1000 | E15: =E13 -> 0 | F15: =F13 -> 1000 | G15: =G13 -> 0 | H15: =H13 -> 1000 | I15: =I13 -> 0 | J15: =J13 -> 1000 | K15: =K13 -> 0
B16: S4 | C16: Consumido | D16: =E7 -> 1000 | E16: =F7 -> 0 | F16: =G7 -> 1000 | G16: =H7 -> 0 | H16: =I7 -> 1000 | I16: =J7 -> 0 | J16: =K7 -> 1000 | K16: =0 -> 0
B17: S4 | C17: Inv Final | D17: =D14+D15-D16 -> 0 | E17: =E14+E15-E16 -> 0 | F17: =F14+F15-F16 -> 0 | G17: =G14+G15-G16 -> 0 | H17: =H14+H15-H16 -> 0 | I17: =I14+I15-I16 -> 0 | J17: =J14+J15-J16 -> 0 | K17: =K14+K15-K16 -> 0
B19: S3 | C19: Plan Producción | D19: =E13 -> 0 | E19: =F13 -> 1000 | F19: =G13 -> 0 | G19: =H13 -> 1000 | H19: =I13 -> 0 | I19: =J13 -> 1000 | J19: =K13 -> 0 | K19: =0 -> 0
B20: S3 | C20: Inv Inicial | D20: ='01_INPUTS_MASTER'!C56 -> 6682 | E20: =D23 -> 6682 | F20: =E23 -> 6682 | G20: =F23 -> 6682 | H20: =G23 -> 6682 | I20: =H23 -> 6682 | J20: =I23 -> 6682 | K20: =J23 -> 6682
B21: S3 | C21: Producido | D21: =D19 -> 0 | E21: =E19 -> 1000 | F21: =F19 -> 0 | G21: =G19 -> 1000 | H21: =H19 -> 0 | I21: =I19 -> 1000 | J21: =J19 -> 0 | K21: =K19 -> 0
B22: S3 | C22: Consumido | D22: =E13 -> 0 | E22: =F13 -> 1000 | F22: =G13 -> 0 | G22: =H13 -> 1000 | H22: =I13 -> 0 | I22: =J13 -> 1000 | J22: =K13 -> 0 | K22: =0 -> 0
B23: S3 | C23: Inv Final | D23: =D20+D21-D22 -> 6682 | E23: =E20+E21-E22 -> 6682 | F23: =F20+F21-F22 -> 6682 | G23: =G20+G21-G22 -> 6682 | H23: =H20+H21-H22 -> 6682 | I23: =I20+I21-I22 -> 6682 | J23: =J20+J21-J22 -> 6682 | K23: =K20+K21-K22 -> 6682
B25: S2 | C25: Plan Producción | D25: =E19 -> 1000 | E25: =F19 -> 0 | F25: =G19 -> 1000 | G25: =H19 -> 0 | H25: =I19 -> 1000 | I25: =J19 -> 0 | J25: =K19 -> 0 | K25: =0 -> 0
B26: S2 | C26: Inv Inicial | D26: ='01_INPUTS_MASTER'!C55 -> 6528 | E26: =D29 -> 6528 | F26: =E29 -> 6528 | G26: =F29 -> 6528 | H26: =G29 -> 6528 | I26: =H29 -> 6528 | J26: =I29 -> 6528 | K26: =J29 -> 6528
B27: S2 | C27: Producido | D27: =D25 -> 1000 | E27: =E25 -> 0 | F27: =F25 -> 1000 | G27: =G25 -> 0 | H27: =H25 -> 1000 | I27: =I25 -> 0 | J27: =J25 -> 0 | K27: =K25 -> 0
B28: S2 | C28: Consumido | D28: =E19 -> 1000 | E28: =F19 -> 0 | F28: =G19 -> 1000 | G28: =H19 -> 0 | H28: =I19 -> 1000 | I28: =J19 -> 0 | J28: =K19 -> 0 | K28: =0 -> 0
B29: S2 | C29: Inv Final | D29: =D26+D27-D28 -> 6528 | E29: =E26+E27-E28 -> 6528 | F29: =F26+F27-F28 -> 6528 | G29: =G26+G27-G28 -> 6528 | H29: =H26+H27-H28 -> 6528 | I29: =I26+I27-I28 -> 6528 | J29: =J26+J27-J28 -> 6528 | K29: =K26+K27-K28 -> 6528
B31: S1 | C31: Plan Producción | D31: =E19 -> 1000 | E31: =F19 -> 0 | F31: =G19 -> 1000 | G31: =H19 -> 0 | H31: =I19 -> 1000 | I31: =J19 -> 0 | J31: =K19 -> 0 | K31: =0 -> 0
B32: S1 | C32: Inv Inicial | D32: ='01_INPUTS_MASTER'!C54 -> 7432 | E32: =D35 -> 7432 | F32: =E35 -> 7432 | G32: =F35 -> 7432 | H32: =G35 -> 7432 | I32: =H35 -> 7432 | J32: =I35 -> 7432 | K32: =J35 -> 7432
B33: S1 | C33: Producido | D33: =D31 -> 1000 | E33: =E31 -> 0 | F33: =F31 -> 1000 | G33: =G31 -> 0 | H33: =H31 -> 1000 | I33: =I31 -> 0 | J33: =J31 -> 0 | K33: =K31 -> 0
B34: S1 | C34: Consumido | D34: =E19 -> 1000 | E34: =F19 -> 0 | F34: =G19 -> 1000 | G34: =H19 -> 0 | H34: =I19 -> 1000 | I34: =J19 -> 0 | J34: =K19 -> 0 | K34: =0 -> 0
B35: S1 | C35: Inv Final | D35: =D32+D33-D34 -> 7432 | E35: =E32+E33-E34 -> 7432 | F35: =F32+F33-F34 -> 7432 | G35: =G32+G33-G34 -> 7432 | H35: =H32+H33-H34 -> 7432 | I35: =I32+I33-I34 -> 7432 | J35: =J32+J33-J34 -> 7432 | K35: =K32+K33-K34 -> 7432
A37: West
B38: S5 | C38: Plan Producción | D38: ='03_MPS_S5'!C18 -> 0 | E38: ='03_MPS_S5'!D18 -> 1000 | F38: ='03_MPS_S5'!E18 -> 0 | G38: ='03_MPS_S5'!F18 -> 1000 | H38: ='03_MPS_S5'!G18 -> 0 | I38: ='03_MPS_S5'!H18 -> 1000 | J38: ='03_MPS_S5'!I18 -> 0 | K38: ='03_MPS_S5'!J18 -> 1000
B39: S5 | C39: Inv Inicial | D39: ='01_INPUTS_MASTER'!B68 -> 1299 | E39: =D42 -> 1299 | F39: =E42 -> 1299 | G39: =F42 -> 1299 | H39: =G42 -> 1299 | I39: =H42 -> 1299 | J39: =I42 -> 1299 | K39: =J42 -> 1299
B40: S5 | C40: Producido | D40: =D38 -> 0 | E40: =E38 -> 1000 | F40: =F38 -> 0 | G40: =G38 -> 1000 | H40: =H38 -> 0 | I40: =I38 -> 1000 | J40: =J38 -> 0 | K40: =K38 -> 1000
B41: S5 | C41: Consumido | D41: ='02_DEMAND'!C22 -> 0 | E41: ='02_DEMAND'!D22 -> 1000 | F41: ='02_DEMAND'!E22 -> 0 | G41: ='02_DEMAND'!F22 -> 1000 | H41: ='02_DEMAND'!G22 -> 0 | I41: ='02_DEMAND'!H22 -> 1000 | J41: ='02_DEMAND'!I22 -> 0 | K41: ='02_DEMAND'!J22 -> 1000
B42: S5 | C42: Inv Final | D42: =D39+D40-D41 -> 1299 | E42: =E39+E40-E41 -> 1299 | F42: =F39+F40-F41 -> 1299 | G42: =G39+G40-G41 -> 1299 | H42: =H39+H40-H41 -> 1299 | I42: =I39+I40-I41 -> 1299 | J42: =J39+J40-J41 -> 1299 | K42: =K39+K40-K41 -> 1299
B44: S4 | C44: Plan Producción | D44: =E38 -> 1000 | E44: =F38 -> 0 | F44: =G38 -> 1000 | G44: =H38 -> 0 | H44: =I38 -> 1000 | I44: =J38 -> 0 | J44: =K38 -> 1000 | K44: =0 -> 0
B45: S4 | C45: Inv Inicial | D45: ='01_INPUTS_MASTER'!D57 -> 0 | E45: =D48 -> 0 | F45: =E48 -> 0 | G45: =F48 -> 0 | H45: =G48 -> 0 | I45: =H48 -> 0 | J45: =I48 -> 0 | K45: =J48 -> 0
B46: S4 | C46: Producido | D46: =D44 -> 1000 | E46: =E44 -> 0 | F46: =F44 -> 1000 | G46: =G44 -> 0 | H46: =H44 -> 1000 | I46: =I44 -> 0 | J46: =J44 -> 1000 | K46: =K44 -> 0
B47: S4 | C47: Consumido | D47: =E38 -> 1000 | E47: =F38 -> 0 | F47: =G38 -> 1000 | G47: =H38 -> 0 | H47: =I38 -> 1000 | I47: =J38 -> 0 | J47: =K38 -> 1000 | K47: =0 -> 0
B48: S4 | C48: Inv Final | D48: =D45+D46-D47 -> 0 | E48: =E45+E46-E47 -> 0 | F48: =F45+F46-F47 -> 0 | G48: =G45+G46-G47 -> 0 | H48: =H45+H46-H47 -> 0 | I48: =I45+I46-I47 -> 0 | J48: =J45+J46-J47 -> 0 | K48: =K45+K46-K47 -> 0
B50: S3 | C50: Plan Producción | D50: =E44 -> 0 | E50: =F44 -> 1000 | F50: =G44 -> 0 | G50: =H44 -> 1000 | H50: =I44 -> 0 | I50: =J44 -> 1000 | J50: =K44 -> 0 | K50: =0 -> 0
B51: S3 | C51: Inv Inicial | D51: ='01_INPUTS_MASTER'!D56 -> 0 | E51: =D54 -> 0 | F51: =E54 -> 0 | G51: =F54 -> 0 | H51: =G54 -> 0 | I51: =H54 -> 0 | J51: =I54 -> 0 | K51: =J54 -> 0
B52: S3 | C52: Producido | D52: =D50 -> 0 | E52: =E50 -> 1000 | F52: =F50 -> 0 | G52: =G50 -> 1000 | H52: =H50 -> 0 | I52: =I50 -> 1000 | J52: =J50 -> 0 | K52: =K50 -> 0
B53: S3 | C53: Consumido | D53: =E44 -> 0 | E53: =F44 -> 1000 | F53: =G44 -> 0 | G53: =H44 -> 1000 | H53: =I44 -> 0 | I53: =J44 -> 1000 | J53: =K44 -> 0 | K53: =0 -> 0
B54: S3 | C54: Inv Final | D54: =D51+D52-D53 -> 0 | E54: =E51+E52-E53 -> 0 | F54: =F51+F52-F53 -> 0 | G54: =G51+G52-G53 -> 0 | H54: =H51+H52-H53 -> 0 | I54: =I51+I52-I53 -> 0 | J54: =J51+J52-J53 -> 0 | K54: =K51+K52-K53 -> 0
B56: S2 | C56: Plan Producción | D56: =E50 -> 1000 | E56: =F50 -> 0 | F56: =G50 -> 1000 | G56: =H50 -> 0 | H56: =I50 -> 1000 | I56: =J50 -> 0 | J56: =K50 -> 0 | K56: =0 -> 0
B57: S2 | C57: Inv Inicial | D57: ='01_INPUTS_MASTER'!D55 -> 0 | E57: =D60 -> 0 | F57: =E60 -> 0 | G57: =F60 -> 0 | H57: =G60 -> 0 | I57: =H60 -> 0 | J57: =I60 -> 0 | K57: =J60 -> 0
B58: S2 | C58: Producido | D58: =D56 -> 1000 | E58: =E56 -> 0 | F58: =F56 -> 1000 | G58: =G56 -> 0 | H58: =H56 -> 1000 | I58: =I56 -> 0 | J58: =J56 -> 0 | K58: =K56 -> 0
B59: S2 | C59: Consumido | D59: =E50 -> 1000 | E59: =F50 -> 0 | F59: =G50 -> 1000 | G59: =H50 -> 0 | H59: =I50 -> 1000 | I59: =J50 -> 0 | J59: =K50 -> 0 | K59: =0 -> 0
B60: S2 | C60: Inv Final | D60: =D57+D58-D59 -> 0 | E60: =E57+E58-E59 -> 0 | F60: =F57+F58-F59 -> 0 | G60: =G57+G58-G59 -> 0 | H60: =H57+H58-H59 -> 0 | I60: =I57+I58-I59 -> 0 | J60: =J57+J58-J59 -> 0 | K60: =K57+K58-K59 -> 0
B62: S1 | C62: Plan Producción | D62: =E50 -> 1000 | E62: =F50 -> 0 | F62: =G50 -> 1000 | G62: =H50 -> 0 | H62: =I50 -> 1000 | I62: =J50 -> 0 | J62: =K50 -> 0 | K62: =0 -> 0
B63: S1 | C63: Inv Inicial | D63: ='01_INPUTS_MASTER'!D54 -> 3622 | E63: =D66 -> 3622 | F63: =E66 -> 3622 | G63: =F66 -> 3622 | H63: =G66 -> 3622 | I63: =H66 -> 3622 | J63: =I66 -> 3622 | K63: =J66 -> 3622
B64: S1 | C64: Producido | D64: =D62 -> 1000 | E64: =E62 -> 0 | F64: =F62 -> 1000 | G64: =G62 -> 0 | H64: =H62 -> 1000 | I64: =I62 -> 0 | J64: =J62 -> 0 | K64: =K62 -> 0
B65: S1 | C65: Consumido | D65: =E50 -> 1000 | E65: =F50 -> 0 | F65: =G50 -> 1000 | G65: =H50 -> 0 | H65: =I50 -> 1000 | I65: =J50 -> 0 | J65: =K50 -> 0 | K65: =0 -> 0
B66: S1 | C66: Inv Final | D66: =D63+D64-D65 -> 3622 | E66: =E63+E64-E65 -> 3622 | F66: =F63+F64-F65 -> 3622 | G66: =G63+G64-G65 -> 3622 | H66: =H63+H64-H65 -> 3622 | I66: =I63+I64-I65 -> 3622 | J66: =J63+J64-J65 -> 3622 | K66: =K63+K64-K65 -> 3622

Sheet 05_CAPACITY
A1: ANÁLISIS DE CAPACIDAD POR PLANTA, SECCIÓN Y SUBPERIODO
A3: Planta | B3: Sección | C3: Concepto | D3: S1 | E3: S2 | F3: S3 | G3: S4 | H3: S5 | I3: S6 | J3: S7 | K3: S8
A4: Center
B5: S1 | C5: # Máquinas | D5: ='01_INPUTS_MASTER'!H17 -> 7 | E5: 0 | F5: 0 | G5: 0 | H5: 0 | I5: 0 | J5: 0 | K5: 0
B6: S1 | C6: Capacidad/Máquina | D6: ='01_INPUTS_MASTER'!B17 -> 200 | E6: 0 | F6: 0 | G6: 0 | H6: 0 | I6: 0 | J6: 0 | K6: 0
B7: S1 | C7: Capacidad Máquinas | D7: =D5*D6 -> 1400 | E7: =E5*E6 -> 0 | F7: =F5*F6 -> 0 | G7: =G5*G6 -> 0 | H7: =H5*H6 -> 0 | I7: =I5*I6 -> 0 | J7: =J5*J6 -> 0 | K7: =K5*K6 -> 0
B8: S1 | C8: # Workers | D8: ='10_DECISIONS_UPLOAD'!C13 -> 7 | E8: 0 | F8: 0 | G8: 0 | H8: 0 | I8: 0 | J8: 0 | K8: 0
B9: S1 | C9: Workers/Máquina req | D9: ='01_INPUTS_MASTER'!G17 -> 1 | E9: 0 | F9: 0 | G9: 0 | H9: 0 | I9: 0 | J9: 0 | K9: 0
B10: S1 | C10: Capacidad Labor | D10: =IF(D9>0,D8/D9*D6,0) -> 1400 | E10: =IF(E9>0,E8/E9*E6,0) -> 0 | F10: =IF(F9>0,F8/F9*F6,0) -> 0 | G10: =IF(G9>0,G8/G9*G6,0) -> 0 | H10: =IF(H9>0,H8/H9*H6,0) -> 0 | I10: =IF(I9>0,I8/I9*I6,0) -> 0 | J10: =IF(J9>0,J8/J9*J6,0) -> 0 | K10: =IF(K9>0,K8/K9*K6,0) -> 0
B11: S1 | C11: Capacidad Base (MIN) | D11: =MIN(D7,D10) -> 1400 | E11: =MIN(E7,E10) -> 0 | F11: =MIN(F7,F10) -> 0 | G11: =MIN(G7,G10) -> 0 | H11: =MIN(H7,H10) -> 0 | I11: =MIN(I7,I10) -> 0 | J11: =MIN(J7,J10) -> 0 | K11: =MIN(K7,K10) -> 0
B12: S1 | C12: Overtime (0/1) | D12: ='10_DECISIONS_UPLOAD'!C30 -> 0 | E12: ='10_DECISIONS_UPLOAD'!D30 -> 0 | F12: ='10_DECISIONS_UPLOAD'!E30 -> 0 | G12: ='10_DECISIONS_UPLOAD'!F30 -> 0 | H12: ='10_DECISIONS_UPLOAD'!G30 -> 0 | I12: ='10_DECISIONS_UPLOAD'!H30 -> 0 | J12: ='10_DECISIONS_UPLOAD'!I30 -> 0 | K12: ='10_DECISIONS_UPLOAD'!J30 -> 0
B13: S1 | C13: Capacidad c/Overtime | D13: =D11*(1+0.2*D12) -> 1400 | E13: =E11*(1+0.2*E12) -> 0 | F13: =F11*(1+0.2*F12) -> 0 | G13: =G11*(1+0.2*G12) -> 0 | H13: =H11*(1+0.2*H12) -> 0 | I13: =I11*(1+0.2*I12) -> 0 | J13: =J11*(1+0.2*J12) -> 0 | K13: =K11*(1+0.2*K12) -> 0
B14: S1 | C14: Plan Producción | D14: ='04_FLOW_S1_S5'!D31 -> 1000 | E14: ='04_FLOW_S1_S5'!E31 -> 0 | F14: ='04_FLOW_S1_S5'!F31 -> 1000 | G14: ='04_FLOW_S1_S5'!G31 -> 0 | H14: ='04_FLOW_S1_S5'!H31 -> 1000 | I14: ='04_FLOW_S1_S5'!I31 -> 0 | J14: ='04_FLOW_S1_S5'!J31 -> 0 | K14: ='04_FLOW_S1_S5'!K31 -> 0
B15: S1 | C15: Producción Real | D15: =MIN(D13,D14) -> 1000 | E15: =MIN(E13,E14) -> 0 | F15: =MIN(F13,F14) -> 0 | G15: =MIN(G13,G14) -> 0 | H15: =MIN(H13,H14) -> 0 | I15: =MIN(I13,I14) -> 0 | J15: =MIN(J13,J14) -> 0 | K15: =MIN(K13,K14) -> 0
B16: S1 | C16: Bottleneck | D16: =IF(D14>D13,"CAPACITY","OK") -> OK | E16: =IF(E14>E13,"CAPACITY","OK") -> OK | F16: =IF(F14>F13,"CAPACITY","OK") -> CAPACITY | G16: =IF(G14>G13,"CAPACITY","OK") -> OK | H16: =IF(H14>H13,"CAPACITY","OK") -> CAPACITY | I16: =IF(I14>I13,"CAPACITY","OK") -> OK | J16: =IF(J14>J13,"CAPACITY","OK") -> OK | K16: =IF(K14>K13,"CAPACITY","OK") -> OK
B18: S2 | C18: # Máquinas | D18: ='01_INPUTS_MASTER'!H18 -> 22 | E18: 0 | F18: 0 | G18: 0 | H18: 0 | I18: 0 | J18: 0 | K18: 0
B19: S2 | C19: Capacidad/Máquina | D19: ='01_INPUTS_MASTER'!B18 -> 70 | E19: 0 | F19: 0 | G19: 0 | H19: 0 | I19: 0 | J19: 0 | K19: 0
B20: S2 | C20: Capacidad Máquinas | D20: =D18*D19 -> 1540 | E20: =E18*E19 -> 0 | F20: =F18*F19 -> 0 | G20: =G18*G19 -> 0 | H20: =H18*H19 -> 0 | I20: =I18*I19 -> 0 | J20: =J18*J19 -> 0 | K20: =K18*K19 -> 0
B21: S2 | C21: # Workers | D21: ='10_DECISIONS_UPLOAD'!C14 -> 22 | E21: 0 | F21: 0 | G21: 0 | H21: 0 | I21: 0 | J21: 0 | K21: 0
B22: S2 | C22: Workers/Máquina req | D22: ='01_INPUTS_MASTER'!G18 -> 1 | E22: 0 | F22: 0 | G22: 0 | H22: 0 | I22: 0 | J22: 0 | K22: 0
B23: S2 | C23: Capacidad Labor | D23: =IF(D22>0,D21/D22*D19,0) -> 1540 | E23: =IF(E22>0,E21/E22*E19,0) -> 0 | F23: =IF(F22>0,F21/F22*F19,0) -> 0 | G23: =IF(G22>0,G21/G22*G19,0) -> 0 | H23: =IF(H22>0,H21/H22*H19,0) -> 0 | I23: =IF(I22>0,I21/I22*I19,0) -> 0 | J23: =IF(J22>0,J21/J22*J19,0) -> 0 | K23: =IF(K22>0,K21/K22*K19,0) -> 0
B24: S2 | C24: Capacidad Base (MIN) | D24: =MIN(D20,D23) -> 1540 | E24: =MIN(E20,E23) -> 0 | F24: =MIN(F20,F23) -> 0 | G24: =MIN(G20,G23) -> 0 | H24: =MIN(H20,H23) -> 0 | I24: =MIN(I20,I23) -> 0 | J24: =MIN(J20,J23) -> 0 | K24: =MIN(K20,K23) -> 0
B25: S2 | C25: Overtime (0/1) | D25: ='10_DECISIONS_UPLOAD'!C31 -> 0 | E25: ='10_DECISIONS_UPLOAD'!D31 -> 0 | F25: ='10_DECISIONS_UPLOAD'!E31 -> 0 | G25: ='10_DECISIONS_UPLOAD'!F31 -> 0 | H25: ='10_DECISIONS_UPLOAD'!G31 -> 0 | I25: ='10_DECISIONS_UPLOAD'!H31 -> 0 | J25: ='10_DECISIONS_UPLOAD'!I31 -> 0 | K25: ='10_DECISIONS_UPLOAD'!J31 -> 0
B26: S2 | C26: Capacidad c/Overtime | D26: =D24*(1+0.2*D25) -> 1540 | E26: =E24*(1+0.2*E25) -> 0 | F26: =F24*(1+0.2*F25) -> 0 | G26: =G24*(1+0.2*G25) -> 0 | H26: =H24*(1+0.2*H25) -> 0 | I26: =I24*(1+0.2*I25) -> 0 | J26: =J24*(1+0.2*J25) -> 0 | K26: =K24*(1+0.2*K25) -> 0
B27: S2 | C27: Plan Producción | D27: ='04_FLOW_S1_S5'!D25 -> 1000 | E27: ='04_FLOW_S1_S5'!E25 -> 0 | F27: ='04_FLOW_S1_S5'!F25 -> 1000 | G27: ='04_FLOW_S1_S5'!G25 -> 0 | H27: ='04_FLOW_S1_S5'!H25 -> 1000 | I27: ='04_FLOW_S1_S5'!I25 -> 0 | J27: ='04_FLOW_S1_S5'!J25 -> 0 | K27: ='04_FLOW_S1_S5'!K25 -> 0
B28: S2 | C28: Producción Real | D28: =MIN(D26,D27) -> 1000 | E28: =MIN(E26,E27) -> 0 | F28: =MIN(F26,F27) -> 0 | G28: =MIN(G26,G27) -> 0 | H28: =MIN(H26,H27) -> 0 | I28: =MIN(I26,I27) -> 0 | J28: =MIN(J26,J27) -> 0 | K28: =MIN(K26,K27) -> 0
B29: S2 | C29: Bottleneck | D29: =IF(D27>D26,"CAPACITY","OK") -> OK | E29: =IF(E27>E26,"CAPACITY","OK") -> OK | F29: =IF(F27>F26,"CAPACITY","OK") -> CAPACITY | G29: =IF(G27>G26,"CAPACITY","OK") -> OK | H29: =IF(H27>H26,"CAPACITY","OK") -> CAPACITY | I29: =IF(I27>I26,"CAPACITY","OK") -> OK | J29: =IF(J27>J26,"CAPACITY","OK") -> OK | K29: =IF(K27>K26,"CAPACITY","OK") -> OK
B31: S3 | C31: # Máquinas | D31: ='01_INPUTS_MASTER'!H19+'01_INPUTS_MASTER'!H20 -> 3 | E31: 0 | F31: 0 | G31: 0 | H31: 0 | I31: 0 | J31: 0 | K31: 0
B32: S3 | C32: Capacidad/Máquina | D32: =IF(('01_INPUTS_MASTER'!H19+'01_INPUTS_MASTER'!H20)>0,('01_INPUTS_MASTER'!H19*'01_INPUTS_MASTER'!B19+'01_INPUTS_MASTER'!H20*'01_INPUTS_MASTER'!B20)/('01_INPUTS_MASTER'!H19+'01_INPUTS_MASTER'!H20),0) -> 450 | E32: 0 | F32: 0 | G32: 0 | H32: 0 | I32: 0 | J32: 0 | K32: 0
B33: S3 | C33: Capacidad Máquinas | D33: =MIN('01_INPUTS_MASTER'!H19*'01_INPUTS_MASTER'!B19+'01_INPUTS_MASTER'!H20*'01_INPUTS_MASTER'!B20,'01_INPUTS_MASTER'!H21*'01_INPUTS_MASTER'!B21) -> 1350 | E33: =E31*E32 -> 0 | F33: =F31*F32 -> 0 | G33: =G31*G32 -> 0 | H33: =H31*H32 -> 0 | I33: =I31*I32 -> 0 | J33: =J31*J32 -> 0 | K33: =K31*K32 -> 0
B34: S3 | C34: # Workers | D34: ='10_DECISIONS_UPLOAD'!C15 -> 90 | E34: 0 | F34: 0 | G34: 0 | H34: 0 | I34: 0 | J34: 0 | K34: 0
B35: S3 | C35: Workers/Máquina req | D35: ='01_INPUTS_MASTER'!G19 -> 30 | E35: 0 | F35: 0 | G35: 0 | H35: 0 | I35: 0 | J35: 0 | K35: 0
B36: S3 | C36: Capacidad Labor | D36: =IF(D35>0,D34/D35*D32,0) -> 1350 | E36: =IF(E35>0,E34/E35*E32,0) -> 0 | F36: =IF(F35>0,F34/F35*F32,0) -> 0 | G36: =IF(G35>0,G34/G35*G32,0) -> 0 | H36: =IF(H35>0,H34/H35*H32,0) -> 0 | I36: =IF(I35>0,I34/I35*I32,0) -> 0 | J36: =IF(J35>0,J34/J35*J32,0) -> 0 | K36: =IF(K35>0,K34/K35*K32,0) -> 0
B37: S3 | C37: Capacidad Base (MIN) | D37: =MIN(D33,D36) -> 1350 | E37: =MIN(E33,E36) -> 0 | F37: =MIN(F33,F36) -> 0 | G37: =MIN(G33,G36) -> 0 | H37: =MIN(H33,H36) -> 0 | I37: =MIN(I33,I36) -> 0 | J37: =MIN(J33,J36) -> 0 | K37: =MIN(K33,K36) -> 0
B38: S3 | C38: Overtime (0/1) | D38: ='10_DECISIONS_UPLOAD'!C32 -> 0 | E38: ='10_DECISIONS_UPLOAD'!D32 -> 0 | F38: ='10_DECISIONS_UPLOAD'!E32 -> 0 | G38: ='10_DECISIONS_UPLOAD'!F32 -> 0 | H38: ='10_DECISIONS_UPLOAD'!G32 -> 0 | I38: ='10_DECISIONS_UPLOAD'!H32 -> 0 | J38: ='10_DECISIONS_UPLOAD'!I32 -> 0 | K38: ='10_DECISIONS_UPLOAD'!J32 -> 0
B39: S3 | C39: Capacidad c/Overtime | D39: =D37*(1+0.2*D38) -> 1350 | E39: =E37*(1+0.2*E38) -> 0 | F39: =F37*(1+0.2*F38) -> 0 | G39: =G37*(1+0.2*G38) -> 0 | H39: =H37*(1+0.2*H38) -> 0 | I39: =I37*(1+0.2*I38) -> 0 | J39: =J37*(1+0.2*J38) -> 0 | K39: =K37*(1+0.2*K38) -> 0
B40: S3 | C40: Plan Producción | D40: ='04_FLOW_S1_S5'!D19 -> 0 | E40: ='04_FLOW_S1_S5'!E19 -> 1000 | F40: ='04_FLOW_S1_S5'!F19 -> 0 | G40: ='04_FLOW_S1_S5'!G19 -> 1000 | H40: ='04_FLOW_S1_S5'!H19 -> 0 | I40: ='04_FLOW_S1_S5'!I19 -> 1000 | J40: ='04_FLOW_S1_S5'!J19 -> 0 | K40: ='04_FLOW_S1_S5'!K19 -> 0
B41: S3 | C41: Producción Real | D41: =MIN(D39,D40) -> 0 | E41: =MIN(E39,E40) -> 0 | F41: =MIN(F39,F40) -> 0 | G41: =MIN(G39,G40) -> 0 | H41: =MIN(H39,H40) -> 0 | I41: =MIN(I39,I40) -> 0 | J41: =MIN(J39,J40) -> 0 | K41: =MIN(K39,K40) -> 0
B42: S3 | C42: Bottleneck | D42: =IF(D40>D39,"CAPACITY","OK") -> OK | E42: =IF(E40>E39,"CAPACITY","OK") -> CAPACITY | F42: =IF(F40>F39,"CAPACITY","OK") -> OK | G42: =IF(G40>G39,"CAPACITY","OK") -> CAPACITY | H42: =IF(H40>H39,"CAPACITY","OK") -> OK | I42: =IF(I40>I39,"CAPACITY","OK") -> CAPACITY | J42: =IF(J40>J39,"CAPACITY","OK") -> OK | K42: =IF(K40>K39,"CAPACITY","OK") -> OK
B44: S4 | C44: # Máquinas | D44: ='01_INPUTS_MASTER'!H22 -> 10 | E44: 0 | F44: 0 | G44: 0 | H44: 0 | I44: 0 | J44: 0 | K44: 0
B45: S4 | C45: Capacidad/Máquina | D45: ='01_INPUTS_MASTER'!B22 -> 150 | E45: 0 | F45: 0 | G45: 0 | H45: 0 | I45: 0 | J45: 0 | K45: 0
B46: S4 | C46: Capacidad Máquinas | D46: =D44*D45 -> 1500 | E46: =E44*E45 -> 0 | F46: =F44*F45 -> 0 | G46: =G44*G45 -> 0 | H46: =H44*H45 -> 0 | I46: =I44*I45 -> 0 | J46: =J44*J45 -> 0 | K46: =K44*K45 -> 0
B47: S4 | C47: # Workers | D47: ='10_DECISIONS_UPLOAD'!C17 -> 10 | E47: 0 | F47: 0 | G47: 0 | H47: 0 | I47: 0 | J47: 0 | K47: 0
B48: S4 | C48: Workers/Máquina req | D48: ='01_INPUTS_MASTER'!G22 -> 1 | E48: 0 | F48: 0 | G48: 0 | H48: 0 | I48: 0 | J48: 0 | K48: 0
B49: S4 | C49: Capacidad Labor | D49: =IF(D48>0,D47/D48*D45,0) -> 1500 | E49: =IF(E48>0,E47/E48*E45,0) -> 0 | F49: =IF(F48>0,F47/F48*F45,0) -> 0 | G49: =IF(G48>0,G47/G48*G45,0) -> 0 | H49: =IF(H48>0,H47/H48*H45,0) -> 0 | I49: =IF(I48>0,I47/I48*I45,0) -> 0 | J49: =IF(J48>0,J47/J48*J45,0) -> 0 | K49: =IF(K48>0,K47/K48*K45,0) -> 0
B50: S4 | C50: Capacidad Base (MIN) | D50: =MIN(D46,D49) -> 1500 | E50: =MIN(E46,E49) -> 0 | F50: =MIN(F46,F49) -> 0 | G50: =MIN(G46,G49) -> 0 | H50: =MIN(H46,H49) -> 0 | I50: =MIN(I46,I49) -> 0 | J50: =MIN(J46,J49) -> 0 | K50: =MIN(K46,K49) -> 0
B51: S4 | C51: Overtime (0/1) | D51: ='10_DECISIONS_UPLOAD'!C33 -> 0 | E51: ='10_DECISIONS_UPLOAD'!D33 -> 0 | F51: ='10_DECISIONS_UPLOAD'!E33 -> 0 | G51: ='10_DECISIONS_UPLOAD'!F33 -> 0 | H51: ='10_DECISIONS_UPLOAD'!G33 -> 0 | I51: ='10_DECISIONS_UPLOAD'!H33 -> 0 | J51: ='10_DECISIONS_UPLOAD'!I33 -> 0 | K51: ='10_DECISIONS_UPLOAD'!J33 -> 0
B52: S4 | C52: Capacidad c/Overtime | D52: =D50*(1+0.2*D51) -> 1500 | E52: =E50*(1+0.2*E51) -> 0 | F52: =F50*(1+0.2*F51) -> 0 | G52: =G50*(1+0.2*G51) -> 0 | H52: =H50*(1+0.2*H51) -> 0 | I52: =I50*(1+0.2*I51) -> 0 | J52: =J50*(1+0.2*J51) -> 0 | K52: =K50*(1+0.2*K51) -> 0
B53: S4 | C53: Plan Producción | D53: ='04_FLOW_S1_S5'!D13 -> 1000 | E53: ='04_FLOW_S1_S5'!E13 -> 0 | F53: ='04_FLOW_S1_S5'!F13 -> 1000 | G53: ='04_FLOW_S1_S5'!G13 -> 0 | H53: ='04_FLOW_S1_S5'!H13 -> 1000 | I53: ='04_FLOW_S1_S5'!I13 -> 0 | J53: ='04_FLOW_S1_S5'!J13 -> 1000 | K53: ='04_FLOW_S1_S5'!K13 -> 0
B54: S4 | C54: Producción Real | D54: =MIN(D52,D53) -> 1000 | E54: =MIN(E52,E53) -> 0 | F54: =MIN(F52,F53) -> 0 | G54: =MIN(G52,G53) -> 0 | H54: =MIN(H52,H53) -> 0 | I54: =MIN(I52,I53) -> 0 | J54: =MIN(J52,J53) -> 0 | K54: =MIN(K52,K53) -> 0
B55: S4 | C55: Bottleneck | D55: =IF(D53>D52,"CAPACITY","OK") -> OK | E55: =IF(E53>E52,"CAPACITY","OK") -> OK | F55: =IF(F53>F52,"CAPACITY","OK") -> CAPACITY | G55: =IF(G53>G52,"CAPACITY","OK") -> OK | H55: =IF(H53>H52,"CAPACITY","OK") -> CAPACITY | I55: =IF(I53>I52,"CAPACITY","OK") -> OK | J55: =IF(J53>J52,"CAPACITY","OK") -> CAPACITY | K55: =IF(K53>K52,"CAPACITY","OK") -> OK
B57: S5 | C57: # Máquinas | D57: ='01_INPUTS_MASTER'!H23 -> 11 | E57: 0 | F57: 0 | G57: 0 | H57: 0 | I57: 0 | J57: 0 | K57: 0
B58: S5 | C58: Capacidad/Máquina | D58: ='01_INPUTS_MASTER'!B23 -> 130 | E58: 0 | F58: 0 | G58: 0 | H58: 0 | I58: 0 | J58: 0 | K58: 0
B59: S5 | C59: Capacidad Máquinas | D59: =D57*D58 -> 1430 | E59: =E57*E58 -> 0 | F59: =F57*F58 -> 0 | G59: =G57*G58 -> 0 | H59: =H57*H58 -> 0 | I59: =I57*I58 -> 0 | J59: =J57*J58 -> 0 | K59: =K57*K58 -> 0
B60: S5 | C60: # Workers | D60: ='10_DECISIONS_UPLOAD'!C19 -> 75 | E60: 0 | F60: 0 | G60: 0 | H60: 0 | I60: 0 | J60: 0 | K60: 0
B61: S5 | C61: Workers/Máquina req | D61: ='01_INPUTS_MASTER'!G24 -> 3 | E61: 0 | F61: 0 | G61: 0 | H61: 0 | I61: 0 | J61: 0 | K61: 0
B62: S5 | C62: Capacidad Labor | D62: =IF(D61>0,D60/D61*'01_INPUTS_MASTER'!B24,0) -> 1250 | E62: =IF(E61>0,E60/E61*'01_INPUTS_MASTER'!B24,0) -> 0 | F62: =IF(F61>0,F60/F61*'01_INPUTS_MASTER'!B24,0) -> 0 | G62: =IF(G61>0,G60/G61*'01_INPUTS_MASTER'!B24,0) -> 0 | H62: =IF(H61>0,H60/H61*'01_INPUTS_MASTER'!B24,0) -> 0 | I62: =IF(I61>0,I60/I61*'01_INPUTS_MASTER'!B24,0) -> 0 | J62: =IF(J61>0,J60/J61*'01_INPUTS_MASTER'!B24,0) -> 0 | K62: =IF(K61>0,K60/K61*'01_INPUTS_MASTER'!B24,0) -> 0
B63: S5 | C63: Capacidad Base (MIN) | D63: =MIN(D59,D62) -> 1250 | E63: =MIN(E59,E62) -> 0 | F63: =MIN(F59,F62) -> 0 | G63: =MIN(G59,G62) -> 0 | H63: =MIN(H59,H62) -> 0 | I63: =MIN(I59,I62) -> 0 | J63: =MIN(J59,J62) -> 0 | K63: =MIN(K59,K62) -> 0
B64: S5 | C64: Overtime (0/1) | D64: ='10_DECISIONS_UPLOAD'!C34 -> 0 | E64: ='10_DECISIONS_UPLOAD'!D34 -> 0 | F64: ='10_DECISIONS_UPLOAD'!E34 -> 0 | G64: ='10_DECISIONS_UPLOAD'!F34 -> 0 | H64: ='10_DECISIONS_UPLOAD'!G34 -> 0 | I64: ='10_DECISIONS_UPLOAD'!H34 -> 0 | J64: ='10_DECISIONS_UPLOAD'!I34 -> 0 | K64: ='10_DECISIONS_UPLOAD'!J34 -> 0
B65: S5 | C65: Capacidad c/Overtime | D65: =D63*(1+0.2*D64) -> 1250 | E65: =E63*(1+0.2*E64) -> 0 | F65: =F63*(1+0.2*F64) -> 0 | G65: =G63*(1+0.2*G64) -> 0 | H65: =H63*(1+0.2*H64) -> 0 | I65: =I63*(1+0.2*I64) -> 0 | J65: =J63*(1+0.2*J64) -> 0 | K65: =K63*(1+0.2*K64) -> 0
B66: S5 | C66: Plan Producción | D66: ='04_FLOW_S1_S5'!D7 -> 0 | E66: ='04_FLOW_S1_S5'!E7 -> 1000 | F66: ='04_FLOW_S1_S5'!F7 -> 0 | G66: ='04_FLOW_S1_S5'!G7 -> 1000 | H66: ='04_FLOW_S1_S5'!H7 -> 0 | I66: ='04_FLOW_S1_S5'!I7 -> 1000 | J66: ='04_FLOW_S1_S5'!J7 -> 0 | K66: ='04_FLOW_S1_S5'!K7 -> 1000
B67: S5 | C67: Producción Real | D67: =MIN(D65,D66) -> 0 | E67: =MIN(E65,E66) -> 0 | F67: =MIN(F65,F66) -> 0 | G67: =MIN(G65,G66) -> 0 | H67: =MIN(H65,H66) -> 0 | I67: =MIN(I65,I66) -> 0 | J67: =MIN(J65,J66) -> 0 | K67: =MIN(K65,K66) -> 0
B68: S5 | C68: Bottleneck | D68: =IF(D66>D65,"CAPACITY","OK") -> OK | E68: =IF(E66>E65,"CAPACITY","OK") -> CAPACITY | F68: =IF(F66>F65,"CAPACITY","OK") -> OK | G68: =IF(G66>G65,"CAPACITY","OK") -> CAPACITY | H68: =IF(H66>H65,"CAPACITY","OK") -> OK | I68: =IF(I66>I65,"CAPACITY","OK") -> CAPACITY | J68: =IF(J66>J65,"CAPACITY","OK") -> OK | K68: =IF(K66>K65,"CAPACITY","OK") -> CAPACITY
A70: West
B71: S1 | C71: # Máquinas | D71: ='01_INPUTS_MASTER'!I17 -> 3 | E71: 0 | F71: 0 | G71: 0 | H71: 0 | I71: 0 | J71: 0 | K71: 0
B72: S1 | C72: Capacidad/Máquina | D72: ='01_INPUTS_MASTER'!B17 -> 200 | E72: 0 | F72: 0 | G72: 0 | H72: 0 | I72: 0 | J72: 0 | K72: 0
B73: S1 | C73: Capacidad Máquinas | D73: =D71*D72 -> 600 | E73: =E71*E72 -> 0 | F73: =F71*F72 -> 0 | G73: =G71*G72 -> 0 | H73: =H71*H72 -> 0 | I73: =I71*I72 -> 0 | J73: =J71*J72 -> 0 | K73: =K71*K72 -> 0
B74: S1 | C74: # Workers | D74: ='10_DECISIONS_UPLOAD'!C20 -> 3 | E74: 0 | F74: 0 | G74: 0 | H74: 0 | I74: 0 | J74: 0 | K74: 0
B75: S1 | C75: Workers/Máquina req | D75: ='01_INPUTS_MASTER'!G17 -> 1 | E75: 0 | F75: 0 | G75: 0 | H75: 0 | I75: 0 | J75: 0 | K75: 0
B76: S1 | C76: Capacidad Labor | D76: =IF(D75>0,D74/D75*D72,0) -> 600 | E76: =IF(E75>0,E74/E75*E72,0) -> 0 | F76: =IF(F75>0,F74/F75*F72,0) -> 0 | G76: =IF(G75>0,G74/G75*G72,0) -> 0 | H76: =IF(H75>0,H74/H75*H72,0) -> 0 | I76: =IF(I75>0,I74/I75*I72,0) -> 0 | J76: =IF(J75>0,J74/J75*J72,0) -> 0 | K76: =IF(K75>0,K74/K75*K72,0) -> 0
B77: S1 | C77: Capacidad Base (MIN) | D77: =MIN(D73,D76) -> 600 | E77: =MIN(E73,E76) -> 0 | F77: =MIN(F73,F76) -> 0 | G77: =MIN(G73,G76) -> 0 | H77: =MIN(H73,H76) -> 0 | I77: =MIN(I73,I76) -> 0 | J77: =MIN(J73,J76) -> 0 | K77: =MIN(K73,K76) -> 0
B78: S1 | C78: Overtime (0/1) | D78: ='10_DECISIONS_UPLOAD'!C35 -> 0 | E78: ='10_DECISIONS_UPLOAD'!D35 -> 0 | F78: ='10_DECISIONS_UPLOAD'!E35 -> 0 | G78: ='10_DECISIONS_UPLOAD'!F35 -> 0 | H78: ='10_DECISIONS_UPLOAD'!G35 -> 0 | I78: ='10_DECISIONS_UPLOAD'!H35 -> 0 | J78: ='10_DECISIONS_UPLOAD'!I35 -> 0 | K78: ='10_DECISIONS_UPLOAD'!J35 -> 0
B79: S1 | C79: Capacidad c/Overtime | D79: =D77*(1+0.2*D78) -> 600 | E79: =E77*(1+0.2*E78) -> 0 | F79: =F77*(1+0.2*F78) -> 0 | G79: =G77*(1+0.2*G78) -> 0 | H79: =H77*(1+0.2*H78) -> 0 | I79: =I77*(1+0.2*I78) -> 0 | J79: =J77*(1+0.2*J78) -> 0 | K79: =K77*(1+0.2*K78) -> 0
B80: S1 | C80: Plan Producción | D80: ='04_FLOW_S1_S5'!D62 -> 1000 | E80: ='04_FLOW_S1_S5'!E62 -> 0 | F80: ='04_FLOW_S1_S5'!F62 -> 1000 | G80: ='04_FLOW_S1_S5'!G62 -> 0 | H80: ='04_FLOW_S1_S5'!H62 -> 1000 | I80: ='04_FLOW_S1_S5'!I62 -> 0 | J80: ='04_FLOW_S1_S5'!J62 -> 0 | K80: ='04_FLOW_S1_S5'!K62 -> 0
B81: S1 | C81: Producción Real | D81: =MIN(D79,D80) -> 600 | E81: =MIN(E79,E80) -> 0 | F81: =MIN(F79,F80) -> 0 | G81: =MIN(G79,G80) -> 0 | H81: =MIN(H79,H80) -> 0 | I81: =MIN(I79,I80) -> 0 | J81: =MIN(J79,J80) -> 0 | K81: =MIN(K79,K80) -> 0
B82: S1 | C82: Bottleneck | D82: =IF(D80>D79,"CAPACITY","OK") -> CAPACITY | E82: =IF(E80>E79,"CAPACITY","OK") -> OK | F82: =IF(F80>F79,"CAPACITY","OK") -> CAPACITY | G82: =IF(G80>G79,"CAPACITY","OK") -> OK | H82: =IF(H80>H79,"CAPACITY","OK") -> CAPACITY | I82: =IF(I80>I79,"CAPACITY","OK") -> OK | J82: =IF(J80>J79,"CAPACITY","OK") -> OK | K82: =IF(K80>K79,"CAPACITY","OK") -> OK
B84: S2 | C84: # Máquinas | D84: ='01_INPUTS_MASTER'!I18 -> 9 | E84: 0 | F84: 0 | G84: 0 | H84: 0 | I84: 0 | J84: 0 | K84: 0
B85: S2 | C85: Capacidad/Máquina | D85: ='01_INPUTS_MASTER'!B18 -> 70 | E85: 0 | F85: 0 | G85: 0 | H85: 0 | I85: 0 | J85: 0 | K85: 0
B86: S2 | C86: Capacidad Máquinas | D86: =D84*D85 -> 630 | E86: =E84*E85 -> 0 | F86: =F84*F85 -> 0 | G86: =G84*G85 -> 0 | H86: =H84*H85 -> 0 | I86: =I84*I85 -> 0 | J86: =J84*J85 -> 0 | K86: =K84*K85 -> 0
B87: S2 | C87: # Workers | D87: ='10_DECISIONS_UPLOAD'!C21 -> 9 | E87: 0 | F87: 0 | G87: 0 | H87: 0 | I87: 0 | J87: 0 | K87: 0
B88: S2 | C88: Workers/Máquina req | D88: ='01_INPUTS_MASTER'!G18 -> 1 | E88: 0 | F88: 0 | G88: 0 | H88: 0 | I88: 0 | J88: 0 | K88: 0
B89: S2 | C89: Capacidad Labor | D89: =IF(D88>0,D87/D88*D85,0) -> 630 | E89: =IF(E88>0,E87/E88*E85,0) -> 0 | F89: =IF(F88>0,F87/F88*F85,0) -> 0 | G89: =IF(G88>0,G87/G88*G85,0) -> 0 | H89: =IF(H88>0,H87/H88*H85,0) -> 0 | I89: =IF(I88>0,I87/I88*I85,0) -> 0 | J89: =IF(J88>0,J87/J88*J85,0) -> 0 | K89: =IF(K88>0,K87/K88*K85,0) -> 0
B90: S2 | C90: Capacidad Base (MIN) | D90: =MIN(D86,D89) -> 630 | E90: =MIN(E86,E89) -> 0 | F90: =MIN(F86,F89) -> 0 | G90: =MIN(G86,G89) -> 0 | H90: =MIN(H86,H89) -> 0 | I90: =MIN(I86,I89) -> 0 | J90: =MIN(J86,J89) -> 0 | K90: =MIN(K86,K89) -> 0
B91: S2 | C91: Overtime (0/1) | D91: ='10_DECISIONS_UPLOAD'!C36 -> 0 | E91: ='10_DECISIONS_UPLOAD'!D36 -> 0 | F91: ='10_DECISIONS_UPLOAD'!E36 -> 0 | G91: ='10_DECISIONS_UPLOAD'!F36 -> 0 | H91: ='10_DECISIONS_UPLOAD'!G36 -> 0 | I91: ='10_DECISIONS_UPLOAD'!H36 -> 0 | J91: ='10_DECISIONS_UPLOAD'!I36 -> 0 | K91: ='10_DECISIONS_UPLOAD'!J36 -> 0
B92: S2 | C92: Capacidad c/Overtime | D92: =D90*(1+0.2*D91) -> 630 | E92: =E90*(1+0.2*E91) -> 0 | F92: =F90*(1+0.2*F91) -> 0 | G92: =G90*(1+0.2*G91) -> 0 | H92: =H90*(1+0.2*H91) -> 0 | I92: =I90*(1+0.2*I91) -> 0 | J92: =J90*(1+0.2*J91) -> 0 | K92: =K90*(1+0.2*K91) -> 0
B93: S2 | C93: Plan Producción | D93: ='04_FLOW_S1_S5'!D56 -> 1000 | E93: ='04_FLOW_S1_S5'!E56 -> 0 | F93: ='04_FLOW_S1_S5'!F56 -> 1000 | G93: ='04_FLOW_S1_S5'!G56 -> 0 | H93: ='04_FLOW_S1_S5'!H56 -> 1000 | I93: ='04_FLOW_S1_S5'!I56 -> 0 | J93: ='04_FLOW_S1_S5'!J56 -> 0 | K93: ='04_FLOW_S1_S5'!K56 -> 0
B94: S2 | C94: Producción Real | D94: =MIN(D92,D93) -> 630 | E94: =MIN(E92,E93) -> 0 | F94: =MIN(F92,F93) -> 0 | G94: =MIN(G92,G93) -> 0 | H94: =MIN(H92,H93) -> 0 | I94: =MIN(I92,I93) -> 0 | J94: =MIN(J92,J93) -> 0 | K94: =MIN(K92,K93) -> 0
B95: S2 | C95: Bottleneck | D95: =IF(D93>D92,"CAPACITY","OK") -> CAPACITY | E95: =IF(E93>E92,"CAPACITY","OK") -> OK | F95: =IF(F93>F92,"CAPACITY","OK") -> CAPACITY | G95: =IF(G93>G92,"CAPACITY","OK") -> OK | H95: =IF(H93>H92,"CAPACITY","OK") -> CAPACITY | I95: =IF(I93>I92,"CAPACITY","OK") -> OK | J95: =IF(J93>J92,"CAPACITY","OK") -> OK | K95: =IF(K93>K92,"CAPACITY","OK") -> OK
B97: S3 | C97: # Máquinas | D97: ='01_INPUTS_MASTER'!I19+'01_INPUTS_MASTER'!I20 -> 1 | E97: 0 | F97: 0 | G97: 0 | H97: 0 | I97: 0 | J97: 0 | K97: 0
B98: S3 | C98: Capacidad/Máquina | D98: =IF(('01_INPUTS_MASTER'!I19+'01_INPUTS_MASTER'!I20)>0,('01_INPUTS_MASTER'!I19*'01_INPUTS_MASTER'!B19+'01_INPUTS_MASTER'!I20*'01_INPUTS_MASTER'!B20)/('01_INPUTS_MASTER'!I19+'01_INPUTS_MASTER'!I20),0) -> 450 | E98: 0 | F98: 0 | G98: 0 | H98: 0 | I98: 0 | J98: 0 | K98: 0
B99: S3 | C99: Capacidad Máquinas | D99: =MIN('01_INPUTS_MASTER'!I19*'01_INPUTS_MASTER'!B19+'01_INPUTS_MASTER'!I20*'01_INPUTS_MASTER'!B20,'01_INPUTS_MASTER'!I21*'01_INPUTS_MASTER'!B21) -> 450 | E99: =E97*E98 -> 0 | F99: =F97*F98 -> 0 | G99: =G97*G98 -> 0 | H99: =H97*H98 -> 0 | I99: =I97*I98 -> 0 | J99: =J97*J98 -> 0 | K99: =K97*K98 -> 0
B100: S3 | C100: # Workers | D100: ='10_DECISIONS_UPLOAD'!C22 -> 30 | E100: 0 | F100: 0 | G100: 0 | H100: 0 | I100: 0 | J100: 0 | K100: 0
B101: S3 | C101: Workers/Máquina req | D101: ='01_INPUTS_MASTER'!G19 -> 30 | E101: 0 | F101: 0 | G101: 0 | H101: 0 | I101: 0 | J101: 0 | K101: 0
B102: S3 | C102: Capacidad Labor | D102: =IF(D101>0,D100/D101*D98,0) -> 450 | E102: =IF(E101>0,E100/E101*E98,0) -> 0 | F102: =IF(F101>0,F100/F101*F98,0) -> 0 | G102: =IF(G101>0,G100/G101*G98,0) -> 0 | H102: =IF(H101>0,H100/H101*H98,0) -> 0 | I102: =IF(I101>0,I100/I101*I98,0) -> 0 | J102: =IF(J101>0,J100/J101*J98,0) -> 0 | K102: =IF(K101>0,K100/K101*K98,0) -> 0
B103: S3 | C103: Capacidad Base (MIN) | D103: =MIN(D99,D102) -> 450 | E103: =MIN(E99,E102) -> 0 | F103: =MIN(F99,F102) -> 0 | G103: =MIN(G99,G102) -> 0 | H103: =MIN(H99,H102) -> 0 | I103: =MIN(I99,I102) -> 0 | J103: =MIN(J99,J102) -> 0 | K103: =MIN(K99,K102) -> 0
B104: S3 | C104: Overtime (0/1) | D104: ='10_DECISIONS_UPLOAD'!C37 -> 0 | E104: ='10_DECISIONS_UPLOAD'!D37 -> 0 | F104: ='10_DECISIONS_UPLOAD'!E37 -> 0 | G104: ='10_DECISIONS_UPLOAD'!F37 -> 0 | H104: ='10_DECISIONS_UPLOAD'!G37 -> 0 | I104: ='10_DECISIONS_UPLOAD'!H37 -> 0 | J104: ='10_DECISIONS_UPLOAD'!I37 -> 0 | K104: ='10_DECISIONS_UPLOAD'!J37 -> 0
B105: S3 | C105: Capacidad c/Overtime | D105: =D103*(1+0.2*D104) -> 450 | E105: =E103*(1+0.2*E104) -> 0 | F105: =F103*(1+0.2*F104) -> 0 | G105: =G103*(1+0.2*G104) -> 0 | H105: =H103*(1+0.2*H104) -> 0 | I105: =I103*(1+0.2*I104) -> 0 | J105: =J103*(1+0.2*J104) -> 0 | K105: =K103*(1+0.2*K104) -> 0
B106: S3 | C106: Plan Producción | D106: ='04_FLOW_S1_S5'!D50 -> 0 | E106: ='04_FLOW_S1_S5'!E50 -> 1000 | F106: ='04_FLOW_S1_S5'!F50 -> 0 | G106: ='04_FLOW_S1_S5'!G50 -> 1000 | H106: ='04_FLOW_S1_S5'!H50 -> 0 | I106: ='04_FLOW_S1_S5'!I50 -> 1000 | J106: ='04_FLOW_S1_S5'!J50 -> 0 | K106: ='04_FLOW_S1_S5'!K50 -> 0
B107: S3 | C107: Producción Real | D107: =MIN(D105,D106) -> 0 | E107: =MIN(E105,E106) -> 0 | F107: =MIN(F105,F106) -> 0 | G107: =MIN(G105,G106) -> 0 | H107: =MIN(H105,H106) -> 0 | I107: =MIN(I105,I106) -> 0 | J107: =MIN(J105,J106) -> 0 | K107: =MIN(K105,K106) -> 0
B108: S3 | C108: Bottleneck | D108: =IF(D106>D105,"CAPACITY","OK") -> OK | E108: =IF(E106>E105,"CAPACITY","OK") -> CAPACITY | F108: =IF(F106>F105,"CAPACITY","OK") -> OK | G108: =IF(G106>G105,"CAPACITY","OK") -> CAPACITY | H108: =IF(H106>H105,"CAPACITY","OK") -> OK | I108: =IF(I106>I105,"CAPACITY","OK") -> CAPACITY | J108: =IF(J106>J105,"CAPACITY","OK") -> OK | K108: =IF(K106>K105,"CAPACITY","OK") -> OK
...

Sheet 06_MRP_MATERIALS
A1: MRP - PLANIFICACIÓN DE MATERIALES (Parts A/B y Pieces 1-6)
A2: PLANT: CENTER
A3: Material | B3: Concepto | C3: S0 | D3: S1 | E3: S2 | F3: S3 | G3: S4 | H3: S5 | I3: S6 | J3: S7 | K3: S8 | L3: TOTAL
A4: Part A
B5: Batch Size | C5: ='01_INPUTS_MASTER'!B49 -> 30 | D5: ='01_INPUTS_MASTER'!B49 -> 30 | E5: ='01_INPUTS_MASTER'!B49 -> 30 | F5: ='01_INPUTS_MASTER'!B49 -> 30 | G5: ='01_INPUTS_MASTER'!B49 -> 30 | H5: ='01_INPUTS_MASTER'!B49 -> 30 | I5: ='01_INPUTS_MASTER'!B49 -> 30 | J5: ='01_INPUTS_MASTER'!B49 -> 30 | K5: ='01_INPUTS_MASTER'!B49 -> 30
B6: Consumo/EC | C6: ='01_INPUTS_MASTER'!H49 -> 1 | D6: ='01_INPUTS_MASTER'!H49 -> 1 | E6: ='01_INPUTS_MASTER'!H49 -> 1 | F6: ='01_INPUTS_MASTER'!H49 -> 1 | G6: ='01_INPUTS_MASTER'!H49 -> 1 | H6: ='01_INPUTS_MASTER'!H49 -> 1 | I6: ='01_INPUTS_MASTER'!H49 -> 1 | J6: ='01_INPUTS_MASTER'!H49 -> 1 | K6: ='01_INPUTS_MASTER'!H49 -> 1
B7: Producción Plan | C7: =0 -> 0 | D7: ='04_FLOW_S1_S5'!D7 -> 0 | E7: ='04_FLOW_S1_S5'!E7 -> 1000 | F7: ='04_FLOW_S1_S5'!F7 -> 0 | G7: ='04_FLOW_S1_S5'!G7 -> 1000 | H7: ='04_FLOW_S1_S5'!H7 -> 0 | I7: ='04_FLOW_S1_S5'!I7 -> 1000 | J7: ='04_FLOW_S1_S5'!J7 -> 0 | K7: ='04_FLOW_S1_S5'!K7 -> 1000
B8: Req Bruto | C8: =0 -> 0 | D8: =D7*D6 -> 0 | E8: =E7*E6 -> 1000 | F8: =F7*F6 -> 0 | G8: =G7*G6 -> 1000 | H8: =H7*H6 -> 0 | I8: =I7*I6 -> 1000 | J8: =J7*J6 -> 0 | K8: =K7*K6 -> 1000 | L8: =SUM(D8:K8) -> 4000
B9: Inv Inicial | C9: ='01_INPUTS_MASTER'!M49 -> 0 | D9: =C9 -> 0 | E9: =D13 -> 0 | F9: =E13 -> 20 | G9: =F13 -> 20 | H9: =G13 -> 10 | I9: =H13 -> 10 | J9: =I13 -> 0 | K9: =J13 -> 0
B10: Req Neto | C10: =0 -> 0 | D10: =MAX(0,D8-D9) -> 0 | E10: =MAX(0,E8-E9) -> 1000 | F10: =MAX(0,F8-F9) -> 0 | G10: =MAX(0,G8-G9) -> 980 | H10: =MAX(0,H8-H9) -> 0 | I10: =MAX(0,I8-I9) -> 990 | J10: =MAX(0,J8-J9) -> 0 | K10: =MAX(0,K8-K9) -> 1000
B11: Lotes a Pedir | C11: =0 -> 0 | D11: =IF(D5>0,CEILING(D10/D5,1),0) -> 0 | E11: =IF(E5>0,CEILING(E10/E5,1),0) -> 34 | F11: =IF(F5>0,CEILING(F10/F5,1),0) -> 0 | G11: =IF(G5>0,CEILING(G10/G5,1),0) -> 33 | H11: =IF(H5>0,CEILING(H10/H5,1),0) -> 0 | I11: =IF(I5>0,CEILING(I10/I5,1),0) -> 33 | J11: =IF(J5>0,CEILING(J10/J5,1),0) -> 0 | K11: =IF(K5>0,CEILING(K10/K5,1),0) -> 34
B12: Pedido (lotes*batch) | C12: =0 -> 0 | D12: =D11*D5 -> 0 | E12: =E11*E5 -> 1020 | F12: =F11*F5 -> 0 | G12: =G11*G5 -> 990 | H12: =H11*H5 -> 0 | I12: =I11*I5 -> 990 | J12: =J11*J5 -> 0 | K12: =K11*K5 -> 1020 | L12: =SUM(D12:K12) -> 4020
B13: Inv Final | C13: =C9 -> 0 | D13: =D9+D12*(IF('01_INPUTS_MASTER'!M54="B",1-'01_INPUTS_MASTER'!Q54,1))-D8 -> 0 | E13: =E9+E12*(IF('01_INPUTS_MASTER'!M54="B",1-'01_INPUTS_MASTER'!Q54,1))-E8 -> 20 | F13: =F9+F12*(IF('01_INPUTS_MASTER'!M54="B",1-'01_INPUTS_MASTER'!Q54,1))-F8 -> 20 | G13: =G9+G12*(IF('01_INPUTS_MASTER'!M54="B",1-'01_INPUTS_MASTER'!Q54,1))-G8 -> 10 | H13: =H9+H12*(IF('01_INPUTS_MASTER'!M54="B",1-'01_INPUTS_MASTER'!Q54,1))-H8 -> 10 | I13: =I9+I12*(IF('01_INPUTS_MASTER'!M54="B",1-'01_INPUTS_MASTER'!Q54,1))-I8 -> 0 | J13: =J9+J12*(IF('01_INPUTS_MASTER'!M54="B",1-'01_INPUTS_MASTER'!Q54,1))-J8 -> 0 | K13: =K9+K12*(IF('01_INPUTS_MASTER'!M54="B",1-'01_INPUTS_MASTER'!Q54,1))-K8 -> 20
B14: Ordering Cost | C14: =0 -> 0 | D14: =IF(D12>0,'01_INPUTS_MASTER'!F49,0) -> 0 | E14: =IF(E12>0,'01_INPUTS_MASTER'!F49,0) -> 2300 | F14: =IF(F12>0,'01_INPUTS_MASTER'!F49,0) -> 0 | G14: =IF(G12>0,'01_INPUTS_MASTER'!F49,0) -> 2300 | H14: =IF(H12>0,'01_INPUTS_MASTER'!F49,0) -> 0 | I14: =IF(I12>0,'01_INPUTS_MASTER'!F49,0) -> 2300 | J14: =IF(J12>0,'01_INPUTS_MASTER'!F49,0) -> 0 | K14: =IF(K12>0,'01_INPUTS_MASTER'!F49,0) -> 2300 | L14: =SUM(D14:K14) -> 9200
B15: Holding Cost | C15: =0 -> 0 | D15: =D13*'01_INPUTS_MASTER'!G49 -> 0 | E15: =E13*'01_INPUTS_MASTER'!G49 -> 6 | F15: =F13*'01_INPUTS_MASTER'!G49 -> 6 | G15: =G13*'01_INPUTS_MASTER'!G49 -> 3 | H15: =H13*'01_INPUTS_MASTER'!G49 -> 3 | I15: =I13*'01_INPUTS_MASTER'!G49 -> 0 | J15: =J13*'01_INPUTS_MASTER'!G49 -> 0 | K15: =K13*'01_INPUTS_MASTER'!G49 -> 6 | L15: =SUM(D15:K15) -> 24
A17: Part B
B18: Batch Size | C18: ='01_INPUTS_MASTER'!B50 -> 12 | D18: ='01_INPUTS_MASTER'!B50 -> 12 | E18: ='01_INPUTS_MASTER'!B50 -> 12 | F18: ='01_INPUTS_MASTER'!B50 -> 12 | G18: ='01_INPUTS_MASTER'!B50 -> 12 | H18: ='01_INPUTS_MASTER'!B50 -> 12 | I18: ='01_INPUTS_MASTER'!B50 -> 12 | J18: ='01_INPUTS_MASTER'!B50 -> 12 | K18: ='01_INPUTS_MASTER'!B50 -> 12
B19: Consumo/EC | C19: ='01_INPUTS_MASTER'!H50 -> 0.2 | D19: ='01_INPUTS_MASTER'!H50 -> 0.2 | E19: ='01_INPUTS_MASTER'!H50 -> 0.2 | F19: ='01_INPUTS_MASTER'!H50 -> 0.2 | G19: ='01_INPUTS_MASTER'!H50 -> 0.2 | H19: ='01_INPUTS_MASTER'!H50 -> 0.2 | I19: ='01_INPUTS_MASTER'!H50 -> 0.2 | J19: ='01_INPUTS_MASTER'!H50 -> 0.2 | K19: ='01_INPUTS_MASTER'!H50 -> 0.2
B20: Producción Plan | C20: =0 -> 0 | D20: ='04_FLOW_S1_S5'!D7 -> 0 | E20: ='04_FLOW_S1_S5'!E7 -> 1000 | F20: ='04_FLOW_S1_S5'!F7 -> 0 | G20: ='04_FLOW_S1_S5'!G7 -> 1000 | H20: ='04_FLOW_S1_S5'!H7 -> 0 | I20: ='04_FLOW_S1_S5'!I7 -> 1000 | J20: ='04_FLOW_S1_S5'!J7 -> 0 | K20: ='04_FLOW_S1_S5'!K7 -> 1000
B21: Req Bruto | C21: =0 -> 0 | D21: =D20*D19 -> 0 | E21: =E20*E19 -> 200 | F21: =F20*F19 -> 0 | G21: =G20*G19 -> 200 | H21: =H20*H19 -> 0 | I21: =I20*I19 -> 200 | J21: =J20*J19 -> 0 | K21: =K20*K19 -> 200 | L21: =SUM(D21:K21) -> 800
B22: Inv Inicial | C22: ='01_INPUTS_MASTER'!M50 -> 0 | D22: =C22 -> 0 | E22: =D26 -> 0 | F22: =E26 -> 4 | G22: =F26 -> 4 | H22: =G26 -> 8 | I22: =H26 -> 8 | J22: =I26 -> 0 | K22: =J26 -> 0
B23: Req Neto | C23: =0 -> 0 | D23: =MAX(0,D21-D22) -> 0 | E23: =MAX(0,E21-E22) -> 200 | F23: =MAX(0,F21-F22) -> 0 | G23: =MAX(0,G21-G22) -> 196 | H23: =MAX(0,H21-H22) -> 0 | I23: =MAX(0,I21-I22) -> 192 | J23: =MAX(0,J21-J22) -> 0 | K23: =MAX(0,K21-K22) -> 200
B24: Lotes a Pedir | C24: =0 -> 0 | D24: =IF(D18>0,CEILING(D23/D18,1),0) -> 0 | E24: =IF(E18>0,CEILING(E23/E18,1),0) -> 17 | F24: =IF(F18>0,CEILING(F23/F18,1),0) -> 0 | G24: =IF(G18>0,CEILING(G23/G18,1),0) -> 17 | H24: =IF(H18>0,CEILING(H23/H18,1),0) -> 0 | I24: =IF(I18>0,CEILING(I23/I18,1),0) -> 16 | J24: =IF(J18>0,CEILING(J23/J18,1),0) -> 0 | K24: =IF(K18>0,CEILING(K23/K18,1),0) -> 17
B25: Pedido (lotes*batch) | C25: =0 -> 0 | D25: =D24*D18 -> 0 | E25: =E24*E18 -> 204 | F25: =F24*F18 -> 0 | G25: =G24*G18 -> 204 | H25: =H24*H18 -> 0 | I25: =I24*I18 -> 192 | J25: =J24*J18 -> 0 | K25: =K24*K18 -> 204 | L25: =SUM(D25:K25) -> 804
B26: Inv Final | C26: =C22 -> 0 | D26: =D22+D25*(IF('01_INPUTS_MASTER'!N54="B",1-'01_INPUTS_MASTER'!Q54,1))-D21 -> 0 | E26: =E22+E25*(IF('01_INPUTS_MASTER'!N54="B",1-'01_INPUTS_MASTER'!Q54,1))-E21 -> 4 | F26: =F22+F25*(IF('01_INPUTS_MASTER'!N54="B",1-'01_INPUTS_MASTER'!Q54,1))-F21 -> 4 | G26: =G22+G25*(IF('01_INPUTS_MASTER'!N54="B",1-'01_INPUTS_MASTER'!Q54,1))-G21 -> 8 | H26: =H22+H25*(IF('01_INPUTS_MASTER'!N54="B",1-'01_INPUTS_MASTER'!Q54,1))-H21 -> 8 | I26: =I22+I25*(IF('01_INPUTS_MASTER'!N54="B",1-'01_INPUTS_MASTER'!Q54,1))-I21 -> 0 | J26: =J22+J25*(IF('01_INPUTS_MASTER'!N54="B",1-'01_INPUTS_MASTER'!Q54,1))-J21 -> 0 | K26: =K22+K25*(IF('01_INPUTS_MASTER'!N54="B",1-'01_INPUTS_MASTER'!Q54,1))-K21 -> 4
B27: Ordering Cost | C27: =0 -> 0 | D27: =IF(D25>0,'01_INPUTS_MASTER'!F50,0) -> 0 | E27: =IF(E25>0,'01_INPUTS_MASTER'!F50,0) -> 6000 | F27: =IF(F25>0,'01_INPUTS_MASTER'!F50,0) -> 0 | G27: =IF(G25>0,'01_INPUTS_MASTER'!F50,0) -> 6000 | H27: =IF(H25>0,'01_INPUTS_MASTER'!F50,0) -> 0 | I27: =IF(I25>0,'01_INPUTS_MASTER'!F50,0) -> 6000 | J27: =IF(J25>0,'01_INPUTS_MASTER'!F50,0) -> 0 | K27: =IF(K25>0,'01_INPUTS_MASTER'!F50,0) -> 6000 | L27: =SUM(D27:K27) -> 24000
B28: Holding Cost | C28: =0 -> 0 | D28: =D26*'01_INPUTS_MASTER'!G50 -> 0 | E28: =E26*'01_INPUTS_MASTER'!G50 -> 18 | F28: =F26*'01_INPUTS_MASTER'!G50 -> 18 | G28: =G26*'01_INPUTS_MASTER'!G50 -> 36 | H28: =H26*'01_INPUTS_MASTER'!G50 -> 36 | I28: =I26*'01_INPUTS_MASTER'!G50 -> 0 | J28: =J26*'01_INPUTS_MASTER'!G50 -> 0 | K28: =K26*'01_INPUTS_MASTER'!G50 -> 18 | L28: =SUM(D28:K28) -> 126
A30: Piece 1
B31: Batch Size | C31: ='01_INPUTS_MASTER'!B40 -> 1 | D31: ='01_INPUTS_MASTER'!B40 -> 1 | E31: ='01_INPUTS_MASTER'!B40 -> 1 | F31: ='01_INPUTS_MASTER'!B40 -> 1 | G31: ='01_INPUTS_MASTER'!B40 -> 1 | H31: ='01_INPUTS_MASTER'!B40 -> 1 | I31: ='01_INPUTS_MASTER'!B40 -> 1 | J31: ='01_INPUTS_MASTER'!B40 -> 1 | K31: ='01_INPUTS_MASTER'!B40 -> 1
B32: Consumo/EC | C32: ='01_INPUTS_MASTER'!D40 -> 0.01 | D32: ='01_INPUTS_MASTER'!D40 -> 0.01 | E32: ='01_INPUTS_MASTER'!D40 -> 0.01 | F32: ='01_INPUTS_MASTER'!D40 -> 0.01 | G32: ='01_INPUTS_MASTER'!D40 -> 0.01 | H32: ='01_INPUTS_MASTER'!D40 -> 0.01 | I32: ='01_INPUTS_MASTER'!D40 -> 0.01 | J32: ='01_INPUTS_MASTER'!D40 -> 0.01 | K32: ='01_INPUTS_MASTER'!D40 -> 0.01
B33: Producción Plan | C33: =0 -> 0 | D33: ='04_FLOW_S1_S5'!D7 -> 0 | E33: ='04_FLOW_S1_S5'!E7 -> 1000 | F33: ='04_FLOW_S1_S5'!F7 -> 0 | G33: ='04_FLOW_S1_S5'!G7 -> 1000 | H33: ='04_FLOW_S1_S5'!H7 -> 0 | I33: ='04_FLOW_S1_S5'!I7 -> 1000 | J33: ='04_FLOW_S1_S5'!J7 -> 0 | K33: ='04_FLOW_S1_S5'!K7 -> 1000
B34: Req Bruto | C34: =0 -> 0 | D34: =D33*D32 -> 0 | E34: =E33*E32 -> 10 | F34: =F33*F32 -> 0 | G34: =G33*G32 -> 10 | H34: =H33*H32 -> 0 | I34: =I33*I32 -> 10 | J34: =J33*J32 -> 0 | K34: =K33*K32 -> 10 | L34: =SUM(D34:K34) -> 40
B35: Inv Inicial | C35: ='01_INPUTS_MASTER'!E40 -> 94 | D35: =C35 -> 94 | E35: =D39 -> 94 | F35: =E39 -> 84 | G35: =F39 -> 84 | H35: =G39 -> 74 | I35: =H39 -> 74 | J35: =I39 -> 64 | K35: =J39 -> 64
B36: Req Neto | C36: =0 -> 0 | D36: =MAX(0,D34-D35) -> 0 | E36: =MAX(0,E34-E35) -> 0 | F36: =MAX(0,F34-F35) -> 0 | G36: =MAX(0,G34-G35) -> 0 | H36: =MAX(0,H34-H35) -> 0 | I36: =MAX(0,I34-I35) -> 0 | J36: =MAX(0,J34-J35) -> 0 | K36: =MAX(0,K34-K35) -> 0
B37: Lotes a Pedir | C37: =0 -> 0 | D37: =IF(D31>0,CEILING(D36/D31,1),0) -> 0 | E37: =IF(E31>0,CEILING(E36/E31,1),0) -> 0 | F37: =IF(F31>0,CEILING(F36/F31,1),0) -> 0 | G37: =IF(G31>0,CEILING(G36/G31,1),0) -> 0 | H37: =IF(H31>0,CEILING(H36/H31,1),0) -> 0 | I37: =IF(I31>0,CEILING(I36/I31,1),0) -> 0 | J37: =IF(J31>0,CEILING(J36/J31,1),0) -> 0 | K37: =IF(K31>0,CEILING(K36/K31,1),0) -> 0
B38: Pedido (lotes*batch) | C38: =0 -> 0 | D38: =D37*D31 -> 0 | E38: =E37*E31 -> 0 | F38: =F37*F31 -> 0 | G38: =G37*G31 -> 0 | H38: =H37*H31 -> 0 | I38: =I37*I31 -> 0 | J38: =J37*J31 -> 0 | K38: =K37*K31 -> 0 | L38: =SUM(D38:K38) -> 0
B39: Inv Final | C39: =C35 -> 94 | D39: =D35+D38*(1)-D34 -> 94 | E39: =E35+E38*(1)-E34 -> 84 | F39: =F35+F38*(1)-F34 -> 84 | G39: =G35+G38*(1)-G34 -> 74 | H39: =H35+H38*(1)-H34 -> 74 | I39: =I35+I38*(1)-I34 -> 64 | J39: =J35+J38*(1)-J34 -> 64 | K39: =K35+K38*(1)-K34 -> 54
B40: Ordering Cost | C40: =0 -> 0 | D40: =IF(D38>0,0,0) -> 0 | E40: =IF(E38>0,0,0) -> 0 | F40: =IF(F38>0,0,0) -> 0 | G40: =IF(G38>0,0,0) -> 0 | H40: =IF(H38>0,0,0) -> 0 | I40: =IF(I38>0,0,0) -> 0 | J40: =IF(J38>0,0,0) -> 0 | K40: =IF(K38>0,0,0) -> 0 | L40: =SUM(D40:K40) -> 0
B41: Holding Cost | C41: =0 -> 0 | D41: =D39*0 -> 0 | E41: =E39*0 -> 0 | F41: =F39*0 -> 0 | G41: =G39*0 -> 0 | H41: =H39*0 -> 0 | I41: =I39*0 -> 0 | J41: =J39*0 -> 0 | K41: =K39*0 -> 0 | L41: =SUM(D41:K41) -> 0
A43: Piece 2
B44: Batch Size | C44: ='01_INPUTS_MASTER'!B41 -> 100 | D44: ='01_INPUTS_MASTER'!B41 -> 100 | E44: ='01_INPUTS_MASTER'!B41 -> 100 | F44: ='01_INPUTS_MASTER'!B41 -> 100 | G44: ='01_INPUTS_MASTER'!B41 -> 100 | H44: ='01_INPUTS_MASTER'!B41 -> 100 | I44: ='01_INPUTS_MASTER'!B41 -> 100 | J44: ='01_INPUTS_MASTER'!B41 -> 100 | K44: ='01_INPUTS_MASTER'!B41 -> 100
B45: Consumo/EC | C45: ='01_INPUTS_MASTER'!D41 -> 8 | D45: ='01_INPUTS_MASTER'!D41 -> 8 | E45: ='01_INPUTS_MASTER'!D41 -> 8 | F45: ='01_INPUTS_MASTER'!D41 -> 8 | G45: ='01_INPUTS_MASTER'!D41 -> 8 | H45: ='01_INPUTS_MASTER'!D41 -> 8 | I45: ='01_INPUTS_MASTER'!D41 -> 8 | J45: ='01_INPUTS_MASTER'!D41 -> 8 | K45: ='01_INPUTS_MASTER'!D41 -> 8
B46: Producción Plan | C46: =0 -> 0 | D46: ='04_FLOW_S1_S5'!D7 -> 0 | E46: ='04_FLOW_S1_S5'!E7 -> 1000 | F46: ='04_FLOW_S1_S5'!F7 -> 0 | G46: ='04_FLOW_S1_S5'!G7 -> 1000 | H46: ='04_FLOW_S1_S5'!H7 -> 0 | I46: ='04_FLOW_S1_S5'!I7 -> 1000 | J46: ='04_FLOW_S1_S5'!J7 -> 0 | K46: ='04_FLOW_S1_S5'!K7 -> 1000
B47: Req Bruto | C47: =0 -> 0 | D47: =D46*D45 -> 0 | E47: =E46*E45 -> 8000 | F47: =F46*F45 -> 0 | G47: =G46*G45 -> 8000 | H47: =H46*H45 -> 0 | I47: =I46*I45 -> 8000 | J47: =J46*J45 -> 0 | K47: =K46*K45 -> 8000 | L47: =SUM(D47:K47) -> 32000
B48: Inv Inicial | C48: ='01_INPUTS_MASTER'!E41 -> 3844 | D48: =C48 -> 3844 | E48: =D52 -> 3844 | F48: =E52 -> 44 | G48: =F52 -> 44 | H48: =G52 -> 44 | I48: =H52 -> 44 | J48: =I52 -> 44 | K48: =J52 -> 44
B49: Req Neto | C49: =0 -> 0 | D49: =MAX(0,D47-D48) -> 0 | E49: =MAX(0,E47-E48) -> 4156 | F49: =MAX(0,F47-F48) -> 0 | G49: =MAX(0,G47-G48) -> 7956 | H49: =MAX(0,H47-H48) -> 0 | I49: =MAX(0,I47-I48) -> 7956 | J49: =MAX(0,J47-J48) -> 0 | K49: =MAX(0,K47-K48) -> 7956
B50: Lotes a Pedir | C50: =0 -> 0 | D50: =IF(D44>0,CEILING(D49/D44,1),0) -> 0 | E50: =IF(E44>0,CEILING(E49/E44,1),0) -> 42 | F50: =IF(F44>0,CEILING(F49/F44,1),0) -> 0 | G50: =IF(G44>0,CEILING(G49/G44,1),0) -> 80 | H50: =IF(H44>0,CEILING(H49/H44,1),0) -> 0 | I50: =IF(I44>0,CEILING(I49/I44,1),0) -> 80 | J50: =IF(J44>0,CEILING(J49/J44,1),0) -> 0 | K50: =IF(K44>0,CEILING(K49/K44,1),0) -> 80
B51: Pedido (lotes*batch) | C51: =0 -> 0 | D51: =D50*D44 -> 0 | E51: =E50*E44 -> 4200 | F51: =F50*F44 -> 0 | G51: =G50*G44 -> 8000 | H51: =H50*H44 -> 0 | I51: =I50*I44 -> 8000 | J51: =J50*J44 -> 0 | K51: =K50*K44 -> 8000 | L51: =SUM(D51:K51) -> 28200
B52: Inv Final | C52: =C48 -> 3844 | D52: =D48+D51*(1)-D47 -> 3844 | E52: =E48+E51*(1)-E47 -> 44 | F52: =F48+F51*(1)-F47 -> 44 | G52: =G48+G51*(1)-G47 -> 44 | H52: =H48+H51*(1)-H47 -> 44 | I52: =I48+I51*(1)-I47 -> 44 | J52: =J48+J51*(1)-J47 -> 44 | K52: =K48+K51*(1)-K47 -> 44
B53: Ordering Cost | C53: =0 -> 0 | D53: =IF(D51>0,0,0) -> 0 | E53: =IF(E51>0,0,0) -> 0 | F53: =IF(F51>0,0,0) -> 0 | G53: =IF(G51>0,0,0) -> 0 | H53: =IF(H51>0,0,0) -> 0 | I53: =IF(I51>0,0,0) -> 0 | J53: =IF(J51>0,0,0) -> 0 | K53: =IF(K51>0,0,0) -> 0 | L53: =SUM(D53:K53) -> 0
B54: Holding Cost | C54: =0 -> 0 | D54: =D52*0 -> 0 | E54: =E52*0 -> 0 | F54: =F52*0 -> 0 | G54: =G52*0 -> 0 | H54: =H52*0 -> 0 | I54: =I52*0 -> 0 | J54: =J52*0 -> 0 | K54: =K52*0 -> 0 | L54: =SUM(D54:K54) -> 0
A56: Piece 3
B57: Batch Size | C57: ='01_INPUTS_MASTER'!B42 -> 30 | D57: ='01_INPUTS_MASTER'!B42 -> 30 | E57: ='01_INPUTS_MASTER'!B42 -> 30 | F57: ='01_INPUTS_MASTER'!B42 -> 30 | G57: ='01_INPUTS_MASTER'!B42 -> 30 | H57: ='01_INPUTS_MASTER'!B42 -> 30 | I57: ='01_INPUTS_MASTER'!B42 -> 30 | J57: ='01_INPUTS_MASTER'!B42 -> 30 | K57: ='01_INPUTS_MASTER'!B42 -> 30
B58: Consumo/EC | C58: ='01_INPUTS_MASTER'!D42 -> 0.3 | D58: ='01_INPUTS_MASTER'!D42 -> 0.3 | E58: ='01_INPUTS_MASTER'!D42 -> 0.3 | F58: ='01_INPUTS_MASTER'!D42 -> 0.3 | G58: ='01_INPUTS_MASTER'!D42 -> 0.3 | H58: ='01_INPUTS_MASTER'!D42 -> 0.3 | I58: ='01_INPUTS_MASTER'!D42 -> 0.3 | J58: ='01_INPUTS_MASTER'!D42 -> 0.3 | K58: ='01_INPUTS_MASTER'!D42 -> 0.3
B59: Producción Plan | C59: =0 -> 0 | D59: ='04_FLOW_S1_S5'!D7 -> 0 | E59: ='04_FLOW_S1_S5'!E7 -> 1000 | F59: ='04_FLOW_S1_S5'!F7 -> 0 | G59: ='04_FLOW_S1_S5'!G7 -> 1000 | H59: ='04_FLOW_S1_S5'!H7 -> 0 | I59: ='04_FLOW_S1_S5'!I7 -> 1000 | J59: ='04_FLOW_S1_S5'!J7 -> 0 | K59: ='04_FLOW_S1_S5'!K7 -> 1000
B60: Req Bruto | C60: =0 -> 0 | D60: =D59*D58 -> 0 | E60: =E59*E58 -> 300 | F60: =F59*F58 -> 0 | G60: =G59*G58 -> 300 | H60: =H59*H58 -> 0 | I60: =I59*I58 -> 300 | J60: =J59*J58 -> 0 | K60: =K59*K58 -> 300 | L60: =SUM(D60:K60) -> 1200
B61: Inv Inicial | C61: ='01_INPUTS_MASTER'!E42 -> 3125 | D61: =C61 -> 3125 | E61: =D65 -> 3125 | F61: =E65 -> 2825 | G61: =F65 -> 2825 | H61: =G65 -> 2525 | I61: =H65 -> 2525 | J61: =I65 -> 2225 | K61: =J65 -> 2225
B62: Req Neto | C62: =0 -> 0 | D62: =MAX(0,D60-D61) -> 0 | E62: =MAX(0,E60-E61) -> 0 | F62: =MAX(0,F60-F61) -> 0 | G62: =MAX(0,G60-G61) -> 0 | H62: =MAX(0,H60-H61) -> 0 | I62: =MAX(0,I60-I61) -> 0 | J62: =MAX(0,J60-J61) -> 0 | K62: =MAX(0,K60-K61) -> 0
B63: Lotes a Pedir | C63: =0 -> 0 | D63: =IF(D57>0,CEILING(D62/D57,1),0) -> 0 | E63: =IF(E57>0,CEILING(E62/E57,1),0) -> 0 | F63: =IF(F57>0,CEILING(F62/F57,1),0) -> 0 | G63: =IF(G57>0,CEILING(G62/G57,1),0) -> 0 | H63: =IF(H57>0,CEILING(H62/H57,1),0) -> 0 | I63: =IF(I57>0,CEILING(I62/I57,1),0) -> 0 | J63: =IF(J57>0,CEILING(J62/J57,1),0) -> 0 | K63: =IF(K57>0,CEILING(K62/K57,1),0) -> 0
B64: Pedido (lotes*batch) | C64: =0 -> 0 | D64: =D63*D57 -> 0 | E64: =E63*E57 -> 0 | F64: =F63*F57 -> 0 | G64: =G63*G57 -> 0 | H64: =H63*H57 -> 0 | I64: =I63*I57 -> 0 | J64: =J63*J57 -> 0 | K64: =K63*K57 -> 0 | L64: =SUM(D64:K64) -> 0
B65: Inv Final | C65: =C61 -> 3125 | D65: =D61+D64*(1)-D60 -> 3125 | E65: =E61+E64*(1)-E60 -> 2825 | F65: =F61+F64*(1)-F60 -> 2825 | G65: =G61+G64*(1)-G60 -> 2525 | H65: =H61+H64*(1)-H60 -> 2525 | I65: =I61+I64*(1)-I60 -> 2225 | J65: =J61+J64*(1)-J60 -> 2225 | K65: =K61+K64*(1)-K60 -> 1925
B66: Ordering Cost | C66: =0 -> 0 | D66: =IF(D64>0,0,0) -> 0 | E66: =IF(E64>0,0,0) -> 0 | F66: =IF(F64>0,0,0) -> 0 | G66: =IF(G64>0,0,0) -> 0 | H66: =IF(H64>0,0,0) -> 0 | I66: =IF(I64>0,0,0) -> 0 | J66: =IF(J64>0,0,0) -> 0 | K66: =IF(K64>0,0,0) -> 0 | L66: =SUM(D66:K66) -> 0
B67: Holding Cost | C67: =0 -> 0 | D67: =D65*0 -> 0 | E67: =E65*0 -> 0 | F67: =F65*0 -> 0 | G67: =G65*0 -> 0 | H67: =H65*0 -> 0 | I67: =I65*0 -> 0 | J67: =J65*0 -> 0 | K67: =K65*0 -> 0 | L67: =SUM(D67:K67) -> 0
A69: Piece 4
B70: Batch Size | C70: ='01_INPUTS_MASTER'!B43 -> 60 | D70: ='01_INPUTS_MASTER'!B43 -> 60 | E70: ='01_INPUTS_MASTER'!B43 -> 60 | F70: ='01_INPUTS_MASTER'!B43 -> 60 | G70: ='01_INPUTS_MASTER'!B43 -> 60 | H70: ='01_INPUTS_MASTER'!B43 -> 60 | I70: ='01_INPUTS_MASTER'!B43 -> 60 | J70: ='01_INPUTS_MASTER'!B43 -> 60 | K70: ='01_INPUTS_MASTER'!B43 -> 60
B71: Consumo/EC | C71: ='01_INPUTS_MASTER'!D43 -> 0.6 | D71: ='01_INPUTS_MASTER'!D43 -> 0.6 | E71: ='01_INPUTS_MASTER'!D43 -> 0.6 | F71: ='01_INPUTS_MASTER'!D43 -> 0.6 | G71: ='01_INPUTS_MASTER'!D43 -> 0.6 | H71: ='01_INPUTS_MASTER'!D43 -> 0.6 | I71: ='01_INPUTS_MASTER'!D43 -> 0.6 | J71: ='01_INPUTS_MASTER'!D43 -> 0.6 | K71: ='01_INPUTS_MASTER'!D43 -> 0.6
B72: Producción Plan | C72: =0 -> 0 | D72: ='04_FLOW_S1_S5'!D7 -> 0 | E72: ='04_FLOW_S1_S5'!E7 -> 1000 | F72: ='04_FLOW_S1_S5'!F7 -> 0 | G72: ='04_FLOW_S1_S5'!G7 -> 1000 | H72: ='04_FLOW_S1_S5'!H7 -> 0 | I72: ='04_FLOW_S1_S5'!I7 -> 1000 | J72: ='04_FLOW_S1_S5'!J7 -> 0 | K72: ='04_FLOW_S1_S5'!K7 -> 1000
B73: Req Bruto | C73: =0 -> 0 | D73: =D72*D71 -> 0 | E73: =E72*E71 -> 600 | F73: =F72*F71 -> 0 | G73: =G72*G71 -> 600 | H73: =H72*H71 -> 0 | I73: =I72*I71 -> 600 | J73: =J72*J71 -> 0 | K73: =K72*K71 -> 600 | L73: =SUM(D73:K73) -> 2400
B74: Inv Inicial | C74: ='01_INPUTS_MASTER'!E43 -> 6131 | D74: =C74 -> 6131 | E74: =D78 -> 6131 | F74: =E78 -> 5531 | G74: =F78 -> 5531 | H74: =G78 -> 4931 | I74: =H78 -> 4931 | J74: =I78 -> 4331 | K74: =J78 -> 4331
B75: Req Neto | C75: =0 -> 0 | D75: =MAX(0,D73-D74) -> 0 | E75: =MAX(0,E73-E74) -> 0 | F75: =MAX(0,F73-F74) -> 0 | G75: =MAX(0,G73-G74) -> 0 | H75: =MAX(0,H73-H74) -> 0 | I75: =MAX(0,I73-I74) -> 0 | J75: =MAX(0,J73-J74) -> 0 | K75: =MAX(0,K73-K74) -> 0
B76: Lotes a Pedir | C76: =0 -> 0 | D76: =IF(D70>0,CEILING(D75/D70,1),0) -> 0 | E76: =IF(E70>0,CEILING(E75/E70,1),0) -> 0 | F76: =IF(F70>0,CEILING(F75/F70,1),0) -> 0 | G76: =IF(G70>0,CEILING(G75/G70,1),0) -> 0 | H76: =IF(H70>0,CEILING(H75/H70,1),0) -> 0 | I76: =IF(I70>0,CEILING(I75/I70,1),0) -> 0 | J76: =IF(J70>0,CEILING(J75/J70,1),0) -> 0 | K76: =IF(K70>0,CEILING(K75/K70,1),0) -> 0
B77: Pedido (lotes*batch) | C77: =0 -> 0 | D77: =D76*D70 -> 0 | E77: =E76*E70 -> 0 | F77: =F76*F70 -> 0 | G77: =G76*G70 -> 0 | H77: =H76*H70 -> 0 | I77: =I76*I70 -> 0 | J77: =J76*J70 -> 0 | K77: =K76*K70 -> 0 | L77: =SUM(D77:K77) -> 0
B78: Inv Final | C78: =C74 -> 6131 | D78: =D74+D77*(1)-D73 -> 6131 | E78: =E74+E77*(1)-E73 -> 5531 | F78: =F74+F77*(1)-F73 -> 5531 | G78: =G74+G77*(1)-G73 -> 4931 | H78: =H74+H77*(1)-H73 -> 4931 | I78: =I74+I77*(1)-I73 -> 4331 | J78: =J74+J77*(1)-J73 -> 4331 | K78: =K74+K77*(1)-K73 -> 3731
B79: Ordering Cost | C79: =0 -> 0 | D79: =IF(D77>0,0,0) -> 0 | E79: =IF(E77>0,0,0) -> 0 | F79: =IF(F77>0,0,0) -> 0 | G79: =IF(G77>0,0,0) -> 0 | H79: =IF(H77>0,0,0) -> 0 | I79: =IF(I77>0,0,0) -> 0 | J79: =IF(J77>0,0,0) -> 0 | K79: =IF(K77>0,0,0) -> 0 | L79: =SUM(D79:K79) -> 0
B80: Holding Cost | C80: =0 -> 0 | D80: =D78*0 -> 0 | E80: =E78*0 -> 0 | F80: =F78*0 -> 0 | G80: =G78*0 -> 0 | H80: =H78*0 -> 0 | I80: =I78*0 -> 0 | J80: =J78*0 -> 0 | K80: =K78*0 -> 0 | L80: =SUM(D80:K80) -> 0
A82: Piece 5
B83: Batch Size | C83: ='01_INPUTS_MASTER'!B44 -> 100 | D83: ='01_INPUTS_MASTER'!B44 -> 100 | E83: ='01_INPUTS_MASTER'!B44 -> 100 | F83: ='01_INPUTS_MASTER'!B44 -> 100 | G83: ='01_INPUTS_MASTER'!B44 -> 100 | H83: ='01_INPUTS_MASTER'!B44 -> 100 | I83: ='01_INPUTS_MASTER'!B44 -> 100 | J83: ='01_INPUTS_MASTER'!B44 -> 100 | K83: ='01_INPUTS_MASTER'!B44 -> 100
B84: Consumo/EC | C84: ='01_INPUTS_MASTER'!D44 -> 2 | D84: ='01_INPUTS_MASTER'!D44 -> 2 | E84: ='01_INPUTS_MASTER'!D44 -> 2 | F84: ='01_INPUTS_MASTER'!D44 -> 2 | G84: ='01_INPUTS_MASTER'!D44 -> 2 | H84: ='01_INPUTS_MASTER'!D44 -> 2 | I84: ='01_INPUTS_MASTER'!D44 -> 2 | J84: ='01_INPUTS_MASTER'!D44 -> 2 | K84: ='01_INPUTS_MASTER'!D44 -> 2
B85: Producción Plan | C85: =0 -> 0 | D85: ='04_FLOW_S1_S5'!D7 -> 0 | E85: ='04_FLOW_S1_S5'!E7 -> 1000 | F85: ='04_FLOW_S1_S5'!F7 -> 0 | G85: ='04_FLOW_S1_S5'!G7 -> 1000 | H85: ='04_FLOW_S1_S5'!H7 -> 0 | I85: ='04_FLOW_S1_S5'!I7 -> 1000 | J85: ='04_FLOW_S1_S5'!J7 -> 0 | K85: ='04_FLOW_S1_S5'!K7 -> 1000
B86: Req Bruto | C86: =0 -> 0 | D86: =D85*D84 -> 0 | E86: =E85*E84 -> 2000 | F86: =F85*F84 -> 0 | G86: =G85*G84 -> 2000 | H86: =H85*H84 -> 0 | I86: =I85*I84 -> 2000 | J86: =J85*J84 -> 0 | K86: =K85*K84 -> 2000 | L86: =SUM(D86:K86) -> 8000
B87: Inv Inicial | C87: ='01_INPUTS_MASTER'!E44 -> 16736 | D87: =C87 -> 16736 | E87: =D91 -> 16736 | F87: =E91 -> 14736 | G87: =F91 -> 14736 | H87: =G91 -> 12736 | I87: =H91 -> 12736 | J87: =I91 -> 10736 | K87: =J91 -> 10736
B88: Req Neto | C88: =0 -> 0 | D88: =MAX(0,D86-D87) -> 0 | E88: =MAX(0,E86-E87) -> 0 | F88: =MAX(0,F86-F87) -> 0 | G88: =MAX(0,G86-G87) -> 0 | H88: =MAX(0,H86-H87) -> 0 | I88: =MAX(0,I86-I87) -> 0 | J88: =MAX(0,J86-J87) -> 0 | K88: =MAX(0,K86-K87) -> 0
B89: Lotes a Pedir | C89: =0 -> 0 | D89: =IF(D83>0,CEILING(D88/D83,1),0) -> 0 | E89: =IF(E83>0,CEILING(E88/E83,1),0) -> 0 | F89: =IF(F83>0,CEILING(F88/F83,1),0) -> 0 | G89: =IF(G83>0,CEILING(G88/G83,1),0) -> 0 | H89: =IF(H83>0,CEILING(H88/H83,1),0) -> 0 | I89: =IF(I83>0,CEILING(I88/I83,1),0) -> 0 | J89: =IF(J83>0,CEILING(J88/J83,1),0) -> 0 | K89: =IF(K83>0,CEILING(K88/K83,1),0) -> 0
B90: Pedido (lotes*batch) | C90: =0 -> 0 | D90: =D89*D83 -> 0 | E90: =E89*E83 -> 0 | F90: =F89*F83 -> 0 | G90: =G89*G83 -> 0 | H90: =H89*H83 -> 0 | I90: =I89*I83 -> 0 | J90: =J89*J83 -> 0 | K90: =K89*K83 -> 0 | L90: =SUM(D90:K90) -> 0
B91: Inv Final | C91: =C87 -> 16736 | D91: =D87+D90*(1)-D86 -> 16736 | E91: =E87+E90*(1)-E86 -> 14736 | F91: =F87+F90*(1)-F86 -> 14736 | G91: =G87+G90*(1)-G86 -> 12736 | H91: =H87+H90*(1)-H86 -> 12736 | I91: =I87+I90*(1)-I86 -> 10736 | J91: =J87+J90*(1)-J86 -> 10736 | K91: =K87+K90*(1)-K86 -> 8736
B92: Ordering Cost | C92: =0 -> 0 | D92: =IF(D90>0,0,0) -> 0 | E92: =IF(E90>0,0,0) -> 0 | F92: =IF(F90>0,0,0) -> 0 | G92: =IF(G90>0,0,0) -> 0 | H92: =IF(H90>0,0,0) -> 0 | I92: =IF(I90>0,0,0) -> 0 | J92: =IF(J90>0,0,0) -> 0 | K92: =IF(K90>0,0,0) -> 0 | L92: =SUM(D92:K92) -> 0
B93: Holding Cost | C93: =0 -> 0 | D93: =D91*0 -> 0 | E93: =E91*0 -> 0 | F93: =F91*0 -> 0 | G93: =G91*0 -> 0 | H93: =H91*0 -> 0 | I93: =I91*0 -> 0 | J93: =J91*0 -> 0 | K93: =K91*0 -> 0 | L93: =SUM(D93:K93) -> 0
A95: Piece 6
B96: Batch Size | C96: ='01_INPUTS_MASTER'!B45 -> 150 | D96: ='01_INPUTS_MASTER'!B45 -> 150 | E96: ='01_INPUTS_MASTER'!B45 -> 150 | F96: ='01_INPUTS_MASTER'!B45 -> 150 | G96: ='01_INPUTS_MASTER'!B45 -> 150 | H96: ='01_INPUTS_MASTER'!B45 -> 150 | I96: ='01_INPUTS_MASTER'!B45 -> 150 | J96: ='01_INPUTS_MASTER'!B45 -> 150 | K96: ='01_INPUTS_MASTER'!B45 -> 150
B97: Consumo/EC | C97: ='01_INPUTS_MASTER'!D45 -> 0.75 | D97: ='01_INPUTS_MASTER'!D45 -> 0.75 | E97: ='01_INPUTS_MASTER'!D45 -> 0.75 | F97: ='01_INPUTS_MASTER'!D45 -> 0.75 | G97: ='01_INPUTS_MASTER'!D45 -> 0.75 | H97: ='01_INPUTS_MASTER'!D45 -> 0.75 | I97: ='01_INPUTS_MASTER'!D45 -> 0.75 | J97: ='01_INPUTS_MASTER'!D45 -> 0.75 | K97: ='01_INPUTS_MASTER'!D45 -> 0.75
B98: Producción Plan | C98: =0 -> 0 | D98: ='04_FLOW_S1_S5'!D7 -> 0 | E98: ='04_FLOW_S1_S5'!E7 -> 1000 | F98: ='04_FLOW_S1_S5'!F7 -> 0 | G98: ='04_FLOW_S1_S5'!G7 -> 1000 | H98: ='04_FLOW_S1_S5'!H7 -> 0 | I98: ='04_FLOW_S1_S5'!I7 -> 1000 | J98: ='04_FLOW_S1_S5'!J7 -> 0 | K98: ='04_FLOW_S1_S5'!K7 -> 1000
B99: Req Bruto | C99: =0 -> 0 | D99: =D98*D97 -> 0 | E99: =E98*E97 -> 750 | F99: =F98*F97 -> 0 | G99: =G98*G97 -> 750 | H99: =H98*H97 -> 0 | I99: =I98*I97 -> 750 | J99: =J98*J97 -> 0 | K99: =K98*K97 -> 750 | L99: =SUM(D99:K99) -> 3000
B100: Inv Inicial | C100: ='01_INPUTS_MASTER'!E45 -> 4439 | D100: =C100 -> 4439 | E100: =D104 -> 4439 | F100: =E104 -> 3689 | G100: =F104 -> 3689 | H100: =G104 -> 2939 | I100: =H104 -> 2939 | J100: =I104 -> 2189 | K100: =J104 -> 2189
B101: Req Neto | C101: =0 -> 0 | D101: =MAX(0,D99-D100) -> 0 | E101: =MAX(0,E99-E100) -> 0 | F101: =MAX(0,F99-F100) -> 0 | G101: =MAX(0,G99-G100) -> 0 | H101: =MAX(0,H99-H100) -> 0 | I101: =MAX(0,I99-I100) -> 0 | J101: =MAX(0,J99-J100) -> 0 | K101: =MAX(0,K99-K100) -> 0
B102: Lotes a Pedir | C102: =0 -> 0 | D102: =IF(D96>0,CEILING(D101/D96,1),0) -> 0 | E102: =IF(E96>0,CEILING(E101/E96,1),0) -> 0 | F102: =IF(F96>0,CEILING(F101/F96,1),0) -> 0 | G102: =IF(G96>0,CEILING(G101/G96,1),0) -> 0 | H102: =IF(H96>0,CEILING(H101/H96,1),0) -> 0 | I102: =IF(I96>0,CEILING(I101/I96,1),0) -> 0 | J102: =IF(J96>0,CEILING(J101/J96,1),0) -> 0 | K102: =IF(K96>0,CEILING(K101/K96,1),0) -> 0
B103: Pedido (lotes*batch) | C103: =0 -> 0 | D103: =D102*D96 -> 0 | E103: =E102*E96 -> 0 | F103: =F102*F96 -> 0 | G103: =G102*G96 -> 0 | H103: =H102*H96 -> 0 | I103: =I102*I96 -> 0 | J103: =J102*J96 -> 0 | K103: =K102*K96 -> 0 | L103: =SUM(D103:K103) -> 0
B104: Inv Final | C104: =C100 -> 4439 | D104: =D100+D103*(1)-D99 -> 4439 | E104: =E100+E103*(1)-E99 -> 3689 | F104: =F100+F103*(1)-F99 -> 3689 | G104: =G100+G103*(1)-G99 -> 2939 | H104: =H100+H103*(1)-H99 -> 2939 | I104: =I100+I103*(1)-I99 -> 2189 | J104: =J100+J103*(1)-J99 -> 2189 | K104: =K100+K103*(1)-K99 -> 1439
B105: Ordering Cost | C105: =0 -> 0 | D105: =IF(D103>0,0,0) -> 0 | E105: =IF(E103>0,0,0) -> 0 | F105: =IF(F103>0,0,0) -> 0 | G105: =IF(G103>0,0,0) -> 0 | H105: =IF(H103>0,0,0) -> 0 | I105: =IF(I103>0,0,0) -> 0 | J105: =IF(J103>0,0,0) -> 0 | K105: =IF(K103>0,0,0) -> 0 | L105: =SUM(D105:K105) -> 0
B106: Holding Cost | C106: =0 -> 0 | D106: =D104*0 -> 0 | E106: =E104*0 -> 0 | F106: =F104*0 -> 0 | G106: =G104*0 -> 0 | H106: =H104*0 -> 0 | I106: =I104*0 -> 0 | J106: =J104*0 -> 0 | K106: =K104*0 -> 0 | L106: =SUM(D106:K106) -> 0
A109: PLANT: WEST
...

Sheet 07_SPACES
A1: ANÁLISIS DE ESPACIOS Y MÓDULOS
A3: Planta | B3: Concepto | C3: Valor
A4: Center
B5: M1 qty | C5: 7
B6: M1 espacios/maq | C6: 1
B7: M2 qty | C7: 22
B8: M2 espacios/maq | C8: 1
B9: M3a qty | C9: 3
B10: M3a espacios/maq | C10: 5
B11: M3b qty | C11: 0
B12: M3b espacios/maq | C12: 6
B13: M4 qty total | C13: 25
B14: M4 espacios/maq | C14: 1
B15: Espacios Usados | C15: =C5*C6+C7*C8+C9*C10+C11*C12+C13*C14 -> 69
B16: Módulos Actuales | C16: 4
B17: Espacios Disponibles | C17: =C16*18 -> 72
B18: Faltante | C18: =MAX(0,C15-C17) -> 0
B19: Módulos Requeridos | C19: =CEILING(C15/18,1) -> 4
B20: ALERTA | C20: =IF(C18>0,"⚠️ FALTA ESPACIO","✓ OK") -> ✓ OK
A22: West
B23: M1 qty | C23: 3
B24: M1 espacios/maq | C24: 1
B25: M2 qty | C25: 9
B26: M2 espacios/maq | C26: 1
B27: M3a qty | C27: 1
B28: M3a espacios/maq | C28: 5
B29: M3b qty | C29: 0
B30: M3b espacios/maq | C30: 6
B31: M4 qty total | C31: 8
B32: M4 espacios/maq | C32: 1
B33: Espacios Usados | C33: =C23*C24+C25*C26+C27*C28+C29*C30+C31*C32 -> 25
B34: Módulos Actuales | C34: 2
B35: Espacios Disponibles | C35: =C34*18 -> 36
B36: Faltante | C36: =MAX(0,C33-C35) -> 0
B37: Módulos Requeridos | C37: =CEILING(C33/18,1) -> 2
B38: ALERTA | C38: =IF(C36>0,"⚠️ FALTA ESPACIO","✓ OK") -> ✓ OK

Sheet 08_COSTING
A1: ANÁLISIS DE COSTOS DE PRODUCCIÓN
A3: Concepto | B3: S1 | C3: S2 | D3: S3 | E3: S4 | F3: S5 | G3: S6 | H3: S7 | I3: S8 | J3: TOTAL PERIODO
A4: LABOR
A5: # Workers | B5: =SUM('10_DECISIONS_UPLOAD'!C13:C19,'10_DECISIONS_UPLOAD'!C20:C26) -> 290 | C5: =SUM('10_DECISIONS_UPLOAD'!C13:C19,'10_DECISIONS_UPLOAD'!C20:C26) -> 290 | D5: =SUM('10_DECISIONS_UPLOAD'!C13:C19,'10_DECISIONS_UPLOAD'!C20:C26) -> 290 | E5: =SUM('10_DECISIONS_UPLOAD'!C13:C19,'10_DECISIONS_UPLOAD'!C20:C26) -> 290 | F5: =SUM('10_DECISIONS_UPLOAD'!C13:C19,'10_DECISIONS_UPLOAD'!C20:C26) -> 290 | G5: =SUM('10_DECISIONS_UPLOAD'!C13:C19,'10_DECISIONS_UPLOAD'!C20:C26) -> 290 | H5: =SUM('10_DECISIONS_UPLOAD'!C13:C19,'10_DECISIONS_UPLOAD'!C20:C26) -> 290 | I5: =SUM('10_DECISIONS_UPLOAD'!C13:C19,'10_DECISIONS_UPLOAD'!C20:C26) -> 290 | J5: =SUM(B5:I5) -> 2320
A6: Salario/worker/quinc | B6: ='01_INPUTS_MASTER'!B27 -> 26 | C6: ='01_INPUTS_MASTER'!B27 -> 26 | D6: ='01_INPUTS_MASTER'!B27 -> 26 | E6: ='01_INPUTS_MASTER'!B27 -> 26 | F6: ='01_INPUTS_MASTER'!B27 -> 26 | G6: ='01_INPUTS_MASTER'!B27 -> 26 | H6: ='01_INPUTS_MASTER'!B27 -> 26 | I6: ='01_INPUTS_MASTER'!B27 -> 26 | J6: =SUM(B6:I6) -> 208
A7: Total Salarios | B7: =B5*B6 -> 7540 | C7: =C5*C6 -> 7540 | D7: =D5*D6 -> 7540 | E7: =E5*E6 -> 7540 | F7: =F5*F6 -> 7540 | G7: =G5*G6 -> 7540 | H7: =H5*H6 -> 7540 | I7: =I5*I6 -> 7540 | J7: =SUM(B7:I7) -> 60320
A8: # Workers Overtime | B8: ='05_CAPACITY'!D8*'05_CAPACITY'!D12+'05_CAPACITY'!D21*'05_CAPACITY'!D25+'05_CAPACITY'!D34*'05_CAPACITY'!D38+'05_CAPACITY'!D47*'05_CAPACITY'!D51+'05_CAPACITY'!D60*'05_CAPACITY'!D64+'05_CAPACITY'!D74*'05_CAPACITY'!D78+'05_CAPACITY'!D87*'05_CAPACITY'!D91+'05_CAPACITY'!D100*'05_CAPACITY'!D104+'05_CAPACITY'!D113*'05_CAPACITY'!D117+'05_CAPACITY'!D126*'05_CAPACITY'!D130 -> 0 | C8: ='05_CAPACITY'!E8*'05_CAPACITY'!E12+'05_CAPACITY'!E21*'05_CAPACITY'!E25+'05_CAPACITY'!E34*'05_CAPACITY'!E38+'05_CAPACITY'!E47*'05_CAPACITY'!E51+'05_CAPACITY'!E60*'05_CAPACITY'!E64+'05_CAPACITY'!E74*'05_CAPACITY'!E78+'05_CAPACITY'!E87*'05_CAPACITY'!E91+'05_CAPACITY'!E100*'05_CAPACITY'!E104+'05_CAPACITY'!E113*'05_CAPACITY'!E117+'05_CAPACITY'!E126*'05_CAPACITY'!E130 -> 0 | D8: ='05_CAPACITY'!F8*'05_CAPACITY'!F12+'05_CAPACITY'!F21*'05_CAPACITY'!F25+'05_CAPACITY'!F34*'05_CAPACITY'!F38+'05_CAPACITY'!F47*'05_CAPACITY'!F51+'05_CAPACITY'!F60*'05_CAPACITY'!F64+'05_CAPACITY'!F74*'05_CAPACITY'!F78+'05_CAPACITY'!F87*'05_CAPACITY'!F91+'05_CAPACITY'!F100*'05_CAPACITY'!F104+'05_CAPACITY'!F113*'05_CAPACITY'!F117+'05_CAPACITY'!F126*'05_CAPACITY'!F130 -> 0 | E8: ='05_CAPACITY'!G8*'05_CAPACITY'!G12+'05_CAPACITY'!G21*'05_CAPACITY'!G25+'05_CAPACITY'!G34*'05_CAPACITY'!G38+'05_CAPACITY'!G47*'05_CAPACITY'!G51+'05_CAPACITY'!G60*'05_CAPACITY'!G64+'05_CAPACITY'!G74*'05_CAPACITY'!G78+'05_CAPACITY'!G87*'05_CAPACITY'!G91+'05_CAPACITY'!G100*'05_CAPACITY'!G104+'05_CAPACITY'!G113*'05_CAPACITY'!G117+'05_CAPACITY'!G126*'05_CAPACITY'!G130 -> 0 | F8: ='05_CAPACITY'!H8*'05_CAPACITY'!H12+'05_CAPACITY'!H21*'05_CAPACITY'!H25+'05_CAPACITY'!H34*'05_CAPACITY'!H38+'05_CAPACITY'!H47*'05_CAPACITY'!H51+'05_CAPACITY'!H60*'05_CAPACITY'!H64+'05_CAPACITY'!H74*'05_CAPACITY'!H78+'05_CAPACITY'!H87*'05_CAPACITY'!H91+'05_CAPACITY'!H100*'05_CAPACITY'!H104+'05_CAPACITY'!H113*'05_CAPACITY'!H117+'05_CAPACITY'!H126*'05_CAPACITY'!H130 -> 0 | G8: ='05_CAPACITY'!I8*'05_CAPACITY'!I12+'05_CAPACITY'!I21*'05_CAPACITY'!I25+'05_CAPACITY'!I34*'05_CAPACITY'!I38+'05_CAPACITY'!I47*'05_CAPACITY'!I51+'05_CAPACITY'!I60*'05_CAPACITY'!I64+'05_CAPACITY'!I74*'05_CAPACITY'!I78+'05_CAPACITY'!I87*'05_CAPACITY'!I91+'05_CAPACITY'!I100*'05_CAPACITY'!I104+'05_CAPACITY'!I113*'05_CAPACITY'!I117+'05_CAPACITY'!I126*'05_CAPACITY'!I130 -> 0 | H8: ='05_CAPACITY'!J8*'05_CAPACITY'!J12+'05_CAPACITY'!J21*'05_CAPACITY'!J25+'05_CAPACITY'!J34*'05_CAPACITY'!J38+'05_CAPACITY'!J47*'05_CAPACITY'!J51+'05_CAPACITY'!J60*'05_CAPACITY'!J64+'05_CAPACITY'!J74*'05_CAPACITY'!J78+'05_CAPACITY'!J87*'05_CAPACITY'!J91+'05_CAPACITY'!J100*'05_CAPACITY'!J104+'05_CAPACITY'!J113*'05_CAPACITY'!J117+'05_CAPACITY'!J126*'05_CAPACITY'!J130 -> 0 | I8: ='05_CAPACITY'!K8*'05_CAPACITY'!K12+'05_CAPACITY'!K21*'05_CAPACITY'!K25+'05_CAPACITY'!K34*'05_CAPACITY'!K38+'05_CAPACITY'!K47*'05_CAPACITY'!K51+'05_CAPACITY'!K60*'05_CAPACITY'!K64+'05_CAPACITY'!K74*'05_CAPACITY'!K78+'05_CAPACITY'!K87*'05_CAPACITY'!K91+'05_CAPACITY'!K100*'05_CAPACITY'!K104+'05_CAPACITY'!K113*'05_CAPACITY'!K117+'05_CAPACITY'!K126*'05_CAPACITY'!K130 -> 0 | J8: =SUM(B8:I8) -> 0
A9: Overtime cost/worker | B9: ='01_INPUTS_MASTER'!B28 -> 12 | C9: ='01_INPUTS_MASTER'!B28 -> 12 | D9: ='01_INPUTS_MASTER'!B28 -> 12 | E9: ='01_INPUTS_MASTER'!B28 -> 12 | F9: ='01_INPUTS_MASTER'!B28 -> 12 | G9: ='01_INPUTS_MASTER'!B28 -> 12 | H9: ='01_INPUTS_MASTER'!B28 -> 12 | I9: ='01_INPUTS_MASTER'!B28 -> 12 | J9: =SUM(B9:I9) -> 96
A10: Total Overtime | B10: =B8*B9 -> 0 | C10: =C8*C9 -> 0 | D10: =D8*D9 -> 0 | E10: =E8*E9 -> 0 | F10: =F8*F9 -> 0 | G10: =G8*G9 -> 0 | H10: =H8*H9 -> 0 | I10: =I8*I9 -> 0 | J10: =SUM(B10:I10) -> 0
A11: Total Labor | B11: =B7+B10 -> 7540 | C11: =C7+C10 -> 7540 | D11: =D7+D10 -> 7540 | E11: =E7+E10 -> 7540 | F11: =F7+F10 -> 7540 | G11: =G7+G10 -> 7540 | H11: =H7+H10 -> 7540 | I11: =I7+I10 -> 7540 | J11: =SUM(B11:I11) -> 60320
A12: Indirect Labor (50%) | B12: =B11*'01_INPUTS_MASTER'!B31 -> 3770 | C12: =C11*'01_INPUTS_MASTER'!B31 -> 3770 | D12: =D11*'01_INPUTS_MASTER'!B31 -> 3770 | E12: =E11*'01_INPUTS_MASTER'!B31 -> 3770 | F12: =F11*'01_INPUTS_MASTER'!B31 -> 3770 | G12: =G11*'01_INPUTS_MASTER'!B31 -> 3770 | H12: =H11*'01_INPUTS_MASTER'!B31 -> 3770 | I12: =I11*'01_INPUTS_MASTER'!B31 -> 3770 | J12: =SUM(B12:I12) -> 30160
A14: ENERGÍA
A15: kW instalados | B15: ='01_INPUTS_MASTER'!D17*('01_INPUTS_MASTER'!H17+'01_INPUTS_MASTER'!I17)+'01_INPUTS_MASTER'!D18*('01_INPUTS_MASTER'!H18+'01_INPUTS_MASTER'!I18)+'01_INPUTS_MASTER'!D19*('01_INPUTS_MASTER'!H19+'01_INPUTS_MASTER'!I19)+'01_INPUTS_MASTER'!D20*('01_INPUTS_MASTER'!H20+'01_INPUTS_MASTER'!I20)+'01_INPUTS_MASTER'!D21*('01_INPUTS_MASTER'!H21+'01_INPUTS_MASTER'!I21)+'01_INPUTS_MASTER'!D22*('01_INPUTS_MASTER'!H22+'01_INPUTS_MASTER'!I22)+'01_INPUTS_MASTER'!D23*('01_INPUTS_MASTER'!H23+'01_INPUTS_MASTER'!I23) -> 637 | C15: ='01_INPUTS_MASTER'!D17*('01_INPUTS_MASTER'!H17+'01_INPUTS_MASTER'!I17)+'01_INPUTS_MASTER'!D18*('01_INPUTS_MASTER'!H18+'01_INPUTS_MASTER'!I18)+'01_INPUTS_MASTER'!D19*('01_INPUTS_MASTER'!H19+'01_INPUTS_MASTER'!I19)+'01_INPUTS_MASTER'!D20*('01_INPUTS_MASTER'!H20+'01_INPUTS_MASTER'!I20)+'01_INPUTS_MASTER'!D21*('01_INPUTS_MASTER'!H21+'01_INPUTS_MASTER'!I21)+'01_INPUTS_MASTER'!D22*('01_INPUTS_MASTER'!H22+'01_INPUTS_MASTER'!I22)+'01_INPUTS_MASTER'!D23*('01_INPUTS_MASTER'!H23+'01_INPUTS_MASTER'!I23) -> 637 | D15: ='01_INPUTS_MASTER'!D17*('01_INPUTS_MASTER'!H17+'01_INPUTS_MASTER'!I17)+'01_INPUTS_MASTER'!D18*('01_INPUTS_MASTER'!H18+'01_INPUTS_MASTER'!I18)+'01_INPUTS_MASTER'!D19*('01_INPUTS_MASTER'!H19+'01_INPUTS_MASTER'!I19)+'01_INPUTS_MASTER'!D20*('01_INPUTS_MASTER'!H20+'01_INPUTS_MASTER'!I20)+'01_INPUTS_MASTER'!D21*('01_INPUTS_MASTER'!H21+'01_INPUTS_MASTER'!I21)+'01_INPUTS_MASTER'!D22*('01_INPUTS_MASTER'!H22+'01_INPUTS_MASTER'!I22)+'01_INPUTS_MASTER'!D23*('01_INPUTS_MASTER'!H23+'01_INPUTS_MASTER'!I23) -> 637 | E15: ='01_INPUTS_MASTER'!D17*('01_INPUTS_MASTER'!H17+'01_INPUTS_MASTER'!I17)+'01_INPUTS_MASTER'!D18*('01_INPUTS_MASTER'!H18+'01_INPUTS_MASTER'!I18)+'01_INPUTS_MASTER'!D19*('01_INPUTS_MASTER'!H19+'01_INPUTS_MASTER'!I19)+'01_INPUTS_MASTER'!D20*('01_INPUTS_MASTER'!H20+'01_INPUTS_MASTER'!I20)+'01_INPUTS_MASTER'!D21*('01_INPUTS_MASTER'!H21+'01_INPUTS_MASTER'!I21)+'01_INPUTS_MASTER'!D22*('01_INPUTS_MASTER'!H22+'01_INPUTS_MASTER'!I22)+'01_INPUTS_MASTER'!D23*('01_INPUTS_MASTER'!H23+'01_INPUTS_MASTER'!I23) -> 637 | F15: ='01_INPUTS_MASTER'!D17*('01_INPUTS_MASTER'!H17+'01_INPUTS_MASTER'!I17)+'01_INPUTS_MASTER'!D18*('01_INPUTS_MASTER'!H18+'01_INPUTS_MASTER'!I18)+'01_INPUTS_MASTER'!D19*('01_INPUTS_MASTER'!H19+'01_INPUTS_MASTER'!I19)+'01_INPUTS_MASTER'!D20*('01_INPUTS_MASTER'!H20+'01_INPUTS_MASTER'!I20)+'01_INPUTS_MASTER'!D21*('01_INPUTS_MASTER'!H21+'01_INPUTS_MASTER'!I21)+'01_INPUTS_MASTER'!D22*('01_INPUTS_MASTER'!H22+'01_INPUTS_MASTER'!I22)+'01_INPUTS_MASTER'!D23*('01_INPUTS_MASTER'!H23+'01_INPUTS_MASTER'!I23) -> 637 | G15: ='01_INPUTS_MASTER'!D17*('01_INPUTS_MASTER'!H17+'01_INPUTS_MASTER'!I17)+'01_INPUTS_MASTER'!D18*('01_INPUTS_MASTER'!H18+'01_INPUTS_MASTER'!I18)+'01_INPUTS_MASTER'!D19*('01_INPUTS_MASTER'!H19+'01_INPUTS_MASTER'!I19)+'01_INPUTS_MASTER'!D20*('01_INPUTS_MASTER'!H20+'01_INPUTS_MASTER'!I20)+'01_INPUTS_MASTER'!D21*('01_INPUTS_MASTER'!H21+'01_INPUTS_MASTER'!I21)+'01_INPUTS_MASTER'!D22*('01_INPUTS_MASTER'!H22+'01_INPUTS_MASTER'!I22)+'01_INPUTS_MASTER'!D23*('01_INPUTS_MASTER'!H23+'01_INPUTS_MASTER'!I23) -> 637 | H15: ='01_INPUTS_MASTER'!D17*('01_INPUTS_MASTER'!H17+'01_INPUTS_MASTER'!I17)+'01_INPUTS_MASTER'!D18*('01_INPUTS_MASTER'!H18+'01_INPUTS_MASTER'!I18)+'01_INPUTS_MASTER'!D19*('01_INPUTS_MASTER'!H19+'01_INPUTS_MASTER'!I19)+'01_INPUTS_MASTER'!D20*('01_INPUTS_MASTER'!H20+'01_INPUTS_MASTER'!I20)+'01_INPUTS_MASTER'!D21*('01_INPUTS_MASTER'!H21+'01_INPUTS_MASTER'!I21)+'01_INPUTS_MASTER'!D22*('01_INPUTS_MASTER'!H22+'01_INPUTS_MASTER'!I22)+'01_INPUTS_MASTER'!D23*('01_INPUTS_MASTER'!H23+'01_INPUTS_MASTER'!I23) -> 637 | I15: ='01_INPUTS_MASTER'!D17*('01_INPUTS_MASTER'!H17+'01_INPUTS_MASTER'!I17)+'01_INPUTS_MASTER'!D18*('01_INPUTS_MASTER'!H18+'01_INPUTS_MASTER'!I18)+'01_INPUTS_MASTER'!D19*('01_INPUTS_MASTER'!H19+'01_INPUTS_MASTER'!I19)+'01_INPUTS_MASTER'!D20*('01_INPUTS_MASTER'!H20+'01_INPUTS_MASTER'!I20)+'01_INPUTS_MASTER'!D21*('01_INPUTS_MASTER'!H21+'01_INPUTS_MASTER'!I21)+'01_INPUTS_MASTER'!D22*('01_INPUTS_MASTER'!H22+'01_INPUTS_MASTER'!I22)+'01_INPUTS_MASTER'!D23*('01_INPUTS_MASTER'!H23+'01_INPUTS_MASTER'!I23) -> 637 | J15: =SUM(B15:I15) -> 5096
A16: Costo fijo ($/kW/periodo) | B16: ='01_INPUTS_MASTER'!B34 -> 10 | C16: ='01_INPUTS_MASTER'!B34 -> 10 | D16: ='01_INPUTS_MASTER'!B34 -> 10 | E16: ='01_INPUTS_MASTER'!B34 -> 10 | F16: ='01_INPUTS_MASTER'!B34 -> 10 | G16: ='01_INPUTS_MASTER'!B34 -> 10 | H16: ='01_INPUTS_MASTER'!B34 -> 10 | I16: ='01_INPUTS_MASTER'!B34 -> 10 | J16: =SUM(B16:I16) -> 80
A17: Total Costo Fijo | B17: =B15*B16 -> 6370 | C17: =C15*C16 -> 6370 | D17: =D15*D16 -> 6370 | E17: =E15*E16 -> 6370 | F17: =F15*F16 -> 6370 | G17: =G15*G16 -> 6370 | H17: =H15*H16 -> 6370 | I17: =I15*I16 -> 6370 | J17: =SUM(B17:I17) -> 50960
A18: kWh consumidos | B18: ='01_INPUTS_MASTER'!B36*(('01_INPUTS_MASTER'!D17*('01_INPUTS_MASTER'!H17+'01_INPUTS_MASTER'!I17))*IF(('05_CAPACITY'!D13+'05_CAPACITY'!D79)>0,('05_CAPACITY'!D15+'05_CAPACITY'!D81)/('05_CAPACITY'!D13+'05_CAPACITY'!D79),0)+('01_INPUTS_MASTER'!D18*('01_INPUTS_MASTER'!H18+'01_INPUTS_MASTER'!I18))*IF(('05_CAPACITY'!D26+'05_CAPACITY'!D92)>0,('05_CAPACITY'!D28+'05_CAPACITY'!D94)/('05_CAPACITY'!D26+'05_CAPACITY'!D92),0)+('01_INPUTS_MASTER'!D19*('01_INPUTS_MASTER'!H19+'01_INPUTS_MASTER'!I19)+'01_INPUTS_MASTER'!D20*('01_INPUTS_MASTER'!H20+'01_INPUTS_MASTER'!I20)+'01_INPUTS_MASTER'!D21*('01_INPUTS_MASTER'!H21+'01_INPUTS_MASTER'!I21))*IF(('05_CAPACITY'!D39+'05_CAPACITY'!D105)>0,('05_CAPACITY'!D41+'05_CAPACITY'!D107)/('05_CAPACITY'!D39+'05_CAPACITY'!D105),0)+('01_INPUTS_MASTER'!D22*('01_INPUTS_MASTER'!H22+'01_INPUTS_MASTER'!I22))*IF(('05_CAPACITY'!D52+'05_CAPACITY'!D118)>0,('05_CAPACITY'!D54+'05_CAPACITY'!D120)/('05_CAPACITY'!D52+'05_CAPACITY'!D118),0)+('01_INPUTS_MASTER'!D23*('01_INPUTS_MASTER'!H23+'01_INPUTS_MASTER'!I23))*IF(('05_CAPACITY'!D65+'05_CAPACITY'!D131)>0,('05_CAPACITY'!D67+'05_CAPACITY'!D133)/('05_CAPACITY'!D65+'05_CAPACITY'!D131),0)) -> 27805.714 | C18: ='01_INPUTS_MASTER'!B36*(('01_INPUTS_MASTER'!D17*('01_INPUTS_MASTER'!H17+'01_INPUTS_MASTER'!I17))*IF(('05_CAPACITY'!E13+'05_CAPACITY'!E79)>0,('05_CAPACITY'!E15+'05_CAPACITY'!E81)/('05_CAPACITY'!E13+'05_CAPACITY'!E79),0)+('01_INPUTS_MASTER'!D18*('01_INPUTS_MASTER'!H18+'01_INPUTS_MASTER'!I18))*IF(('05_CAPACITY'!E26+'05_CAPACITY'!E92)>0,('05_CAPACITY'!E28+'05_CAPACITY'!E94)/('05_CAPACITY'!E26+'05_CAPACITY'!E92),0)+('01_INPUTS_MASTER'!D19*('01_INPUTS_MASTER'!H19+'01_INPUTS_MASTER'!I19)+'01_INPUTS_MASTER'!D20*('01_INPUTS_MASTER'!H20+'01_INPUTS_MASTER'!I20)+'01_INPUTS_MASTER'!D21*('01_INPUTS_MASTER'!H21+'01_INPUTS_MASTER'!I21))*IF(('05_CAPACITY'!E39+'05_CAPACITY'!E105)>0,('05_CAPACITY'!E41+'05_CAPACITY'!E107)/('05_CAPACITY'!E39+'05_CAPACITY'!E105),0)+('01_INPUTS_MASTER'!D22*('01_INPUTS_MASTER'!H22+'01_INPUTS_MASTER'!I22))*IF(('05_CAPACITY'!E52+'05_CAPACITY'!E118)>0,('05_CAPACITY'!E54+'05_CAPACITY'!E120)/('05_CAPACITY'!E52+'05_CAPACITY'!E118),0)+('01_INPUTS_MASTER'!D23*('01_INPUTS_MASTER'!H23+'01_INPUTS_MASTER'!I23))*IF(('05_CAPACITY'!E65+'05_CAPACITY'!E131)>0,('05_CAPACITY'!E67+'05_CAPACITY'!E133)/('05_CAPACITY'!E65+'05_CAPACITY'!E131),0)) -> 0 | D18: ='01_INPUTS_MASTER'!B36*(('01_INPUTS_MASTER'!D17*('01_INPUTS_MASTER'!H17+'01_INPUTS_MASTER'!I17))*IF(('05_CAPACITY'!F13+'05_CAPACITY'!F79)>0,('05_CAPACITY'!F15+'05_CAPACITY'!F81)/('05_CAPACITY'!F13+'05_CAPACITY'!F79),0)+('01_INPUTS_MASTER'!D18*('01_INPUTS_MASTER'!H18+'01_INPUTS_MASTER'!I18))*IF(('05_CAPACITY'!F26+'05_CAPACITY'!F92)>0,('05_CAPACITY'!F28+'05_CAPACITY'!F94)/('05_CAPACITY'!F26+'05_CAPACITY'!F92),0)+('01_INPUTS_MASTER'!D19*('01_INPUTS_MASTER'!H19+'01_INPUTS_MASTER'!I19)+'01_INPUTS_MASTER'!D20*('01_INPUTS_MASTER'!H20+'01_INPUTS_MASTER'!I20)+'01_INPUTS_MASTER'!D21*('01_INPUTS_MASTER'!H21+'01_INPUTS_MASTER'!I21))*IF(('05_CAPACITY'!F39+'05_CAPACITY'!F105)>0,('05_CAPACITY'!F41+'05_CAPACITY'!F107)/('05_CAPACITY'!F39+'05_CAPACITY'!F105),0)+('01_INPUTS_MASTER'!D22*('01_INPUTS_MASTER'!H22+'01_INPUTS_MASTER'!I22))*IF(('05_CAPACITY'!F52+'05_CAPACITY'!F118)>0,('05_CAPACITY'!F54+'05_CAPACITY'!F120)/('05_CAPACITY'!F52+'05_CAPACITY'!F118),0)+('01_INPUTS_MASTER'!D23*('01_INPUTS_MASTER'!H23+'01_INPUTS_MASTER'!I23))*IF(('05_CAPACITY'!F65+'05_CAPACITY'!F131)>0,('05_CAPACITY'!F67+'05_CAPACITY'!F133)/('05_CAPACITY'!F65+'05_CAPACITY'!F131),0)) -> 0 | E18: ='01_INPUTS_MASTER'!B36*(('01_INPUTS_MASTER'!D17*('01_INPUTS_MASTER'!H17+'01_INPUTS_MASTER'!I17))*IF(('05_CAPACITY'!G13+'05_CAPACITY'!G79)>0,('05_CAPACITY'!G15+'05_CAPACITY'!G81)/('05_CAPACITY'!G13+'05_CAPACITY'!G79),0)+('01_INPUTS_MASTER'!D18*('01_INPUTS_MASTER'!H18+'01_INPUTS_MASTER'!I18))*IF(('05_CAPACITY'!G26+'05_CAPACITY'!G92)>0,('05_CAPACITY'!G28+'05_CAPACITY'!G94)/('05_CAPACITY'!G26+'05_CAPACITY'!G92),0)+('01_INPUTS_MASTER'!D19*('01_INPUTS_MASTER'!H19+'01_INPUTS_MASTER'!I19)+'01_INPUTS_MASTER'!D20*('01_INPUTS_MASTER'!H20+'01_INPUTS_MASTER'!I20)+'01_INPUTS_MASTER'!D21*('01_INPUTS_MASTER'!H21+'01_INPUTS_MASTER'!I21))*IF(('05_CAPACITY'!G39+'05_CAPACITY'!G105)>0,('05_CAPACITY'!G41+'05_CAPACITY'!G107)/('05_CAPACITY'!G39+'05_CAPACITY'!G105),0)+('01_INPUTS_MASTER'!D22*('01_INPUTS_MASTER'!H22+'01_INPUTS_MASTER'!I22))*IF(('05_CAPACITY'!G52+'05_CAPACITY'!G118)>0,('05_CAPACITY'!G54+'05_CAPACITY'!G120)/('05_CAPACITY'!G52+'05_CAPACITY'!G118),0)+('01_INPUTS_MASTER'!D23*('01_INPUTS_MASTER'!H23+'01_INPUTS_MASTER'!I23))*IF(('05_CAPACITY'!G65+'05_CAPACITY'!G131)>0,('05_CAPACITY'!G67+'05_CAPACITY'!G133)/('05_CAPACITY'!G65+'05_CAPACITY'!G131),0)) -> 0 | F18: ='01_INPUTS_MASTER'!B36*(('01_INPUTS_MASTER'!D17*('01_INPUTS_MASTER'!H17+'01_INPUTS_MASTER'!I17))*IF(('05_CAPACITY'!H13+'05_CAPACITY'!H79)>0,('05_CAPACITY'!H15+'05_CAPACITY'!H81)/('05_CAPACITY'!H13+'05_CAPACITY'!H79),0)+('01_INPUTS_MASTER'!D18*('01_INPUTS_MASTER'!H18+'01_INPUTS_MASTER'!I18))*IF(('05_CAPACITY'!H26+'05_CAPACITY'!H92)>0,('05_CAPACITY'!H28+'05_CAPACITY'!H94)/('05_CAPACITY'!H26+'05_CAPACITY'!H92),0)+('01_INPUTS_MASTER'!D19*('01_INPUTS_MASTER'!H19+'01_INPUTS_MASTER'!I19)+'01_INPUTS_MASTER'!D20*('01_INPUTS_MASTER'!H20+'01_INPUTS_MASTER'!I20)+'01_INPUTS_MASTER'!D21*('01_INPUTS_MASTER'!H21+'01_INPUTS_MASTER'!I21))*IF(('05_CAPACITY'!H39+'05_CAPACITY'!H105)>0,('05_CAPACITY'!H41+'05_CAPACITY'!H107)/('05_CAPACITY'!H39+'05_CAPACITY'!H105),0)+('01_INPUTS_MASTER'!D22*('01_INPUTS_MASTER'!H22+'01_INPUTS_MASTER'!I22))*IF(('05_CAPACITY'!H52+'05_CAPACITY'!H118)>0,('05_CAPACITY'!H54+'05_CAPACITY'!H120)/('05_CAPACITY'!H52+'05_CAPACITY'!H118),0)+('01_INPUTS_MASTER'!D23*('01_INPUTS_MASTER'!H23+'01_INPUTS_MASTER'!I23))*IF(('05_CAPACITY'!H65+'05_CAPACITY'!H131)>0,('05_CAPACITY'!H67+'05_CAPACITY'!H133)/('05_CAPACITY'!H65+'05_CAPACITY'!H131),0)) -> 0 | G18: ='01_INPUTS_MASTER'!B36*(('01_INPUTS_MASTER'!D17*('01_INPUTS_MASTER'!H17+'01_INPUTS_MASTER'!I17))*IF(('05_CAPACITY'!I13+'05_CAPACITY'!I79)>0,('05_CAPACITY'!I15+'05_CAPACITY'!I81)/('05_CAPACITY'!I13+'05_CAPACITY'!I79),0)+('01_INPUTS_MASTER'!D18*('01_INPUTS_MASTER'!H18+'01_INPUTS_MASTER'!I18))*IF(('05_CAPACITY'!I26+'05_CAPACITY'!I92)>0,('05_CAPACITY'!I28+'05_CAPACITY'!I94)/('05_CAPACITY'!I26+'05_CAPACITY'!I92),0)+('01_INPUTS_MASTER'!D19*('01_INPUTS_MASTER'!H19+'01_INPUTS_MASTER'!I19)+'01_INPUTS_MASTER'!D20*('01_INPUTS_MASTER'!H20+'01_INPUTS_MASTER'!I20)+'01_INPUTS_MASTER'!D21*('01_INPUTS_MASTER'!H21+'01_INPUTS_MASTER'!I21))*IF(('05_CAPACITY'!I39+'05_CAPACITY'!I105)>0,('05_CAPACITY'!I41+'05_CAPACITY'!I107)/('05_CAPACITY'!I39+'05_CAPACITY'!I105),0)+('01_INPUTS_MASTER'!D22*('01_INPUTS_MASTER'!H22+'01_INPUTS_MASTER'!I22))*IF(('05_CAPACITY'!I52+'05_CAPACITY'!I118)>0,('05_CAPACITY'!I54+'05_CAPACITY'!I120)/('05_CAPACITY'!I52+'05_CAPACITY'!I118),0)+('01_INPUTS_MASTER'!D23*('01_INPUTS_MASTER'!H23+'01_INPUTS_MASTER'!I23))*IF(('05_CAPACITY'!I65+'05_CAPACITY'!I131)>0,('05_CAPACITY'!I67+'05_CAPACITY'!I133)/('05_CAPACITY'!I65+'05_CAPACITY'!I131),0)) -> 0 | H18: ='01_INPUTS_MASTER'!B36*(('01_INPUTS_MASTER'!D17*('01_INPUTS_MASTER'!H17+'01_INPUTS_MASTER'!I17))*IF(('05_CAPACITY'!J13+'05_CAPACITY'!J79)>0,('05_CAPACITY'!J15+'05_CAPACITY'!J81)/('05_CAPACITY'!J13+'05_CAPACITY'!J79),0)+('01_INPUTS_MASTER'!D18*('01_INPUTS_MASTER'!H18+'01_INPUTS_MASTER'!I18))*IF(('05_CAPACITY'!J26+'05_CAPACITY'!J92)>0,('05_CAPACITY'!J28+'05_CAPACITY'!J94)/('05_CAPACITY'!J26+'05_CAPACITY'!J92),0)+('01_INPUTS_MASTER'!D19*('01_INPUTS_MASTER'!H19+'01_INPUTS_MASTER'!I19)+'01_INPUTS_MASTER'!D20*('01_INPUTS_MASTER'!H20+'01_INPUTS_MASTER'!I20)+'01_INPUTS_MASTER'!D21*('01_INPUTS_MASTER'!H21+'01_INPUTS_MASTER'!I21))*IF(('05_CAPACITY'!J39+'05_CAPACITY'!J105)>0,('05_CAPACITY'!J41+'05_CAPACITY'!J107)/('05_CAPACITY'!J39+'05_CAPACITY'!J105),0)+('01_INPUTS_MASTER'!D22*('01_INPUTS_MASTER'!H22+'01_INPUTS_MASTER'!I22))*IF(('05_CAPACITY'!J52+'05_CAPACITY'!J118)>0,('05_CAPACITY'!J54+'05_CAPACITY'!J120)/('05_CAPACITY'!J52+'05_CAPACITY'!J118),0)+('01_INPUTS_MASTER'!D23*('01_INPUTS_MASTER'!H23+'01_INPUTS_MASTER'!I23))*IF(('05_CAPACITY'!J65+'05_CAPACITY'!J131)>0,('05_CAPACITY'!J67+'05_CAPACITY'!J133)/('05_CAPACITY'!J65+'05_CAPACITY'!J131),0)) -> 0 | I18: ='01_INPUTS_MASTER'!B36*(('01_INPUTS_MASTER'!D17*('01_INPUTS_MASTER'!H17+'01_INPUTS_MASTER'!I17))*IF(('05_CAPACITY'!K13+'05_CAPACITY'!K79)>0,('05_CAPACITY'!K15+'05_CAPACITY'!K81)/('05_CAPACITY'!K13+'05_CAPACITY'!K79),0)+('01_INPUTS_MASTER'!D18*('01_INPUTS_MASTER'!H18+'01_INPUTS_MASTER'!I18))*IF(('05_CAPACITY'!K26+'05_CAPACITY'!K92)>0,('05_CAPACITY'!K28+'05_CAPACITY'!K94)/('05_CAPACITY'!K26+'05_CAPACITY'!K92),0)+('01_INPUTS_MASTER'!D19*('01_INPUTS_MASTER'!H19+'01_INPUTS_MASTER'!I19)+'01_INPUTS_MASTER'!D20*('01_INPUTS_MASTER'!H20+'01_INPUTS_MASTER'!I20)+'01_INPUTS_MASTER'!D21*('01_INPUTS_MASTER'!H21+'01_INPUTS_MASTER'!I21))*IF(('05_CAPACITY'!K39+'05_CAPACITY'!K105)>0,('05_CAPACITY'!K41+'05_CAPACITY'!K107)/('05_CAPACITY'!K39+'05_CAPACITY'!K105),0)+('01_INPUTS_MASTER'!D22*('01_INPUTS_MASTER'!H22+'01_INPUTS_MASTER'!I22))*IF(('05_CAPACITY'!K52+'05_CAPACITY'!K118)>0,('05_CAPACITY'!K54+'05_CAPACITY'!K120)/('05_CAPACITY'!K52+'05_CAPACITY'!K118),0)+('01_INPUTS_MASTER'!D23*('01_INPUTS_MASTER'!H23+'01_INPUTS_MASTER'!I23))*IF(('05_CAPACITY'!K65+'05_CAPACITY'!K131)>0,('05_CAPACITY'!K67+'05_CAPACITY'!K133)/('05_CAPACITY'!K65+'05_CAPACITY'!K131),0)) -> 0 | J18: =SUM(B18:I18) -> 27805.714
A19: Costo variable ($/kWh) | B19: ='01_INPUTS_MASTER'!B35 -> 0.06 | C19: ='01_INPUTS_MASTER'!B35 -> 0.06 | D19: ='01_INPUTS_MASTER'!B35 -> 0.06 | E19: ='01_INPUTS_MASTER'!B35 -> 0.06 | F19: ='01_INPUTS_MASTER'!B35 -> 0.06 | G19: ='01_INPUTS_MASTER'!B35 -> 0.06 | H19: ='01_INPUTS_MASTER'!B35 -> 0.06 | I19: ='01_INPUTS_MASTER'!B35 -> 0.06 | J19: =SUM(B19:I19) -> 0.48
A20: Total Costo Variable | B20: =B18*B19 -> 1668.3429 | C20: =C18*C19 -> 0 | D20: =D18*D19 -> 0 | E20: =E18*E19 -> 0 | F20: =F18*F19 -> 0 | G20: =G18*G19 -> 0 | H20: =H18*H19 -> 0 | I20: =I18*I19 -> 0 | J20: =SUM(B20:I20) -> 1668.3429
A21: Total Energía | B21: =B17+B20 -> 8038.3429 | C21: =C17+C20 -> 6370 | D21: =D17+D20 -> 6370 | E21: =E17+E20 -> 6370 | F21: =F17+F20 -> 6370 | G21: =G17+G20 -> 6370 | H21: =H17+H20 -> 6370 | I21: =I17+I20 -> 6370 | J21: =SUM(B21:I21) -> 52628.343
A23: MATERIALES
A24: Costo Part A | B24: =('06_MRP_MATERIALS'!D12)*(IF('01_INPUTS_MASTER'!M54="A",'01_INPUTS_MASTER'!C49,IF('01_INPUTS_MASTER'!M54="B",'01_INPUTS_MASTER'!D49,IF('01_INPUTS_MASTER'!M54="C",'01_INPUTS_MASTER'!E49,0))))*(1-'01_INPUTS_MASTER'!O54)+('06_MRP_MATERIALS'!D119)*(IF('01_INPUTS_MASTER'!M55="A",'01_INPUTS_MASTER'!C49,IF('01_INPUTS_MASTER'!M55="B",'01_INPUTS_MASTER'!D49,IF('01_INPUTS_MASTER'!M55="C",'01_INPUTS_MASTER'!E49,0))))*(1-'01_INPUTS_MASTER'!O55) -> 0 | C24: =('06_MRP_MATERIALS'!E12)*(IF('01_INPUTS_MASTER'!M54="A",'01_INPUTS_MASTER'!C49,IF('01_INPUTS_MASTER'!M54="B",'01_INPUTS_MASTER'!D49,IF('01_INPUTS_MASTER'!M54="C",'01_INPUTS_MASTER'!E49,0))))*(1-'01_INPUTS_MASTER'!O54)+('06_MRP_MATERIALS'!E119)*(IF('01_INPUTS_MASTER'!M55="A",'01_INPUTS_MASTER'!C49,IF('01_INPUTS_MASTER'!M55="B",'01_INPUTS_MASTER'!D49,IF('01_INPUTS_MASTER'!M55="C",'01_INPUTS_MASTER'!E49,0))))*(1-'01_INPUTS_MASTER'!O55) -> 255000 | D24: =('06_MRP_MATERIALS'!F12)*(IF('01_INPUTS_MASTER'!M54="A",'01_INPUTS_MASTER'!C49,IF('01_INPUTS_MASTER'!M54="B",'01_INPUTS_MASTER'!D49,IF('01_INPUTS_MASTER'!M54="C",'01_INPUTS_MASTER'!E49,0))))*(1-'01_INPUTS_MASTER'!O54)+('06_MRP_MATERIALS'!F119)*(IF('01_INPUTS_MASTER'!M55="A",'01_INPUTS_MASTER'!C49,IF('01_INPUTS_MASTER'!M55="B",'01_INPUTS_MASTER'!D49,IF('01_INPUTS_MASTER'!M55="C",'01_INPUTS_MASTER'!E49,0))))*(1-'01_INPUTS_MASTER'!O55) -> 0 | E24: =('06_MRP_MATERIALS'!G12)*(IF('01_INPUTS_MASTER'!M54="A",'01_INPUTS_MASTER'!C49,IF('01_INPUTS_MASTER'!M54="B",'01_INPUTS_MASTER'!D49,IF('01_INPUTS_MASTER'!M54="C",'01_INPUTS_MASTER'!E49,0))))*(1-'01_INPUTS_MASTER'!O54)+('06_MRP_MATERIALS'!G119)*(IF('01_INPUTS_MASTER'!M55="A",'01_INPUTS_MASTER'!C49,IF('01_INPUTS_MASTER'!M55="B",'01_INPUTS_MASTER'!D49,IF('01_INPUTS_MASTER'!M55="C",'01_INPUTS_MASTER'!E49,0))))*(1-'01_INPUTS_MASTER'!O55) -> 247500 | F24: =('06_MRP_MATERIALS'!H12)*(IF('01_INPUTS_MASTER'!M54="A",'01_INPUTS_MASTER'!C49,IF('01_INPUTS_MASTER'!M54="B",'01_INPUTS_MASTER'!D49,IF('01_INPUTS_MASTER'!M54="C",'01_INPUTS_MASTER'!E49,0))))*(1-'01_INPUTS_MASTER'!O54)+('06_MRP_MATERIALS'!H119)*(IF('01_INPUTS_MASTER'!M55="A",'01_INPUTS_MASTER'!C49,IF('01_INPUTS_MASTER'!M55="B",'01_INPUTS_MASTER'!D49,IF('01_INPUTS_MASTER'!M55="C",'01_INPUTS_MASTER'!E49,0))))*(1-'01_INPUTS_MASTER'!O55) -> 0 | G24: =('06_MRP_MATERIALS'!I12)*(IF('01_INPUTS_MASTER'!M54="A",'01_INPUTS_MASTER'!C49,IF('01_INPUTS_MASTER'!M54="B",'01_INPUTS_MASTER'!D49,IF('01_INPUTS_MASTER'!M54="C",'01_INPUTS_MASTER'!E49,0))))*(1-'01_INPUTS_MASTER'!O54)+('06_MRP_MATERIALS'!I119)*(IF('01_INPUTS_MASTER'!M55="A",'01_INPUTS_MASTER'!C49,IF('01_INPUTS_MASTER'!M55="B",'01_INPUTS_MASTER'!D49,IF('01_INPUTS_MASTER'!M55="C",'01_INPUTS_MASTER'!E49,0))))*(1-'01_INPUTS_MASTER'!O55) -> 247500 | H24: =('06_MRP_MATERIALS'!J12)*(IF('01_INPUTS_MASTER'!M54="A",'01_INPUTS_MASTER'!C49,IF('01_INPUTS_MASTER'!M54="B",'01_INPUTS_MASTER'!D49,IF('01_INPUTS_MASTER'!M54="C",'01_INPUTS_MASTER'!E49,0))))*(1-'01_INPUTS_MASTER'!O54)+('06_MRP_MATERIALS'!J119)*(IF('01_INPUTS_MASTER'!M55="A",'01_INPUTS_MASTER'!C49,IF('01_INPUTS_MASTER'!M55="B",'01_INPUTS_MASTER'!D49,IF('01_INPUTS_MASTER'!M55="C",'01_INPUTS_MASTER'!E49,0))))*(1-'01_INPUTS_MASTER'!O55) -> 0 | I24: =('06_MRP_MATERIALS'!K12)*(IF('01_INPUTS_MASTER'!M54="A",'01_INPUTS_MASTER'!C49,IF('01_INPUTS_MASTER'!M54="B",'01_INPUTS_MASTER'!D49,IF('01_INPUTS_MASTER'!M54="C",'01_INPUTS_MASTER'!E49,0))))*(1-'01_INPUTS_MASTER'!O54)+('06_MRP_MATERIALS'!K119)*(IF('01_INPUTS_MASTER'!M55="A",'01_INPUTS_MASTER'!C49,IF('01_INPUTS_MASTER'!M55="B",'01_INPUTS_MASTER'!D49,IF('01_INPUTS_MASTER'!M55="C",'01_INPUTS_MASTER'!E49,0))))*(1-'01_INPUTS_MASTER'!O55) -> 255000 | J24: =SUM(B24:I24) -> 1005000
A25: Costo Part B | B25: =('06_MRP_MATERIALS'!D25)*(IF('01_INPUTS_MASTER'!N54="A",'01_INPUTS_MASTER'!C50,IF('01_INPUTS_MASTER'!N54="B",'01_INPUTS_MASTER'!D50,IF('01_INPUTS_MASTER'!N54="C",'01_INPUTS_MASTER'!E50,0))))*(1-'01_INPUTS_MASTER'!O54)+('06_MRP_MATERIALS'!D132)*(IF('01_INPUTS_MASTER'!N55="A",'01_INPUTS_MASTER'!C50,IF('01_INPUTS_MASTER'!N55="B",'01_INPUTS_MASTER'!D50,IF('01_INPUTS_MASTER'!N55="C",'01_INPUTS_MASTER'!E50,0))))*(1-'01_INPUTS_MASTER'!O55) -> 0 | C25: =('06_MRP_MATERIALS'!E25)*(IF('01_INPUTS_MASTER'!N54="A",'01_INPUTS_MASTER'!C50,IF('01_INPUTS_MASTER'!N54="B",'01_INPUTS_MASTER'!D50,IF('01_INPUTS_MASTER'!N54="C",'01_INPUTS_MASTER'!E50,0))))*(1-'01_INPUTS_MASTER'!O54)+('06_MRP_MATERIALS'!E132)*(IF('01_INPUTS_MASTER'!N55="A",'01_INPUTS_MASTER'!C50,IF('01_INPUTS_MASTER'!N55="B",'01_INPUTS_MASTER'!D50,IF('01_INPUTS_MASTER'!N55="C",'01_INPUTS_MASTER'!E50,0))))*(1-'01_INPUTS_MASTER'!O55) -> 134640 | D25: =('06_MRP_MATERIALS'!F25)*(IF('01_INPUTS_MASTER'!N54="A",'01_INPUTS_MASTER'!C50,IF('01_INPUTS_MASTER'!N54="B",'01_INPUTS_MASTER'!D50,IF('01_INPUTS_MASTER'!N54="C",'01_INPUTS_MASTER'!E50,0))))*(1-'01_INPUTS_MASTER'!O54)+('06_MRP_MATERIALS'!F132)*(IF('01_INPUTS_MASTER'!N55="A",'01_INPUTS_MASTER'!C50,IF('01_INPUTS_MASTER'!N55="B",'01_INPUTS_MASTER'!D50,IF('01_INPUTS_MASTER'!N55="C",'01_INPUTS_MASTER'!E50,0))))*(1-'01_INPUTS_MASTER'!O55) -> 0 | E25: =('06_MRP_MATERIALS'!G25)*(IF('01_INPUTS_MASTER'!N54="A",'01_INPUTS_MASTER'!C50,IF('01_INPUTS_MASTER'!N54="B",'01_INPUTS_MASTER'!D50,IF('01_INPUTS_MASTER'!N54="C",'01_INPUTS_MASTER'!E50,0))))*(1-'01_INPUTS_MASTER'!O54)+('06_MRP_MATERIALS'!G132)*(IF('01_INPUTS_MASTER'!N55="A",'01_INPUTS_MASTER'!C50,IF('01_INPUTS_MASTER'!N55="B",'01_INPUTS_MASTER'!D50,IF('01_INPUTS_MASTER'!N55="C",'01_INPUTS_MASTER'!E50,0))))*(1-'01_INPUTS_MASTER'!O55) -> 134640 | F25: =('06_MRP_MATERIALS'!H25)*(IF('01_INPUTS_MASTER'!N54="A",'01_INPUTS_MASTER'!C50,IF('01_INPUTS_MASTER'!N54="B",'01_INPUTS_MASTER'!D50,IF('01_INPUTS_MASTER'!N54="C",'01_INPUTS_MASTER'!E50,0))))*(1-'01_INPUTS_MASTER'!O54)+('06_MRP_MATERIALS'!H132)*(IF('01_INPUTS_MASTER'!N55="A",'01_INPUTS_MASTER'!C50,IF('01_INPUTS_MASTER'!N55="B",'01_INPUTS_MASTER'!D50,IF('01_INPUTS_MASTER'!N55="C",'01_INPUTS_MASTER'!E50,0))))*(1-'01_INPUTS_MASTER'!O55) -> 0 | G25: =('06_MRP_MATERIALS'!I25)*(IF('01_INPUTS_MASTER'!N54="A",'01_INPUTS_MASTER'!C50,IF('01_INPUTS_MASTER'!N54="B",'01_INPUTS_MASTER'!D50,IF('01_INPUTS_MASTER'!N54="C",'01_INPUTS_MASTER'!E50,0))))*(1-'01_INPUTS_MASTER'!O54)+('06_MRP_MATERIALS'!I132)*(IF('01_INPUTS_MASTER'!N55="A",'01_INPUTS_MASTER'!C50,IF('01_INPUTS_MASTER'!N55="B",'01_INPUTS_MASTER'!D50,IF('01_INPUTS_MASTER'!N55="C",'01_INPUTS_MASTER'!E50,0))))*(1-'01_INPUTS_MASTER'!O55) -> 126720 | H25: =('06_MRP_MATERIALS'!J25)*(IF('01_INPUTS_MASTER'!N54="A",'01_INPUTS_MASTER'!C50,IF('01_INPUTS_MASTER'!N54="B",'01_INPUTS_MASTER'!D50,IF('01_INPUTS_MASTER'!N54="C",'01_INPUTS_MASTER'!E50,0))))*(1-'01_INPUTS_MASTER'!O54)+('06_MRP_MATERIALS'!J132)*(IF('01_INPUTS_MASTER'!N55="A",'01_INPUTS_MASTER'!C50,IF('01_INPUTS_MASTER'!N55="B",'01_INPUTS_MASTER'!D50,IF('01_INPUTS_MASTER'!N55="C",'01_INPUTS_MASTER'!E50,0))))*(1-'01_INPUTS_MASTER'!O55) -> 0 | I25: =('06_MRP_MATERIALS'!K25)*(IF('01_INPUTS_MASTER'!N54="A",'01_INPUTS_MASTER'!C50,IF('01_INPUTS_MASTER'!N54="B",'01_INPUTS_MASTER'!D50,IF('01_INPUTS_MASTER'!N54="C",'01_INPUTS_MASTER'!E50,0))))*(1-'01_INPUTS_MASTER'!O54)+('06_MRP_MATERIALS'!K132)*(IF('01_INPUTS_MASTER'!N55="A",'01_INPUTS_MASTER'!C50,IF('01_INPUTS_MASTER'!N55="B",'01_INPUTS_MASTER'!D50,IF('01_INPUTS_MASTER'!N55="C",'01_INPUTS_MASTER'!E50,0))))*(1-'01_INPUTS_MASTER'!O55) -> 134640 | J25: =SUM(B25:I25) -> 530640
A26: Costo Pieces | B26: =('06_MRP_MATERIALS'!D38+'06_MRP_MATERIALS'!D145)*'01_INPUTS_MASTER'!C40+('06_MRP_MATERIALS'!D51+'06_MRP_MATERIALS'!D158)*'01_INPUTS_MASTER'!C41+('06_MRP_MATERIALS'!D64+'06_MRP_MATERIALS'!D171)*'01_INPUTS_MASTER'!C42+('06_MRP_MATERIALS'!D77+'06_MRP_MATERIALS'!D184)*'01_INPUTS_MASTER'!C43+('06_MRP_MATERIALS'!D90+'06_MRP_MATERIALS'!D197)*'01_INPUTS_MASTER'!C44+('06_MRP_MATERIALS'!D103+'06_MRP_MATERIALS'!D210)*'01_INPUTS_MASTER'!C45 -> 0 | C26: =('06_MRP_MATERIALS'!E38+'06_MRP_MATERIALS'!E145)*'01_INPUTS_MASTER'!C40+('06_MRP_MATERIALS'!E51+'06_MRP_MATERIALS'!E158)*'01_INPUTS_MASTER'!C41+('06_MRP_MATERIALS'!E64+'06_MRP_MATERIALS'!E171)*'01_INPUTS_MASTER'!C42+('06_MRP_MATERIALS'!E77+'06_MRP_MATERIALS'!E184)*'01_INPUTS_MASTER'!C43+('06_MRP_MATERIALS'!E90+'06_MRP_MATERIALS'!E197)*'01_INPUTS_MASTER'!C44+('06_MRP_MATERIALS'!E103+'06_MRP_MATERIALS'!E210)*'01_INPUTS_MASTER'!C45 -> 75600 | D26: =('06_MRP_MATERIALS'!F38+'06_MRP_MATERIALS'!F145)*'01_INPUTS_MASTER'!C40+('06_MRP_MATERIALS'!F51+'06_MRP_MATERIALS'!F158)*'01_INPUTS_MASTER'!C41+('06_MRP_MATERIALS'!F64+'06_MRP_MATERIALS'!F171)*'01_INPUTS_MASTER'!C42+('06_MRP_MATERIALS'!F77+'06_MRP_MATERIALS'!F184)*'01_INPUTS_MASTER'!C43+('06_MRP_MATERIALS'!F90+'06_MRP_MATERIALS'!F197)*'01_INPUTS_MASTER'!C44+('06_MRP_MATERIALS'!F103+'06_MRP_MATERIALS'!F210)*'01_INPUTS_MASTER'!C45 -> 0 | E26: =('06_MRP_MATERIALS'!G38+'06_MRP_MATERIALS'!G145)*'01_INPUTS_MASTER'!C40+('06_MRP_MATERIALS'!G51+'06_MRP_MATERIALS'!G158)*'01_INPUTS_MASTER'!C41+('06_MRP_MATERIALS'!G64+'06_MRP_MATERIALS'!G171)*'01_INPUTS_MASTER'!C42+('06_MRP_MATERIALS'!G77+'06_MRP_MATERIALS'!G184)*'01_INPUTS_MASTER'!C43+('06_MRP_MATERIALS'!G90+'06_MRP_MATERIALS'!G197)*'01_INPUTS_MASTER'!C44+('06_MRP_MATERIALS'!G103+'06_MRP_MATERIALS'!G210)*'01_INPUTS_MASTER'!C45 -> 112000 | F26: =('06_MRP_MATERIALS'!H38+'06_MRP_MATERIALS'!H145)*'01_INPUTS_MASTER'!C40+('06_MRP_MATERIALS'!H51+'06_MRP_MATERIALS'!H158)*'01_INPUTS_MASTER'!C41+('06_MRP_MATERIALS'!H64+'06_MRP_MATERIALS'!H171)*'01_INPUTS_MASTER'!C42+('06_MRP_MATERIALS'!H77+'06_MRP_MATERIALS'!H184)*'01_INPUTS_MASTER'!C43+('06_MRP_MATERIALS'!H90+'06_MRP_MATERIALS'!H197)*'01_INPUTS_MASTER'!C44+('06_MRP_MATERIALS'!H103+'06_MRP_MATERIALS'!H210)*'01_INPUTS_MASTER'!C45 -> 0 | G26: =('06_MRP_MATERIALS'!I38+'06_MRP_MATERIALS'!I145)*'01_INPUTS_MASTER'!C40+('06_MRP_MATERIALS'!I51+'06_MRP_MATERIALS'!I158)*'01_INPUTS_MASTER'!C41+('06_MRP_MATERIALS'!I64+'06_MRP_MATERIALS'!I171)*'01_INPUTS_MASTER'!C42+('06_MRP_MATERIALS'!I77+'06_MRP_MATERIALS'!I184)*'01_INPUTS_MASTER'!C43+('06_MRP_MATERIALS'!I90+'06_MRP_MATERIALS'!I197)*'01_INPUTS_MASTER'!C44+('06_MRP_MATERIALS'!I103+'06_MRP_MATERIALS'!I210)*'01_INPUTS_MASTER'!C45 -> 133000 | H26: =('06_MRP_MATERIALS'!J38+'06_MRP_MATERIALS'!J145)*'01_INPUTS_MASTER'!C40+('06_MRP_MATERIALS'!J51+'06_MRP_MATERIALS'!J158)*'01_INPUTS_MASTER'!C41+('06_MRP_MATERIALS'!J64+'06_MRP_MATERIALS'!J171)*'01_INPUTS_MASTER'!C42+('06_MRP_MATERIALS'!J77+'06_MRP_MATERIALS'!J184)*'01_INPUTS_MASTER'!C43+('06_MRP_MATERIALS'!J90+'06_MRP_MATERIALS'!J197)*'01_INPUTS_MASTER'!C44+('06_MRP_MATERIALS'!J103+'06_MRP_MATERIALS'!J210)*'01_INPUTS_MASTER'!C45 -> 0 | I26: =('06_MRP_MATERIALS'!K38+'06_MRP_MATERIALS'!K145)*'01_INPUTS_MASTER'!C40+('06_MRP_MATERIALS'!K51+'06_MRP_MATERIALS'!K158)*'01_INPUTS_MASTER'!C41+('06_MRP_MATERIALS'!K64+'06_MRP_MATERIALS'!K171)*'01_INPUTS_MASTER'!C42+('06_MRP_MATERIALS'!K77+'06_MRP_MATERIALS'!K184)*'01_INPUTS_MASTER'!C43+('06_MRP_MATERIALS'!K90+'06_MRP_MATERIALS'!K197)*'01_INPUTS_MASTER'!C44+('06_MRP_MATERIALS'!K103+'06_MRP_MATERIALS'!K210)*'01_INPUTS_MASTER'!C45 -> 182680 | J26: =SUM(B26:I26) -> 503280
A27: Total Materiales | B27: =B24+B25+B26 -> 0 | C27: =C24+C25+C26 -> 465240 | D27: =D24+D25+D26 -> 0 | E27: =E24+E25+E26 -> 494140 | F27: =F24+F25+F26 -> 0 | G27: =G24+G25+G26 -> 507220 | H27: =H24+H25+H26 -> 0 | I27: =I24+I25+I26 -> 572320 | J27: =SUM(B27:I27) -> 2038920
A29: ORDERING + HOLDING
A30: Ordering Cost | B30: ='06_MRP_MATERIALS'!D14+'06_MRP_MATERIALS'!D27+'06_MRP_MATERIALS'!D40+'06_MRP_MATERIALS'!D53+'06_MRP_MATERIALS'!D66+'06_MRP_MATERIALS'!D79+'06_MRP_MATERIALS'!D92+'06_MRP_MATERIALS'!D105+'06_MRP_MATERIALS'!D121+'06_MRP_MATERIALS'!D134+'06_MRP_MATERIALS'!D147+'06_MRP_MATERIALS'!D160+'06_MRP_MATERIALS'!D173+'06_MRP_MATERIALS'!D186+'06_MRP_MATERIALS'!D199+'06_MRP_MATERIALS'!D212 -> 0 | C30: ='06_MRP_MATERIALS'!E14+'06_MRP_MATERIALS'!E27+'06_MRP_MATERIALS'!E40+'06_MRP_MATERIALS'!E53+'06_MRP_MATERIALS'!E66+'06_MRP_MATERIALS'!E79+'06_MRP_MATERIALS'!E92+'06_MRP_MATERIALS'!E105+'06_MRP_MATERIALS'!E121+'06_MRP_MATERIALS'!E134+'06_MRP_MATERIALS'!E147+'06_MRP_MATERIALS'!E160+'06_MRP_MATERIALS'!E173+'06_MRP_MATERIALS'!E186+'06_MRP_MATERIALS'!E199+'06_MRP_MATERIALS'!E212 -> 16600 | D30: ='06_MRP_MATERIALS'!F14+'06_MRP_MATERIALS'!F27+'06_MRP_MATERIALS'!F40+'06_MRP_MATERIALS'!F53+'06_MRP_MATERIALS'!F66+'06_MRP_MATERIALS'!F79+'06_MRP_MATERIALS'!F92+'06_MRP_MATERIALS'!F105+'06_MRP_MATERIALS'!F121+'06_MRP_MATERIALS'!F134+'06_MRP_MATERIALS'!F147+'06_MRP_MATERIALS'!F160+'06_MRP_MATERIALS'!F173+'06_MRP_MATERIALS'!F186+'06_MRP_MATERIALS'!F199+'06_MRP_MATERIALS'!F212 -> 0 | E30: ='06_MRP_MATERIALS'!G14+'06_MRP_MATERIALS'!G27+'06_MRP_MATERIALS'!G40+'06_MRP_MATERIALS'!G53+'06_MRP_MATERIALS'!G66+'06_MRP_MATERIALS'!G79+'06_MRP_MATERIALS'!G92+'06_MRP_MATERIALS'!G105+'06_MRP_MATERIALS'!G121+'06_MRP_MATERIALS'!G134+'06_MRP_MATERIALS'!G147+'06_MRP_MATERIALS'!G160+'06_MRP_MATERIALS'!G173+'06_MRP_MATERIALS'!G186+'06_MRP_MATERIALS'!G199+'06_MRP_MATERIALS'!G212 -> 16600 | F30: ='06_MRP_MATERIALS'!H14+'06_MRP_MATERIALS'!H27+'06_MRP_MATERIALS'!H40+'06_MRP_MATERIALS'!H53+'06_MRP_MATERIALS'!H66+'06_MRP_MATERIALS'!H79+'06_MRP_MATERIALS'!H92+'06_MRP_MATERIALS'!H105+'06_MRP_MATERIALS'!H121+'06_MRP_MATERIALS'!H134+'06_MRP_MATERIALS'!H147+'06_MRP_MATERIALS'!H160+'06_MRP_MATERIALS'!H173+'06_MRP_MATERIALS'!H186+'06_MRP_MATERIALS'!H199+'06_MRP_MATERIALS'!H212 -> 0 | G30: ='06_MRP_MATERIALS'!I14+'06_MRP_MATERIALS'!I27+'06_MRP_MATERIALS'!I40+'06_MRP_MATERIALS'!I53+'06_MRP_MATERIALS'!I66+'06_MRP_MATERIALS'!I79+'06_MRP_MATERIALS'!I92+'06_MRP_MATERIALS'!I105+'06_MRP_MATERIALS'!I121+'06_MRP_MATERIALS'!I134+'06_MRP_MATERIALS'!I147+'06_MRP_MATERIALS'!I160+'06_MRP_MATERIALS'!I173+'06_MRP_MATERIALS'!I186+'06_MRP_MATERIALS'!I199+'06_MRP_MATERIALS'!I212 -> 16600 | H30: ='06_MRP_MATERIALS'!J14+'06_MRP_MATERIALS'!J27+'06_MRP_MATERIALS'!J40+'06_MRP_MATERIALS'!J53+'06_MRP_MATERIALS'!J66+'06_MRP_MATERIALS'!J79+'06_MRP_MATERIALS'!J92+'06_MRP_MATERIALS'!J105+'06_MRP_MATERIALS'!J121+'06_MRP_MATERIALS'!J134+'06_MRP_MATERIALS'!J147+'06_MRP_MATERIALS'!J160+'06_MRP_MATERIALS'!J173+'06_MRP_MATERIALS'!J186+'06_MRP_MATERIALS'!J199+'06_MRP_MATERIALS'!J212 -> 0 | I30: ='06_MRP_MATERIALS'!K14+'06_MRP_MATERIALS'!K27+'06_MRP_MATERIALS'!K40+'06_MRP_MATERIALS'!K53+'06_MRP_MATERIALS'!K66+'06_MRP_MATERIALS'!K79+'06_MRP_MATERIALS'!K92+'06_MRP_MATERIALS'!K105+'06_MRP_MATERIALS'!K121+'06_MRP_MATERIALS'!K134+'06_MRP_MATERIALS'!K147+'06_MRP_MATERIALS'!K160+'06_MRP_MATERIALS'!K173+'06_MRP_MATERIALS'!K186+'06_MRP_MATERIALS'!K199+'06_MRP_MATERIALS'!K212 -> 16600 | J30: =SUM(B30:I30) -> 66400
A31: Holding Cost | B31: ='06_MRP_MATERIALS'!D15+'06_MRP_MATERIALS'!D28+'06_MRP_MATERIALS'!D41+'06_MRP_MATERIALS'!D54+'06_MRP_MATERIALS'!D67+'06_MRP_MATERIALS'!D80+'06_MRP_MATERIALS'!D93+'06_MRP_MATERIALS'!D106+'06_MRP_MATERIALS'!D122+'06_MRP_MATERIALS'!D135+'06_MRP_MATERIALS'!D148+'06_MRP_MATERIALS'!D161+'06_MRP_MATERIALS'!D174+'06_MRP_MATERIALS'!D187+'06_MRP_MATERIALS'!D200+'06_MRP_MATERIALS'!D213 -> 0 | C31: ='06_MRP_MATERIALS'!E15+'06_MRP_MATERIALS'!E28+'06_MRP_MATERIALS'!E41+'06_MRP_MATERIALS'!E54+'06_MRP_MATERIALS'!E67+'06_MRP_MATERIALS'!E80+'06_MRP_MATERIALS'!E93+'06_MRP_MATERIALS'!E106+'06_MRP_MATERIALS'!E122+'06_MRP_MATERIALS'!E135+'06_MRP_MATERIALS'!E148+'06_MRP_MATERIALS'!E161+'06_MRP_MATERIALS'!E174+'06_MRP_MATERIALS'!E187+'06_MRP_MATERIALS'!E200+'06_MRP_MATERIALS'!E213 -> 48 | D31: ='06_MRP_MATERIALS'!F15+'06_MRP_MATERIALS'!F28+'06_MRP_MATERIALS'!F41+'06_MRP_MATERIALS'!F54+'06_MRP_MATERIALS'!F67+'06_MRP_MATERIALS'!F80+'06_MRP_MATERIALS'!F93+'06_MRP_MATERIALS'!F106+'06_MRP_MATERIALS'!F122+'06_MRP_MATERIALS'!F135+'06_MRP_MATERIALS'!F148+'06_MRP_MATERIALS'!F161+'06_MRP_MATERIALS'!F174+'06_MRP_MATERIALS'!F187+'06_MRP_MATERIALS'!F200+'06_MRP_MATERIALS'!F213 -> 48 | E31: ='06_MRP_MATERIALS'!G15+'06_MRP_MATERIALS'!G28+'06_MRP_MATERIALS'!G41+'06_MRP_MATERIALS'!G54+'06_MRP_MATERIALS'!G67+'06_MRP_MATERIALS'!G80+'06_MRP_MATERIALS'!G93+'06_MRP_MATERIALS'!G106+'06_MRP_MATERIALS'!G122+'06_MRP_MATERIALS'!G135+'06_MRP_MATERIALS'!G148+'06_MRP_MATERIALS'!G161+'06_MRP_MATERIALS'!G174+'06_MRP_MATERIALS'!G187+'06_MRP_MATERIALS'!G200+'06_MRP_MATERIALS'!G213 -> 78 | F31: ='06_MRP_MATERIALS'!H15+'06_MRP_MATERIALS'!H28+'06_MRP_MATERIALS'!H41+'06_MRP_MATERIALS'!H54+'06_MRP_MATERIALS'!H67+'06_MRP_MATERIALS'!H80+'06_MRP_MATERIALS'!H93+'06_MRP_MATERIALS'!H106+'06_MRP_MATERIALS'!H122+'06_MRP_MATERIALS'!H135+'06_MRP_MATERIALS'!H148+'06_MRP_MATERIALS'!H161+'06_MRP_MATERIALS'!H174+'06_MRP_MATERIALS'!H187+'06_MRP_MATERIALS'!H200+'06_MRP_MATERIALS'!H213 -> 78 | G31: ='06_MRP_MATERIALS'!I15+'06_MRP_MATERIALS'!I28+'06_MRP_MATERIALS'!I41+'06_MRP_MATERIALS'!I54+'06_MRP_MATERIALS'!I67+'06_MRP_MATERIALS'!I80+'06_MRP_MATERIALS'!I93+'06_MRP_MATERIALS'!I106+'06_MRP_MATERIALS'!I122+'06_MRP_MATERIALS'!I135+'06_MRP_MATERIALS'!I148+'06_MRP_MATERIALS'!I161+'06_MRP_MATERIALS'!I174+'06_MRP_MATERIALS'!I187+'06_MRP_MATERIALS'!I200+'06_MRP_MATERIALS'!I213 -> 0 | H31: ='06_MRP_MATERIALS'!J15+'06_MRP_MATERIALS'!J28+'06_MRP_MATERIALS'!J41+'06_MRP_MATERIALS'!J54+'06_MRP_MATERIALS'!J67+'06_MRP_MATERIALS'!J80+'06_MRP_MATERIALS'!J93+'06_MRP_MATERIALS'!J106+'06_MRP_MATERIALS'!J122+'06_MRP_MATERIALS'!J135+'06_MRP_MATERIALS'!J148+'06_MRP_MATERIALS'!J161+'06_MRP_MATERIALS'!J174+'06_MRP_MATERIALS'!J187+'06_MRP_MATERIALS'!J200+'06_MRP_MATERIALS'!J213 -> 0 | I31: ='06_MRP_MATERIALS'!K15+'06_MRP_MATERIALS'!K28+'06_MRP_MATERIALS'!K41+'06_MRP_MATERIALS'!K54+'06_MRP_MATERIALS'!K67+'06_MRP_MATERIALS'!K80+'06_MRP_MATERIALS'!K93+'06_MRP_MATERIALS'!K106+'06_MRP_MATERIALS'!K122+'06_MRP_MATERIALS'!K135+'06_MRP_MATERIALS'!K148+'06_MRP_MATERIALS'!K161+'06_MRP_MATERIALS'!K174+'06_MRP_MATERIALS'!K187+'06_MRP_MATERIALS'!K200+'06_MRP_MATERIALS'!K213 -> 48 | J31: =SUM(B31:I31) -> 300
A32: Total Ordering+Holding | B32: =B30+B31 -> 0 | C32: =C30+C31 -> 16648 | D32: =D30+D31 -> 48 | E32: =E30+E31 -> 16678 | F32: =F30+F31 -> 78 | G32: =G30+G31 -> 16600 | H32: =H30+H31 -> 0 | I32: =I30+I31 -> 16648 | J32: =SUM(B32:I32) -> 66700
A34: RESUMEN
A35: Total Labor + Indirect | B35: =B11+B12 -> 11310 | C35: =C11+C12 -> 11310 | D35: =D11+D12 -> 11310 | E35: =E11+E12 -> 11310 | F35: =F11+F12 -> 11310 | G35: =G11+G12 -> 11310 | H35: =H11+H12 -> 11310 | I35: =I11+I12 -> 11310 | J35: =SUM(B35:I35) -> 90480
A36: Total Energía | B36: =B21 -> 8038.3429 | C36: =C21 -> 6370 | D36: =D21 -> 6370 | E36: =E21 -> 6370 | F36: =F21 -> 6370 | G36: =G21 -> 6370 | H36: =H21 -> 6370 | I36: =I21 -> 6370 | J36: =SUM(B36:I36) -> 52628.343
A37: Total Materiales | B37: =B27 -> 0 | C37: =C27 -> 465240 | D37: =D27 -> 0 | E37: =E27 -> 494140 | F37: =F27 -> 0 | G37: =G27 -> 507220 | H37: =H27 -> 0 | I37: =I27 -> 572320 | J37: =SUM(B37:I37) -> 2038920
A38: Total Ordering+Holding | B38: =B32 -> 0 | C38: =C32 -> 16648 | D38: =D32 -> 48 | E38: =E32 -> 16678 | F38: =F32 -> 78 | G38: =G32 -> 16600 | H38: =H32 -> 0 | I38: =I32 -> 16648 | J38: =SUM(B38:I38) -> 66700
A39: COSTO TOTAL PRODUCCIÓN | B39: =B35+B36+B37+B38 -> 19348.343 | C39: =C35+C36+C37+C38 -> 499568 | D39: =D35+D36+D37+D38 -> 17728 | E39: =E35+E36+E37+E38 -> 528498 | F39: =F35+F36+F37+F38 -> 17758 | G39: =G35+G36+G37+G38 -> 541500 | H39: =H35+H36+H37+H38 -> 17680 | I39: =I35+I36+I37+I38 -> 606648 | J39: =SUM(B39:I39) -> 2248728.3
A40: Unidades Producidas S5 | B40: ='05_CAPACITY'!D67+'05_CAPACITY'!D133 -> 0 | C40: ='05_CAPACITY'!E67+'05_CAPACITY'!E133 -> 0 | D40: ='05_CAPACITY'!F67+'05_CAPACITY'!F133 -> 0 | E40: ='05_CAPACITY'!G67+'05_CAPACITY'!G133 -> 0 | F40: ='05_CAPACITY'!H67+'05_CAPACITY'!H133 -> 0 | G40: ='05_CAPACITY'!I67+'05_CAPACITY'!I133 -> 0 | H40: ='05_CAPACITY'!J67+'05_CAPACITY'!J133 -> 0 | I40: ='05_CAPACITY'!K67+'05_CAPACITY'!K133 -> 0 | J40: =SUM(B40:I40) -> 0
A41: COSTO UNITARIO | B41: =IF(B40>0,B39/B40,0) -> 0 | C41: =IF(C40>0,C39/C40,0) -> 0 | D41: =IF(D40>0,D39/D40,0) -> 0 | E41: =IF(E40>0,E39/E40,0) -> 0 | F41: =IF(F40>0,F39/F40,0) -> 0 | G41: =IF(G40>0,G39/G40,0) -> 0 | H41: =IF(H40>0,H39/H40,0) -> 0 | I41: =IF(I40>0,I39/I40,0) -> 0 | J41: =SUM(B41:I41) -> 0

Sheet 09_CHECKS
A1: PANEL DE ALERTAS Y VALIDACIÓN
A3: Verificación | B3: Estado | C3: Detalle
A4: Plan > Capacidad en alguna sección/subperiodo | B4: =IF(SUM(COUNTIF('05_CAPACITY'!D16:K16,"CAPACITY"),COUNTIF('05_CAPACITY'!D29:K29,"CAPACITY"),COUNTIF('05_CAPACITY'!D42:K42,"CAPACITY"),COUNTIF('05_CAPACITY'!D55:K55,"CAPACITY"),COUNTIF('05_CAPACITY'!D68:K68,"CAPACITY"),COUNTIF('05_CAPACITY'!D82:K82,"CAPACITY"),COUNTIF('05_CAPACITY'!D95:K95,"CAPACITY"),COUNTIF('05_CAPACITY'!D108:K108,"CAPACITY"),COUNTIF('05_CAPACITY'!D121:K121,"CAPACITY"),COUNTIF('05_CAPACITY'!D134:K134,"CAPACITY"))>0,"FAIL","OK") -> FAIL | C4: Verificar 05_CAPACITY
A5: Inventario negativo de materiales | B5: =IF(MIN(MIN('06_MRP_MATERIALS'!D13:K13),MIN('06_MRP_MATERIALS'!D26:K26),MIN('06_MRP_MATERIALS'!D39:K39),MIN('06_MRP_MATERIALS'!D52:K52),MIN('06_MRP_MATERIALS'!D65:K65),MIN('06_MRP_MATERIALS'!D78:K78),MIN('06_MRP_MATERIALS'!D91:K91),MIN('06_MRP_MATERIALS'!D104:K104),MIN('06_MRP_MATERIALS'!D120:K120),MIN('06_MRP_MATERIALS'!D133:K133),MIN('06_MRP_MATERIALS'!D146:K146),MIN('06_MRP_MATERIALS'!D159:K159),MIN('06_MRP_MATERIALS'!D172:K172),MIN('06_MRP_MATERIALS'!D185:K185),MIN('06_MRP_MATERIALS'!D198:K198),MIN('06_MRP_MATERIALS'!D211:K211))<0,"FAIL","OK") -> OK | C5: Verificar 06_MRP_MATERIALS
A6: Inventario negativo de assemblies | B6: =IF(MIN(MIN('04_FLOW_S1_S5'!D11:K11),MIN('04_FLOW_S1_S5'!D17:K17),MIN('04_FLOW_S1_S5'!D23:K23),MIN('04_FLOW_S1_S5'!D29:K29),MIN('04_FLOW_S1_S5'!D35:K35),MIN('04_FLOW_S1_S5'!D42:K42),MIN('04_FLOW_S1_S5'!D48:K48),MIN('04_FLOW_S1_S5'!D54:K54),MIN('04_FLOW_S1_S5'!D60:K60),MIN('04_FLOW_S1_S5'!D66:K66))<0,"FAIL","OK") -> OK | C6: Verificar 04_FLOW_S1_S5
A7: Espacios insuficientes | B7: =IF(OR(ISNUMBER(SEARCH("FALTA",'07_SPACES'!C20)),ISNUMBER(SEARCH("FALTA",'07_SPACES'!C38))),"FAIL","OK") -> OK | C7: Verificar 07_SPACES
A8: Ventas perdidas en 2/4/6/8 | B8: =IF(SUM('02_DEMAND'!D12,'02_DEMAND'!F12,'02_DEMAND'!H12,'02_DEMAND'!J12,'02_DEMAND'!D23,'02_DEMAND'!F23,'02_DEMAND'!H23,'02_DEMAND'!J23,'02_DEMAND'!D34,'02_DEMAND'!F34,'02_DEMAND'!H34,'02_DEMAND'!J34,'02_DEMAND'!D45,'02_DEMAND'!F45,'02_DEMAND'!H45,'02_DEMAND'!J45,'02_DEMAND'!D56,'02_DEMAND'!F56,'02_DEMAND'!H56,'02_DEMAND'!J56)>0,"FAIL","OK") -> FAIL | C8: Verificar 02_DEMAND
A11: PLAN FACTIBLE: | B11: =IF(COUNTIF(B4:B8,"FAIL")>0,"FAIL","OK") -> FAIL

Sheet 10_DECISIONS_UPLOAD
A1: DECISIONES PARA CARGAR AL SIMULADOR
A3: COMPRA DE MÁQUINAS
A4: Planta | B4: Tipo Máquina | C4: Periodo Compra | D4: Cantidad
A11: WORKERS POR PLANTA/SECCIÓN
A12: Planta | B12: Sección | C12: # Workers
A13: Center | B13: S1 (M1) | C13: 7
A14: Center | B14: S2 (M2) | C14: 22
A15: Center | B15: S3 (M3a) | C15: 90
A16: Center | B16: S3 (M4) | C16: 4
A17: Center | B17: S4 (M4) | C17: 10
A18: Center | B18: S5 (M4) | C18: 11
A19: Center | B19: S5 (Crews) | C19: 75
A20: West | B20: S1 (M1) | C20: 3
A21: West | B21: S2 (M2) | C21: 9
A22: West | B22: S3 (M3a) | C22: 30
A23: West | B23: S3 (M4) | C23: 2
A24: West | B24: S4 (M4) | C24: 3
... A26: West | B26: S5 (Crews) | C26: 21
A28: OVERTIME POR PLANTA/SECCIÓN/SUBPERIODO
A29: Planta | B29: Sección | C29: S1 | D29: S2 | E29: S3 | F29: S4 | G29: S5 | H29: S6 | I29: S7 | J29: S8
A30: Center | B30: S1 | C30: 0 | D30: 0 | E30: 0 | F30: 0 | G30: 0 | H30: 0 | I30: 0 | J30: 0
A31: Center | B31: S2 | C31: 0 | D31: 0 | E31: 0 | F31: 0 | G31: 0 | H31: 0 | I31: 0 | J31: 0
A32: Center | B32: S3 | C32: 0 | D32: 0 | E32: 0 | F32: 0 | G32: 0 | H32: 0 | I32: 0 | J32: 0
A33: Center | B33: S4 | C33: 0 | D33: 0 | E33: 0 | F33: 0 | G33: 0 | H33: 0 | I33: 0 | J33: 0
A34: Center | B34: S5 | C34: 0 | D34: 0 | E34: 0 | F34: 0 | G34: 0 | H34: 0 | I34: 0 | J34: 0
A35: West | B35: S1 | C35: 0 | D35: 0 | E35: 0 | F35: 0 | G35: 0 | H35: 0 | I35: 0 | J35: 0
A36: West | B36: S2 | C36: 0 | D36: 0 | E36: 0 | F36: 0 | G36: 0 | H36: 0 | I36: 0 | J36: 0
A37: West | B37: S3 | C37: 0 | D37: 0 | E37: 0 | F37: 0 | G37: 0 | H37: 0 | I37: 0 | J37: 0
A38: West | B38: S4 | C38: 0 | D38: 0 | E38: 0 | F38: 0 | G38: 0 | H38: 0 | I38: 0 | J38: 0
A39: West | B39: S5 | C39: 0 | D39: 0 | E39: 0 | F39: 0 | G39: 0 | H39: 0 | I39: 0 | J39: 0
A41: PRODUCCIÓN POR PLANTA/SECCIÓN/SUBPERIODO
A42: Planta | B42: Sección | C42: S1 | D42: S2 | E42: S3 | F42: S4 | G42: S5 | H42: S6 | I42: S7 | J42: S8
A43: Center | B43: S1 | C43: 0 | D43: 0 | E43: 0 | F43: 0 | G43: 0 | H43: 0 | I43: 0 | J43: 0
A44: Center | B44: S2 | C44: 0 | D44: 0 | E44: 0 | F44: 0 | G44: 0 | H44: 0 | I44: 0 | J44: 0
A45: Center | B45: S3 | C45: 0 | D45: 0 | E45: 0 | F45: 0 | G45: 0 | H45: 0 | I45: 0 | J45: 0
A46: Center | B46: S4 | C46: 0 | D46: 0 | E46: 0 | F46: 0 | G46: 0 | H46: 0 | I46: 0 | J46: 0
A47: Center | B47: S5 | C47: 0 | D47: 0 | E47: 0 | F47: 0 | G47: 0 | H47: 0 | I47: 0 | J47: 0
A48: West | B48: S1 | C48: 0 | D48: 0 | E48: 0 | F48: 0 | G48: 0 | H48: 0 | I48: 0 | J48: 0
A49: West | B49: S2 | C49: 0 | D49: 0 | E49: 0 | F49: 0 | G49: 0 | H49: 0 | I49: 0 | J49: 0
A50: West | B50: S3 | C50: 0 | D50: 0 | E50: 0 | F50: 0 | G50: 0 | H50: 0 | I50: 0 | J50: 0
A51: West | B51: S4 | C51: 0 | D51: 0 | E51: 0 | F51: 0 | G51: 0 | H51: 0 | I51: 0 | J51: 0
A52: West | B52: S5 | C52: 0 | D52: 0 | E52: 0 | F52: 0 | G52: 0 | H52: 0 | I52: 0 | J52: 0
