Workbook

Sheet INPUT_MarketReport
A1: MARKET REPORT DATA - INPUT MANUAL
A3: Instrucciones: Copiar datos del Market Report por periodo. Celdas azules = input manual.
A5: Period | B5: Region | C5: Segment | D5: Company | E5: Price | F5: Product_Awareness | G5: Promo_Impact | H5: Market_Share_% | I5: Units_Sold | J5: Notes
A6: 6 | B6: Center | C6: High | D6: MyCompany | E6: 68 | F6: 65 | G6: 0.25 | H6: 20 | I6: 1800
A7: 6 | B7: Center | C7: High | D7: Comp_A | E7: 68 | F7: 60 | G7: 0.2 | H7: 20 | I7: 1800
A8: 6 | B8: Center | C8: High | D8: Comp_B | E8: 68 | F8: 60 | G8: 0.2 | H8: 20 | I8: 1800
A9: 6 | B9: Center | C9: High | D9: Comp_C | E9: 68 | F9: 60 | G9: 0.2 | H9: 20 | I9: 1800
A10: 6 | B10: Center | C10: High | D10: Comp_D | E10: 68 | F10: 60 | G10: 0.2 | H10: 20 | I10: 1800
A11: 6 | B11: Center | C11: Low | D11: MyCompany | E11: 68 | F11: 65 | G11: 0.25 | H11: 20 | I11: 2200
A12: 6 | B12: Center | C12: Low | D12: Comp_A | E12: 68 | F12: 60 | G12: 0.2 | H12: 20 | I12: 2200
A13: 6 | B13: Center | C13: Low | D13: Comp_B | E13: 68 | F13: 60 | G13: 0.2 | H13: 20 | I13: 2200
A14: 6 | B14: Center | C14: Low | D14: Comp_C | E14: 68 | F14: 60 | G14: 0.2 | H14: 20 | I14: 2200
A15: 6 | B15: Center | C15: Low | D15: Comp_D | E15: 68 | F15: 60 | G15: 0.2 | H15: 20 | I15: 2200
A16: 6 | B16: West | C16: High | D16: MyCompany | E16: 68 | F16: 65 | G16: 0.25 | H16: 20 | I16: 1800
A17: 6 | B17: West | C17: High | D17: Comp_A | E17: 68 | F17: 60 | G17: 0.2 | H17: 20 | I17: 1800
... A45: 7 | B45: West | C45: Low | D45: Comp_D | E45: 70 | F45: 62 | G45: 0.22 | H45: 19.5 | I45: 2400

Sheet INPUT_SalesAdmin
A1: SALES & ADMINISTRATION EXPENSE REPORT - INPUT MANUAL
A4: Period | B4: Region | C4: Brand | D4: Units | E4: Local_Price | F4: Gross_Sales | G4: Discount_% | H4: Net_Sales | I4: TV_Ads_$ | J4: Radio_Ads_$ | K4: Salespeople_# | L4: Salespeople_Salary_$ | M4: Admin_Expenses_$
A5: 6 | B5: Center | C5: A | D5: 4000 | E5: 68 | F5: 272000 | G5: 7.5 | H5: 251600 | I5: 52500 | J5: 17700 | K5: 17 | L5: 12750 | M5: 30000
A6: 6 | B6: West | C6: A | D6: 2000 | E6: 68 | F6: 136000 | G6: 7.5 | H6: 125800 | I6: 52500 | J6: 17700 | K6: 8 | L6: 6000 | M6: 30000
A7: 7 | B7: Center | C7: A | D7: 4000 | E7: 68 | F7: 272000 | G7: 7.5 | H7: 251600 | I7: 52500 | J7: 19500 | K7: 17 | L7: 12750 | M7: 30000
A8: 7 | B8: West | C8: A | D8: 2000 | E8: 68 | F8: 136000 | G8: 7.5 | H8: 125800 | I8: 52500 | J8: 19500 | K8: 8 | L8: 6000 | M8: 30000

Sheet INPUT_Inventory
A1: FINISHED GOODS INVENTORY & LOST SALES - INPUT MANUAL
A4: Period | B4: Region | C4: FG_Initial | D4: Production | E4: Receptions | F4: Shipments_Out | G4: Sales | H4: FG_Final | I4: Thrown_Away | J4: Lost_Sales_Units | K4: Salespeople_Quit
A5: 6 | B5: Center | C5: 3862 | D5: 11052 | E5: 0 | F5: 4277 | G5: 8900 | H5: 1737 | I5: 0 | J5: 0 | K5: 0
A6: 6 | B6: West | C6: 1816 | D6: 2940 | E6: 0 | F6: 0 | G6: 4028 | H6: 1299 | I6: 0 | J6: 0 | K6: 0
A7: 7 | B7: Center | C7: 3862 | D7: 11052 | E7: 0 | F7: 4277 | G7: 8900 | H7: 1737 | I7: 0 | J7: 150 | K7: 1
A8: 7 | B8: West | C8: 1816 | D8: 2940 | E8: 0 | F8: 0 | G8: 4028 | H8: 1299 | I8: 0 | J8: 0 | K8: 0

Sheet MASTER_Table
A1: CONSOLIDATED MASTER TABLE - KPIs BY PERIOD & REGION
A3: Las fórmulas calculan KPIs automáticamente desde los inputs. Negro = fórmula, Verde = link a otra hoja.
A5: Period | B5: Region | C5: MyPrice | D5: AvgCompPrice | E5: Price_Index | F5: MyAwareness | G5: MaxCompAwareness | H5: Awareness_Gap | I5: MyPromo | J5: MaxCompPromo | K5: Promo_Gap | L5: MyShare_% | M5: Units_Sold | N5: Net_Sales | O5: Lost_Sales_Units | P5: Lost_Sales_% | Q5: TV_Ads | R5: Radio_Ads | S5: Total_Ads | T5: Sellers | U5: Seller_Cost | V5: S&A_Total | W5: S&A_%_NetSales | X5: Comm_Spend_per_Unit
A6: 6 | B6: Center | C6: =SUMIFS(INPUT_MarketReport!E:E,INPUT_MarketReport!A:A,A6,INPUT_MarketReport!B:B,B6,INPUT_MarketReport!D:D,"MyCompany")/2 -> 68 | D6: =AVERAGEIFS(INPUT_MarketReport!E:E,INPUT_MarketReport!A:A,A6,INPUT_MarketReport!B:B,B6,INPUT_MarketReport!D:D,"<>MyCompany")/2 -> 34 | E6: =IF(D6=0,"-",C6/D6) -> 2 | F6: =AVERAGEIFS(INPUT_MarketReport!F:F,INPUT_MarketReport!A:A,A6,INPUT_MarketReport!B:B,B6,INPUT_MarketReport!D:D,"MyCompany") -> 65 | G6: =MAX(IF((INPUT_MarketReport!A$6:A$100=A6)*(INPUT_MarketReport!B$6:B$100=B6)*(INPUT_MarketReport!D$6:D$100<>"MyCompany"),INPUT_MarketReport!F$6:F$100,0)) -> 0 | H6: =F6-G6 -> 65 | I6: =AVERAGEIFS(INPUT_MarketReport!G:G,INPUT_MarketReport!A:A,A6,INPUT_MarketReport!B:B,B6,INPUT_MarketReport!D:D,"MyCompany") -> 0.25 | J6: =MAX(IF((INPUT_MarketReport!A$6:A$100=A6)*(INPUT_MarketReport!B$6:B$100=B6)*(INPUT_MarketReport!D$6:D$100<>"MyCompany"),INPUT_MarketReport!G$6:G$100,0)) -> 0 | K6: =I6-J6 -> 0.25 | L6: =AVERAGEIFS(INPUT_MarketReport!H:H,INPUT_MarketReport!A:A,A6,INPUT_MarketReport!B:B,B6,INPUT_MarketReport!D:D,"MyCompany") -> 20 | M6: =SUMIFS(INPUT_SalesAdmin!D:D,INPUT_SalesAdmin!A:A,A6,INPUT_SalesAdmin!B:B,B6) -> 4000 | N6: =SUMIFS(INPUT_SalesAdmin!H:H,INPUT_SalesAdmin!A:A,A6,INPUT_SalesAdmin!B:B,B6) -> 251600 | O6: =SUMIFS(INPUT_Inventory!J:J,INPUT_Inventory!A:A,A6,INPUT_Inventory!B:B,B6) -> 0 | P6: =IF((M6+O6)=0,0,O6/(M6+O6)) -> 0 | Q6: =SUMIFS(INPUT_SalesAdmin!I:I,INPUT_SalesAdmin!A:A,A6,INPUT_SalesAdmin!B:B,B6) -> 52500 | R6: =SUMIFS(INPUT_SalesAdmin!J:J,INPUT_SalesAdmin!A:A,A6,INPUT_SalesAdmin!B:B,B6) -> 17700 | S6: =Q6+R6 -> 70200 | T6: =SUMIFS(INPUT_SalesAdmin!K:K,INPUT_SalesAdmin!A:A,A6,INPUT_SalesAdmin!B:B,B6) -> 17 | U6: =SUMIFS(INPUT_SalesAdmin!L:L,INPUT_SalesAdmin!A:A,A6,INPUT_SalesAdmin!B:B,B6) -> 12750 | V6: =S6+U6+SUMIFS(INPUT_SalesAdmin!M:M,INPUT_SalesAdmin!A:A,A6,INPUT_SalesAdmin!B:B,B6) -> 112950 | W6: =IF(N6=0,0,V6/N6) -> 0.44892687 | X6: =IF(M6=0,0,(S6+U6)/M6) -> 20.7375
A7: 6 | B7: West | C7: =SUMIFS(INPUT_MarketReport!E:E,INPUT_MarketReport!A:A,A7,INPUT_MarketReport!B:B,B7,INPUT_MarketReport!D:D,"MyCompany")/2 -> 68 | D7: =AVERAGEIFS(INPUT_MarketReport!E:E,INPUT_MarketReport!A:A,A7,INPUT_MarketReport!B:B,B7,INPUT_MarketReport!D:D,"<>MyCompany")/2 -> 34 | E7: =IF(D7=0,"-",C7/D7) -> 2 | F7: =AVERAGEIFS(INPUT_MarketReport!F:F,INPUT_MarketReport!A:A,A7,INPUT_MarketReport!B:B,B7,INPUT_MarketReport!D:D,"MyCompany") -> 65 | G7: =MAX(IF((INPUT_MarketReport!A$6:A$100=A7)*(INPUT_MarketReport!B$6:B$100=B7)*(INPUT_MarketReport!D$6:D$100<>"MyCompany"),INPUT_MarketReport!F$6:F$100,0)) -> 0 | H7: =F7-G7 -> 65 | I7: =AVERAGEIFS(INPUT_MarketReport!G:G,INPUT_MarketReport!A:A,A7,INPUT_MarketReport!B:B,B7,INPUT_MarketReport!D:D,"MyCompany") -> 0.25 | J7: =MAX(IF((INPUT_MarketReport!A$6:A$100=A7)*(INPUT_MarketReport!B$6:B$100=B7)*(INPUT_MarketReport!D$6:D$100<>"MyCompany"),INPUT_MarketReport!G$6:G$100,0)) -> 0 | K7: =I7-J7 -> 0.25 | L7: =AVERAGEIFS(INPUT_MarketReport!H:H,INPUT_MarketReport!A:A,A7,INPUT_MarketReport!B:B,B7,INPUT_MarketReport!D:D,"MyCompany") -> 20 | M7: =SUMIFS(INPUT_SalesAdmin!D:D,INPUT_SalesAdmin!A:A,A7,INPUT_SalesAdmin!B:B,B7) -> 2000 | N7: =SUMIFS(INPUT_SalesAdmin!H:H,INPUT_SalesAdmin!A:A,A7,INPUT_SalesAdmin!B:B,B7) -> 125800 | O7: =SUMIFS(INPUT_Inventory!J:J,INPUT_Inventory!A:A,A7,INPUT_Inventory!B:B,B7) -> 0 | P7: =IF((M7+O7)=0,0,O7/(M7+O7)) -> 0 | Q7: =SUMIFS(INPUT_SalesAdmin!I:I,INPUT_SalesAdmin!A:A,A7,INPUT_SalesAdmin!B:B,B7) -> 52500 | R7: =SUMIFS(INPUT_SalesAdmin!J:J,INPUT_SalesAdmin!A:A,A7,INPUT_SalesAdmin!B:B,B7) -> 17700 | S7: =Q7+R7 -> 70200 | T7: =SUMIFS(INPUT_SalesAdmin!K:K,INPUT_SalesAdmin!A:A,A7,INPUT_SalesAdmin!B:B,B7) -> 8 | U7: =SUMIFS(INPUT_SalesAdmin!L:L,INPUT_SalesAdmin!A:A,A7,INPUT_SalesAdmin!B:B,B7) -> 6000 | V7: =S7+U7+SUMIFS(INPUT_SalesAdmin!M:M,INPUT_SalesAdmin!A:A,A7,INPUT_SalesAdmin!B:B,B7) -> 106200 | W7: =IF(N7=0,0,V7/N7) -> 0.84419714 | X7: =IF(M7=0,0,(S7+U7)/M7) -> 38.1
A8: 7 | B8: Center | C8: =SUMIFS(INPUT_MarketReport!E:E,INPUT_MarketReport!A:A,A8,INPUT_MarketReport!B:B,B8,INPUT_MarketReport!D:D,"MyCompany")/2 -> 70 | D8: =AVERAGEIFS(INPUT_MarketReport!E:E,INPUT_MarketReport!A:A,A8,INPUT_MarketReport!B:B,B8,INPUT_MarketReport!D:D,"<>MyCompany")/2 -> 35 | E8: =IF(D8=0,"-",C8/D8) -> 2 | F8: =AVERAGEIFS(INPUT_MarketReport!F:F,INPUT_MarketReport!A:A,A8,INPUT_MarketReport!B:B,B8,INPUT_MarketReport!D:D,"MyCompany") -> 68 | G8: =MAX(IF((INPUT_MarketReport!A$6:A$100=A8)*(INPUT_MarketReport!B$6:B$100=B8)*(INPUT_MarketReport!D$6:D$100<>"MyCompany"),INPUT_MarketReport!F$6:F$100,0)) -> 0 | H8: =F8-G8 -> 68 | I8: =AVERAGEIFS(INPUT_MarketReport!G:G,INPUT_MarketReport!A:A,A8,INPUT_MarketReport!B:B,B8,INPUT_MarketReport!D:D,"MyCompany") -> 0.28 | J8: =MAX(IF((INPUT_MarketReport!A$6:A$100=A8)*(INPUT_MarketReport!B$6:B$100=B8)*(INPUT_MarketReport!D$6:D$100<>"MyCompany"),INPUT_MarketReport!G$6:G$100,0)) -> 0 | K8: =I8-J8 -> 0.28 | L8: =AVERAGEIFS(INPUT_MarketReport!H:H,INPUT_MarketReport!A:A,A8,INPUT_MarketReport!B:B,B8,INPUT_MarketReport!D:D,"MyCompany") -> 22 | M8: =SUMIFS(INPUT_SalesAdmin!D:D,INPUT_SalesAdmin!A:A,A8,INPUT_SalesAdmin!B:B,B8) -> 4000 | N8: =SUMIFS(INPUT_SalesAdmin!H:H,INPUT_SalesAdmin!A:A,A8,INPUT_SalesAdmin!B:B,B8) -> 251600 | O8: =SUMIFS(INPUT_Inventory!J:J,INPUT_Inventory!A:A,A8,INPUT_Inventory!B:B,B8) -> 150 | P8: =IF((M8+O8)=0,0,O8/(M8+O8)) -> 0.036144578 | Q8: =SUMIFS(INPUT_SalesAdmin!I:I,INPUT_SalesAdmin!A:A,A8,INPUT_SalesAdmin!B:B,B8) -> 52500 | R8: =SUMIFS(INPUT_SalesAdmin!J:J,INPUT_SalesAdmin!A:A,A8,INPUT_SalesAdmin!B:B,B8) -> 19500 | S8: =Q8+R8 -> 72000 | T8: =SUMIFS(INPUT_SalesAdmin!K:K,INPUT_SalesAdmin!A:A,A8,INPUT_SalesAdmin!B:B,B8) -> 17 | U8: =SUMIFS(INPUT_SalesAdmin!L:L,INPUT_SalesAdmin!A:A,A8,INPUT_SalesAdmin!B:B,B8) -> 12750 | V8: =S8+U8+SUMIFS(INPUT_SalesAdmin!M:M,INPUT_SalesAdmin!A:A,A8,INPUT_SalesAdmin!B:B,B8) -> 114750 | W8: =IF(N8=0,0,V8/N8) -> 0.45608108 | X8: =IF(M8=0,0,(S8+U8)/M8) -> 21.1875
A9: 7 | B9: West | C9: =SUMIFS(INPUT_MarketReport!E:E,INPUT_MarketReport!A:A,A9,INPUT_MarketReport!B:B,B9,INPUT_MarketReport!D:D,"MyCompany")/2 -> 70 | D9: =AVERAGEIFS(INPUT_MarketReport!E:E,INPUT_MarketReport!A:A,A9,INPUT_MarketReport!B:B,B9,INPUT_MarketReport!D:D,"<>MyCompany")/2 -> 35 | E9: =IF(D9=0,"-",C9/D9) -> 2 | F9: =AVERAGEIFS(INPUT_MarketReport!F:F,INPUT_MarketReport!A:A,A9,INPUT_MarketReport!B:B,B9,INPUT_MarketReport!D:D,"MyCompany") -> 68 | G9: =MAX(IF((INPUT_MarketReport!A$6:A$100=A9)*(INPUT_MarketReport!B$6:B$100=B9)*(INPUT_MarketReport!D$6:D$100<>"MyCompany"),INPUT_MarketReport!F$6:F$100,0)) -> 0 | H9: =F9-G9 -> 68 | I9: =AVERAGEIFS(INPUT_MarketReport!G:G,INPUT_MarketReport!A:A,A9,INPUT_MarketReport!B:B,B9,INPUT_MarketReport!D:D,"MyCompany") -> 0.28 | J9: =MAX(IF((INPUT_MarketReport!A$6:A$100=A9)*(INPUT_MarketReport!B$6:B$100=B9)*(INPUT_MarketReport!D$6:D$100<>"MyCompany"),INPUT_MarketReport!G$6:G$100,0)) -> 0 | K9: =I9-J9 -> 0.28 | L9: =AVERAGEIFS(INPUT_MarketReport!H:H,INPUT_MarketReport!A:A,A9,INPUT_MarketReport!B:B,B9,INPUT_MarketReport!D:D,"MyCompany") -> 22 | M9: =SUMIFS(INPUT_SalesAdmin!D:D,INPUT_SalesAdmin!A:A,A9,INPUT_SalesAdmin!B:B,B9) -> 2000 | N9: =SUMIFS(INPUT_SalesAdmin!H:H,INPUT_SalesAdmin!A:A,A9,INPUT_SalesAdmin!B:B,B9) -> 125800 | O9: =SUMIFS(INPUT_Inventory!J:J,INPUT_Inventory!A:A,A9,INPUT_Inventory!B:B,B9) -> 0 | P9: =IF((M9+O9)=0,0,O9/(M9+O9)) -> 0 | Q9: =SUMIFS(INPUT_SalesAdmin!I:I,INPUT_SalesAdmin!A:A,A9,INPUT_SalesAdmin!B:B,B9) -> 52500 | R9: =SUMIFS(INPUT_SalesAdmin!J:J,INPUT_SalesAdmin!A:A,A9,INPUT_SalesAdmin!B:B,B9) -> 19500 | S9: =Q9+R9 -> 72000 | T9: =SUMIFS(INPUT_SalesAdmin!K:K,INPUT_SalesAdmin!A:A,A9,INPUT_SalesAdmin!B:B,B9) -> 8 | U9: =SUMIFS(INPUT_SalesAdmin!L:L,INPUT_SalesAdmin!A:A,A9,INPUT_SalesAdmin!B:B,B9) -> 6000 | V9: =S9+U9+SUMIFS(INPUT_SalesAdmin!M:M,INPUT_SalesAdmin!A:A,A9,INPUT_SalesAdmin!B:B,B9) -> 108000 | W9: =IF(N9=0,0,V9/N9) -> 0.85850556 | X9: =IF(M9=0,0,(S9+U9)/M9) -> 39

Sheet KPI_Dashboard
A1: KPI DASHBOARD - ANÁLISIS Y ROI OBSERVADO
A3: MÉTRICAS CLAVE POR REGIÓN Y PERIODO
A5: Metric | B5: P6_Center | C5: P6_West | D5: P7_Center | E5: P7_West | F5: Δ_Center | G5: Δ_West
A6: Market Share % | B6: =MASTER_Table!L6 -> 20 | C6: =MASTER_Table!L7 -> 20 | D6: =MASTER_Table!L8 -> 22 | E6: =MASTER_Table!L9 -> 22 | F6: =D6-B6 -> 2 | G6: =E6-C6 -> 2
A7: Awareness | B7: =MASTER_Table!F6 -> 65 | C7: =MASTER_Table!F7 -> 65 | D7: =MASTER_Table!F8 -> 68 | E7: =MASTER_Table!F9 -> 68 | F7: =D7-B7 -> 3 | G7: =E7-C7 -> 3
A8: Promo Impact | B8: =MASTER_Table!I6 -> 0.25 | C8: =MASTER_Table!I7 -> 0.25 | D8: =MASTER_Table!I8 -> 0.28 | E8: =MASTER_Table!I9 -> 0.28 | F8: =D8-B8 -> 0.03 | G8: =E8-C8 -> 0.03
A9: Price | B9: =MASTER_Table!C6 -> 68 | C9: =MASTER_Table!C7 -> 68 | D9: =MASTER_Table!C8 -> 70 | E9: =MASTER_Table!C9 -> 70 | F9: =D9-B9 -> 2 | G9: =E9-C9 -> 2
A10: Units Sold | B10: =MASTER_Table!M6 -> 4000 | C10: =MASTER_Table!M7 -> 2000 | D10: =MASTER_Table!M8 -> 4000 | E10: =MASTER_Table!M9 -> 2000 | F10: =D10-B10 -> 0 | G10: =E10-C10 -> 0
A11: Net Sales | B11: =MASTER_Table!N6 -> 251600 | C11: =MASTER_Table!N7 -> 125800 | D11: =MASTER_Table!N8 -> 251600 | E11: =MASTER_Table!N9 -> 125800 | F11: =D11-B11 -> 0 | G11: =E11-C11 -> 0
A12: Lost Sales % | B12: =MASTER_Table!P6 -> 0 | C12: =MASTER_Table!P7 -> 0 | D12: =MASTER_Table!P8 -> 0.036144578 | E12: =MASTER_Table!P9 -> 0 | F12: =D12-B12 -> 0.036144578 | G12: =E12-C12 -> 0
A13: S&A % Net Sales | B13: =MASTER_Table!W6 -> 0.44892687 | C13: =MASTER_Table!W7 -> 0.84419714 | D13: =MASTER_Table!W8 -> 0.45608108 | E13: =MASTER_Table!W9 -> 0.85850556 | F13: =D13-B13 -> 0.007154213 | G13: =E13-C13 -> 0.014308426
A14: Comm Spend/Unit | B14: =MASTER_Table!X6 -> 20.7375 | C14: =MASTER_Table!X7 -> 38.1 | D14: =MASTER_Table!X8 -> 21.1875 | E14: =MASTER_Table!X9 -> 39 | F14: =D14-B14 -> 0.45 | G14: =E14-C14 -> 0.9
A17: ROI OBSERVADO (Delta periodo a periodo)
A19: ROI Metric | B19: Center | C19: West | D19: Interpretación
A20: ROI Awareness per $Ads | B20: =IF((MASTER_Table!S8-MASTER_Table!S6)=0,"-",(MASTER_Table!F8-MASTER_Table!F6)/(MASTER_Table!S8-MASTER_Table!S6)*1000) -> 1.6666667 | C20: =IF((MASTER_Table!S9-MASTER_Table!S7)=0,"-",(MASTER_Table!F9-MASTER_Table!F7)/(MASTER_Table!S9-MASTER_Table!S7)*1000) -> 1.6666667 | D20: pts Awareness por cada $1,000 ads
A21: ROI Share per $Ads | B21: =IF((MASTER_Table!S8-MASTER_Table!S6)=0,"-",(MASTER_Table!L8-MASTER_Table!L6)/(MASTER_Table!S8-MASTER_Table!S6)*1000) -> 1.1111111 | C21: =IF((MASTER_Table!S9-MASTER_Table!S7)=0,"-",(MASTER_Table!L9-MASTER_Table!L7)/(MASTER_Table!S9-MASTER_Table!S7)*1000) -> 1.1111111 | D21: pts Share por cada $1,000 ads
A22: ROI Units per Seller | B22: =IF(MASTER_Table!T8=0,"-",(MASTER_Table!M8-MASTER_Table!M6)/MASTER_Table!T8) -> 0 | C22: =IF(MASTER_Table!T9=0,"-",(MASTER_Table!M9-MASTER_Table!M7)/MASTER_Table!T9) -> 0 | D22: ΔUnits / #Sellers actual
A23: Elasticidad Precio | B23: =IF(OR(MASTER_Table!C6=0,MASTER_Table!M6=0,(MASTER_Table!C8-MASTER_Table!C6)=0),"-",((MASTER_Table!M8-MASTER_Table!M6)/MASTER_Table!M6)/((MASTER_Table!C8-MASTER_Table!C6)/MASTER_Table!C6)) -> 0 | C23: =IF(OR(MASTER_Table!C7=0,MASTER_Table!M7=0,(MASTER_Table!C9-MASTER_Table!C7)=0),"-",((MASTER_Table!M9-MASTER_Table!M7)/MASTER_Table!M7)/((MASTER_Table!C9-MASTER_Table!C7)/MASTER_Table!C7)) -> 0 | D23: %ΔUnits / %ΔPrecio (negativo=normal)
A26: ALERTAS Y GUARDRAILS
A28: Region | B28: Lost Sales Alert | C28: S&A Overspend Alert | D28: Sellers Quit Alert | E28: Status
A29: Center | B29: =IF(MASTER_Table!P8>0.03,"🔴 ROJO: Lost Sales>"&TEXT(MASTER_Table!P8,"0.0%"),IF(MASTER_Table!P8>0,"🟡 AMARILLO","🟢 OK")) -> 🔴 ROJO: Lost Sales>3.6% | C29: =IF(MASTER_Table!W8>0.35,"🔴 ROJO: S&A>"&TEXT(MASTER_Table!W8,"0.0%"),IF(MASTER_Table!W8>0.28,"🟡 AMARILLO","🟢 OK")) -> 🔴 ROJO: S&A>45.6% | D29: =IF(SUMIFS(INPUT_Inventory!K:K,INPUT_Inventory!A:A,7,INPUT_Inventory!B:B,"Center")>0,"🔴 ROJO: Salespeople Quit","🟢 OK") -> 🔴 ROJO: Salespeople Quit | E29: =IF(OR(LEFT(B29,1)="🔴",LEFT(C29,1)="🔴",LEFT(D29,1)="🔴"),"⛔ NO AUMENTAR ADS/SELLERS",IF(OR(LEFT(B29,1)="🟡",LEFT(C29,1)="🟡"),"⚠️ PRECAUCIÓN","✅ PUEDE CRECER")) -> ⛔ NO AUMENTAR ADS/SELLERS
A30: West | B30: =IF(MASTER_Table!P9>0.03,"🔴 ROJO: Lost Sales>"&TEXT(MASTER_Table!P9,"0.0%"),IF(MASTER_Table!P9>0,"🟡 AMARILLO","🟢 OK")) -> 🟢 OK | C30: =IF(MASTER_Table!W9>0.35,"🔴 ROJO: S&A>"&TEXT(MASTER_Table!W9,"0.0%"),IF(MASTER_Table!W9>0.28,"🟡 AMARILLO","🟢 OK")) -> 🔴 ROJO: S&A>85.9% | D30: =IF(SUMIFS(INPUT_Inventory!K:K,INPUT_Inventory!A:A,7,INPUT_Inventory!B:B,"West")>0,"🔴 ROJO: Salespeople Quit","🟢 OK") -> 🟢 OK | E30: =IF(OR(LEFT(B30,1)="🔴",LEFT(C30,1)="🔴",LEFT(D30,1)="🔴"),"⛔ NO AUMENTAR ADS/SELLERS",IF(OR(LEFT(B30,1)="🟡",LEFT(C30,1)="🟡"),"⚠️ PRECAUCIÓN","✅ PUEDE CRECER")) -> ⛔ NO AUMENTAR ADS/SELLERS

Sheet Decision_Panel
A1: PANEL DE DECISIONES - PERIODO SIGUIENTE
A3: Celdas AZULES = editar. El panel calcula presupuesto y riesgos automáticamente.
A5: PARÁMETROS GLOBALES
A6: Periodo a planear: | B6: 8
A7: TV Spot Cost: | B7: 3000
A8: Radio Spot Cost: | B8: 300
A9: Seller Hiring Cost: | B9: 1000
A10: Seller Salary/Period: | B10: 750
A11: Umbral S&A % (alerta): | B11: 0.3
A12: Umbral Lost Sales % (alerta): | B12: 0.03
A15: DECISIONES POR REGIÓN
A17: Region | B17: Price_Prop | C17: TV_Spots | D17: Radio_Spots | E17: Brand_Focus_% | F17: Sellers_Prop | G17: Forecast_Units | H17: Mejora_1 | I17: Mejora_2 | J17: Mejora_3
A18: Center | B18: 70 | C18: 35 | D18: 102 | E18: 85 | F18: 17 | G18: 5600 | H18: No | I18: No | J18: No
A19: West | B19: 70 | C19: 35 | D19: 90 | E19: 85 | F19: 8 | G19: 4500 | H19: No | I19: No | J19: No
A20: North | B20: 93 | C20: 35 | D20: 90 | E20: 85 | F20: 15 | G20: 4400 | H20: No | I20: No | J20: No
A21: East | B21: 89 | C21: 0 | D21: 40 | E21: 85 | F21: 5 | G21: 1500 | H21: No | I21: No | J21: No
A22: South | B22: 89 | C22: 0 | D22: 40 | E22: 85 | F22: 5 | G22: 1500 | H22: No | I22: No | J22: No
A25: CÁLCULOS DE PRESUPUESTO
A27: Region | B27: TV_Cost | C27: Radio_Cost | D27: Total_Ads | E27: Seller_Cost | F27: Total_Comm | G27: vs_P7 | H27: Forecast_Revenue | I27: Est_S&A_%
A28: Center | B28: =C18*$B$7 -> 105000 | C28: =D18*$B$8 -> 30600 | D28: =B28+C28 -> 135600 | E28: =F18*$B$10 -> 12750 | F28: =D28+E28 -> 148350 | G28: =F28-(MASTER_Table!S8+MASTER_Table!U8) -> 63600 | H28: =G18*B18*0.87 -> 341040 | I28: =IF(H28=0,0,(F28+30000)/H28) -> 0.52295918
A29: West | B29: =C19*$B$7 -> 105000 | C29: =D19*$B$8 -> 27000 | D29: =B29+C29 -> 132000 | E29: =F19*$B$10 -> 6000 | F29: =D29+E29 -> 138000 | G29: =F29-(MASTER_Table!S9+MASTER_Table!U9) -> 60000 | H29: =G19*B19*0.87 -> 274050 | I29: =IF(H29=0,0,(F29+30000)/H29) -> 0.61302682
A30: North | B30: =C20*$B$7 -> 105000 | C30: =D20*$B$8 -> 27000 | D30: =B30+C30 -> 132000 | E30: =F20*$B$10 -> 11250 | F30: =D30+E30 -> 143250 | G30: N/A (nuevo) | H30: =G20*B20*0.87 -> 356004 | I30: =IF(H30=0,0,(F30+30000)/H30) -> 0.48665184
A31: East | B31: =C21*$B$7 -> 0 | C31: =D21*$B$8 -> 12000 | D31: =B31+C31 -> 12000 | E31: =F21*$B$10 -> 3750 | F31: =D31+E31 -> 15750 | G31: N/A (nuevo) | H31: =G21*B21*0.87 -> 116145 | I31: =IF(H31=0,0,(F31+30000)/H31) -> 0.39390417
A32: South | B32: =C22*$B$7 -> 0 | C32: =D22*$B$8 -> 12000 | D32: =B32+C32 -> 12000 | E32: =F22*$B$10 -> 3750 | F32: =D32+E32 -> 15750 | G32: N/A (nuevo) | H32: =G22*B22*0.87 -> 116145 | I32: =IF(H32=0,0,(F32+30000)/H32) -> 0.39390417
A33: TOTAL | B33: =SUM(B28:B32) -> 315000 | C33: =SUM(C28:C32) -> 108600 | D33: =SUM(D28:D32) -> 423600 | E33: =SUM(E28:E32) -> 37500 | F33: =SUM(F28:F32) -> 461100
A36: VALIDACIÓN Y ALERTAS
A38: Region | B38: Price vs P7 | C38: Ads vs P7 | D38: Sellers vs P7 | E38: S&A % Alert | F38: Recommendation
A39: Center | B39: =B18-MASTER_Table!C8 -> 0 | C39: =D28-(MASTER_Table!S8) -> 63600 | D39: =F18-MASTER_Table!T8 -> 0 | E39: =IF(I28>$B$11,"🔴 ALTO",IF(I28>$B$11*0.9,"🟡 MEDIO","🟢 OK")) -> 🔴 ALTO | F39: =IF(E39="🔴 ALTO","Reducir gasto",IF(AND(B39<>0,B39>5),"Revisar precio alto","OK")) -> Reducir gasto
A40: West | B40: =B19-MASTER_Table!C9 -> 0 | C40: =D29-(MASTER_Table!S9) -> 60000 | D40: =F19-MASTER_Table!T9 -> 0 | E40: =IF(I29>$B$11,"🔴 ALTO",IF(I29>$B$11*0.9,"🟡 MEDIO","🟢 OK")) -> 🔴 ALTO | F40: =IF(E40="🔴 ALTO","Reducir gasto",IF(AND(B40<>0,B40>5),"Revisar precio alto","OK")) -> Reducir gasto
A41: North | B41: N/A | C41: N/A | D41: N/A | E41: =IF(I30>$B$11,"🔴 ALTO",IF(I30>$B$11*0.9,"🟡 MEDIO","🟢 OK")) -> 🔴 ALTO | F41: =IF(E41="🔴 ALTO","Reducir gasto",IF(AND(B41<>0,B41>5),"Revisar precio alto","OK")) -> Reducir gasto
A42: East | B42: N/A | C42: N/A | D42: N/A | E42: =IF(I31>$B$11,"🔴 ALTO",IF(I31>$B$11*0.9,"🟡 MEDIO","🟢 OK")) -> 🔴 ALTO | F42: =IF(E42="🔴 ALTO","Reducir gasto",IF(AND(B42<>0,B42>5),"Revisar precio alto","OK")) -> Reducir gasto
A43: South | B43: N/A | C43: N/A | D43: N/A | E43: =IF(I32>$B$11,"🔴 ALTO",IF(I32>$B$11*0.9,"🟡 MEDIO","🟢 OK")) -> 🔴 ALTO | F43: =IF(E43="🔴 ALTO","Reducir gasto",IF(AND(B43<>0,B43>5),"Revisar precio alto","OK")) -> Reducir gasto

Sheet Scenario_Compare
A1: COMPARACIÓN DE ESCENARIOS
A3: Modifica los valores en Plan A y Plan B para comparar estrategias alternativas.
A5: Variable | B5: Region | C5: BASE (P7) | D5: PLAN_A | E5: PLAN_B | F5: Δ_A_vs_Base | G5: Δ_B_vs_Base
A6: Price | B6: Center | C6: 70 | D6: 70 | E6: 67 | F6: =D6-C6 -> 0 | G6: =E6-C6 -> -3
A7: TV_Spots | B7: Center | C7: 35 | D7: 38 | E7: 31 | F7: =D7-C7 -> 3 | G7: =E7-C7 -> -4
A8: Radio_Spots | B8: Center | C8: 102 | D8: 112 | E8: 91 | F8: =D8-C8 -> 10 | G8: =E8-C8 -> -11
A9: Sellers | B9: Center | C9: 17 | D9: 18 | E9: 15 | F9: =D9-C9 -> 1 | G9: =E9-C9 -> -2
A10: Forecast | B10: Center | C10: 5600 | D10: 6160 | E10: 5600 | F10: =D10-C10 -> 560 | G10: =E10-C10 -> 0
A11: Price | B11: West | C11: 70 | D11: 70 | E11: 67 | F11: =D11-C11 -> 0 | G11: =E11-C11 -> -3
A12: TV_Spots | B12: West | C12: 35 | D12: 38 | E12: 31 | F12: =D12-C12 -> 3 | G12: =E12-C12 -> -4
A13: Radio_Spots | B13: West | C13: 90 | D13: 99 | E13: 81 | F13: =D13-C13 -> 9 | G13: =E13-C13 -> -9
A14: Sellers | B14: West | C14: 8 | D14: 8 | E14: 7 | F14: =D14-C14 -> 0 | G14: =E14-C14 -> -1
A15: Forecast | B15: West | C15: 4500 | D15: 4950 | E15: 4500 | F15: =D15-C15 -> 450 | G15: =E15-C15 -> 0
A18: ESTIMACIÓN DE RESULTADOS POR ESCENARIO
A20: Metric | B20: Region | C20: BASE | D20: PLAN_A | E20: PLAN_B
A21: Est_Revenue | B21: Center | C21: =C6*C10*0.87 -> 341040 | D21: =D6*D10*0.87 -> 375144 | E21: =E6*E10*0.87 -> 326424
A22: Est_Ads_Cost | B22: Center | C22: =C7*3000+C8*300 -> 135600 | D22: =D7*3000+D8*300 -> 147600 | E22: =E7*3000+E8*300 -> 120300
A23: Est_Seller_Cost | B23: Center | C23: =C9*750 -> 12750 | D23: =D9*750 -> 13500 | E23: =E9*750 -> 11250
A24: Est_Total_Comm | B24: Center | C24: =C22+C23 -> 148350 | D24: =D22+D23 -> 161100 | E24: =E22+E23 -> 131550
A25: Est_S&A_% | B25: Center | C25: =IF(C21=0,0,(C24+30000)/C21) -> 0.52295918 | D25: =IF(D21=0,0,(D24+30000)/D21) -> 0.50940439 | E25: =IF(E21=0,0,(E24+30000)/E21) -> 0.49490846
A26: Est_Revenue | B26: West | C26: =C11*C15*0.87 -> 274050 | D26: =D11*D15*0.87 -> 301455 | E26: =E11*E15*0.87 -> 262305
A27: Est_Ads_Cost | B27: West | C27: =C12*3000+C13*300 -> 132000 | D27: =D12*3000+D13*300 -> 143700 | E27: =E12*3000+E13*300 -> 117300
A28: Est_Seller_Cost | B28: West | C28: =C14*750 -> 6000 | D28: =D14*750 -> 6000 | E28: =E14*750 -> 5250
A29: Est_Total_Comm | B29: West | C29: =C27+C28 -> 138000 | D29: =D27+D28 -> 149700 | E29: =E27+E28 -> 122550
A30: Est_S&A_% | B30: West | C30: =IF(C26=0,0,(C29+30000)/C26) -> 0.61302682 | D30: =IF(D26=0,0,(D29+30000)/D26) -> 0.59610887 | E30: =IF(E26=0,0,(E29+30000)/E26) -> 0.58157488

Sheet Data_Dictionary
A1: DICCIONARIO DE DATOS E INSTRUCCIONES
A3: INSTRUCCIONES DE USO
A5: 1. Después de cada periodo simulado, actualizar las 3 hojas INPUT con datos de los reportes EXSIM.
A6: 2. INPUT_MarketReport: Copiar datos del Market Report (precio, awareness, promo, share por empresa).
A7: 3. INPUT_SalesAdmin: Copiar datos del Sales & Administration Report (unidades, ventas, gastos).
A8: 4. INPUT_Inventory: Copiar datos del Finished Goods Inventory (stock, lost sales, vendedores que renunciaron).
A9: 5. MASTER_Table se actualiza automáticamente con fórmulas.
A10: 6. KPI_Dashboard muestra métricas clave y alertas.
A11: 7. Decision_Panel: Editar celdas amarillas para planear el siguiente periodo.
A12: 8. Scenario_Compare: Comparar hasta 3 escenarios alternativos.
A14: CÓDIGO DE COLORES:
A15: - Azul: Inputs manuales (datos de reportes)
... A22: DEFINICIÓN DE COLUMNAS
A24: Hoja | B24: Columna | C24: Descripción | D24: Fuente en EXSIM | E24: Tipo
A25: INPUT_MarketReport | B25: Price | C25: Precio de venta al cliente final | D25: Market Report > Price | E25: Input
A26: INPUT_MarketReport | B26: Product_Awareness | C26: % de conocimiento de producto (0-100) | D26: Market Report > Product Awareness | E26: Input
A27: INPUT_MarketReport | B27: Promo_Impact | C27: Impacto promocional salesforce (0-1) | D27: Market Report > Evaluation of Promotional Impact | E27: Input
A28: INPUT_MarketReport | B28: Market_Share_% | C28: Cuota de mercado en la región (%) | D28: Market Report > Market Share Per Region | E28: Input
A29: INPUT_SalesAdmin | B29: Units | C29: Unidades vendidas en el periodo | D29: Sales Report > Sales > Units | E29: Input
A30: INPUT_SalesAdmin | B30: Net_Sales | C30: Ventas netas después de descuentos | D30: Sales Report > Sales > Net Sales | E30: Input
A31: INPUT_SalesAdmin | B31: TV_Ads_$ | C31: Gasto en publicidad de TV | D31: S&A Expenses > TV Advertisement | E31: Input
A32: INPUT_SalesAdmin | B32: Radio_Ads_$ | C32: Gasto en publicidad de Radio | D32: S&A Expenses > Radio Advertisement | E32: Input
A33: INPUT_Inventory | B33: Lost_Sales_Units | C33: Unidades de demanda no satisfecha | D33: Finished Goods Inventory > (Demanda - Sales) | E33: Input
A34: INPUT_Inventory | B34: Salespeople_Quit | C34: Vendedores que renunciaron por stockout | D34: Simulation Messages o cálculo | E34: Input
A35: MASTER_Table | B35: Price_Index | C35: Tu precio / Promedio competidores | D35: Calculado | E35: Fórmula
... A40: KPI_Dashboard | B40: Elasticidad_Precio | C40: %ΔUnits / %ΔPrecio | D40: Calculado | E40: Fórmula
A43: GUARDRAILS Y UMBRALES
A45: Condición | B45: Nivel | C45: Acción Recomendada
A46: Lost Sales % > 3% | B46: 🔴 ROJO | C46: NO aumentar ads/sellers en esa región. Resolver stockout primero.
A47: Lost Sales % > 0% | B47: 🟡 AMARILLO | C47: Precaución. Coordinar con operaciones para evitar recurrencia.
A48: S&A % Net Sales > 35% | B48: 🔴 ROJO | C48: Gasto comercial excesivo. Reducir o mejorar conversión.
A49: S&A % Net Sales > 28% | B49: 🟡 AMARILLO | C49: Gasto alto. Monitorear ROI de inversiones.
A50: Salespeople Quit > 0 | B50: 🔴 ROJO | C50: Stockout causó renuncias. Impacto en promo de siguiente periodo.
