Workbook

Sheet EXHIBITS
C1: 1 | D1: 2 | E1: 3 | F1: 4 | G1: 5 | H1: 6 | I1: 7
B2: Center | C2: 4100 | D2: 3600 | E2: 6600 | F2: 6000 | G2: 5100 | H2: 8900 | I2: ='DF Q7'!K13 -> 7792
B3: West | C3: 1800 | D3: 1900 | E3: 2700 | F3: 2800 | G3: 2900 | H3: 4028 | I3: ='DF Q7'!K14 -> 3948
B4: North | C4: 700 | D4: 1200 | E4: 2600 | F4: 2700 | G4: 2700 | H4: 4400 | I4: ='DF Q7'!K15 -> 3868
B5: East | I5: ='DF Q7'!K16 -> 788
B6: South | I6: ='DF Q7'!K17 -> 684
C8: Expected Demand in Year 3
C9: Min | D9: Max
B10: East | C10: 3000 | D10: 5000
B11: South | C11: 2500 | D11: 3500
B13: Table I.1 Target Populations* Per Company by Region and Segment (in # of households)
C14: 68 | D14: 68 | E14: 91
C15: Center | D15: West | E15: North | F15: East | G15: South
B16: HIGH END | C16: 35200 | D16: 24000 | E16: 19600 | F16: 10000 | G16: 9600
B17: Low End | C17: 74800 | D17: 51000 | E17: 50400 | F17: 40000 | G17: 20400
B18: High/ TOTAL | C18: =C16/(C16+C17) -> 0.32 | D18: =D16/(D16+D17) -> 0.32 | E18: =E16/(E16+E17) -> 0.28 | F18: =F16/(F16+F17) -> 0.2 | G18: =G16/(G16+G17) -> 0.32
C19: =C16+C17 -> 110000 | D19: =D16+D17 -> 75000 | E19: =E16+E17 -> 70000 | F19: =F16+F17 -> 50000 | G19: =G16+G17 -> 30000
B21: TOTAL TARGET POPULATION
B22: Exhibits | C22: 68 | D22: 68 | E22: 91
C23: Center | D23: West | E23: North | F23: East | G23: South
B24: HIGH END | C24: =C16*7 -> 246400 | D24: =D16*7 -> 168000 | E24: =E16*7 -> 137200 | F24: =F16*7 -> 70000 | G24: =G16*7 -> 67200
B25: Low End | C25: =C17*7 -> 523600 | D25: =D17*7 -> 357000 | E25: =E17*7 -> 352800 | F25: =F17*7 -> 280000 | G25: =G17*7 -> 142800
C29: =(C24+C25)*14.3 -> 11011000

Sheet FEATURES
B1: Improvement | C1: Innovation Cost | D1: Product Cost / Unit sold | E1: Emmisions
A2: STAINLESS MATERIAL | B2: Makes the appliance attractive and durable. | C2: 15000 | D2: 0.15 | E2: -0.025 | F2: Design and Durability
A3: RECYCLABLE MATERIALS | B3: The appliance is built using environmentally friendly materials that can be recycled at the end of its life cycle, reducing waste and promoting sustainability. | C3: 30000 | D3: 0.15 | E3: 0.023 | F3: ESG
A4: ENERGY EFFICIENCY | B4: The appliance becomes more efficient and uses less electric power for its operation. | C4: 30000 | D4: 0.15 | E4: -0.025 | F4: ESG
A5: LIGHTER AND MORE COMPACT | B5: The external design of the appliance is modified so it may be installed in an easier way. | C5: 30000 | D5: 0.3 | E5: 0.045 | F5: Design
A6: IMPACT RESISTANCE | B6: The frame material is replaced so it becomes more resistant to the impacts | C6: 30000 | D6: 0.3 | E6: -0.05 | F6: Durability
A7: NOISE REDUCTION | B7: The Electroclean becomes less noisy while operating. | C7: 45000 | D7: 0.3 | E7: 0.045 | F7: Performance
A8: IMPROVED BATTERY CAPACITY | B8: Equipped with a higher-capacity battery, the Electroclean can operate for longer periods between charges, making it more convenient for extended use. | C8: 45000 | D8: 0.45 | E8: -0.075 | F8: Performance
A9: SELF-CLEANING | B9: The appliance features a self-cleaning function, automatically removing dirt and debris from internal components, reducing maintenance and ensuring optimal performance. | C9: 45000 | D9: 0.45 | E9: 0.068 | F9: Performance and convinience
A10: SPEED SETTINGS | B10: By substituting the electronic device used by the appliance to supply energy to the motor, the Electroclean may operate at three different speeds, which allows increasing its applications. | C10: 30000 | D10: 0.45 | E10: 0.068 | F10: Performance
A11: DIGITAL CONTROLS | B11: A new digital-type unit in the controls of the appliance, with luminous display, makes it more attractive and sophisticated. | C11: 45000 | D11: 0.45 | E11: -0.075 | F11: Design
A12: VOICE ASSISTANCE INTEGRATION | B12: The integration with voice-controlled systems, like Siri or Alexa, enables users to control it through voice commands for a hands-free experience. | C12: 45000 | D12: 0.75 | E12: 0.107 | F12: Performance and convinience
A13: AUTOMATION AND PROGRAMMABILITY | B13: It automatically starts and ends the programmed functions. | C13: 45000 | D13: 0.75 | E13: 0.107 | F13: Performance and convinience
... A15: MAPPING TECHNOLOGY | B15: Using advanced mapping technology, the Electroclean efficiently navigates and cleans spaces, covering all areas while avoiding obstacles. | C15: 115000 | D15: 1 | E15: 0.143 | F15: Performance and convinience

Sheet REPORT
A1: Market Share Per Region (%)
A2: Zone | B2: ElectroMexSA A | C2: Startek A | D2: Forastero LLC. A | E2: Baobab A | F2: Company 5 A | G2: Borealis Group A | H2: Esquites A
A3: Center | B3: 14.3 | C3: 14.3 | D3: 14.3 | E3: 14.3 | F3: 14.3 | G3: 14.3 | H3: 14.3
A4: West | B4: 14.3 | C4: 14.3 | D4: 14.3 | E4: 14.3 | F4: 14.3 | G4: 14.3 | H4: 14.3
A5: North | B5: 14.3 | C5: 14.3 | D5: 14.3 | E5: 14.3 | F5: 14.3 | G5: 14.3 | H5: 14.3
A6: East | B6: 0.0 | C6: 0.0 | D6: 0.0 | E6: 0.0 | F6: 0.0 | G6: 0.0 | H6: 0.0
A7: South | B7: 0.0 | C7: 0.0 | D7: 0.0 | E7: 0.0 | F7: 0.0 | G7: 0.0 | H7: 0.0
A9: Market Share Per Region Per Segment (%)
A10: Zone | B10: Segment | C10: ElectroMexSA A | D10: Startek A | E10: Forastero LLC. A | F10: Baobab A | G10: Company 5 A | H10: Borealis Group A | I10: Esquites A
A11: Center | B11: High | C11: 14.3 | D11: 14.3 | E11: 14.3 | F11: 14.3 | G11: 14.3 | H11: 14.3 | I11: 14.3
B12: Low | C12: 14.3 | D12: 14.3 | E12: 14.3 | F12: 14.3 | G12: 14.3 | H12: 14.3 | I12: 14.3
A13: West | B13: High | C13: 14.3 | D13: 14.3 | E13: 14.3 | F13: 14.3 | G13: 14.3 | H13: 14.3 | I13: 14.3
B14: Low | C14: 14.3 | D14: 14.3 | E14: 14.3 | F14: 14.3 | G14: 14.3 | H14: 14.3 | I14: 14.3
A15: North | B15: High | C15: 14.3 | D15: 14.3 | E15: 14.3 | F15: 14.3 | G15: 14.3 | H15: 14.3 | I15: 14.3
B16: Low | C16: 14.3 | D16: 14.3 | E16: 14.3 | F16: 14.3 | G16: 14.3 | H16: 14.3 | I16: 14.3
A17: East | B17: High | C17: 0.0 | D17: 0.0 | E17: 0.0 | F17: 0.0 | G17: 0.0 | H17: 0.0 | I17: 0.0
B18: Low | C18: 0.0 | D18: 0.0 | E18: 0.0 | F18: 0.0 | G18: 0.0 | H18: 0.0 | I18: 0.0
A19: South | B19: High | C19: 0.0 | D19: 0.0 | E19: 0.0 | F19: 0.0 | G19: 0.0 | H19: 0.0 | I19: 0.0
B20: Low | C20: 0.0 | D20: 0.0 | E20: 0.0 | F20: 0.0 | G20: 0.0 | H20: 0.0 | I20: 0.0
A22: Price
A23: Zone | B23: ElectroMexSA A | C23: Startek A | D23: Forastero LLC. A | E23: Baobab A | F23: Company 5 A | G23: Borealis Group A | H23: Esquites A
A24: Center | B24: 68.00 | C24: 68.00 | D24: 68.00 | E24: 68.00 | F24: 68.00 | G24: 68.00 | H24: 68.00
A25: West | B25: 68.00 | C25: 68.00 | D25: 68.00 | E25: 68.00 | F25: 68.00 | G25: 68.00 | H25: 68.00
A26: North | B26: 91.00 | C26: 91.00 | D26: 91.00 | E26: 91.00 | F26: 91.00 | G26: 91.00 | H26: 91.00
A27: East | B27: 0.00 | C27: 0.00 | D27: 0.00 | E27: 0.00 | F27: 0.00 | G27: 0.00 | H27: 0.00
A28: South | B28: 0.00 | C28: 0.00 | D28: 0.00 | E28: 0.00 | F28: 0.00 | G28: 0.00 | H28: 0.00
A30: Product Awareness Percentage Per Segment
A31: Zone | B31: Segment | C31: ElectroMexSA A | D31: Startek A | E31: Forastero LLC. A | F31: Baobab A | G31: Company 5 A | H31: Borealis Group A | I31: Esquites A
A32: Center | B32: High | C32: 42.39 | D32: 42.39 | E32: 42.39 | F32: 42.39 | G32: 42.39 | H32: 42.39 | I32: 42.39
B33: Low | C33: 28.72 | D33: 28.72 | E33: 28.72 | F33: 28.72 | G33: 28.72 | H33: 28.72 | I33: 28.72
A34: West | B34: High | C34: 34.58 | D34: 34.58 | E34: 34.58 | F34: 34.58 | G34: 34.58 | H34: 34.58 | I34: 34.58
B35: Low | C35: 22.16 | D35: 22.16 | E35: 22.16 | F35: 22.16 | G35: 22.16 | H35: 22.16 | I35: 22.16
A36: North | B36: High | C36: 26.84 | D36: 26.84 | E36: 26.84 | F36: 26.84 | G36: 26.84 | H36: 26.84 | I36: 26.84
B37: Low | C37: 23.10 | D37: 23.10 | E37: 23.10 | F37: 23.10 | G37: 23.10 | H37: 23.10 | I37: 23.10
A38: East | B38: High | C38: 0.00 | D38: 0.00 | E38: 0.00 | F38: 0.00 | G38: 0.00 | H38: 0.00 | I38: 0.00
B39: Low | C39: 0.00 | D39: 0.00 | E39: 0.00 | F39: 0.00 | G39: 0.00 | H39: 0.00 | I39: 0.00
A40: South | B40: High | C40: 0.00 | D40: 0.00 | E40: 0.00 | F40: 0.00 | G40: 0.00 | H40: 0.00 | I40: 0.00
B41: Low | C41: 0.00 | D41: 0.00 | E41: 0.00 | F41: 0.00 | G41: 0.00 | H41: 0.00 | I41: 0.00
A43: Product attractiveness (Perceived)
A44: Zone | B44: Segment | C44: ElectroMexSA A | D44: Startek A | E44: Forastero LLC. A | F44: Baobab A | G44: Company 5 A | H44: Borealis Group A | I44: Esquites A
A45: Center | B45: High | C45: 20.00 | D45: 20.00 | E45: 20.00 | F45: 20.00 | G45: 20.00 | H45: 20.00 | I45: 20.00
B46: Low | C46: 20.00 | D46: 20.00 | E46: 20.00 | F46: 20.00 | G46: 20.00 | H46: 20.00 | I46: 20.00
A47: West | B47: High | C47: 20.00 | D47: 20.00 | E47: 20.00 | F47: 20.00 | G47: 20.00 | H47: 20.00 | I47: 20.00
B48: Low | C48: 20.00 | D48: 20.00 | E48: 20.00 | F48: 20.00 | G48: 20.00 | H48: 20.00 | I48: 20.00
A49: North | B49: High | C49: 20.00 | D49: 20.00 | E49: 20.00 | F49: 20.00 | G49: 20.00 | H49: 20.00 | I49: 20.00
B50: Low | C50: 20.00 | D50: 20.00 | E50: 20.00 | F50: 20.00 | G50: 20.00 | H50: 20.00 | I50: 20.00
A51: East | B51: High | C51: 0.00 | D51: 0.00 | E51: 0.00 | F51: 0.00 | G51: 0.00 | H51: 0.00 | I51: 0.00
B52: Low | C52: 0.00 | D52: 0.00 | E52: 0.00 | F52: 0.00 | G52: 0.00 | H52: 0.00 | I52: 0.00
A53: South | B53: High | C53: 0.00 | D53: 0.00 | E53: 0.00 | F53: 0.00 | G53: 0.00 | H53: 0.00 | I53: 0.00
B54: Low | C54: 0.00 | D54: 0.00 | E54: 0.00 | F54: 0.00 | G54: 0.00 | H54: 0.00 | I54: 0.00
A56: Evaluation of the Promotional Impact of Salesforce
A57: Zone | B57: ElectroMexSA | C57: Startek | D57: Forastero LLC. | E57: Baobab | F57: Company 5 | G57: Borealis Group | H57: Esquites
A58: Center | B58: 94.44 | C58: 94.44 | D58: 94.44 | E58: 94.44 | F58: 94.44 | G58: 94.44 | H58: 94.44
A59: West | B59: 81.55 | C59: 81.55 | D59: 81.55 | E59: 81.55 | F59: 81.55 | G59: 81.55 | H59: 81.55
A60: North | B60: 95.32 | C60: 95.32 | D60: 95.32 | E60: 95.32 | F60: 95.32 | G60: 95.32 | H60: 95.32
A61: East | B61: 0.00 | C61: 0.00 | D61: 0.00 | E61: 0.00 | F61: 0.00 | G61: 0.00 | H61: 0.00
A62: South | B62: 0.00 | C62: 0.00 | D62: 0.00 | E62: 0.00 | F62: 0.00 | G62: 0.00 | H62: 0.00
A64: Brand | B64: Media | C64: Zone | D64: Amount | E64: Features Focus (0-100)
A65: A | B65: TV | C65: All | D65: 35 | E65: 0.5 | G65: =D65/((SUM(#REF!))) -> #REF!
A66: A | B66: Radio | C66: Center | D66: 210 | E66: 0.5 | F66: =D66/(SUM((#REF!))) -> #REF! | G66: =D66/#REF! -> #REF!
A67: A | B67: Radio | C67: West | D67: 102 | E67: 0.5 | F67: =D67/(SUM(#REF!)) -> #REF! | G67: =D67/#REF! -> #REF!
A68: A | B68: Radio | C68: North | D68: 82 | E68: 0.5 | F68: =D68/(SUM(#REF!)) -> #REF! | G68: =D68/#REF! -> #REF!
B70: Distributors
A71: Zone | B71: Payment Terms | C71: Salespeople | E71: Payment Terms | F71: # FORTNIGHTS | G71: DISCOUNT
A72: Center | B72: B | C72: 17 | D72: =C72/#REF! -> #REF! | E72: A | F72: 0 | G72: 0.13
A73: West | B73: B | C73: 13 | D73: =C73/#REF! -> #REF! | E73: B | F73: 2 | G73: 0.075
A74: North | B74: B | C74: 14 | D74: =C74/#REF! -> #REF! | E74: C | F74: 4 | G74: 0.025
A75: East | B75: A | C75: 0 | E75: D | F75: 8 | G75: 0
A76: South | B76: A | C76: 0
A78: Media | B78: Rreach | C78: Cost
A79: Tv | B79: National / HE | C79: 3000 | F79: =D65*C79 -> 105000
A80: Radio | B80: Regional / LE | C80: 300 | F80: =(SUM(D66:D68)*C80) -> 118200
F81: =SUM(F79:F80) -> 223200
A82: # Persons | B82: Hiring | C82: Salary
A83: 44 | B83: 1000 | C83: 750

Sheet DF Q7
B2: FORECAST | C2: AVERAGE DEMAND | K2: Q VS Q | R2: Crecimiento | S2: YVSY | Z2: Center | AA2: =ROUNDUP(R4,0) -> 8091 | AD2: 9 | AH2: 9
C3: 1 | D3: 2 | E3: 3 | F3: 4 | G3: 5 | H3: 6 | I3: 7 | K3: 1 | L3: 2 | M3: 3 | N3: 4 | O3: 5 | P3: 6 | Q3: 7 | R3: 0 | S3: 4 VS 1 | T3: 5 VS 2 | U3: 6 VS 3 | V3: FQ7 | Z3: West | AA3: =ROUNDUP(R5,0) -> 4178 | AD3: Center | AE3: Section 2 | AF3: M2 | AG3: 22 | AH3: 24
B4: Center | C4: 4100 | D4: 3600 | E4: 6600 | F4: 6000 | G4: 5100 | H4: 8900 | L4: =(D4/C4)-1 -> -0.12195122 | M4: =(E4/D4)-1 -> 0.83333333 | N4: =(F4/E4)-1 -> -0.090909091 | O4: =(G4/F4)-1 -> -0.15 | P4: =(H4/G4)-1 -> 0.74509804 | Q4: =H4*(1+N4) -> 8090.9091 | R4: =Q4*(1+$R$3) -> 8090.9091 | S4: =(F4/C4)-1 -> 0.46341463 | T4: =(G4/D4)-1 -> 0.41666667 | U4: =(H4/E4)-1 -> 0.34848485 | V4: =F4*(1+S4) -> 8780.4878 | Z4: North | AA4: =ROUNDUP(R6,0) -> 4570 | AD4: Center | AE4: Section 3 | AF4: M3-alpha | AG4: 4 | AH4: 120
B5: West | C5: 1800 | D5: 1900 | E5: 2700 | F5: 2800 | G5: 2900 | H5: 4028 | L5: =(D5/C5)-1 -> 0.055555556 | M5: =(E5/D5)-1 -> 0.42105263 | N5: =(F5/E5)-1 -> 0.037037037 | O5: =(G5/F5)-1 -> 0.035714286 | P5: =(H5/G5)-1 -> 0.38896552 | Q5: =H5*(1+N5) -> 4177.1852 | R5: =Q5*(1+$R$3) -> 4177.1852 | S5: =(F5/C5)-1 -> 0.55555556 | T5: =(G5/D5)-1 -> 0.52631579 | U5: =(H5/E5)-1 -> 0.49185185 | V5: =F5*(1+S5) -> 4355.5556 | Z5: East | AA5: =ROUNDUP(R7,0) -> 1334 | AD5: Center | AE5: Section 3 | AF5: M3-beta | AG5: 0 | AH5: 0
B6: North | C6: 700 | D6: 1200 | E6: 2600 | F6: 2700 | G6: 2700 | H6: 4400 | L6: =(D6/C6)-1 -> 0.71428571 | M6: =(E6/D6)-1 -> 1.1666667 | N6: =(F6/E6)-1 -> 0.038461538 | O6: =(G6/F6)-1 -> 0 | P6: =(H6/G6)-1 -> 0.62962963 | Q6: =H6*(1+N6) -> 4569.2308 | R6: =Q6*(1+$R$3) -> 4569.2308 | S6: =(F6/C6)-1 -> 2.8571429 | T6: =(G6/D6)-1 -> 1.25 | U6: =(H6/E6)-1 -> 0.69230769 | V6: =F6*(1+S6) -> 10414.286 | Z6: South | AA6: =ROUNDUP(R8,0) -> 1000 | AD6: Center | AE6: Section 3 | AF6: M4 | AG6: 4 | AH6: 5
B7: East | Q7: =((EXHIBITS!C10+EXHIBITS!D10)/2)/3 -> 1333.3333 | R7: =Q7 -> 1333.3333 | V7: =Q7 -> 1333.3333 | AA7: =SUM(AA2:AA6) -> 19173 | AD7: Center | AE7: Section 4 | AF7: M4 | AG7: 10 | AH7: 11
B8: South | O8: =(M13/H4)-1 -> -1 | Q8: =((EXHIBITS!C11+EXHIBITS!D11)/2)/3 -> 1000 | R8: =Q8 -> 1000 | V8: =Q8 -> 1000 | AD8: Center | AE8: Section 5 | AF8: M4 | AG8: 12 | AH8: 13
B9: TOTAL | C9: =SUM(C4:C8) -> 6600 | D9: =SUM(D4:D8) -> 6700 | E9: =SUM(E4:E8) -> 11900 | F9: =SUM(F4:F8) -> 11500 | G9: =SUM(G4:G8) -> 10700 | H9: =SUM(H4:H8) -> 17328 | O9: =(M14/H5)-1 -> -1 | AD9: Center | AE9: Section 5 | AF9: Crew | AG9: - | AH9: 90
B10: TARGET POPULATION | C10: =EXHIBITS!C19 -> 110000 | D10: =EXHIBITS!D19 -> 75000 | E10: =EXHIBITS!E19 -> 70000 | F10: =EXHIBITS!F19 -> 50000 | G10: =EXHIBITS!G19 -> 30000 | O10: =(M15/H6)-1 -> -1 | AD10: East | AE10: Section 1 | AF10: M1 | AG10: 0 | AH10: 0
C11: =H4/C10 -> 0.080909091 | D11: =H5/D10 -> 0.053706667 | E11: =H6/F10 -> 0.088 | AD11: East | AE11: Section 2 | AF11: M2 | AG11: 0 | AH11: 0
B12: Demanda | K12: Real | L12: Sobraron | N12: % Dif | AD12: East | AE12: Section 3 | AF12: M3-alpha | AG12: 0 | AH12: 0
C13: F2 | D13: F4 | E13: F6 | F13: F8 | H13: Center | I13: =AA2 -> 8091 | K13: 7792 | L13: =I13-K13 -> 299 | N13: =1-(K13/I13) -> 0.036954641 | AD13: East | AE13: Section 3 | AF13: M3-beta | AG13: 0 | AH13: 0
C14: =$I$13/4 -> 2022.75 | D14: =$I$13/4 -> 2022.75 | E14: =$I$13/4 -> 2022.75 | F14: =$I$13/4 -> 2022.75 | G14: =SUM(C14:F14) -> 8091 | H14: West | I14: =AA3 -> 4178 | K14: 3948 | L14: =I14-K14 -> 230 | N14: =1-(K14/I14) -> 0.055050263 | AD14: East | AE14: Section 3 | AF14: M4 | AG14: 0 | AH14: 0
C15: =$I$14/4 -> 1044.5 | D15: =$I$14/4 -> 1044.5 | E15: =$I$14/4 -> 1044.5 | F15: =$I$14/4 -> 1044.5 | G15: =SUM(C15:F15) -> 4178 | H15: North | I15: =AA4 -> 4570 | K15: 3868 | L15: =I15-K15 -> 702 | N15: =1-(K15/I15) -> 0.1536105 | AD15: East | AE15: Section 4 | AF15: M4 | AG15: 0 | AH15: 0
C16: =$I$15/4 -> 1142.5 | D16: =$I$15/4 -> 1142.5 | E16: =$I$15/4 -> 1142.5 | F16: =$I$15/4 -> 1142.5 | G16: =SUM(C16:F16) -> 4570 | H16: East | I16: =AA5 -> 1334 | K16: 788 | L16: =I16-K16 -> 546 | N16: =1-(K16/I16) -> 0.40929535 | AD16: East | AE16: Section 5 | AF16: M4 | AG16: 0 | AH16: 0
C17: =$I$16/4 -> 333.5 | D17: =$I$16/4 -> 333.5 | E17: =$I$16/4 -> 333.5 | F17: =$I$16/4 -> 333.5 | G17: =SUM(C17:F17) -> 1334 | H17: South | I17: =AA6 -> 1000 | K17: 684 | L17: =I17-K17 -> 316 | N17: =1-(K17/I17) -> 0.316 | AD17: East | AE17: Section 5 | AF17: Crew | AG17: - | AH17: 0
C18: =$I$17/4 -> 250 | D18: =$I$17/4 -> 250 | E18: =$I$17/4 -> 250 | F18: =$I$17/4 -> 250 | G18: =SUM(C18:F18) -> 1000 | H18: TOTAL | I18: =SUM(I13:I17) -> 19173 | K18: =SUM(K13:K17) -> 17080 | L18: =I18-K18 -> 2093 | AD18: North | AE18: Section 1 | AF18: M1 | AG18: 0 | AH18: 0
AD19: North | AE19: Section 2 | AF19: M2 | AG19: 0 | AH19: 0
B20: Precio | AD20: North | AE20: Section 3 | AF20: M3-alpha | AG20: 0 | AH20: 0
A21: COGS 7 | B21: 31.39 | C21: Zone | D21: PRICE | E21: Final price +6% | F21: TRANSPORT | I21: Zone | J21: GROSS MARG Sin trans | K21: GROSS MARG Con trans | L21: GROSS MARG Con trans | M21: GMar Sin tran - Dcto | N21: GMar Sin tran - Dcto | O21: % | AD21: North | AE21: Section 3 | AF21: M3-beta | AG21: 0 | AH21: 0
A22: 68 | B22: 0.11 | C22: Center | D22: =ROUNDUP(A22+E47,0) -> 69 | E22: =ROUNDUP(D22*1.11,0) -> 77 | I22: Center | J22: =E22-$B$21 -> 45.61 | L22: =(J22/$B$21)-1 -> 0.45301051 | M22: =(E22*(1-G61))-$B$21 -> 39.835 | O22: =(M22/$B$21)-1 -> 0.26903472 | AD22: North | AE22: Section 3 | AF22: M4 | AG22: 0 | AH22: 0
A23: 68 | B23: 0.11 | C23: West | D23: =ROUNDUP(A23+E47,0) -> 69 | E23: =ROUNDUP(D23*1.11,0) -> 77 | I23: West | J23: =E23-$B$21 -> 45.61 | L23: =(J23/$B$21)-1 -> 0.45301051 | M23: =(E23*(1-G62))-$B$21 -> 39.835 | O23: =(M23/$B$21)-1 -> 0.26903472 | AD23: North | AE23: Section 4 | AF23: M4 | AG23: 0 | AH23: 0
A24: 91 | B24: 0.095 | C24: North | D24: =ROUNDUP(A24+'DF Q7'!E47,0) -> 92 | E24: =ROUNDUP(D24*1.095,0) -> 101 | F24: 26.4 | G24: 19.6 | I24: North | J24: =E24-$B$21 -> 69.61 | K24: =E24-$B$21-F24 -> 43.21 | L24: =(K24/$B$21)-1 -> 0.37655304 | M24: =(E24*(1-G63))-$B$21 -> 62.035 | N24: =M24-F24 -> 35.635 | O24: =(N24/$B$21)-1 -> 0.13523415 | AD24: North | AE24: Section 5 | AF24: M4 | AG24: 0 | AH24: 0
A25: 0 | C25: East | D25: =ROUNDUP(A22+'DF Q7'!E47+'DF Q7'!F25,0) -> 98 | E25: =ROUNDUP(D25*1,0) -> 98 | F25: 28.8 | I25: East | J25: =E25-$B$21 -> 66.61 | K25: =E25-$B$21-F25 -> 37.81 | L25: =(K25/$B$21)-1 -> 0.20452373 | M25: =(E25*(1-G64))-$B$21 -> 59.26 | N25: =M25-F25 -> 30.46 | O25: =(N25/$B$21)-1 -> -0.02962727 | AD25: North | AE25: Section 5 | AF25: Crew | AG25: - | AH25: 0
A26: 0 | B26: 7%% | C26: South | D26: =ROUNDUP(A22+'DF Q7'!E47+'DF Q7'!F26,0) -> 93 | E26: =ROUNDUP(D26*1.07,0) -> 100 | F26: 24 | I26: South | J26: =E26-$B$21 -> 68.61 | K26: =E26-$B$21-F26 -> 44.61 | L26: =(K26/$B$21)-1 -> 0.42115323 | M26: =(E26*(1-G65))-$B$21 -> 61.11 | N26: =M26-F26 -> 37.11 | O26: =(N26/$B$21)-1 -> 0.18222364 | AD26: South | AE26: Section 1 | AF26: M1 | AG26: 0 | AH26: 0
AD27: South | AE27: Section 2 | AF27: M2 | AG27: 0 | AH27: 0
AD28: South | AE28: Section 3 | AF28: M3-alpha | AG28: 0 | AH28: 0
B29: Advertaising | AD29: South | AE29: Section 3 | AF29: M3-beta | AG29: 0 | AH29: 0
C30: Media | D30: Zone | E30: # Spots | F30: $ per spot | G30: TC | H30: FOCUS | I30: TC/ FORTNIGHT | AD30: South | AE30: Section 3 | AF30: M4 | AG30: 0 | AH30: 0
A31: 35 | B31: =REPORT!D65/'DF Q7'!H9 -> 0.0020198523 | C31: TV | D31: All | E31: 35 | F31: 3000 | G31: =F31*E31 -> 105000 | H31: 60 | I31: =G31/8 -> 13125 | AD31: South | AE31: Section 4 | AF31: M4 | AG31: 0 | AH31: 0
A32: 210 | B32: =REPORT!D66/'DF Q7'!H4 -> 0.023595506 | C32: Radio | D32: Center | E32: 210 | F32: 300 | G32: =F32*E32 -> 63000 | H32: 55 | I32: =G32/8 -> 7875 | J32: Me quedé corta en advertaising en east and south | AD32: South | AE32: Section 5 | AF32: M4 | AG32: 0 | AH32: 0
A33: 102 | B33: =REPORT!D67/'DF Q7'!H5 -> 0.025322741 | D33: West | E33: 102 | F33: 300 | G33: =F33*E33 -> 30600 | H33: 55 | I33: =G33/8 -> 3825 | J33: Un poco en tele | AD33: South | AE33: Section 5 | AF33: Crew | AG33: - | AH33: 0
A34: 82 | B34: =REPORT!D68/'DF Q7'!H6 -> 0.018636364 | D34: North | E34: 82 | F34: 300 | G34: =F34*E34 -> 24600 | H34: 55 | I34: =G34/8 -> 3075 | AD34: West | AE34: Section 1 | AF34: M1 | AG34: 3 | AH34: 4
A35: 0 | B35: =B33 -> 0.025322741 | D35: East | E35: =ROUNDUP(I16*B35,0) -> 34 | F35: 300 | G35: =F35*E35 -> 10200 | H35: 50 | I35: =G35/8 -> 1275 | AD35: West | AE35: Section 2 | AF35: M2 | AG35: 8 | AH35: 9
A36: 0 | B36: =B33 -> 0.025322741 | D36: South | E36: =ROUNDUP(I17*B36,0) -> 26 | F36: 300 | G36: =F36*E36 -> 7800 | H36: 50 | I36: =G36/8 -> 975 | AD36: West | AE36: Section 3 | AF36: M3-alpha | AG36: 2 | AH36: 60
G37: =SUM(G31:G36) -> 241200 | H37: TOTAL | I37: =SUM(I31:I36) -> 30150 | AD37: West | AE37: Section 3 | AF37: M3-beta | AG37: 0 | AH37: 0
AD38: West | AE38: Section 3 | AF38: M4 | AG38: 2 | AH38: 3
B39: Features | AD39: West | AE39: Section 4 | AF39: M4 | AG39: 4 | AH39: 5
C40: Feature | D40: UP FRONT | E40: VC | F40: # Units | G40: Total Cost | AD40: West | AE40: Section 5 | AF40: M4 | AG40: 4 | AH40: 5
C41: =FEATURES!A2 -> STAINLESS MATERIAL | D41: =VLOOKUP(C41,FEATURES!$A$2:$E$15,3,FALSE) -> 15000 | E41: =VLOOKUP(C41,FEATURES!$A$2:$E$15,4,) -> 0.15 | F41: =$I$18 -> 19173 | G41: =E41*F41 -> 2875.95 | AD41: West | AE41: Section 5 | AF41: Crew | AG41: - | AH41: 30
C42: =FEATURES!A11 -> DIGITAL CONTROLS | D42: =VLOOKUP(C42,FEATURES!$A$2:$E$15,3,FALSE) -> 45000 | E42: =VLOOKUP(C42,FEATURES!$A$2:$E$15,4,) -> 0.45 | F42: =$I$18 -> 19173 | G42: =E42*F42 -> 8627.85 | I42: TC FEATURES / F | J42: =(I18*E47)/4 -> 2875.95 | AK42: Q
D43: =VLOOKUP(C43,FEATURES!$A$2:$E$15,3,FALSE) -> #N/A | E43: =VLOOKUP(C43,FEATURES!$A$2:$E$15,4,) -> #N/A | F43: =$I$18 -> 19173 | G43: =E43*F43 -> #N/A | AG43: DL | AH43: =SUM(AH2:AH41) -> 388 | AI43: 28 | AJ43: 8 | AK43: =AH43*AI43*AJ43 -> 86912 | AL43: =AK43/$AM$60 -> 0.15832811
D44: =VLOOKUP(C44,FEATURES!$A$2:$E$15,3,FALSE) -> #N/A | E44: =VLOOKUP(C44,FEATURES!$A$2:$E$15,4,) -> #N/A | F44: =$I$18 -> 19173 | G44: =E44*F44 -> #N/A | AG44: OVERTIME | AH44: =AH8+AH34+AH35+AH39+AH40+AH41+AH9 -> 156 | AI44: 12 | AJ44: 8 | AK44: =AH44*AI44*AJ44 -> 14976 | AL44: =AK44/$AM$60 -> 0.027281869
D45: =VLOOKUP(C45,FEATURES!$A$2:$E$15,3,FALSE) -> #N/A | E45: =VLOOKUP(C45,FEATURES!$A$2:$E$15,4,) -> #N/A | F45: =$I$18 -> 19173 | G45: =E45*F45 -> #N/A | AG45: INDIRECT | AK45: =(AK43+AK44)*0.5 -> 50944 | AL45: =AK45/$AM$60 -> 0.09280499
D46: =VLOOKUP(C46,FEATURES!$A$2:$E$15,3,FALSE) -> #N/A | E46: =VLOOKUP(C46,FEATURES!$A$2:$E$15,4,) -> #N/A | F46: =$I$18 -> 19173 | G46: =E46*F46 -> #N/A | AL46: =AK46/$AM$60 -> 0
C47: TOTAL | D47: =D41+D42 -> 60000 | E47: =E41+E42 -> 0.6 | AG47: VC | AI47: 0.6 | AJ47: 17080 | AK47: =AI47*AJ47 -> 10248 | AL47: =AK47/$AM$60 -> 0.018668843
AG48: RAW 1-6 | AI48: 2.5 | AJ48: 17080 | AK48: =AI48*AJ48 -> 42700 | AL48: =AK48/$AM$60 -> 0.077786846
B49: # Sales People | AG49: A | AH49: 1 | AI49: =140/30 -> 4.6666667 | AJ49: 17080 | AK49: =AI49*AJ49 -> 79706.667 | AL49: =AK49/$AM$60 -> 0.14520211
C50: Zone | D50: # People | E50: T Hiring Cost | F50: SALARY PER Q | H50: Hiring C | I50: Salary | AG50: B | AH50: 0.2 | AI50: =370/12 -> 30.833333 | AJ50: 17080 | AK50: =AJ50*AH50*AI50 -> 105326.67 | AL50: =AK50/$AM$60 -> 0.19187422
A51: 17 | B51: =A51/H4 -> 0.0019101124 | C51: Center | D51: =ROUNDUP(I13*B51,0)+1 -> 17 | E51: =(D51-17)*$H$51 -> 0 | F51: =D51*$I$51 -> 12750 | H51: 1000 | I51: 750 | AG51: ORDERING COST A | AH51: 3 | AI51: 2300 | AK51: =AH51*AI51 -> 6900 | AL51: =AK51/$AM$60 -> 0.012569771
A52: 13 | B52: =A52/H5 -> 0.0032274081 | C52: West | D52: =ROUNDUP(I14*B52,0) -> 14 | E52: =(D52-13)*$H$51 -> 1000 | F52: =D52*$I$51 -> 10500 | AG52: ORDERING COST B | AH52: 7 | AI52: 6000 | AK52: =AH52*AI52 -> 42000 | AL52: =AK52/$AM$60 -> 0.076511652 | AS52: 304 | AT52: 2712 | AU52: 2000 | AV52: 1288 | AW52: 576 | AX52: 0 | AY52: 2408 | AZ52: 1696
A53: 14 | B53: =A53/H6 -> 0.0031818182 | C53: North | D53: =ROUNDUP(I15*B53,0) -> 15 | E53: =(D53-14)*$H$51 -> 1000 | F53: =D53*$I$51 -> 11250 | K53: Me faltaa gente | AG53: Holding Cost A | AK53: =BA55 -> 7786.8 | AL53: =AK53/$AM$60 -> 0.01418526 | AR53: Holding Cost A | AS53: 2875 | AT53: 2254 | AU53: 1633 | AV53: 1012 | AW53: 391 | AX53: 2890 | AY53: 2269 | AZ53: 1648
A54: 0 | B54: 0.006 | C54: East | D54: =ROUNDUP(I16*B54,0) -> 9 | E54: =D54*$H$51 -> 9000 | F54: =D54*$I$51 -> 6750 | K54: West | AG54: Holding Cost B | AK54: =BA60 -> 20214 | AL54: =AK54/$AM$60 -> 0.036823965 | AS54: 0.3 | AT54: 0.3 | AU54: 0.3 | AV54: 0.3 | AW54: 0.3 | AX54: 0.3 | AY54: 0.3 | AZ54: 0.3
A55: 0 | B55: 0.008 | C55: South | D55: =ROUNDUP(I17*B55,0) -> 8 | E55: =D55*$H$51 -> 8000 | F55: =D55*$I$51 -> 6000 | K55: East South | AG55: Holding Cost Assembly A | AK55: =BA66 -> 14372 | AL55: =AK55/$AM$60 -> 0.026181559 | AS55: =(AS52+AS53)*AS54 -> 953.7 | AT55: =(AT52+AT53)*AT54 -> 1489.8 | AU55: =(AU52+AU53)*AU54 -> 1089.9 | AV55: =(AV52+AV53)*AV54 -> 690 | AW55: =(AW52+AW53)*AW54 -> 290.1 | AX55: =(AX52+AX53)*AX54 -> 867 | AY55: =(AY52+AY53)*AY54 -> 1403.1 | AZ55: =(AZ52+AZ53)*AZ54 -> 1003.2 | BA55: =SUM(AS55:AZ55) -> 7786.8
C56: TOTAL | D56: =SUM(D51:D55) -> 63 | E56: =SUM(E51:E55) -> 19000 | F56: =SUM(F51:F55) -> 47250 | AG56: Holding Cost Assembly B | AK56: =BA71 -> 21201.6 | AL56: =AK56/$AM$60 -> 0.038623082
AG57: Holding Cost Assembly C | AK57: =BA76 -> 21181.2 | AL57: =AK57/$AM$60 -> 0.038585919 | AR57: Holding Cost B | AS57: 160 | AT57: 327 | AU57: 194 | AV57: 361 | AW57: 228 | AX57: 395 | AY57: 262 | AZ57: 429
B58: Payment type | AG58: Holding Cost Assembly D | AK58: =BA81 -> 11631.6 | AL58: =AK58/$AM$60 -> 0.021189355 | AS58: 585 | AT58: 405 | AU58: 225 | AV58: 45 | AW58: 177 | AX58: 309 | AY58: 129 | AZ58: 261
AG59: Lost Finished Goods | AI59: =31.39 -> 31.39 | AJ59: =SUM(AS90:AS93) -> 405 | AK59: =AI59*AJ59 -> 12712.95 | AS59: 4.5 | AT59: 4.5 | AU59: 4.5 | AV59: 4.5 | AW59: 4.5 | AX59: 4.5 | AY59: 4.5 | AZ59: 4.5
C60: Zone | D60: Type | E60: Payment term | F60: Sales | G60: Discount | H60: Tota Payment per 2 F | AK60: =SUM(AK43:AK58) -> 536100.53 | AL60: =AK60+AK59 -> 548813.48 | AM60: 548936 | AN60: =AL60-AM60 -> -122.51667 | AS60: =(AS57+AS58)*AS59 -> 3352.5 | AT60: =(AT57+AT58)*AT59 -> 3294 | AU60: =(AU57+AU58)*AU59 -> 1885.5 | AV60: =(AV57+AV58)*AV59 -> 1827 | AW60: =(AW57+AW58)*AW59 -> 1822.5 | AX60: =(AX57+AX58)*AX59 -> 3168 | AY60: =(AY57+AY58)*AY59 -> 1759.5 | AZ60: =(AZ57+AZ58)*AZ59 -> 3105 | BA60: =SUM(AS60:AZ60) -> 20214
C61: Center | D61: B | E61: =IF(D61="A",REPORT!$F$72,IF('DF Q7'!D61="B",REPORT!$F$73,IF('DF Q7'!D61="C",REPORT!$F$74,IF('DF Q7'!D61="D",REPORT!$F$75,"error")))) -> 2 | F61: =I13*E22 -> 623007 | G61: =IF(D61="A",REPORT!$G$72,IF('DF Q7'!D61="B",REPORT!$G$73,IF('DF Q7'!D61="C",REPORT!$G$74,IF('DF Q7'!D61="D",REPORT!$G$75,"error")))) -> 0.075 | H61: =(F61*(1-G61))/4 -> 144070.37 | I61: =I13*D22 -> 558279 | J61: =I61*0.925 -> 516408.08 | K61: =J61/4 -> 129102.02 | AK61: =AK60/$AJ$50 -> 31.387619 | AM61: =AM60/$AJ$50 -> 32.13911
C62: West | D62: B | E62: =IF(D62="A",REPORT!$F$72,IF('DF Q7'!D62="B",REPORT!$F$73,IF('DF Q7'!D62="C",REPORT!$F$74,IF('DF Q7'!D62="D",REPORT!$F$75,"error")))) -> 2 | F62: =I14*E23 -> 321706 | G62: =IF(D62="A",REPORT!$G$72,IF('DF Q7'!D62="B",REPORT!$G$73,IF('DF Q7'!D62="C",REPORT!$G$74,IF('DF Q7'!D62="D",REPORT!$G$75,"error")))) -> 0.075 | H62: =(F62*(1-G62))/4 -> 74394.512 | I62: =I14*D23 -> 288282 | J62: =I62*0.925 -> 266660.85 | K62: =J62/4 -> 66665.213
C63: North | D63: B | E63: =IF(D63="A",REPORT!$F$72,IF('DF Q7'!D63="B",REPORT!$F$73,IF('DF Q7'!D63="C",REPORT!$F$74,IF('DF Q7'!D63="D",REPORT!$F$75,"error")))) -> 2 | F63: =I15*E24 -> 461570 | G63: =IF(D63="A",REPORT!$G$72,IF('DF Q7'!D63="B",REPORT!$G$73,IF('DF Q7'!D63="C",REPORT!$G$74,IF('DF Q7'!D63="D",REPORT!$G$75,"error")))) -> 0.075 | H63: =(F63*(1-G63))/4 -> 106738.06 | I63: =I15*D24 -> 420440 | J63: =I63*0.925 -> 388907 | K63: =J63/4 -> 97226.75 | AR63: Holding Cost Assembly A | AS63: =2936+712 -> 3648 | AT63: =2962+712 -> 3674 | AU63: =2988+712 -> 3700 | AV63: =3014+712 -> 3726 | AW63: =3040+712 -> 3752 | AX63: =3066+576 -> 3642 | AY63: =2956+712 -> 3668 | AZ63: =2982+712 -> 3694
C64: East | D64: B | E64: =IF(D64="A",REPORT!$F$72,IF('DF Q7'!D64="B",REPORT!$F$73,IF('DF Q7'!D64="C",REPORT!$F$74,IF('DF Q7'!D64="D",REPORT!$F$75,"error")))) -> 2 | F64: =I16*E25 -> 130732 | G64: =IF(D64="A",REPORT!$G$72,IF('DF Q7'!D64="B",REPORT!$G$73,IF('DF Q7'!D64="C",REPORT!$G$74,IF('DF Q7'!D64="D",REPORT!$G$75,"error")))) -> 0.075 | H64: =(F64*(1-G64))/4 -> 30231.775 | I64: =I16*D25 -> 130732 | J64: =I64*0.925 -> 120927.1 | K64: =J64/4 -> 30231.775 | AS64: =6336+621 -> 6957 | AT64: =5861+621 -> 6482 | AU64: =5386+621 -> 6007 | AV64: =4911+621 -> 5532 | AW64: =4436+621 -> 5057 | AX64: =3961+621 -> 4582 | AY64: =3486+621 -> 4107 | AZ64: =3011+621 -> 3632
C65: South | D65: B | E65: =IF(D65="A",REPORT!$F$72,IF('DF Q7'!D65="B",REPORT!$F$73,IF('DF Q7'!D65="C",REPORT!$F$74,IF('DF Q7'!D65="D",REPORT!$F$75,"error")))) -> 2 | F65: =I17*E26 -> 100000 | G65: =IF(D65="A",REPORT!$G$72,IF('DF Q7'!D65="B",REPORT!$G$73,IF('DF Q7'!D65="C",REPORT!$G$74,IF('DF Q7'!D65="D",REPORT!$G$75,"error")))) -> 0.075 | H65: =(F65*(1-G65))/4 -> 23125 | I65: =I17*D26 -> 93000 | J65: =I65*0.925 -> 86025 | K65: =J65/4 -> 21506.25 | AS65: 0.2 | AT65: 0.2 | AU65: 0.2 | AV65: 0.2 | AW65: 0.2 | AX65: 0.2 | AY65: 0.2 | AZ65: 0.2
F66: =SUM(F61:F65) -> 1637015 | G66: TOTAL | H66: =SUM(H61:H65) -> 378559.72 | AS66: =(AS63+AS64)*AS65 -> 2121 | AT66: =(AT63+AT64)*AT65 -> 2031.2 | AU66: =(AU63+AU64)*AU65 -> 1941.4 | AV66: =(AV63+AV64)*AV65 -> 1851.6 | AW66: =(AW63+AW64)*AW65 -> 1761.8 | AX66: =(AX63+AX64)*AX65 -> 1644.8 | AY66: =(AY63+AY64)*AY65 -> 1555 | AZ66: =(AZ63+AZ64)*AZ65 -> 1465.2 | BA66: =SUM(AS66:AZ66) -> 14372
C67: TC/ FORTNIGHT | D67: TC Q
B68: Advertaising | C68: =I37 -> 30150 | D68: =C68*8 -> 241200 | AR68: Holding Cost Assembly B | AS68: =1524+665 -> 2189 | AT68: =1503+665 -> 2168 | AU68: =1482+665 -> 2147 | AV68: =1461+665 -> 2126 | AW68: =1440+665 -> 2105 | AX68: =1419+665 -> 2084 | AY68: =1398+665 -> 2063 | AZ68: =1377+665 -> 2042
B69: Features | C69: =J42 -> 2875.95 | AS69: =4296+900 -> 5196 | AT69: =4100+900 -> 5000 | AU69: =3904+900 -> 4804 | AV69: =3708+900 -> 4608 | AW69: =3512+900 -> 4412 | AX69: =3316+900 -> 4216 | AY69: =3120+900 -> 4020 | AZ69: =2924+900 -> 3824
B70: # Sales People | C70: =D70/8 -> 5906.25 | D70: =F56 -> 47250 | AS70: 0.4 | AT70: 0.4 | AU70: 0.4 | AV70: 0.4 | AW70: 0.4 | AX70: 0.4 | AY70: 0.4 | AZ70: 0.4
B71: Hiring | D71: =E56 -> 19000 | AS71: =(AS68+AS69)*AS70 -> 2954 | AT71: =(AT68+AT69)*AT70 -> 2867.2 | AU71: =(AU68+AU69)*AU70 -> 2780.4 | AV71: =(AV68+AV69)*AV70 -> 2693.6 | AW71: =(AW68+AW69)*AW70 -> 2606.8 | AX71: =(AX68+AX69)*AX70 -> 2520 | AY71: =(AY68+AY69)*AY70 -> 2433.2 | AZ71: =(AZ68+AZ69)*AZ70 -> 2346.4 | BA71: =SUM(AS71:AZ71) -> 21201.6
D72: =D68+D70+D71 -> 307450 | BA72: Transit
AR73: Holding Cost Assembly C | AS73: =1822+686 -> 2508 | AT73: =1914+686 -> 2600 | AU73: =2006+686 -> 2692 | AV73: =2098+686 -> 2784 | AW73: =2190+686 -> 2876 | AX73: =2282+686 -> 2968 | AY73: =2374+686 -> 3060 | AZ73: =2466+686 -> 3152
AS74: =1984+1096 -> 3080 | AT74: =1298+1096 -> 2394 | AU74: =612+1096 -> 1708 | AV74: =1096 -> 1096 | AW74: 1096 | AX74: 1096 | AY74: 1096 | AZ74: 1096
AS75: 0.6 | AT75: 0.6 | AU75: 0.6 | AV75: 0.6 | AW75: 0.6 | AX75: 0.6 | AY75: 0.6 | AZ75: 0.6
AS76: =(AS73+AS74)*AS75 -> 3352.8 | AT76: =(AT73+AT74)*AT75 -> 2996.4 | AU76: =(AU73+AU74)*AU75 -> 2640 | AV76: =(AV73+AV74)*AV75 -> 2328 | AW76: =(AW73+AW74)*AW75 -> 2383.2 | AX76: =(AX73+AX74)*AX75 -> 2438.4 | AY76: =(AY73+AY74)*AY75 -> 2493.6 | AZ76: =(AZ73+AZ74)*AZ75 -> 2548.8 | BA76: =SUM(AS76:AZ76) -> 21181.2
AR78: Holding Cost Assembly D | AS78: =1672+712 -> 2384 | AT78: =1790+712 -> 2502 | AU78: =1908+712 -> 2620 | AV78: =2026+712 -> 2738 | AW78: =2144+712 -> 2856 | AX78: =2262+712 -> 2974 | AY78: =2380+656 -> 3036 | AZ78: 2442
AS79: =4824+1130 -> 5954 | AT79: =4172+1130 -> 5302 | AU79: =3520+1130 -> 4650 | AV79: =2942+1130 -> 4072 | AW79: =2976+1130 -> 4106 | AX79: =3010+1130 -> 4140 | AY79: =3044+1130 -> 4174 | AZ79: =3078+1130 -> 4208
AS80: 0.2 | AT80: 0.2 | AU80: 0.2 | AV80: 0.2 | AW80: 0.2 | AX80: 0.2 | AY80: 0.2 | AZ80: 0.2
AS81: =(AS78+AS79)*AS80 -> 1667.6 | AT81: =(AT78+AT79)*AT80 -> 1560.8 | AU81: =(AU78+AU79)*AU80 -> 1454 | AV81: =(AV78+AV79)*AV80 -> 1362 | AW81: =(AW78+AW79)*AW80 -> 1392.4 | AX81: =(AX78+AX79)*AX80 -> 1422.8 | AY81: =(AY78+AY79)*AY80 -> 1442 | AZ81: =(AZ78+AZ79)*AZ80 -> 1330 | BA81: =SUM(AS81:AZ81) -> 11631.6 | BB81: 11632
AS83: =AS55+AS60+AS66+AS71+AS76+AS81 -> 14401.6 | AT83: =AT55+AT60+AT66+AT71+AT76+AT81 -> 14239.4 | AU83: =AU55+AU60+AU66+AU71+AU76+AU81 -> 11791.2 | AV83: =AV55+AV60+AV66+AV71+AV76+AV81 -> 10752.2 | AW83: =AW55+AW60+AW66+AW71+AW76+AW81 -> 10256.8 | AX83: =AX55+AX60+AX66+AX71+AX76+AX81 -> 12061 | AY83: =AY55+AY60+AY66+AY71+AY76+AY81 -> 11086.4 | AZ83: =AZ55+AZ60+AZ66+AZ71+AZ76+AZ81 -> 11798.6 | BA83: =BA55+BA60+BA66+BA71+BA76+BA81 -> 96387.2
AS86: 14402 | AT86: 14239 | AU86: 11791 | AV86: 10752 | AW86: 10257 | AX86: 12061 | AY86: 11086 | AZ86: 11799 | BA86: =SUM(AS86:AZ86) -> 96387
AS90: 103
AS91: 29
AS92: 115
AS93: 158
AS94: =SUM(AS90:AS93) -> 405 | AT94: =AN60/AS94 -> -0.30251029

Sheet REPORT 8
A1: R
B2: Market Share Per Region (%)
B3: Zone | C3: ElectroMexSA | D3: Startek | E3: Forastero LLC. | F3: Baobab | G3: Sleeping Shrimp | H3: Borealis Group | I3: Esquites
C4: A | D4: A | E4: A | F4: A | G4: A | H4: A | I4: A | N4: CENTER | T4: Borealis Group
B5: Center | C5: 15.3 | D5: 13.8 | E5: 14.6 | F5: 12.5 | G5: 14.1 | H5: 14.1 | I5: 15.5 | N5: 1. Más anuncios con TV tuvimos o con mejor focus | T5: A | U5: Mkt share | V5: Price | W5: Awareness | X5: Atractiveness | Y5: Salespeople
B6: West | C6: 13.2 | D6: 14.1 | E6: 13 | F6: 13.6 | G6: 14.4 | H6: 15.2 | I6: 16.4 | N6: 2. Más fuerza de venta | T6: Center | U6: =H5 -> 14.1 | V6: =H26 -> 77 | W6: =I50 -> 60.17 | X6: =I63 -> 43.58 | Y6: =H75 -> 92.27
B7: North | C7: 13 | D7: 15.1 | E7: 13.4 | F7: 11.6 | G7: 14.3 | H7: 14.6 | I7: 17.9 | T7: West | U7: =H6 -> 15.2 | V7: =H27 -> 76.5 | W7: =I52 -> 54.18 | X7: =I65 -> 43.58 | Y7: =H76 -> 92.27
B8: East | C8: 7.6 | D8: 14.9 | E8: 15 | F8: 12.4 | G8: 13.4 | H8: 16.4 | I8: 20.2 | T8: North | U8: =H7 -> 14.6 | V8: =H28 -> 101 | W8: =I54 -> 48.83 | X8: =I67 -> 43.58 | Y8: =H77 -> 95.32
B9: South | C9: 7.5 | D9: 15.3 | E9: 5.1 | F9: 14.3 | G9: 15.3 | H9: 17.6 | I9: 24.8 | T9: East | U9: =H8 -> 16.4 | V9: =H29 -> 98 | W9: =I56 -> 36.46 | X9: =I69 -> 53.57 | Y9: =H78 -> 98.17
B10: Market Share Per Region Per Segment (%) | T10: South | U10: =H9 -> 17.6 | V10: =H30 -> 100 | W10: =I58 -> 35.78 | X10: =I71 -> 53.57 | Y10: =H79 -> 91.54
B11: Zone | C11: Segment | D11: ElectroMexSA | E11: Startek | F11: Forastero LLC. | G11: Baobab | H11: Sleeping Shrimp | I11: Borealis Group | J11: Esquites | N11: WEST | O11: Nos comieron Mkt share, sobre todo en el low
D12: A | E12: A | F12: A | G12: A | H12: A | I12: A | J12: A | O12: 1. $0.50 menos de precio
B13: Center | C13: High | D13: 12.9 | E13: 14.6 | F13: 13 | G13: 13.5 | H13: 14.9 | I13: 14.5 | J13: 16.7 | O13: 2. Sales representatives fue lo que más pudo impactar
C14: Low | D14: 16.4 | E14: 13.5 | F14: 15.3 | G14: 12.1 | H14: 13.8 | I14: 13.9 | J14: 15 | O14: 3. Tuvieron más anuncios en radio | T14: Sleeping Shrimp
B15: West | C15: High | D15: 11.6 | E15: 15 | F15: 11.9 | G15: 13.8 | H15: 15.1 | I15: 15.2 | J15: 17.4 | T15: A | U15: Mkt share | V15: Price | W15: Awareness | X15: Atractiveness | Y15: Salespeople
C16: Low | D16: 14 | E16: 13.7 | F16: 13.5 | G16: 13.5 | H16: 14.1 | I16: 15.2 | J16: 15.9 | N16: NORTH | T16: Center | U16: =G5 -> 14.1 | V16: =G26 -> 77 | W16: =H50 -> 63.02 | X16: =H63 -> 43.58 | Y16: =G75 -> 94.44
B17: North | C17: High | D17: 11.6 | E17: 15.7 | F17: 11.9 | G17: 11.6 | H17: 15.4 | I17: 15.3 | J17: 18.5 | N17: Mtuvimos más anuncios de tele que ellos | T17: West | U17: =G6 -> 14.4 | V17: =G27 -> 77 | W17: =H52 -> 54.51 | X17: =H65 -> 43.58 | Y17: =G76 -> 85.91
C18: Low | D18: 13.7 | E18: 14.8 | F18: 14.2 | G18: 11.6 | H18: 13.8 | I18: 14.3 | J18: 17.6 | N18: Tuvimos más sales people que ellos | T18: North | U18: =G7 -> 14.3 | V18: =G28 -> 101 | W18: =H54 -> 49.18 | X18: =H67 -> 43.58 | Y18: =G77 -> 97.03
B19: East | C19: High | D19: 3.7 | E19: 16.9 | F19: 8.1 | G19: 12.1 | H19: 16.5 | I19: 17.9 | J19: 24.8 | N19: Nos comieron Mkt share en el norte pero en el low | T19: East | U19: =G8 -> 13.4 | V19: =G29 -> 98 | W19: =H56 -> 34.1 | X19: =H69 -> 53.57 | Y19: =G78 -> 80.85
C20: Low | D20: 8.9 | E20: 14.2 | F20: 17.4 | G20: 12.6 | H20: 12.4 | I20: 15.9 | J20: 18.7 | N20: La diferencia estuvo en los anuncios de radio | T20: South | U20: =G9 -> 15.3 | V20: =G30 -> 100 | W20: =H58 -> 33.96 | X20: =H71 -> 53.57 | Y20: =G79 -> 72.91
B21: South | C21: High | D21: 4.1 | E21: 16.9 | F21: 3.4 | G21: 13.2 | H21: 17.1 | I21: 18.4 | J21: 27 | N21: Awreness en low es 39 vs 36
C22: Low | D22: 10.9 | E22: 13.8 | F22: 6.9 | G22: 15.3 | H22: 13.7 | I22: 16.8 | J22: 22.8
B23: Price | N23: EAST
B24: Zone | C24: ElectroMexSA | D24: Startek | E24: Forastero LLC. | F24: Baobab | G24: Sleeping Shrimp | H24: Borealis Group | I24: Esquites | N24: Fue donde más nos comieron mkt share
C25: A | D25: A | E25: A | F25: A | G25: A | H25: A | I25: A | N25: Ellos tuvieron más anuncios de tele o mejoraron el focus al high
B26: Center | C26: 69.99 | D26: 77 | E26: 71 | F26: 77 | G26: 77 | H26: 77 | I26: 74 | N26: Tuvieron más radio
B27: West | C27: 69.99 | D27: 77 | E27: 72 | F27: 75 | G27: 77 | H27: 76.5 | I27: 75 | N27: La fuerza de ventas fue mucho más grande
B28: North | C28: 93 | D28: 99 | E28: 93 | F28: 96 | G28: 101 | H28: 101 | I28: 95
B29: East | C29: 93 | D29: 100 | E29: 90 | F29: 98 | G29: 98 | H29: 98 | I29: 94 | N29: SOUTH
B30: South | C30: 93 | D30: 105 | E30: 90 | F30: 98 | G30: 100 | H30: 100 | I30: 94 | N30: Tuvieron muchos mas anuncios de radio que nosotros
B31: Product Improvements | N31: Mucha más gente en el sur
B32: Improvements | C32: ElectroMexSA - A | D32: Startek - A | E32: Forastero LLC. - A | F32: Baobab - A | G32: Sleeping Shrimp - A | H32: Borealis Group - A | I32: Esquites - A
B33: STAINLESS MATERIAL | C33: ​ | D33: ​ | E33: ✔ | F33: ✔ | G33: ✔ | H33: ✔ | I33: ✔
B34: RECYCLABLE MATERIALS | C34: ​ | D34: ​ | E34: ​ | F34: ​ | G34: ​ | H34: ​ | I34: ​
B35: ENERGY EFFICIENCY | C35: ✔ | D35: ✔ | E35: ​ | F35: ✔ | G35: ​ | H35: ​ | I35: ​
B36: LIGHTER AND MORE COMPACT | C36: ​ | D36: ​ | E36: ​ | F36: ✔ | G36: ​ | H36: ​ | I36: ​ | N36: Nos están comiendo mkt en el low
B37: IMPACT RESISTANCE | C37: ​ | D37: ​ | E37: ​ | F37: ​ | G37: ​ | H37: ​ | I37: ​
B38: NOISE REDUCTION | C38: ​ | D38: ​ | E38: ​ | F38: ​ | G38: ​ | H38: ​ | I38: ​
B39: IMPROVED BATTERY CAPACITY | C39: ​ | D39: ​ | E39: ​ | F39: ​ | G39: ​ | H39: ​ | I39: ✔
B40: SELF-CLEANING | C40: ​ | D40: ​ | E40: ​ | F40: ​ | G40: ​ | H40: ​ | I40: ​
B41: SPEED SETTINGS | C41: ​ | D41: ​ | E41: ​ | F41: ​ | G41: ​ | H41: ​ | I41: ​
B42: DIGITAL CONTROLS | C42: ​ | D42: ✔ | E42: ​ | F42: ​ | G42: ✔ | H42: ✔ | I42: ✔
B43: VOICE ASSISTANCE INTEGRATION | C43: ​ | D43: ​ | E43: ​ | F43: ​ | G43: ​ | H43: ​ | I43: ​
B44: AUTOMATION AND PROGRAMMABILITY | C44: ​ | D44: ​ | E44: ​ | F44: ​ | G44: ​ | H44: ​ | I44: ​
B45: MULTIFUNCTIONAL ACCESSORIES | C45: ​ | D45: ​ | E45: ​ | F45: ​ | G45: ​ | H45: ​ | I45: ​
B46: MAPPING TECHNOLOGY | C46: ​ | D46: ​ | E46: ​ | F46: ​ | G46: ​ | H46: ​ | I46: ​
B47: Product Awareness Percentage Per Segment
B48: Zone | C48: Segment | D48: ElectroMexSA | E48: Startek | F48: Forastero LLC. | G48: Baobab | H48: Sleeping Shrimp | I48: Borealis Group | J48: Esquites
D49: A | E49: A | F49: A | G49: A | H49: A | I49: A | J49: A
B50: Center | C50: High | D50: 53.47 | E50: 62.72 | F50: 53.41 | G50: 55.11 | H50: 63.02 | I50: 60.17 | J50: 61.92
C51: Low | D51: 45.07 | E51: 45.39 | F51: 41.04 | G51: 32.63 | H51: 46.55 | I51: 47.7 | J51: 39.78
B52: West | C52: High | D52: 32.97 | E52: 55.83 | F52: 36.72 | G52: 50.29 | H52: 54.51 | I52: 54.18 | J52: 57.23
C53: Low | D53: 24.6 | E53: 34.97 | F53: 25.8 | G53: 28.5 | H53: 36.39 | I53: 39.86 | J53: 35.91
B54: North | C54: High | D54: 28.33 | E54: 51.61 | F54: 28.96 | G54: 45.57 | H54: 49.18 | I54: 48.83 | J54: 52.72
C55: Low | D55: 25.17 | E55: 36.83 | F55: 26.89 | G55: 29.08 | H55: 35.4 | I55: 38.21 | J55: 36.99
B56: East | C56: High | D56: 7.58 | E56: 37.55 | F56: 19.18 | G56: 30.08 | H56: 34.1 | I56: 36.46 | J56: 39.71
C57: Low | D57: 12.65 | E57: 25.74 | F57: 25.33 | G57: 17.78 | H57: 20.26 | I57: 26.34 | J57: 25.2
B58: South | C58: High | D58: 7.58 | E58: 37.04 | F58: 10.22 | G58: 30.08 | H58: 33.96 | I58: 35.78 | J58: 39.71
C59: Low | D59: 12.65 | E59: 23.86 | F59: 10.93 | G59: 17.78 | H59: 19.9 | I59: 24.26 | J59: 25.16
B60: Product attractiveness (Perceived)
B61: Zone | C61: Segment | D61: ElectroMexSA | E61: Startek | F61: Forastero LLC. | G61: Baobab | H61: Sleeping Shrimp | I61: Borealis Group | J61: Esquites
D62: A | E62: A | F62: A | G62: A | H62: A | I62: A | J62: A
B63: Center | C63: High | D63: 28.02 | E63: 41.8 | F63: 29.8 | G63: 39.85 | H63: 43.58 | I63: 43.58 | J63: 50.91
C64: Low | D64: 29.81 | E64: 44.09 | F64: 31.65 | G64: 53.1 | H64: 45.93 | I64: 45.93 | J64: 52.16
B65: West | C65: High | D65: 28.02 | E65: 41.8 | F65: 29.8 | G65: 39.85 | H65: 43.58 | I65: 43.58 | J65: 50.91
C66: Low | D66: 29.81 | E66: 44.09 | F66: 31.65 | G66: 53.1 | H66: 45.93 | I66: 45.93 | J66: 52.16
B67: North | C67: High | D67: 28.02 | E67: 41.8 | F67: 29.8 | G67: 39.85 | H67: 43.58 | I67: 43.58 | J67: 50.91
C68: Low | D68: 29.81 | E68: 44.09 | F68: 31.65 | G68: 53.1 | H68: 45.93 | I68: 45.93 | J68: 52.16
B69: East | C69: High | D69: 32.18 | E69: 51.35 | F69: 34.4 | G69: 42.22 | H69: 53.57 | I69: 53.57 | J69: 63.39
C70: Low | D70: 32.17 | E70: 48.17 | F70: 34.63 | G70: 58.77 | H70: 50.63 | I70: 50.63 | J70: 59.1
B71: South | C71: High | D71: 32.18 | E71: 51.35 | F71: 34.4 | G71: 42.22 | H71: 53.57 | I71: 53.57 | J71: 63.39
C72: Low | D72: 32.17 | E72: 48.17 | F72: 34.63 | G72: 58.77 | H72: 50.63 | I72: 50.63 | J72: 59.1
B73: Evaluation of the Promotional Impact of Salesforce
B74: Zone | C74: ElectroMexSA | D74: Startek | E74: Forastero LLC. | F74: Baobab | G74: Sleeping Shrimp | H74: Borealis Group | I74: Esquites
B75: Center | C75: 85.91 | D75: 94.44 | E75: 96.08 | F75: 99.99 | G75: 94.44 | H75: 92.27 | I75: 98.78
B76: West | C76: 85.91 | D76: 89.46 | E76: 85.91 | F76: 92.27 | G76: 85.91 | H76: 92.27 | I76: 97.29
B77: North | C77: 95.32 | D77: 95.32 | E77: 97.03 | F77: 95.32 | G77: 97.03 | H77: 95.32 | I77: 99.9
B78: East | C78: 87.01 | D78: 94.71 | E78: 94.71 | F78: 99.46 | G78: 80.85 | H78: 98.17 | I78: 98.17
B79: South | C79: 87.01 | D79: 94.71 | E79: 7.84 | F79: 99.46 | G79: 72.91 | H79: 91.54 | I79: 98.99

Sheet DF Q8
B2: FORECAST | C2: AVERAGE DEMAND | K2: Q VS Q | T2: Crecimiento | V2: YVSY | AC2: Center | AD2: =ROUNDUP(T4,0) -> 0 | AG2: 9 | AK2: 9
C3: 1 | D3: 2 | E3: 3 | F3: 4 | G3: 5 | H3: 6 | I3: 7 | K3: 1 | M3: 2 | N3: 3 | O3: 4 | P3: 5 | Q3: 6 | R3: 7 | S3: 8 | T3: 0 | V3: 4 VS 1 | W3: 5 VS 2 | X3: 6 VS 3 | Y3: FQ7 | AC3: West | AD3: =ROUNDUP(T5,0) -> 0 | AG3: Center | AH3: Section 2 | AI3: M2 | AJ3: 22 | AK3: 24
B4: Center | C4: 4100 | D4: 3600 | E4: 6600 | F4: 6000 | G4: 5100 | H4: 8900 | I4: ='DF Q7'!K13 -> 7792 | L4: Center | M4: =(D4/C4)-1 -> -0.12195122 | N4: =(E4/D4)-1 -> 0.83333333 | O4: =(F4/E4)-1 -> -0.090909091 | P4: =(G4/F4)-1 -> -0.15 | Q4: =(H4/G4)-1 -> 0.74509804 | R4: =(I4/H4)-1 -> -0.12449438 | S4: =I4*(1+P4) -> 6623.2 | V4: =(F4/C4)-1 -> 0.46341463 | W4: =(G4/D4)-1 -> 0.41666667 | X4: =(H4/E4)-1 -> 0.34848485 | Y4: =F4*(1+V4) -> 8780.4878 | AC4: North | AD4: =ROUNDUP(T6,0) -> 0 | AG4: Center | AH4: Section 3 | AI4: M3-alpha | AJ4: 4 | AK4: 120
B5: West | C5: 1800 | D5: 1900 | E5: 2700 | F5: 2800 | G5: 2900 | H5: 4028 | I5: ='DF Q7'!K14 -> 3948 | L5: West | M5: =(D5/C5)-1 -> 0.055555556 | N5: =(E5/D5)-1 -> 0.42105263 | O5: =(F5/E5)-1 -> 0.037037037 | P5: =(G5/F5)-1 -> 0.035714286 | Q5: =(H5/G5)-1 -> 0.38896552 | R5: =(I5/H5)-1 -> -0.019860973 | S5: =I5*(1+P5) -> 4089 | V5: =(F5/C5)-1 -> 0.55555556 | W5: =(G5/D5)-1 -> 0.52631579 | X5: =(H5/E5)-1 -> 0.49185185 | Y5: =F5*(1+V5) -> 4355.5556 | AC5: East | AD5: =ROUNDUP(T7,0) -> -1 | AG5: Center | AH5: Section 3 | AI5: M3-beta | AJ5: 0 | AK5: 0
A6: TORMENTA | B6: North | C6: 700 | D6: 1200 | E6: 2600 | F6: 2700 | G6: 2700 | H6: 4400 | I6: ='DF Q7'!K15 -> 3868 | K6: TORMENTA | L6: North | M6: =(D6/C6)-1 -> 0.71428571 | N6: =(E6/D6)-1 -> 1.1666667 | O6: =(F6/E6)-1 -> 0.038461538 | P6: =(G6/F6)-1 -> 0 | Q6: =(H6/G6)-1 -> 0.62962963 | R6: =(I6/H6)-1 -> -0.12090909 | S6: =I6*(1+P6) -> 3868 | V6: =(F6/C6)-1 -> 2.8571429 | W6: =(G6/D6)-1 -> 1.25 | X6: =(H6/E6)-1 -> 0.69230769 | Y6: =F6*(1+V6) -> 10414.286 | AC6: South | AD6: =ROUNDUP(T8,0) -> 0 | AG6: Center | AH6: Section 3 | AI6: M4 | AJ6: 4 | AK6: 5
A7: ESG | B7: East | I7: ='DF Q7'!K16 -> 788 | K7: ESG | L7: East | S7: =I7 -> 788 | T7: -0.02 | Y7: =S7 -> 788 | AD7: =SUM(AD2:AD6) -> -1 | AG7: Center | AH7: Section 4 | AI7: M4 | AJ7: 10 | AK7: 11
B8: South | I8: ='DF Q7'!K17 -> 684 | L8: South | P8: =(N13/H4)-1 -> -1 | S8: =I8*(1.05) -> 718.2 | Y8: =S8 -> 718.2 | AG8: Center | AH8: Section 5 | AI8: M4 | AJ8: 12 | AK8: 13
B9: TOTAL | C9: =SUM(C4:C8) -> 6600 | D9: =SUM(D4:D8) -> 6700 | E9: =SUM(E4:E8) -> 11900 | F9: =SUM(F4:F8) -> 11500 | G9: =SUM(G4:G8) -> 10700 | H9: =SUM(H4:H8) -> 17328 | I9: =SUM(I4:I8) -> 17080 | P9: =(N14/H5)-1 -> -1 | S9: =SUM(S4:S8) -> 16086.4 | AG9: Center | AH9: Section 5 | AI9: Crew | AJ9: - | AK9: 90
B10: TARGET POPULATION | C10: =EXHIBITS!C19 -> 110000 | D10: =EXHIBITS!D19 -> 75000 | E10: =EXHIBITS!E19 -> 70000 | F10: =EXHIBITS!F19 -> 50000 | G10: =EXHIBITS!G19 -> 30000 | P10: =(N15/H6)-1 -> -1 | AG10: East | AH10: Section 1 | AI10: M1 | AJ10: 0 | AK10: 0
C11: =H4/C10 -> 0.080909091 | D11: =H5/D10 -> 0.053706667 | E11: =H6/F10 -> 0.088 | AG11: East | AH11: Section 2 | AI11: M2 | AJ11: 0 | AK11: 0
B12: Demanda | K12: Real | M12: Sobraron | AG12: East | AH12: Section 3 | AI12: M3-alpha | AJ12: 0 | AK12: 0
C13: F2 | D13: F4 | E13: F6 | F13: F8 | H13: Center | I13: =AD2 -> 0 | AG13: East | AH13: Section 3 | AI13: M3-beta | AJ13: 0 | AK13: 0
C14: =$I$13/4 -> 0 | D14: =$I$13/4 -> 0 | E14: =$I$13/4 -> 0 | F14: =$I$13/4 -> 0 | G14: =SUM(C14:F14) -> 0 | H14: West | I14: =AD3 -> 0 | AG14: East | AH14: Section 3 | AI14: M4 | AJ14: 0 | AK14: 0
C15: =$I$14/4 -> 0 | D15: =$I$14/4 -> 0 | E15: =$I$14/4 -> 0 | F15: =$I$14/4 -> 0 | G15: =SUM(C15:F15) -> 0 | H15: North | I15: =AD4 -> 0 | AG15: East | AH15: Section 4 | AI15: M4 | AJ15: 0 | AK15: 0
C16: =$I$15/4 -> 0 | D16: =$I$15/4 -> 0 | E16: =$I$15/4 -> 0 | F16: =$I$15/4 -> 0 | G16: =SUM(C16:F16) -> 0 | H16: East | I16: =AD5 -> -1 | AG16: East | AH16: Section 5 | AI16: M4 | AJ16: 0 | AK16: 0
C17: =$I$16/4 -> -0.25 | D17: =$I$16/4 -> -0.25 | E17: =$I$16/4 -> -0.25 | F17: =$I$16/4 -> -0.25 | G17: =SUM(C17:F17) -> -1 | H17: South | I17: =AD6 -> 0 | AG17: East | AH17: Section 5 | AI17: Crew | AJ17: - | AK17: 0
C18: =$I$17/4 -> 0 | D18: =$I$17/4 -> 0 | E18: =$I$17/4 -> 0 | F18: =$I$17/4 -> 0 | G18: =SUM(C18:F18) -> 0 | H18: TOTAL | I18: =SUM(I13:I17) -> -1 | K18: =SUM(K13:K17) -> 0 | M18: =I18-K18 -> -1 | AG18: North | AH18: Section 1 | AI18: M1 | AJ18: 0 | AK18: 0
AG19: North | AH19: Section 2 | AI19: M2 | AJ19: 0 | AK19: 0
B20: Precio | AG20: North | AH20: Section 3 | AI20: M3-alpha | AJ20: 0 | AK20: 0
A21: COGS 7 | B21: 31.39 | C21: Zone | D21: PRICE | E21: Final price | F21: TRANSPORT | I21: Zone | J21: GROSS MARG Sin trans | K21: G Marg Con trans | L21: % | M21: GMar Sin tran - Dcto | N21: GMar Sin tran - Dcto | O21: % | AG21: North | AH21: Section 3 | AI21: M3-beta | AJ21: 0 | AK21: 0
A22: 68 | B22: 0.11 | C22: Center | D22: =ROUNDUP(A22+E47,0) -> 69 | E22: =ROUNDUP(D22*1.11,0) -> 77 | I22: Center | J22: =E22-$B$21 -> 45.61 | K22: =J22 -> 45.61 | L22: =(K22/$B$21)-1 -> 0.45301051 | M22: =(E22*(1-$G$61))-$B$21 -> 39.835 | N22: =M22 -> 39.835 | O22: =(N22/$B$21)-1 -> 0.26903472 | AG22: North | AH22: Section 3 | AI22: M4 | AJ22: 0 | AK22: 0
A23: 68 | B23: 0.11 | C23: West | D23: =ROUNDUP(A23+E47,0) -> 69 | E23: =ROUNDUP(D23*1.11,0) -> 77 | I23: West | J23: =E23-$B$21 -> 45.61 | K23: =J23 -> 45.61 | L23: =(K23/$B$21)-1 -> 0.45301051 | M23: =(E23*(1-$G$61))-$B$21 -> 39.835 | N23: =M23 -> 39.835 | O23: =(N23/$B$21)-1 -> 0.26903472 | AG23: North | AH23: Section 4 | AI23: M4 | AJ23: 0 | AK23: 0
A24: 91 | B24: 0.095 | C24: North | D24: =ROUNDUP(A24+'DF Q8'!E47,0) -> 92 | E24: =ROUNDUP(D24*1.095,0) -> 101 | F24: 26.4 | G24: 19.6 | I24: North | J24: =E24-$B$21 -> 69.61 | K24: =E24-$B$21-F24 -> 43.21 | L24: =(K24/$B$21)-1 -> 0.37655304 | M24: =(E24*(1-$G$61))-$B$21 -> 62.035 | N24: =M24-F24 -> 35.635 | O24: =(N24/$B$21)-1 -> 0.13523415 | AG24: North | AH24: Section 5 | AI24: M4 | AJ24: 0 | AK24: 0
A25: 0 | C25: East | D25: =ROUNDUP(A22+'DF Q8'!E47+'DF Q8'!F25,0) -> 98 | E25: =ROUNDUP(D25*1,0) -> 98 | F25: 28.8 | I25: East | J25: =E25-$B$21 -> 66.61 | K25: =E25-$B$21-F25 -> 37.81 | L25: =(K25/$B$21)-1 -> 0.20452373 | M25: =(E25*(1-$G$61))-$B$21 -> 59.26 | N25: =M25-F25 -> 30.46 | O25: =(N25/$B$21)-1 -> -0.02962727 | AG25: North | AH25: Section 5 | AI25: Crew | AJ25: - | AK25: 0
A26: 0 | B26: 0.07 | C26: South | D26: =ROUNDUP(A22+'DF Q8'!E47+'DF Q8'!F26,0) -> 93 | E26: =ROUNDUP(D26*1.07,0) -> 100 | F26: 24 | I26: South | J26: =E26-$B$21 -> 68.61 | K26: =E26-$B$21-F26 -> 44.61 | L26: =(K26/$B$21)-1 -> 0.42115323 | M26: =(E26*(1-$G$61))-$B$21 -> 61.11 | N26: =M26-F26 -> 37.11 | O26: =(N26/$B$21)-1 -> 0.18222364 | AG26: South | AH26: Section 1 | AI26: M1 | AJ26: 0 | AK26: 0
AG27: South | AH27: Section 2 | AI27: M2 | AJ27: 0 | AK27: 0
AG28: South | AH28: Section 3 | AI28: M3-alpha | AJ28: 0 | AK28: 0
B29: Advertaising | AG29: South | AH29: Section 3 | AI29: M3-beta | AJ29: 0 | AK29: 0
C30: Media | D30: Zone | E30: # Spots | F30: $ per spot | G30: TC | H30: FOCUS | I30: TC/ FORTNIGHT | AG30: South | AH30: Section 3 | AI30: M4 | AJ30: 0 | AK30: 0
A31: 35 | B31: =REPORT!D65/'DF Q8'!H9 -> 0.0020198523 | C31: TV | D31: All | E31: 35 | F31: 3000 | G31: =F31*E31 -> 105000 | H31: 60 | I31: =G31/8 -> 13125 | AG31: South | AH31: Section 4 | AI31: M4 | AJ31: 0 | AK31: 0
A32: 210 | B32: =REPORT!D66/'DF Q8'!H4 -> 0.023595506 | C32: Radio | D32: Center | E32: 210 | F32: 300 | G32: =F32*E32 -> 63000 | H32: 55 | I32: =G32/8 -> 7875 | J32: Me quedé corta en advertaising en east and south | AG32: South | AH32: Section 5 | AI32: M4 | AJ32: 0 | AK32: 0
A33: 102 | B33: =REPORT!D67/'DF Q8'!H5 -> 0.025322741 | D33: West | E33: 102 | F33: 300 | G33: =F33*E33 -> 30600 | H33: 55 | I33: =G33/8 -> 3825 | J33: Un poco en tele | AG33: South | AH33: Section 5 | AI33: Crew | AJ33: - | AK33: 0
A34: 82 | B34: =REPORT!D68/'DF Q8'!H6 -> 0.018636364 | D34: North | E34: 82 | F34: 300 | G34: =F34*E34 -> 24600 | H34: 55 | I34: =G34/8 -> 3075 | AG34: West | AH34: Section 1 | AI34: M1 | AJ34: 3 | AK34: 4
A35: 0 | B35: =B33 -> 0.025322741 | D35: East | E35: =ROUNDUP(I16*B35,0) -> -1 | F35: 300 | G35: =F35*E35 -> -300 | H35: 50 | I35: =G35/8 -> -37.5 | AG35: West | AH35: Section 2 | AI35: M2 | AJ35: 8 | AK35: 9
A36: 0 | B36: =B33 -> 0.025322741 | D36: South | E36: =ROUNDUP(I17*B36,0) -> 0 | F36: 300 | G36: =F36*E36 -> 0 | H36: 50 | I36: =G36/8 -> 0 | AG36: West | AH36: Section 3 | AI36: M3-alpha | AJ36: 2 | AK36: 60
G37: =SUM(G31:G36) -> 222900 | H37: TOTAL | I37: =SUM(I31:I36) -> 27862.5 | AG37: West | AH37: Section 3 | AI37: M3-beta | AJ37: 0 | AK37: 0
AG38: West | AH38: Section 3 | AI38: M4 | AJ38: 2 | AK38: 3
B39: Features | AG39: West | AH39: Section 4 | AI39: M4 | AJ39: 4 | AK39: 5
C40: Feature | D40: UP FRONT | E40: VC | F40: # Units | G40: Total Cost | AG40: West | AH40: Section 5 | AI40: M4 | AJ40: 4 | AK40: 5
C41: =FEATURES!A2 -> STAINLESS MATERIAL | D41: =VLOOKUP(C41,FEATURES!$A$2:$E$15,3,FALSE) -> 15000 | E41: =VLOOKUP(C41,FEATURES!$A$2:$E$15,4,) -> 0.15 | F41: =$I$18 -> -1 | G41: =E41*F41 -> -0.15 | AG41: West | AH41: Section 5 | AI41: Crew | AJ41: - | AK41: 30
C42: =FEATURES!A11 -> DIGITAL CONTROLS | D42: =VLOOKUP(C42,FEATURES!$A$2:$E$15,3,FALSE) -> 45000 | E42: =VLOOKUP(C42,FEATURES!$A$2:$E$15,4,) -> 0.45 | F42: =$I$18 -> -1 | G42: =E42*F42 -> -0.45 | I42: TC FEATURES / F | J42: =(I18*E47)/4 -> -0.15 | AN42: Q
D43: =VLOOKUP(C43,FEATURES!$A$2:$E$15,3,FALSE) -> #N/A | E43: =VLOOKUP(C43,FEATURES!$A$2:$E$15,4,) -> #N/A | F43: =$I$18 -> -1 | G43: =E43*F43 -> #N/A | AJ43: DL | AK43: =SUM(AK2:AK41) -> 388 | AL43: 28 | AM43: 8 | AN43: =AK43*AL43*AM43 -> 86912 | AO43: =AN43/$AP$60 -> 0.15832811
D44: =VLOOKUP(C44,FEATURES!$A$2:$E$15,3,FALSE) -> #N/A | E44: =VLOOKUP(C44,FEATURES!$A$2:$E$15,4,) -> #N/A | F44: =$I$18 -> -1 | G44: =E44*F44 -> #N/A | AJ44: OVERTIME | AK44: =AK8+AK34+AK35+AK39+AK40+AK41+AK9 -> 156 | AL44: 12 | AM44: 8 | AN44: =AK44*AL44*AM44 -> 14976 | AO44: =AN44/$AP$60 -> 0.027281869
D45: =VLOOKUP(C45,FEATURES!$A$2:$E$15,3,FALSE) -> #N/A | E45: =VLOOKUP(C45,FEATURES!$A$2:$E$15,4,) -> #N/A | F45: =$I$18 -> -1 | G45: =E45*F45 -> #N/A | AJ45: INDIRECT | AN45: =(AN43+AN44)*0.5 -> 50944 | AO45: =AN45/$AP$60 -> 0.09280499
D46: =VLOOKUP(C46,FEATURES!$A$2:$E$15,3,FALSE) -> #N/A | E46: =VLOOKUP(C46,FEATURES!$A$2:$E$15,4,) -> #N/A | F46: =$I$18 -> -1 | G46: =E46*F46 -> #N/A | AO46: =AN46/$AP$60 -> 0
C47: TOTAL | D47: =D41+D42 -> 60000 | E47: =E41+E42 -> 0.6 | AJ47: VC | AL47: 0.6 | AM47: 17080 | AN47: =AL47*AM47 -> 10248 | AO47: =AN47/$AP$60 -> 0.018668843
AJ48: RAW 1-6 | AL48: 2.5 | AM48: 17080 | AN48: =AL48*AM48 -> 42700 | AO48: =AN48/$AP$60 -> 0.077786846
B49: # Sales People | AJ49: A | AK49: 1 | AL49: =140/30 -> 4.6666667 | AM49: 17080 | AN49: =AL49*AM49 -> 79706.667 | AO49: =AN49/$AP$60 -> 0.14520211
C50: Zone | D50: # People | E50: T Hiring Cost | F50: SALARY PER Q | H50: Hiring C | I50: Salary | AJ50: B | AK50: 0.2 | AL50: =370/12 -> 30.833333 | AM50: 17080 | AN50: =AM50*AK50*AL50 -> 105326.67 | AO50: =AN50/$AP$60 -> 0.19187422
A51: 17 | B51: =A51/H4 -> 0.0019101124 | C51: Center | D51: =ROUNDUP(I13*B51,0)+1 -> 1 | E51: =(D51-17)*$H$51 -> -16000 | F51: =D51*$I$51 -> 750 | H51: 1000 | I51: 750 | AJ51: ORDERING COST A | AK51: 3 | AL51: 2300 | AN51: =AK51*AL51 -> 6900 | AO51: =AN51/$AP$60 -> 0.012569771
A52: 13 | B52: =A52/H5 -> 0.0032274081 | C52: West | D52: =ROUNDUP(I14*B52,0) -> 0 | E52: =(D52-13)*$H$51 -> -13000 | F52: =D52*$I$51 -> 0 | AJ52: ORDERING COST B | AK52: 7 | AL52: 6000 | AN52: =AK52*AL52 -> 42000 | AO52: =AN52/$AP$60 -> 0.076511652 | AV52: 304 | AW52: 2712 | AX52: 2000 | AY52: 1288 | AZ52: 576 | BA52: 0 | BB52: 2408 | BC52: 1696
A53: 14 | B53: =A53/H6 -> 0.0031818182 | C53: North | D53: =ROUNDUP(I15*B53,0) -> 0 | E53: =(D53-14)*$H$51 -> -14000 | F53: =D53*$I$51 -> 0 | K53: Me faltaa gente | AJ53: Holding Cost A | AN53: =BD55 -> 7786.8 | AO53: =AN53/$AP$60 -> 0.01418526 | AU53: Holding Cost A | AV53: 2875 | AW53: 2254 | AX53: 1633 | AY53: 1012 | AZ53: 391 | BA53: 2890 | BB53: 2269 | BC53: 1648
A54: 0 | B54: 0.006 | C54: East | D54: =ROUNDUP(I16*B54,0) -> -1 | E54: =D54*$H$51 -> -1000 | F54: =D54*$I$51 -> -750 | K54: West | AJ54: Holding Cost B | AN54: =BD60 -> 20214 | AO54: =AN54/$AP$60 -> 0.036823965 | AV54: 0.3 | AW54: 0.3 | AX54: 0.3 | AY54: 0.3 | AZ54: 0.3 | BA54: 0.3 | BB54: 0.3 | BC54: 0.3
A55: 0 | B55: 0.008 | C55: South | D55: =ROUNDUP(I17*B55,0) -> 0 | E55: =D55*$H$51 -> 0 | F55: =D55*$I$51 -> 0 | K55: East South | AJ55: Holding Cost Assembly A | AN55: =BD66 -> 14372 | AO55: =AN55/$AP$60 -> 0.026181559 | AV55: =(AV52+AV53)*AV54 -> 953.7 | AW55: =(AW52+AW53)*AW54 -> 1489.8 | AX55: =(AX52+AX53)*AX54 -> 1089.9 | AY55: =(AY52+AY53)*AY54 -> 690 | AZ55: =(AZ52+AZ53)*AZ54 -> 290.1 | BA55: =(BA52+BA53)*BA54 -> 867 | BB55: =(BB52+BB53)*BB54 -> 1403.1 | BC55: =(BC52+BC53)*BC54 -> 1003.2 | BD55: =SUM(AV55:BC55) -> 7786.8
C56: TOTAL | D56: =SUM(D51:D55) -> 0 | E56: =SUM(E51:E55) -> -44000 | F56: =SUM(F51:F55) -> 0 | AJ56: Holding Cost Assembly B | AN56: =BD71 -> 21201.6 | AO56: =AN56/$AP$60 -> 0.038623082
AJ57: Holding Cost Assembly C | AN57: =BD76 -> 21181.2 | AO57: =AN57/$AP$60 -> 0.038585919 | AU57: Holding Cost B | AV57: 160 | AW57: 327 | AX57: 194 | AY57: 361 | AZ57: 228 | BA57: 395 | BB57: 262 | BC57: 429
B58: Payment type | AJ58: Holding Cost Assembly D | AN58: =BD81 -> 11631.6 | AO58: =AN58/$AP$60 -> 0.021189355 | AV58: 585 | AW58: 405 | AX58: 225 | AY58: 45 | AZ58: 177 | BA58: 309 | BB58: 129 | BC58: 261
AJ59: Lost Finished Goods | AL59: =31.39 -> 31.39 | AM59: =SUM(AV90:AV93) -> 405 | AN59: =AL59*AM59 -> 12712.95 | AO59: =AN59/$AP$60 -> 0.023159257 | AV59: 4.5 | AW59: 4.5 | AX59: 4.5 | AY59: 4.5 | AZ59: 4.5 | BA59: 4.5 | BB59: 4.5 | BC59: 4.5
C60: Zone | D60: Type | E60: Payment term | F60: Sales | G60: Discount | H60: Tota Payment per 2 F | AN60: =SUM(AN43:AN58) -> 536100.53 | AO60: =AN60+AN59 -> 548813.48 | AP60: 548936 | AQ60: =AO60-AP60 -> -122.51667 | AV60: =(AV57+AV58)*AV59 -> 3352.5 | AW60: =(AW57+AW58)*AW59 -> 3294 | AX60: =(AX57+AX58)*AX59 -> 1885.5 | AY60: =(AY57+AY58)*AY59 -> 1827 | AZ60: =(AZ57+AZ58)*AZ59 -> 1822.5 | BA60: =(BA57+BA58)*BA59 -> 3168 | BB60: =(BB57+BB58)*BB59 -> 1759.5 | BC60: =(BC57+BC58)*BC59 -> 3105 | BD60: =SUM(AV60:BC60) -> 20214
C61: Center | D61: B | E61: =IF(D61="A",REPORT!$F$72,IF('DF Q8'!D61="B",REPORT!$F$73,IF('DF Q8'!D61="C",REPORT!$F$74,IF('DF Q8'!D61="D",REPORT!$F$75,"error")))) -> 2 | F61: =I13*E22 -> 0 | G61: =IF(D61="A",REPORT!$G$72,IF('DF Q8'!D61="B",REPORT!$G$73,IF('DF Q8'!D61="C",REPORT!$G$74,IF('DF Q8'!D61="D",REPORT!$G$75,"error")))) -> 0.075 | H61: =(F61*(1-G61))/4 -> 0 | I61: =I13*D22 -> 0 | J61: =I61*0.925 -> 0 | K61: =J61/4 -> 0 | AN61: =AN60/$AM$50 -> 31.387619 | AP61: =AP60/$AM$50 -> 32.13911
B62: ESG | C62: West | D62: C | E62: =IF(D62="A",REPORT!$F$72,IF('DF Q8'!D62="B",REPORT!$F$73,IF('DF Q8'!D62="C",REPORT!$F$74,IF('DF Q8'!D62="D",REPORT!$F$75,"error")))) -> 4 | F62: =I14*E23 -> 0 | G62: =IF(D62="A",REPORT!$G$72,IF('DF Q8'!D62="B",REPORT!$G$73,IF('DF Q8'!D62="C",REPORT!$G$74,IF('DF Q8'!D62="D",REPORT!$G$75,"error")))) -> 0.025 | H62: =(F62*(1-G62))/4 -> 0 | I62: =I14*D23 -> 0 | J62: =I62*0.925 -> 0 | K62: =J62/4 -> 0
C63: North | D63: B | E63: =IF(D63="A",REPORT!$F$72,IF('DF Q8'!D63="B",REPORT!$F$73,IF('DF Q8'!D63="C",REPORT!$F$74,IF('DF Q8'!D63="D",REPORT!$F$75,"error")))) -> 2 | F63: =I15*E24 -> 0 | G63: =IF(D63="A",REPORT!$G$72,IF('DF Q8'!D63="B",REPORT!$G$73,IF('DF Q8'!D63="C",REPORT!$G$74,IF('DF Q8'!D63="D",REPORT!$G$75,"error")))) -> 0.075 | H63: =(F63*(1-G63))/4 -> 0 | I63: =I15*D24 -> 0 | J63: =I63*0.925 -> 0 | K63: =J63/4 -> 0 | AU63: Holding Cost Assembly A | AV63: =2936+712 -> 3648 | AW63: =2962+712 -> 3674 | AX63: =2988+712 -> 3700 | AY63: =3014+712 -> 3726 | AZ63: =3040+712 -> 3752 | BA63: =3066+576 -> 3642 | BB63: =2956+712 -> 3668 | BC63: =2982+712 -> 3694
B64: TORMENTA | C64: East | D64: C | E64: =IF(D64="A",REPORT!$F$72,IF('DF Q8'!D64="B",REPORT!$F$73,IF('DF Q8'!D64="C",REPORT!$F$74,IF('DF Q8'!D64="D",REPORT!$F$75,"error")))) -> 4 | F64: =I16*E25 -> -98 | G64: =IF(D64="A",REPORT!$G$72,IF('DF Q8'!D64="B",REPORT!$G$73,IF('DF Q8'!D64="C",REPORT!$G$74,IF('DF Q8'!D64="D",REPORT!$G$75,"error")))) -> 0.025 | H64: =(F64*(1-G64))/4 -> -23.8875 | I64: =I16*D25 -> -98 | J64: =I64*0.925 -> -90.65 | K64: =J64/4 -> -22.6625 | AV64: =6336+621 -> 6957 | AW64: =5861+621 -> 6482 | AX64: =5386+621 -> 6007 | AY64: =4911+621 -> 5532 | AZ64: =4436+621 -> 5057 | BA64: =3961+621 -> 4582 | BB64: =3486+621 -> 4107 | BC64: =3011+621 -> 3632
C65: South | D65: C | E65: =IF(D65="A",REPORT!$F$72,IF('DF Q8'!D65="B",REPORT!$F$73,IF('DF Q8'!D65="C",REPORT!$F$74,IF('DF Q8'!D65="D",REPORT!$F$75,"error")))) -> 4 | F65: =I17*E26 -> 0 | G65: =IF(D65="A",REPORT!$G$72,IF('DF Q8'!D65="B",REPORT!$G$73,IF('DF Q8'!D65="C",REPORT!$G$74,IF('DF Q8'!D65="D",REPORT!$G$75,"error")))) -> 0.025 | H65: =(F65*(1-G65))/4 -> 0 | I65: =I17*D26 -> 0 | J65: =I65*0.925 -> 0 | K65: =J65/4 -> 0 | AV65: 0.2 | AW65: 0.2 | AX65: 0.2 | AY65: 0.2 | AZ65: 0.2 | BA65: 0.2 | BB65: 0.2 | BC65: 0.2
F66: =SUM(F61:F65) -> -98 | G66: TOTAL | H66: =SUM(H61:H65) -> -23.8875 | AV66: =(AV63+AV64)*AV65 -> 2121 | AW66: =(AW63+AW64)*AW65 -> 2031.2 | AX66: =(AX63+AX64)*AX65 -> 1941.4 | AY66: =(AY63+AY64)*AY65 -> 1851.6 | AZ66: =(AZ63+AZ64)*AZ65 -> 1761.8 | BA66: =(BA63+BA64)*BA65 -> 1644.8 | BB66: =(BB63+BB64)*BB65 -> 1555 | BC66: =(BC63+BC64)*BC65 -> 1465.2 | BD66: =SUM(AV66:BC66) -> 14372
C67: TC/ FORTNIGHT | D67: TC Q
B68: Advertaising | C68: =I37 -> 27862.5 | D68: =C68*8 -> 222900 | AU68: Holding Cost Assembly B | AV68: =1524+665 -> 2189 | AW68: =1503+665 -> 2168 | AX68: =1482+665 -> 2147 | AY68: =1461+665 -> 2126 | AZ68: =1440+665 -> 2105 | BA68: =1419+665 -> 2084 | BB68: =1398+665 -> 2063 | BC68: =1377+665 -> 2042
B69: Features | C69: =J42 -> -0.15 | AV69: =4296+900 -> 5196 | AW69: =4100+900 -> 5000 | AX69: =3904+900 -> 4804 | AY69: =3708+900 -> 4608 | AZ69: =3512+900 -> 4412 | BA69: =3316+900 -> 4216 | BB69: =3120+900 -> 4020 | BC69: =2924+900 -> 3824
B70: # Sales People | C70: =D70/8 -> 0 | D70: =F56 -> 0 | AV70: 0.4 | AW70: 0.4 | AX70: 0.4 | AY70: 0.4 | AZ70: 0.4 | BA70: 0.4 | BB70: 0.4 | BC70: 0.4
B71: Hiring | D71: =E56 -> -44000 | AV71: =(AV68+AV69)*AV70 -> 2954 | AW71: =(AW68+AW69)*AW70 -> 2867.2 | AX71: =(AX68+AX69)*AX70 -> 2780.4 | AY71: =(AY68+AY69)*AY70 -> 2693.6 | AZ71: =(AZ68+AZ69)*AZ70 -> 2606.8 | BA71: =(BA68+BA69)*BA70 -> 2520 | BB71: =(BB68+BB69)*BB70 -> 2433.2 | BC71: =(BC68+BC69)*BC70 -> 2346.4 | BD71: =SUM(AV71:BC71) -> 21201.6
D72: =D68+D70+D71 -> 178900 | BD72: Transit
AU73: Holding Cost Assembly C | AV73: =1822+686 -> 2508 | AW73: =1914+686 -> 2600 | AX73: =2006+686 -> 2692 | AY73: =2098+686 -> 2784 | AZ73: =2190+686 -> 2876 | BA73: =2282+686 -> 2968 | BB73: =2374+686 -> 3060 | BC73: =2466+686 -> 3152
AV74: =1984+1096 -> 3080 | AW74: =1298+1096 -> 2394 | AX74: =612+1096 -> 1708 | AY74: =1096 -> 1096 | AZ74: 1096 | BA74: 1096 | BB74: 1096 | BC74: 1096
AV75: 0.6 | AW75: 0.6 | AX75: 0.6 | AY75: 0.6 | AZ75: 0.6 | BA75: 0.6 | BB75: 0.6 | BC75: 0.6
AV76: =(AV73+AV74)*AV75 -> 3352.8 | AW76: =(AW73+AW74)*AW75 -> 2996.4 | AX76: =(AX73+AX74)*AX75 -> 2640 | AY76: =(AY73+AY74)*AY75 -> 2328 | AZ76: =(AZ73+AZ74)*AZ75 -> 2383.2 | BA76: =(BA73+BA74)*BA75 -> 2438.4 | BB76: =(BB73+BB74)*BB75 -> 2493.6 | BC76: =(BC73+BC74)*BC75 -> 2548.8 | BD76: =SUM(AV76:BC76) -> 21181.2
AU78: Holding Cost Assembly D | AV78: =1672+712 -> 2384 | AW78: =1790+712 -> 2502 | AX78: =1908+712 -> 2620 | AY78: =2026+712 -> 2738 | AZ78: =2144+712 -> 2856 | BA78: =2262+712 -> 2974 | BB78: =2380+656 -> 3036 | BC78: 2442
AV79: =4824+1130 -> 5954 | AW79: =4172+1130 -> 5302 | AX79: =3520+1130 -> 4650 | AY79: =2942+1130 -> 4072 | AZ79: =2976+1130 -> 4106 | BA79: =3010+1130 -> 4140 | BB79: =3044+1130 -> 4174 | BC79: =3078+1130 -> 4208
AV80: 0.2 | AW80: 0.2 | AX80: 0.2 | AY80: 0.2 | AZ80: 0.2 | BA80: 0.2 | BB80: 0.2 | BC80: 0.2
AV81: =(AV78+AV79)*AV80 -> 1667.6 | AW81: =(AW78+AW79)*AW80 -> 1560.8 | AX81: =(AX78+AX79)*AX80 -> 1454 | AY81: =(AY78+AY79)*AY80 -> 1362 | AZ81: =(AZ78+AZ79)*AZ80 -> 1392.4 | BA81: =(BA78+BA79)*BA80 -> 1422.8 | BB81: =(BB78+BB79)*BB80 -> 1442 | BC81: =(BC78+BC79)*BC80 -> 1330 | BD81: =SUM(AV81:BC81) -> 11631.6 | BE81: 11632
AV83: =AV55+AV60+AV66+AV71+AV76+AV81 -> 14401.6 | AW83: =AW55+AW60+AW66+AW71+AW76+AW81 -> 14239.4 | AX83: =AX55+AX60+AX66+AX71+AX76+AX81 -> 11791.2 | AY83: =AY55+AY60+AY66+AY71+AY76+AY81 -> 10752.2 | AZ83: =AZ55+AZ60+AZ66+AZ71+AZ76+AZ81 -> 10256.8 | BA83: =BA55+BA60+BA66+BA71+BA76+BA81 -> 12061 | BB83: =BB55+BB60+BB66+BB71+BB76+BB81 -> 11086.4 | BC83: =BC55+BC60+BC66+BC71+BC76+BC81 -> 11798.6 | BD83: =BD55+BD60+BD66+BD71+BD76+BD81 -> 96387.2
AV86: 14402 | AW86: 14239 | AX86: 11791 | AY86: 10752 | AZ86: 10257 | BA86: 12061 | BB86: 11086 | BC86: 11799 | BD86: =SUM(AV86:BC86) -> 96387
AV90: 103
AV91: 29
AV92: 115
AV93: 158
AV94: =SUM(AV90:AV93) -> 405 | AW94: =AQ60/AV94 -> -0.30251029

Sheet Sheet7
E15: 1800 | F15: 1900 | G15: 2700 | H15: 2800 | I15: 2900 | J15: 4028 | K15: ='DF Q7'!M24 -> 62.035
E16: =E15*7 -> 12600 | F16: =F15*7 -> 13300 | G16: =G15*7 -> 18900 | H16: =H15*7 -> 19600 | I16: =I15*7 -> 20300 | J16: =J15*7 -> 28196 | K16: 25290
D17: West
G43: Periodo | H43: Season | I43: Total Sales
F44: Center | G44: 1 | H44: A | I44: =Q46*7 -> 28700
F45: Center | G45: 2 | H45: B | I45: =R46*7 -> 25200 | Q45: 1 | R45: 2 | S45: 3 | T45: 4 | U45: 5 | V45: 6 | W45: 7 | X45: 1
F46: Center | G46: 3 | H46: C | I46: =S46*7 -> 46200 | P46: Center | Q46: 4100 | R46: 3600 | S46: 6600 | T46: 6000 | U46: 5100 | V46: 8900 | W46: 7792 | X46: 0.141
F47: Center | G47: 4 | H47: A | I47: =T46*7 -> 42000 | P47: West | Q47: 1800 | R47: 1900 | S47: 2700 | T47: 2800 | U47: 2900 | V47: 4028 | W47: 3948 | X47: 0.141
F48: Center | G48: 5 | H48: B | I48: =U46*7 -> 35700 | P48: North | Q48: 700 | R48: 1200 | S48: 2600 | T48: 2700 | U48: 2700 | V48: 4400 | W48: 3868 | X48: 0.143
F49: Center | G49: 6 | H49: C | I49: =V46*7 -> 62300 | P49: East | W49: 788 | X49: 0.134
F50: Center | G50: 7 | H50: A | I50: =(W46*$X$45)/X46 -> 55262.411 | P50: South | W50: 684 | X50: 0.153
F51: West | G51: 1 | H51: A | I51: =Q47*7 -> 12600
F52: West | G52: 2 | H52: B | I52: =R47*7 -> 13300
F53: West | G53: 3 | H53: C | I53: =S47*7 -> 18900
F54: West | G54: 4 | H54: A | I54: =T47*7 -> 19600
F55: West | G55: 5 | H55: B | I55: =U47*7 -> 20300
F56: West | G56: 6 | H56: C | I56: =V47*7 -> 28196
F57: West | G57: 7 | H57: A | I57: =(W47*$X$45)/X47 -> 28000
F58: North | G58: 1 | H58: A | I58: =Q48*7 -> 4900
F59: North | G59: 2 | H59: B | I59: =R48*7 -> 8400
F60: North | G60: 3 | H60: C | I60: =S48*7 -> 18200
F61: North | G61: 4 | H61: A | I61: =T48*7 -> 18900
F62: North | G62: 5 | H62: B | I62: =U48*8 -> 21600
F63: North | G63: 6 | H63: C | I63: =V48*7 -> 30800
F64: North | G64: 7 | H64: A | I64: =(W48*$X$45)/X48 -> 27048.951
F65: East | G65: 7 | H65: A | I65: =(W49*$X$45)/X49 -> 5880.597
F66: South | G66: 7 | H66: A | I66: =(W50*$X$45)/X50 -> 4470.5882
