Workbook
Name tZeroValue: #REF!

Sheet Inputs
A1: INPUTS - PURCHASING MANAGER
A2: Solo inputs manuales. AZUL = modificar según tu estrategia. Sin fórmulas en esta hoja.
A4: 1. PRODUCCIÓN PLANEADA POR QUINCENA (Electroclean)
A5: Quincena → | B5: Q1 | C5: Q2 | D5: Q3 | E5: Q4 | F5: Q5 | G5: Q6 | H5: Q7 | I5: Q8 | J5: TOTAL
A6: Producción EC | B6: 2520 | C6: 2520 | D6: 2520 | E6: 2520 | F6: 2520 | G6: 2520 | H6: 2520 | I6: 2520 | J6: =SUM(B6:I6) -> 20160
A9: 2. INVENTARIO INICIAL (Fin Periodo Anterior)
A10: Material | B10: Inventario Inicial | C10: Unidad | D10: Fuente
A11: Parte A | B11: 4512 | C11: unidades | D11: Fin Periodo 6
A12: Parte B | B12: 1058 | C12: unidades | D12: Fin Periodo 6
A13: Pieza 1 | B13: 130 | C13: unidades | D13: Fin Periodo 6
A14: Pieza 2 | B14: 5268 | C14: unidades | D14: Fin Periodo 6
A15: Pieza 3 | B15: 4333 | C15: unidades | D15: Fin Periodo 6
A16: Pieza 4 | B16: 8487 | C16: unidades | D16: Fin Periodo 6
A17: Pieza 5 | B17: 23192 | C17: unidades | D17: Fin Periodo 6
A18: Pieza 6 | B18: 6035 | C18: unidades | D18: Fin Periodo 6
A21: 3. BILL OF MATERIALS (BOM) - Consumo por Electroclean
A22: Material | B22: Consumo por EC | C22: Unidad | D22: Observaciones
A23: Parte A | B23: 1 | C23: unidades/EC | D23: 1:1
A24: Parte B | B24: 0.2 | C24: unidades/EC | D24: 1:5
A25: Pieza 1 | B25: 0.01 | C25: unidades/EC | D25: 1:100
A26: Pieza 2 | B26: 8 | C26: unidades/EC | D26: 8:1
A27: Pieza 3 | B27: 0.3 | C27: unidades/EC | D27: 30%
A28: Pieza 4 | B28: 0.6 | C28: unidades/EC | D28: 60%
A29: Pieza 5 | B29: 2 | C29: unidades/EC | D29: 2:1
A30: Pieza 6 | B30: 0.75 | C30: unidades/EC | D30: 75%
A33: 4. BATCH SIZES (Tamaño de Lote)
A34: Material | B34: Batch Size | C34: MOQ (Batch Size) | D34: Observaciones
A35: Parte A | B35: 30 | C35: =B35 -> 30 | D35: Lote fijo
A36: Parte B | B36: 12 | C36: =B36 -> 12 | D36: Lote fijo
A37: Pieza 1 | B37: 1 | C37: =B37 -> 1 | D37: Individual
A38: Pieza 2 | B38: 100 | C38: =B38 -> 100 | D38: Caja 100
A39: Pieza 3 | B39: 30 | C39: =B39 -> 30 | D39: Lote 30
A40: Pieza 4 | B40: 60 | C40: =B40 -> 60 | D40: Lote 60
A41: Pieza 5 | B41: 100 | C41: =B41 -> 100 | D41: Lote 100
A42: Pieza 6 | B42: 150 | C42: =B42 -> 150 | D42: Pallet 150
B43: 125 | C43: =B43/B35 -> 4.1666667
B44: 330 | C44: =B44/B36 -> 27.5
A45: 5. PRECIOS POR BATCH
A46: Material | B46: 7 | C46: =B46/B38 -> 0.07 | D46: Moneda
A47: Parte A | B47: 125 | C47: =B47/B35 -> 4.1666667 | D47: $
A48: Parte B | B48: 330 | C48: =B48/B36 -> 27.5 | D48: $
A49: Pieza 1 | B49: 60 | C49: =B49/B37 -> 60 | D49: $
A50: Pieza 2 | B50: 7 | C50: =B50/B38 -> 0.07 | D50: $
A51: Pieza 3 | B51: 36 | C51: =B51/B39 -> 1.2 | D51: $
A52: Pieza 4 | B52: 24 | C52: =B52/B40 -> 0.4 | D52: $
A53: Pieza 5 | B53: 30 | C53: =B53/B41 -> 0.3 | D53: $
A54: Pieza 6 | B54: 28 | C54: =B54/B42 -> 0.18666667 | D54: $
A57: 6. ORDERING COST & HOLDING COST
A58: Material | B58: Ordering Cost | C58: Holding Cost/U/Q | D58: Notas
A59: Parte A | B59: 2300 | C59: 0.3 | D59: Por pedido / Por unidad-quincena
A60: Parte B | B60: 6000 | C60: 4.5 | D60: Por pedido / Por unidad-quincena
A61: Piezas 1-6 | B61: 0 | C61: 0 | D61: Solo compra en t=0, sin costos adicionales
A64: 7. PROVEEDORES - PARTE A
A65: ID | B65: Precio Base | C65: Términos Pago | D65: Descuento | E65: Discount Threshold (batches) | F65: Confiabilidad
A66: A | B66: 125 | C66: Inmediato (0Q) | D66: No | E66: - | F66: 100%
A67: B | B67: 100 | C67: +2 Quincenas | D67: 16% si Q≥150 | E67: 150 | F67: 80%
A68: C | B68: 140 | C68: +8 Quincenas | D68: No | E68: - | F68: 100%
A69: PROVEEDOR ELEGIDO → | B69: A
A72: 8. PROVEEDORES - PARTE B
A73: ID | B73: Precio Base | C73: Términos Pago | D73: Descuento | E73: Discount Threshold (batches) | F73: Confiabilidad
A74: A | B74: 330 | C74: Inmediato (0Q) | D74: No | E74: - | F74: 100%
A75: B | B75: 264 | C75: +2 Quincenas | D75: 16% si Q≥80 | E75: 80 | F75: 80%
A76: C | B76: 370 | C76: +8 Quincenas | D76: No | E76: - | F76: 100%
A77: PROVEEDOR ELEGIDO → | B77: A
A80: 9. SAFETY STOCK (Stock de Seguridad)
A81: Material | B81: Safety Stock | C81: % Consumo Prom | D81: Días Cobertura
A82: Parte A | B82: 2000 | C82: 10 | D82: 1
A83: Parte B | B83: 500 | C83: 10 | D83: 1
A84: Pieza 1 | B84: 50 | C84: 20 | D84: 2
A85: Pieza 2 | B85: 10000 | C85: 10 | D85: 1
A86: Pieza 3 | B86: 1000 | C86: 15 | D86: 1
A87: Pieza 4 | B87: 2000 | C87: 15 | D87: 1
A88: 10. BUFFER MÍNIMO (Cobertura Operativa)
A89: Buffer = Quincenas de cobertura mínima antes de alerta
A90: Material | B90: Buffer (Quincenas) | C90: Consumo Prom/Q | D90: Inv. Mínimo Calc | E90: Crítico?
A91: Parte A | B91: 1 | C91: =#REF!/8 -> #REF! | D91: =B91*C91 -> #REF! | E91: =IF(B91>=1.5,"NO","SÍ - RIESGO ALTO") -> SÍ - RIESGO ALTO
A92: Parte B | B92: 1 | C92: =#REF!/8 -> #REF! | D92: =B92*C92 -> #REF! | E92: =IF(B92>=1.5,"NO","SÍ - RIESGO ALTO") -> SÍ - RIESGO ALTO
A93: Pieza 1 | B93: 2 | C93: =#REF!/8 -> #REF! | D93: =B93*C93 -> #REF! | E93: =IF(B93>=1.5,"NO","SÍ - RIESGO ALTO") -> NO
A94: Pieza 2 | B94: 1 | C94: =#REF!/8 -> #REF! | D94: =B94*C94 -> #REF! | E94: =IF(B94>=1.5,"NO","SÍ - RIESGO ALTO") -> SÍ - RIESGO ALTO
A95: Pieza 3 | B95: 1 | C95: =#REF!/8 -> #REF! | D95: =B95*C95 -> #REF! | E95: =IF(B95>=1.5,"NO","SÍ - RIESGO ALTO") -> SÍ - RIESGO ALTO
A96: Pieza 4 | B96: 1 | C96: =#REF!/8 -> #REF! | D96: =B96*C96 -> #REF! | E96: =IF(B96>=1.5,"NO","SÍ - RIESGO ALTO") -> SÍ - RIESGO ALTO
A97: Pieza 5 | B97: 1 | C97: =#REF!/8 -> #REF! | D97: =B97*C97 -> #REF! | E97: =IF(B97>=1.5,"NO","SÍ - RIESGO ALTO") -> SÍ - RIESGO ALTO
A98: Pieza 6 | B98: 1 | C98: =#REF!/8 -> #REF! | D98: =B98*C98 -> #REF! | E98: =IF(B98>=1.5,"NO","SÍ - RIESGO ALTO") -> SÍ - RIESGO ALTO
A100: 11. SENSIBILIDAD DEMANDA
A101: Factor Demanda | B101: =#REF! -> #REF! | C101: 1.0 = Base
A104: 12. PLANNING PARAMETERS
A105: Parameter | B105: Value | C105: Notes
A106: Stockout penalty ($/EC) | B106: =#REF! -> #REF!
A107: Financing cost per Q | B107: 0 | C107: 0 = ignore cash cost
A108: Review period R (Q) | B108: 1
A109: Order-up-to coverage (Q) | B109: 1
A110: Pieces buy at t=0 (1/0) | B110: 1
A111: Disc rate Part A (B) | B111: =IFERROR(VALUE(SUBSTITUTE(LEFT(D67,FIND("%",D67)-1),"%",""))/100,0) -> 0.16
A112: Disc rate Part B (B) | B112: =IFERROR(VALUE(SUBSTITUTE(LEFT(D75,FIND("%",D75)-1),"%",""))/100,0) -> 0.16
A113: Prob fail Supplier B | B113: =#REF! -> #REF!

Sheet Inventario_Dinamico
A1: INVENTARIO DINÁMICO - Control por Quincena
A2: Fórmula: Inv_Final_Q = Inv_Inicial_Q + Recepciones_Q - Consumo_Q
A3: AMARILLO = ingresar recepciones manualmente | ROJO = inventario negativo (ALERTA)
A5: Parte A
A6: Concepto | B6: Q1 | C6: Q2 | D6: Q3 | E6: Q4 | F6: Q5 | G6: Q6 | H6: Q7 | I6: Q8
A7: Inv_Inicial | B7: =#REF! -> #REF! | C7: =B10 -> #REF! | D7: =C10 -> #REF! | E7: =D10 -> #REF! | F7: =E10 -> #REF! | G7: =F10 -> #REF! | H7: =G10 -> #REF! | I7: =H10 -> #REF!
A8: Recepciones | B8: 2520 | C8: 2520 | D8: 2520 | E8: 2520 | F8: 0 | G8: 0 | H8: 0 | I8: 0
A9: Consumo | B9: =#REF! -> #REF! | C9: =#REF! -> #REF! | D9: =#REF! -> #REF! | E9: =#REF! -> #REF! | F9: =#REF! -> #REF! | G9: =#REF! -> #REF! | H9: =#REF! -> #REF! | I9: =#REF! -> #REF!
A10: Inv_Final | B10: =B7+B8-B9 -> #REF! | C10: =C7+C8-C9 -> #REF! | D10: =D7+D8-D9 -> #REF! | E10: =E7+E8-E9 -> #REF! | F10: =F7+F8-F9 -> #REF! | G10: =G7+G8-G9 -> #REF! | H10: =H7+H8-H9 -> #REF! | I10: =I7+I8-I9 -> #REF!
A11: Parte B
A12: Concepto | B12: Q1 | C12: Q2 | D12: Q3 | E12: Q4 | F12: Q5 | G12: Q6 | H12: Q7 | I12: Q8
A13: Inv_Inicial | B13: =#REF! -> #REF! | C13: =B16 -> #REF! | D13: =C16 -> #REF! | E13: =D16 -> #REF! | F13: =E16 -> #REF! | G13: =F16 -> #REF! | H13: =G16 -> #REF! | I13: =H16 -> #REF!
A14: Recepciones | B14: 504 | C14: 504 | D14: 504 | E14: 504 | F14: 504 | G14: 0 | H14: 0 | I14: 0
A15: Consumo | B15: =#REF! -> #REF! | C15: =#REF! -> #REF! | D15: =#REF! -> #REF! | E15: =#REF! -> #REF! | F15: =#REF! -> #REF! | G15: =#REF! -> #REF! | H15: =#REF! -> #REF! | I15: =#REF! -> #REF!
A16: Inv_Final | B16: =B13+B14-B15 -> #REF! | C16: =C13+C14-C15 -> #REF! | D16: =D13+D14-D15 -> #REF! | E16: =E13+E14-E15 -> #REF! | F16: =F13+F14-F15 -> #REF! | G16: =G13+G14-G15 -> #REF! | H16: =H13+H14-H15 -> #REF! | I16: =I13+I14-I15 -> #REF!
A17: Pieza 1
A18: Concepto | B18: Q1 | C18: Q2 | D18: Q3 | E18: Q4 | F18: Q5 | G18: Q6 | H18: Q7 | I18: Q8
A19: Inv_Inicial | B19: =#REF! -> #REF! | C19: =B22 -> #REF! | D19: =C22 -> #REF! | E19: =D22 -> #REF! | F19: =E22 -> #REF! | G19: =F22 -> #REF! | H19: =G22 -> #REF! | I19: =H22 -> #REF!
A20: Recepciones | B20: 25.2 | C20: 25.2 | D20: 25.2 | E20: 25.2 | F20: 25.2 | G20: 25.2 | H20: 25.2 | I20: 0
A21: Consumo | B21: =#REF! -> #REF! | C21: =#REF! -> #REF! | D21: =#REF! -> #REF! | E21: =#REF! -> #REF! | F21: =#REF! -> #REF! | G21: =#REF! -> #REF! | H21: =#REF! -> #REF! | I21: =#REF! -> #REF!
A22: Inv_Final | B22: =B19+B20-B21 -> #REF! | C22: =C19+C20-C21 -> #REF! | D22: =D19+D20-D21 -> #REF! | E22: =E19+E20-E21 -> #REF! | F22: =F19+F20-F21 -> #REF! | G22: =G19+G20-G21 -> #REF! | H22: =H19+H20-H21 -> #REF! | I22: =I19+I20-I21 -> #REF!
A23: Pieza 2
A24: Concepto | B24: Q1 | C24: Q2 | D24: Q3 | E24: Q4 | F24: Q5 | G24: Q6 | H24: Q7 | I24: Q8
A25: Inv_Inicial | B25: =#REF! -> #REF! | C25: =B28 -> #REF! | D25: =C28 -> #REF! | E25: =D28 -> #REF! | F25: =E28 -> #REF! | G25: =F28 -> #REF! | H25: =G28 -> #REF! | I25: =H28 -> #REF!
A26: Recepciones | B26: 20160 | C26: 20160 | D26: 20160 | E26: 20160 | F26: 20160 | G26: 20160 | H26: 20160 | I26: 0
A27: Consumo | B27: =#REF! -> #REF! | C27: =#REF! -> #REF! | D27: =#REF! -> #REF! | E27: =#REF! -> #REF! | F27: =#REF! -> #REF! | G27: =#REF! -> #REF! | H27: =#REF! -> #REF! | I27: =#REF! -> #REF!
A28: Inv_Final | B28: =B25+B26-B27 -> #REF! | C28: =C25+C26-C27 -> #REF! | D28: =D25+D26-D27 -> #REF! | E28: =E25+E26-E27 -> #REF! | F28: =F25+F26-F27 -> #REF! | G28: =G25+G26-G27 -> #REF! | H28: =H25+H26-H27 -> #REF! | I28: =I25+I26-I27 -> #REF!
A29: Pieza 3
A30: Concepto | B30: Q1 | C30: Q2 | D30: Q3 | E30: Q4 | F30: Q5 | G30: Q6 | H30: Q7 | I30: Q8
A31: Inv_Inicial | B31: =#REF! -> #REF! | C31: =B34 -> #REF! | D31: =C34 -> #REF! | E31: =D34 -> #REF! | F31: =E34 -> #REF! | G31: =F34 -> #REF! | H31: =G34 -> #REF! | I31: =H34 -> #REF!
A32: Recepciones | B32: 756 | C32: 756 | D32: 756 | E32: 756 | F32: 756 | G32: 756 | H32: 756 | I32: 0
A33: Consumo | B33: =#REF! -> #REF! | C33: =#REF! -> #REF! | D33: =#REF! -> #REF! | E33: =#REF! -> #REF! | F33: =#REF! -> #REF! | G33: =#REF! -> #REF! | H33: =#REF! -> #REF! | I33: =#REF! -> #REF!
A34: Inv_Final | B34: =B31+B32-B33 -> #REF! | C34: =C31+C32-C33 -> #REF! | D34: =D31+D32-D33 -> #REF! | E34: =E31+E32-E33 -> #REF! | F34: =F31+F32-F33 -> #REF! | G34: =G31+G32-G33 -> #REF! | H34: =H31+H32-H33 -> #REF! | I34: =I31+I32-I33 -> #REF!
A35: Pieza 4
A36: Concepto | B36: Q1 | C36: Q2 | D36: Q3 | E36: Q4 | F36: Q5 | G36: Q6 | H36: Q7 | I36: Q8
A37: Inv_Inicial | B37: =#REF! -> #REF! | C37: =B40 -> #REF! | D37: =C40 -> #REF! | E37: =D40 -> #REF! | F37: =E40 -> #REF! | G37: =F40 -> #REF! | H37: =G40 -> #REF! | I37: =H40 -> #REF!
A38: Recepciones | B38: 1512 | C38: 1512 | D38: 1512 | E38: 1512 | F38: 1512 | G38: 1512 | H38: 1512 | I38: 0
A39: Consumo | B39: =#REF! -> #REF! | C39: =#REF! -> #REF! | D39: =#REF! -> #REF! | E39: =#REF! -> #REF! | F39: =#REF! -> #REF! | G39: =#REF! -> #REF! | H39: =#REF! -> #REF! | I39: =#REF! -> #REF!
A40: Inv_Final | B40: =B37+B38-B39 -> #REF! | C40: =C37+C38-C39 -> #REF! | D40: =D37+D38-D39 -> #REF! | E40: =E37+E38-E39 -> #REF! | F40: =F37+F38-F39 -> #REF! | G40: =G37+G38-G39 -> #REF! | H40: =H37+H38-H39 -> #REF! | I40: =I37+I38-I39 -> #REF!
A41: Pieza 5
A42: Concepto | B42: Q1 | C42: Q2 | D42: Q3 | E42: Q4 | F42: Q5 | G42: Q6 | H42: Q7 | I42: Q8
A43: Inv_Inicial | B43: =#REF! -> #REF! | C43: =B46 -> #REF! | D43: =C46 -> #REF! | E43: =D46 -> #REF! | F43: =E46 -> #REF! | G43: =F46 -> #REF! | H43: =G46 -> #REF! | I43: =H46 -> #REF!
A44: Recepciones | B44: 5040 | C44: 5040 | D44: 5040 | E44: 5040 | F44: 5040 | G44: 5040 | H44: 5040 | I44: 0
A45: Consumo | B45: =#REF! -> #REF! | C45: =#REF! -> #REF! | D45: =#REF! -> #REF! | E45: =#REF! -> #REF! | F45: =#REF! -> #REF! | G45: =#REF! -> #REF! | H45: =#REF! -> #REF! | I45: =#REF! -> #REF!
A46: Inv_Final | B46: =B43+B44-B45 -> #REF! | C46: =C43+C44-C45 -> #REF! | D46: =D43+D44-D45 -> #REF! | E46: =E43+E44-E45 -> #REF! | F46: =F43+F44-F45 -> #REF! | G46: =G43+G44-G45 -> #REF! | H46: =H43+H44-H45 -> #REF! | I46: =I43+I44-I45 -> #REF!
A47: Pieza 6
A48: Concepto | B48: Q1 | C48: Q2 | D48: Q3 | E48: Q4 | F48: Q5 | G48: Q6 | H48: Q7 | I48: Q8
A49: Inv_Inicial | B49: =#REF! -> #REF! | C49: =B$52 -> #REF! | D49: =C$52 -> #REF! | E49: =D$52 -> #REF! | F49: =E$52 -> #REF! | G49: =F$52 -> #REF! | H49: =G$52 -> #REF! | I49: =H$52 -> #REF!
A50: Recepciones | B50: 1890 | C50: 1890 | D50: 1890 | E50: 1890 | F50: 1890 | G50: 1890 | H50: 1890 | I50: 0
A51: Consumo | B51: =#REF! -> #REF! | C51: =#REF! -> #REF! | D51: =#REF! -> #REF! | E51: =#REF! -> #REF! | F51: =#REF! -> #REF! | G51: =#REF! -> #REF! | H51: =#REF! -> #REF! | I51: =#REF! -> #REF!
A52: Inv_Final | B52: =B$49+B$50-B$51 -> #REF! | C52: =C$49+C$50-C$51 -> #REF! | D52: =D$49+D$50-D$51 -> #REF! | E52: =E$49+E$50-E$51 -> #REF! | F52: =F$49+F$50-F$51 -> #REF! | G52: =G$49+G$50-G$51 -> #REF! | H52: =H$49+H$50-H$51 -> #REF! | I52: =I$49+I$50-I$51 -> #REF!
A53: VALIDACIONES Y ALERTAS
A54: Material | B54: Q1 | C54: Q2 | D54: Q3 | E54: Q4 | F54: Q5 | G54: Q6 | H54: Q7 | I54: Q8 | J54: Min Global
A55: Parte A | B55: =IF(B9<Inputs!D92,"⚠ RIESGO","OK") -> #REF! | C55: =IF(C9<Inputs!D92,"⚠ RIESGO","OK") -> #REF! | D55: =IF(D9<Inputs!D92,"⚠ RIESGO","OK") -> #REF! | E55: =IF(E9<Inputs!D92,"⚠ RIESGO","OK") -> #REF! | F55: =IF(F9<Inputs!D92,"⚠ RIESGO","OK") -> #REF! | G55: =IF(G9<Inputs!D92,"⚠ RIESGO","OK") -> #REF! | H55: =IF(H9<Inputs!D92,"⚠ RIESGO","OK") -> #REF! | I55: =IF(I9<Inputs!D92,"⚠ RIESGO","OK") -> #REF! | J55: =MIN(B9:I9) -> #REF!
A56: Parte B | B56: =IF(B14<Inputs!D93,"⚠ RIESGO","OK") -> #REF! | C56: =IF(C14<Inputs!D93,"⚠ RIESGO","OK") -> #REF! | D56: =IF(D14<Inputs!D93,"⚠ RIESGO","OK") -> #REF! | E56: =IF(E14<Inputs!D93,"⚠ RIESGO","OK") -> #REF! | F56: =IF(F14<Inputs!D93,"⚠ RIESGO","OK") -> #REF! | G56: =IF(G14<Inputs!D93,"⚠ RIESGO","OK") -> #REF! | H56: =IF(H14<Inputs!D93,"⚠ RIESGO","OK") -> #REF! | I56: =IF(I14<Inputs!D93,"⚠ RIESGO","OK") -> #REF! | J56: =MIN(B14:I14) -> 0
A57: Pieza 1 | B57: =IF(B19<Inputs!D94,"⚠ RIESGO","OK") -> #REF! | C57: =IF(C19<Inputs!D94,"⚠ RIESGO","OK") -> #REF! | D57: =IF(D19<Inputs!D94,"⚠ RIESGO","OK") -> #REF! | E57: =IF(E19<Inputs!D94,"⚠ RIESGO","OK") -> #REF! | F57: =IF(F19<Inputs!D94,"⚠ RIESGO","OK") -> #REF! | G57: =IF(G19<Inputs!D94,"⚠ RIESGO","OK") -> #REF! | H57: =IF(H19<Inputs!D94,"⚠ RIESGO","OK") -> #REF! | I57: =IF(I19<Inputs!D94,"⚠ RIESGO","OK") -> #REF! | J57: =MIN(B19:I19) -> #REF!
A58: Pieza 2 | B58: =IF(B24<Inputs!D95,"⚠ RIESGO","OK") -> #REF! | C58: =IF(C24<Inputs!D95,"⚠ RIESGO","OK") -> #REF! | D58: =IF(D24<Inputs!D95,"⚠ RIESGO","OK") -> #REF! | E58: =IF(E24<Inputs!D95,"⚠ RIESGO","OK") -> #REF! | F58: =IF(F24<Inputs!D95,"⚠ RIESGO","OK") -> #REF! | G58: =IF(G24<Inputs!D95,"⚠ RIESGO","OK") -> #REF! | H58: =IF(H24<Inputs!D95,"⚠ RIESGO","OK") -> #REF! | I58: =IF(I24<Inputs!D95,"⚠ RIESGO","OK") -> #REF! | J58: =MIN(B24:I24) -> 0
A59: Pieza 3 | B59: =IF(B29<Inputs!D96,"⚠ RIESGO","OK") -> #REF! | C59: =IF(C29<Inputs!D96,"⚠ RIESGO","OK") -> #REF! | D59: =IF(D29<Inputs!D96,"⚠ RIESGO","OK") -> #REF! | E59: =IF(E29<Inputs!D96,"⚠ RIESGO","OK") -> #REF! | F59: =IF(F29<Inputs!D96,"⚠ RIESGO","OK") -> #REF! | G59: =IF(G29<Inputs!D96,"⚠ RIESGO","OK") -> #REF! | H59: =IF(H29<Inputs!D96,"⚠ RIESGO","OK") -> #REF! | I59: =IF(I29<Inputs!D96,"⚠ RIESGO","OK") -> #REF! | J59: =MIN(B29:I29) -> 0
A60: Pieza 4 | B60: =IF(B34<Inputs!D97,"⚠ RIESGO","OK") -> #REF! | C60: =IF(C34<Inputs!D97,"⚠ RIESGO","OK") -> #REF! | D60: =IF(D34<Inputs!D97,"⚠ RIESGO","OK") -> #REF! | E60: =IF(E34<Inputs!D97,"⚠ RIESGO","OK") -> #REF! | F60: =IF(F34<Inputs!D97,"⚠ RIESGO","OK") -> #REF! | G60: =IF(G34<Inputs!D97,"⚠ RIESGO","OK") -> #REF! | H60: =IF(H34<Inputs!D97,"⚠ RIESGO","OK") -> #REF! | I60: =IF(I34<Inputs!D97,"⚠ RIESGO","OK") -> #REF! | J60: =MIN(B34:I34) -> #REF!
A61: Pieza 5 | B61: =IF(B39<Inputs!D98,"⚠ RIESGO","OK") -> #REF! | C61: =IF(C39<Inputs!D98,"⚠ RIESGO","OK") -> #REF! | D61: =IF(D39<Inputs!D98,"⚠ RIESGO","OK") -> #REF! | E61: =IF(E39<Inputs!D98,"⚠ RIESGO","OK") -> #REF! | F61: =IF(F39<Inputs!D98,"⚠ RIESGO","OK") -> #REF! | G61: =IF(G39<Inputs!D98,"⚠ RIESGO","OK") -> #REF! | H61: =IF(H39<Inputs!D98,"⚠ RIESGO","OK") -> #REF! | I61: =IF(I39<Inputs!D98,"⚠ RIESGO","OK") -> #REF! | J61: =MIN(B39:I39) -> #REF!
A62: Pieza 6 | B62: =IF(B44<Inputs!D99,"⚠ RIESGO","OK") -> OK | C62: =IF(C44<Inputs!D99,"⚠ RIESGO","OK") -> OK | D62: =IF(D44<Inputs!D99,"⚠ RIESGO","OK") -> OK | E62: =IF(E44<Inputs!D99,"⚠ RIESGO","OK") -> OK | F62: =IF(F44<Inputs!D99,"⚠ RIESGO","OK") -> OK | G62: =IF(G44<Inputs!D99,"⚠ RIESGO","OK") -> OK | H62: =IF(H44<Inputs!D99,"⚠ RIESGO","OK") -> OK | I62: =IF(I44<Inputs!D99,"⚠ RIESGO","OK") -> OK | J62: =MIN(B44:I44) -> 0

Sheet MRP_LeadTimes
A1: MRP - PRODUCCIÓN POR SECCIÓN
A2: 5 secciones (S1-S5), cada una tarda 1 quincena. WIP entre secciones.
A4: FLUJO DE PRODUCCIÓN
A5: Sección | B5: Input | C5: Process | D5: Output | E5: Lead Time
A6: S1 | B6: Parte A | C6: Ensambla Piezas | D6: Semi A | E6: 1Q
A7: S2 | B7: Parte B | C7: Ensambla Piezas | D7: Semi B | E7: 1Q
A8: S3 | B8: - | C8: Pieza 3 | D8: Semi C | E8: 1Q
A9: S4 | B9: - | C9: Pieza 6 | D9: Semi D | E9: 1Q
A10: S5 | B10: Semis | C10: Ensambla final | D10: Electroclean | E10: 1Q
A12: CALENDARIO POR SECCION (Lead Time 1Q)
A13: Seccion | B13: Q1 | C13: Q2 | D13: Q3 | E13: Q4 | F13: Q5 | G13: Q6 | H13: Q7 | I13: Q8
A14: S5 - Final (EC) | B14: =Inputs!B6*Inputs!$B$101 -> #REF! | C14: =Inputs!C6*Inputs!$B$101 -> #REF! | D14: =Inputs!D6*Inputs!$B$101 -> #REF! | E14: =Inputs!E6*Inputs!$B$101 -> #REF! | F14: =Inputs!F6*Inputs!$B$101 -> #REF! | G14: =Inputs!G6*Inputs!$B$101 -> #REF! | H14: =Inputs!H6*Inputs!$B$101 -> #REF! | I14: =Inputs!I6*Inputs!$B$101 -> #REF!
A15: S4 - Piezas | B15: =IFERROR(C14,0) -> 0 | C15: =IFERROR(D14,0) -> 0 | D15: =IFERROR(E14,0) -> 0 | E15: =IFERROR(F14,0) -> 0 | F15: =IFERROR(G14,0) -> 0 | G15: =IFERROR(H14,0) -> 0 | H15: =IFERROR(I14,0) -> 0 | I15: =IFERROR(J14,0) -> 0
A16: S3 - Semi | B16: =IFERROR(C15,0) -> 0 | C16: =IFERROR(D15,0) -> 0 | D16: =IFERROR(E15,0) -> 0 | E16: =IFERROR(F15,0) -> 0 | F16: =IFERROR(G15,0) -> 0 | G16: =IFERROR(H15,0) -> 0 | H16: =IFERROR(I15,0) -> 0 | I16: =IFERROR(J15,0) -> 0
A17: S2 - Parte B | B17: =IFERROR(C16,0) -> 0 | C17: =IFERROR(D16,0) -> 0 | D17: =IFERROR(E16,0) -> 0 | E17: =IFERROR(F16,0) -> 0 | F17: =IFERROR(G16,0) -> 0 | G17: =IFERROR(H16,0) -> 0 | H17: =IFERROR(I16,0) -> 0 | I17: =IFERROR(J16,0) -> 0
A18: S1 - Parte A | B18: =IFERROR(C17,0) -> 0 | C18: =IFERROR(D17,0) -> 0 | D18: =IFERROR(E17,0) -> 0 | E18: =IFERROR(F17,0) -> 0 | F18: =IFERROR(G17,0) -> 0 | G18: =IFERROR(H17,0) -> 0 | H18: =IFERROR(I17,0) -> 0 | I18: =IFERROR(J17,0) -> 0
